package com.google.android.gms.wearable.internal;

import android.os.Binder;
import android.os.IBinder;
import android.os.IInterface;
import android.os.Parcel;
import android.os.Parcelable.Creator;
import android.os.RemoteException;
import com.google.android.gms.common.data.DataHolder;
import com.google.android.gms.common.data.f;

public abstract interface ae
  extends IInterface
{
  public abstract void a(ai paramai)
    throws RemoteException;
  
  public abstract void a(al paramal)
    throws RemoteException;
  
  public abstract void aa(DataHolder paramDataHolder)
    throws RemoteException;
  
  public abstract void b(al paramal)
    throws RemoteException;
  
  public static abstract class a
    extends Binder
    implements ae
  {
    public a()
    {
      attachInterface(this, "com.google.android.gms.wearable.internal.IWearableListener");
    }
    
    public static ae bY(IBinder paramIBinder)
    {
      if (paramIBinder == null) {
        return null;
      }
      IInterface localIInterface = paramIBinder.queryLocalInterface("com.google.android.gms.wearable.internal.IWearableListener");
      if ((localIInterface != null) && ((localIInterface instanceof ae))) {
        return (ae)localIInterface;
      }
      return new a(paramIBinder);
    }
    
    public IBinder asBinder()
    {
      return this;
    }
    
    public boolean onTransact(int paramInt1, Parcel paramParcel1, Parcel paramParcel2, int paramInt2)
      throws RemoteException
    {
      switch (paramInt1)
      {
      default: 
        return super.onTransact(paramInt1, paramParcel1, paramParcel2, paramInt2);
      case 1598968902: 
        paramParcel2.writeString("com.google.android.gms.wearable.internal.IWearableListener");
        return true;
      case 1: 
        paramParcel1.enforceInterface("com.google.android.gms.wearable.internal.IWearableListener");
        int m = paramParcel1.readInt();
        DataHolder localDataHolder = null;
        if (m != 0) {
          localDataHolder = DataHolder.CREATOR.B(paramParcel1);
        }
        aa(localDataHolder);
        return true;
      case 2: 
        paramParcel1.enforceInterface("com.google.android.gms.wearable.internal.IWearableListener");
        int k = paramParcel1.readInt();
        ai localai = null;
        if (k != 0) {
          localai = (ai)ai.CREATOR.createFromParcel(paramParcel1);
        }
        a(localai);
        return true;
      case 3: 
        paramParcel1.enforceInterface("com.google.android.gms.wearable.internal.IWearableListener");
        int j = paramParcel1.readInt();
        al localal2 = null;
        if (j != 0) {
          localal2 = (al)al.CREATOR.createFromParcel(paramParcel1);
        }
        a(localal2);
        return true;
      }
      paramParcel1.enforceInterface("com.google.android.gms.wearable.internal.IWearableListener");
      int i = paramParcel1.readInt();
      al localal1 = null;
      if (i != 0) {
        localal1 = (al)al.CREATOR.createFromParcel(paramParcel1);
      }
      b(localal1);
      return true;
    }
    
    private static class a
      implements ae
    {
      private IBinder le;
      
      a(IBinder paramIBinder)
      {
        this.le = paramIBinder;
      }
      
      /* Error */
      public void a(ai paramai)
        throws RemoteException
      {
        // Byte code:
        //   0: invokestatic 25	android/os/Parcel:obtain	()Landroid/os/Parcel;
        //   3: astore_2
        //   4: aload_2
        //   5: ldc 27
        //   7: invokevirtual 31	android/os/Parcel:writeInterfaceToken	(Ljava/lang/String;)V
        //   10: aload_1
        //   11: ifnull +33 -> 44
        //   14: aload_2
        //   15: iconst_1
        //   16: invokevirtual 35	android/os/Parcel:writeInt	(I)V
        //   19: aload_1
        //   20: aload_2
        //   21: iconst_0
        //   22: invokevirtual 41	com/google/android/gms/wearable/internal/ai:writeToParcel	(Landroid/os/Parcel;I)V
        //   25: aload_0
        //   26: getfield 15	com/google/android/gms/wearable/internal/ae$a$a:le	Landroid/os/IBinder;
        //   29: iconst_2
        //   30: aload_2
        //   31: aconst_null
        //   32: iconst_1
        //   33: invokeinterface 47 5 0
        //   38: pop
        //   39: aload_2
        //   40: invokevirtual 50	android/os/Parcel:recycle	()V
        //   43: return
        //   44: aload_2
        //   45: iconst_0
        //   46: invokevirtual 35	android/os/Parcel:writeInt	(I)V
        //   49: goto -24 -> 25
        //   52: astore_3
        //   53: aload_2
        //   54: invokevirtual 50	android/os/Parcel:recycle	()V
        //   57: aload_3
        //   58: athrow
        // Local variable table:
        //   start	length	slot	name	signature
        //   0	59	0	this	a
        //   0	59	1	paramai	ai
        //   3	51	2	localParcel	Parcel
        //   52	6	3	localObject	Object
        // Exception table:
        //   from	to	target	type
        //   4	10	52	finally
        //   14	25	52	finally
        //   25	39	52	finally
        //   44	49	52	finally
      }
      
      /* Error */
      public void a(al paramal)
        throws RemoteException
      {
        // Byte code:
        //   0: invokestatic 25	android/os/Parcel:obtain	()Landroid/os/Parcel;
        //   3: astore_2
        //   4: aload_2
        //   5: ldc 27
        //   7: invokevirtual 31	android/os/Parcel:writeInterfaceToken	(Ljava/lang/String;)V
        //   10: aload_1
        //   11: ifnull +33 -> 44
        //   14: aload_2
        //   15: iconst_1
        //   16: invokevirtual 35	android/os/Parcel:writeInt	(I)V
        //   19: aload_1
        //   20: aload_2
        //   21: iconst_0
        //   22: invokevirtual 54	com/google/android/gms/wearable/internal/al:writeToParcel	(Landroid/os/Parcel;I)V
        //   25: aload_0
        //   26: getfield 15	com/google/android/gms/wearable/internal/ae$a$a:le	Landroid/os/IBinder;
        //   29: iconst_3
        //   30: aload_2
        //   31: aconst_null
        //   32: iconst_1
        //   33: invokeinterface 47 5 0
        //   38: pop
        //   39: aload_2
        //   40: invokevirtual 50	android/os/Parcel:recycle	()V
        //   43: return
        //   44: aload_2
        //   45: iconst_0
        //   46: invokevirtual 35	android/os/Parcel:writeInt	(I)V
        //   49: goto -24 -> 25
        //   52: astore_3
        //   53: aload_2
        //   54: invokevirtual 50	android/os/Parcel:recycle	()V
        //   57: aload_3
        //   58: athrow
        // Local variable table:
        //   start	length	slot	name	signature
        //   0	59	0	this	a
        //   0	59	1	paramal	al
        //   3	51	2	localParcel	Parcel
        //   52	6	3	localObject	Object
        // Exception table:
        //   from	to	target	type
        //   4	10	52	finally
        //   14	25	52	finally
        //   25	39	52	finally
        //   44	49	52	finally
      }
      
      /* Error */
      public void aa(DataHolder paramDataHolder)
        throws RemoteException
      {
        // Byte code:
        //   0: invokestatic 25	android/os/Parcel:obtain	()Landroid/os/Parcel;
        //   3: astore_2
        //   4: aload_2
        //   5: ldc 27
        //   7: invokevirtual 31	android/os/Parcel:writeInterfaceToken	(Ljava/lang/String;)V
        //   10: aload_1
        //   11: ifnull +33 -> 44
        //   14: aload_2
        //   15: iconst_1
        //   16: invokevirtual 35	android/os/Parcel:writeInt	(I)V
        //   19: aload_1
        //   20: aload_2
        //   21: iconst_0
        //   22: invokevirtual 59	com/google/android/gms/common/data/DataHolder:writeToParcel	(Landroid/os/Parcel;I)V
        //   25: aload_0
        //   26: getfield 15	com/google/android/gms/wearable/internal/ae$a$a:le	Landroid/os/IBinder;
        //   29: iconst_1
        //   30: aload_2
        //   31: aconst_null
        //   32: iconst_1
        //   33: invokeinterface 47 5 0
        //   38: pop
        //   39: aload_2
        //   40: invokevirtual 50	android/os/Parcel:recycle	()V
        //   43: return
        //   44: aload_2
        //   45: iconst_0
        //   46: invokevirtual 35	android/os/Parcel:writeInt	(I)V
        //   49: goto -24 -> 25
        //   52: astore_3
        //   53: aload_2
        //   54: invokevirtual 50	android/os/Parcel:recycle	()V
        //   57: aload_3
        //   58: athrow
        // Local variable table:
        //   start	length	slot	name	signature
        //   0	59	0	this	a
        //   0	59	1	paramDataHolder	DataHolder
        //   3	51	2	localParcel	Parcel
        //   52	6	3	localObject	Object
        // Exception table:
        //   from	to	target	type
        //   4	10	52	finally
        //   14	25	52	finally
        //   25	39	52	finally
        //   44	49	52	finally
      }
      
      public IBinder asBinder()
      {
        return this.le;
      }
      
      /* Error */
      public void b(al paramal)
        throws RemoteException
      {
        // Byte code:
        //   0: invokestatic 25	android/os/Parcel:obtain	()Landroid/os/Parcel;
        //   3: astore_2
        //   4: aload_2
        //   5: ldc 27
        //   7: invokevirtual 31	android/os/Parcel:writeInterfaceToken	(Ljava/lang/String;)V
        //   10: aload_1
        //   11: ifnull +33 -> 44
        //   14: aload_2
        //   15: iconst_1
        //   16: invokevirtual 35	android/os/Parcel:writeInt	(I)V
        //   19: aload_1
        //   20: aload_2
        //   21: iconst_0
        //   22: invokevirtual 54	com/google/android/gms/wearable/internal/al:writeToParcel	(Landroid/os/Parcel;I)V
        //   25: aload_0
        //   26: getfield 15	com/google/android/gms/wearable/internal/ae$a$a:le	Landroid/os/IBinder;
        //   29: iconst_4
        //   30: aload_2
        //   31: aconst_null
        //   32: iconst_1
        //   33: invokeinterface 47 5 0
        //   38: pop
        //   39: aload_2
        //   40: invokevirtual 50	android/os/Parcel:recycle	()V
        //   43: return
        //   44: aload_2
        //   45: iconst_0
        //   46: invokevirtual 35	android/os/Parcel:writeInt	(I)V
        //   49: goto -24 -> 25
        //   52: astore_3
        //   53: aload_2
        //   54: invokevirtual 50	android/os/Parcel:recycle	()V
        //   57: aload_3
        //   58: athrow
        // Local variable table:
        //   start	length	slot	name	signature
        //   0	59	0	this	a
        //   0	59	1	paramal	al
        //   3	51	2	localParcel	Parcel
        //   52	6	3	localObject	Object
        // Exception table:
        //   from	to	target	type
        //   4	10	52	finally
        //   14	25	52	finally
        //   25	39	52	finally
        //   44	49	52	finally
      }
    }
  }
}


/* Location:           C:\Users\TGKIM\Downloads\작업폴더\리버싱\androidReversetools\jd-gui-0.3.6.windows\com.appg.golfmon-1-dex2jar.jar
 * Qualified Name:     com.google.android.gms.wearable.internal.ae
 * JD-Core Version:    0.7.0.1
 */