package com.google.android.gms.internal;

import android.content.Intent;
import android.os.Binder;
import android.os.IBinder;
import android.os.IInterface;
import android.os.Parcel;
import android.os.RemoteException;

public abstract interface eq
  extends IInterface
{
  public abstract void finishPurchase()
    throws RemoteException;
  
  public abstract String getProductId()
    throws RemoteException;
  
  public abstract Intent getPurchaseData()
    throws RemoteException;
  
  public abstract int getResultCode()
    throws RemoteException;
  
  public abstract boolean isVerified()
    throws RemoteException;
  
  public static abstract class a
    extends Binder
    implements eq
  {
    public a()
    {
      attachInterface(this, "com.google.android.gms.ads.internal.purchase.client.IInAppPurchaseResult");
    }
    
    public static eq y(IBinder paramIBinder)
    {
      if (paramIBinder == null) {
        return null;
      }
      IInterface localIInterface = paramIBinder.queryLocalInterface("com.google.android.gms.ads.internal.purchase.client.IInAppPurchaseResult");
      if ((localIInterface != null) && ((localIInterface instanceof eq))) {
        return (eq)localIInterface;
      }
      return new a(paramIBinder);
    }
    
    public IBinder asBinder()
    {
      return this;
    }
    
    public boolean onTransact(int paramInt1, Parcel paramParcel1, Parcel paramParcel2, int paramInt2)
      throws RemoteException
    {
      switch (paramInt1)
      {
      default: 
        return super.onTransact(paramInt1, paramParcel1, paramParcel2, paramInt2);
      case 1598968902: 
        paramParcel2.writeString("com.google.android.gms.ads.internal.purchase.client.IInAppPurchaseResult");
        return true;
      case 1: 
        paramParcel1.enforceInterface("com.google.android.gms.ads.internal.purchase.client.IInAppPurchaseResult");
        String str = getProductId();
        paramParcel2.writeNoException();
        paramParcel2.writeString(str);
        return true;
      case 2: 
        paramParcel1.enforceInterface("com.google.android.gms.ads.internal.purchase.client.IInAppPurchaseResult");
        Intent localIntent = getPurchaseData();
        paramParcel2.writeNoException();
        if (localIntent != null)
        {
          paramParcel2.writeInt(1);
          localIntent.writeToParcel(paramParcel2, 1);
          return true;
        }
        paramParcel2.writeInt(0);
        return true;
      case 3: 
        paramParcel1.enforceInterface("com.google.android.gms.ads.internal.purchase.client.IInAppPurchaseResult");
        int j = getResultCode();
        paramParcel2.writeNoException();
        paramParcel2.writeInt(j);
        return true;
      case 4: 
        paramParcel1.enforceInterface("com.google.android.gms.ads.internal.purchase.client.IInAppPurchaseResult");
        boolean bool = isVerified();
        paramParcel2.writeNoException();
        int i = 0;
        if (bool) {
          i = 1;
        }
        paramParcel2.writeInt(i);
        return true;
      }
      paramParcel1.enforceInterface("com.google.android.gms.ads.internal.purchase.client.IInAppPurchaseResult");
      finishPurchase();
      paramParcel2.writeNoException();
      return true;
    }
    
    private static class a
      implements eq
    {
      private IBinder le;
      
      a(IBinder paramIBinder)
      {
        this.le = paramIBinder;
      }
      
      public IBinder asBinder()
      {
        return this.le;
      }
      
      public void finishPurchase()
        throws RemoteException
      {
        Parcel localParcel1 = Parcel.obtain();
        Parcel localParcel2 = Parcel.obtain();
        try
        {
          localParcel1.writeInterfaceToken("com.google.android.gms.ads.internal.purchase.client.IInAppPurchaseResult");
          this.le.transact(5, localParcel1, localParcel2, 0);
          localParcel2.readException();
          return;
        }
        finally
        {
          localParcel2.recycle();
          localParcel1.recycle();
        }
      }
      
      public String getProductId()
        throws RemoteException
      {
        Parcel localParcel1 = Parcel.obtain();
        Parcel localParcel2 = Parcel.obtain();
        try
        {
          localParcel1.writeInterfaceToken("com.google.android.gms.ads.internal.purchase.client.IInAppPurchaseResult");
          this.le.transact(1, localParcel1, localParcel2, 0);
          localParcel2.readException();
          String str = localParcel2.readString();
          return str;
        }
        finally
        {
          localParcel2.recycle();
          localParcel1.recycle();
        }
      }
      
      /* Error */
      public Intent getPurchaseData()
        throws RemoteException
      {
        // Byte code:
        //   0: invokestatic 26	android/os/Parcel:obtain	()Landroid/os/Parcel;
        //   3: astore_1
        //   4: invokestatic 26	android/os/Parcel:obtain	()Landroid/os/Parcel;
        //   7: astore_2
        //   8: aload_1
        //   9: ldc 28
        //   11: invokevirtual 32	android/os/Parcel:writeInterfaceToken	(Ljava/lang/String;)V
        //   14: aload_0
        //   15: getfield 15	com/google/android/gms/internal/eq$a$a:le	Landroid/os/IBinder;
        //   18: iconst_2
        //   19: aload_1
        //   20: aload_2
        //   21: iconst_0
        //   22: invokeinterface 38 5 0
        //   27: pop
        //   28: aload_2
        //   29: invokevirtual 41	android/os/Parcel:readException	()V
        //   32: aload_2
        //   33: invokevirtual 55	android/os/Parcel:readInt	()I
        //   36: ifeq +28 -> 64
        //   39: getstatic 61	android/content/Intent:CREATOR	Landroid/os/Parcelable$Creator;
        //   42: aload_2
        //   43: invokeinterface 67 2 0
        //   48: checkcast 57	android/content/Intent
        //   51: astore 5
        //   53: aload_2
        //   54: invokevirtual 44	android/os/Parcel:recycle	()V
        //   57: aload_1
        //   58: invokevirtual 44	android/os/Parcel:recycle	()V
        //   61: aload 5
        //   63: areturn
        //   64: aconst_null
        //   65: astore 5
        //   67: goto -14 -> 53
        //   70: astore_3
        //   71: aload_2
        //   72: invokevirtual 44	android/os/Parcel:recycle	()V
        //   75: aload_1
        //   76: invokevirtual 44	android/os/Parcel:recycle	()V
        //   79: aload_3
        //   80: athrow
        // Local variable table:
        //   start	length	slot	name	signature
        //   0	81	0	this	a
        //   3	73	1	localParcel1	Parcel
        //   7	65	2	localParcel2	Parcel
        //   70	10	3	localObject	Object
        //   51	15	5	localIntent	Intent
        // Exception table:
        //   from	to	target	type
        //   8	53	70	finally
      }
      
      public int getResultCode()
        throws RemoteException
      {
        Parcel localParcel1 = Parcel.obtain();
        Parcel localParcel2 = Parcel.obtain();
        try
        {
          localParcel1.writeInterfaceToken("com.google.android.gms.ads.internal.purchase.client.IInAppPurchaseResult");
          this.le.transact(3, localParcel1, localParcel2, 0);
          localParcel2.readException();
          int i = localParcel2.readInt();
          return i;
        }
        finally
        {
          localParcel2.recycle();
          localParcel1.recycle();
        }
      }
      
      public boolean isVerified()
        throws RemoteException
      {
        Parcel localParcel1 = Parcel.obtain();
        Parcel localParcel2 = Parcel.obtain();
        try
        {
          localParcel1.writeInterfaceToken("com.google.android.gms.ads.internal.purchase.client.IInAppPurchaseResult");
          this.le.transact(4, localParcel1, localParcel2, 0);
          localParcel2.readException();
          int i = localParcel2.readInt();
          boolean bool = false;
          if (i != 0) {
            bool = true;
          }
          return bool;
        }
        finally
        {
          localParcel2.recycle();
          localParcel1.recycle();
        }
      }
    }
  }
}


/* Location:           C:\Users\TGKIM\Downloads\작업폴더\리버싱\androidReversetools\jd-gui-0.3.6.windows\com.appg.golfmon-1-dex2jar.jar
 * Qualified Name:     com.google.android.gms.internal.eq
 * JD-Core Version:    0.7.0.1
 */