package com.google.android.gms.internal;

import android.os.Binder;
import android.os.IBinder;
import android.os.IInterface;
import android.os.Parcel;
import android.os.ParcelFileDescriptor;
import android.os.Parcelable.Creator;
import android.os.RemoteException;
import com.google.android.gms.common.api.Status;
import com.google.android.gms.common.api.StatusCreator;

public abstract interface hv
  extends IInterface
{
  public abstract void a(Status paramStatus)
    throws RemoteException;
  
  public abstract void a(Status paramStatus, ParcelFileDescriptor paramParcelFileDescriptor)
    throws RemoteException;
  
  public abstract void a(Status paramStatus, boolean paramBoolean)
    throws RemoteException;
  
  public abstract void a(hl.b paramb)
    throws RemoteException;
  
  public static abstract class a
    extends Binder
    implements hv
  {
    public a()
    {
      attachInterface(this, "com.google.android.gms.appdatasearch.internal.ILightweightAppDataSearchCallbacks");
    }
    
    public static hv F(IBinder paramIBinder)
    {
      if (paramIBinder == null) {
        return null;
      }
      IInterface localIInterface = paramIBinder.queryLocalInterface("com.google.android.gms.appdatasearch.internal.ILightweightAppDataSearchCallbacks");
      if ((localIInterface != null) && ((localIInterface instanceof hv))) {
        return (hv)localIInterface;
      }
      return new a(paramIBinder);
    }
    
    public IBinder asBinder()
    {
      return this;
    }
    
    public boolean onTransact(int paramInt1, Parcel paramParcel1, Parcel paramParcel2, int paramInt2)
      throws RemoteException
    {
      switch (paramInt1)
      {
      default: 
        return super.onTransact(paramInt1, paramParcel1, paramParcel2, paramInt2);
      case 1598968902: 
        paramParcel2.writeString("com.google.android.gms.appdatasearch.internal.ILightweightAppDataSearchCallbacks");
        return true;
      case 1: 
        paramParcel1.enforceInterface("com.google.android.gms.appdatasearch.internal.ILightweightAppDataSearchCallbacks");
        int m = paramParcel1.readInt();
        Status localStatus3 = null;
        if (m != 0) {
          localStatus3 = Status.CREATOR.createFromParcel(paramParcel1);
        }
        a(localStatus3);
        return true;
      case 2: 
        paramParcel1.enforceInterface("com.google.android.gms.appdatasearch.internal.ILightweightAppDataSearchCallbacks");
        if (paramParcel1.readInt() != 0) {}
        for (Status localStatus2 = Status.CREATOR.createFromParcel(paramParcel1);; localStatus2 = null)
        {
          int k = paramParcel1.readInt();
          ParcelFileDescriptor localParcelFileDescriptor = null;
          if (k != 0) {
            localParcelFileDescriptor = (ParcelFileDescriptor)ParcelFileDescriptor.CREATOR.createFromParcel(paramParcel1);
          }
          a(localStatus2, localParcelFileDescriptor);
          return true;
        }
      case 3: 
        paramParcel1.enforceInterface("com.google.android.gms.appdatasearch.internal.ILightweightAppDataSearchCallbacks");
        int j = paramParcel1.readInt();
        Status localStatus1 = null;
        if (j != 0) {
          localStatus1 = Status.CREATOR.createFromParcel(paramParcel1);
        }
        if (paramParcel1.readInt() != 0) {}
        for (boolean bool = true;; bool = false)
        {
          a(localStatus1, bool);
          return true;
        }
      }
      paramParcel1.enforceInterface("com.google.android.gms.appdatasearch.internal.ILightweightAppDataSearchCallbacks");
      int i = paramParcel1.readInt();
      hl.b localb = null;
      if (i != 0) {
        localb = hl.b.CREATOR.q(paramParcel1);
      }
      a(localb);
      return true;
    }
    
    private static class a
      implements hv
    {
      private IBinder le;
      
      a(IBinder paramIBinder)
      {
        this.le = paramIBinder;
      }
      
      /* Error */
      public void a(Status paramStatus)
        throws RemoteException
      {
        // Byte code:
        //   0: invokestatic 25	android/os/Parcel:obtain	()Landroid/os/Parcel;
        //   3: astore_2
        //   4: aload_2
        //   5: ldc 27
        //   7: invokevirtual 31	android/os/Parcel:writeInterfaceToken	(Ljava/lang/String;)V
        //   10: aload_1
        //   11: ifnull +33 -> 44
        //   14: aload_2
        //   15: iconst_1
        //   16: invokevirtual 35	android/os/Parcel:writeInt	(I)V
        //   19: aload_1
        //   20: aload_2
        //   21: iconst_0
        //   22: invokevirtual 41	com/google/android/gms/common/api/Status:writeToParcel	(Landroid/os/Parcel;I)V
        //   25: aload_0
        //   26: getfield 15	com/google/android/gms/internal/hv$a$a:le	Landroid/os/IBinder;
        //   29: iconst_1
        //   30: aload_2
        //   31: aconst_null
        //   32: iconst_1
        //   33: invokeinterface 47 5 0
        //   38: pop
        //   39: aload_2
        //   40: invokevirtual 50	android/os/Parcel:recycle	()V
        //   43: return
        //   44: aload_2
        //   45: iconst_0
        //   46: invokevirtual 35	android/os/Parcel:writeInt	(I)V
        //   49: goto -24 -> 25
        //   52: astore_3
        //   53: aload_2
        //   54: invokevirtual 50	android/os/Parcel:recycle	()V
        //   57: aload_3
        //   58: athrow
        // Local variable table:
        //   start	length	slot	name	signature
        //   0	59	0	this	a
        //   0	59	1	paramStatus	Status
        //   3	51	2	localParcel	Parcel
        //   52	6	3	localObject	Object
        // Exception table:
        //   from	to	target	type
        //   4	10	52	finally
        //   14	25	52	finally
        //   25	39	52	finally
        //   44	49	52	finally
      }
      
      public void a(Status paramStatus, ParcelFileDescriptor paramParcelFileDescriptor)
        throws RemoteException
      {
        Parcel localParcel = Parcel.obtain();
        for (;;)
        {
          try
          {
            localParcel.writeInterfaceToken("com.google.android.gms.appdatasearch.internal.ILightweightAppDataSearchCallbacks");
            if (paramStatus != null)
            {
              localParcel.writeInt(1);
              paramStatus.writeToParcel(localParcel, 0);
              if (paramParcelFileDescriptor != null)
              {
                localParcel.writeInt(1);
                paramParcelFileDescriptor.writeToParcel(localParcel, 0);
                this.le.transact(2, localParcel, null, 1);
              }
            }
            else
            {
              localParcel.writeInt(0);
              continue;
            }
            localParcel.writeInt(0);
          }
          finally
          {
            localParcel.recycle();
          }
        }
      }
      
      public void a(Status paramStatus, boolean paramBoolean)
        throws RemoteException
      {
        int i = 1;
        Parcel localParcel = Parcel.obtain();
        for (;;)
        {
          try
          {
            localParcel.writeInterfaceToken("com.google.android.gms.appdatasearch.internal.ILightweightAppDataSearchCallbacks");
            if (paramStatus != null)
            {
              localParcel.writeInt(1);
              paramStatus.writeToParcel(localParcel, 0);
              break label85;
              localParcel.writeInt(i);
              this.le.transact(3, localParcel, null, 1);
            }
            else
            {
              localParcel.writeInt(0);
            }
          }
          finally
          {
            localParcel.recycle();
          }
          label85:
          while (!paramBoolean)
          {
            i = 0;
            break;
          }
        }
      }
      
      /* Error */
      public void a(hl.b paramb)
        throws RemoteException
      {
        // Byte code:
        //   0: invokestatic 25	android/os/Parcel:obtain	()Landroid/os/Parcel;
        //   3: astore_2
        //   4: aload_2
        //   5: ldc 27
        //   7: invokevirtual 31	android/os/Parcel:writeInterfaceToken	(Ljava/lang/String;)V
        //   10: aload_1
        //   11: ifnull +33 -> 44
        //   14: aload_2
        //   15: iconst_1
        //   16: invokevirtual 35	android/os/Parcel:writeInt	(I)V
        //   19: aload_1
        //   20: aload_2
        //   21: iconst_0
        //   22: invokevirtual 59	com/google/android/gms/internal/hl$b:writeToParcel	(Landroid/os/Parcel;I)V
        //   25: aload_0
        //   26: getfield 15	com/google/android/gms/internal/hv$a$a:le	Landroid/os/IBinder;
        //   29: iconst_4
        //   30: aload_2
        //   31: aconst_null
        //   32: iconst_1
        //   33: invokeinterface 47 5 0
        //   38: pop
        //   39: aload_2
        //   40: invokevirtual 50	android/os/Parcel:recycle	()V
        //   43: return
        //   44: aload_2
        //   45: iconst_0
        //   46: invokevirtual 35	android/os/Parcel:writeInt	(I)V
        //   49: goto -24 -> 25
        //   52: astore_3
        //   53: aload_2
        //   54: invokevirtual 50	android/os/Parcel:recycle	()V
        //   57: aload_3
        //   58: athrow
        // Local variable table:
        //   start	length	slot	name	signature
        //   0	59	0	this	a
        //   0	59	1	paramb	hl.b
        //   3	51	2	localParcel	Parcel
        //   52	6	3	localObject	Object
        // Exception table:
        //   from	to	target	type
        //   4	10	52	finally
        //   14	25	52	finally
        //   25	39	52	finally
        //   44	49	52	finally
      }
      
      public IBinder asBinder()
      {
        return this.le;
      }
    }
  }
}


/* Location:           C:\Users\TGKIM\Downloads\작업폴더\리버싱\androidReversetools\jd-gui-0.3.6.windows\com.appg.golfmon-1-dex2jar.jar
 * Qualified Name:     com.google.android.gms.internal.hv
 * JD-Core Version:    0.7.0.1
 */