package com.google.android.gms.internal;

import android.app.PendingIntent;
import android.os.Binder;
import android.os.IBinder;
import android.os.IInterface;
import android.os.Parcel;
import android.os.Parcelable.Creator;
import android.os.RemoteException;

public abstract interface ih
  extends IInterface
{
  public abstract void a(int paramInt, String paramString, PendingIntent paramPendingIntent)
    throws RemoteException;
  
  public abstract void a(if paramif)
    throws RemoteException;
  
  public static abstract class a
    extends Binder
    implements ih
  {
    public a()
    {
      attachInterface(this, "com.google.android.gms.auth.api.IGoogleAuthApiCallbacks");
    }
    
    public static ih K(IBinder paramIBinder)
    {
      if (paramIBinder == null) {
        return null;
      }
      IInterface localIInterface = paramIBinder.queryLocalInterface("com.google.android.gms.auth.api.IGoogleAuthApiCallbacks");
      if ((localIInterface != null) && ((localIInterface instanceof ih))) {
        return (ih)localIInterface;
      }
      return new a(paramIBinder);
    }
    
    public IBinder asBinder()
    {
      return this;
    }
    
    public boolean onTransact(int paramInt1, Parcel paramParcel1, Parcel paramParcel2, int paramInt2)
      throws RemoteException
    {
      switch (paramInt1)
      {
      default: 
        return super.onTransact(paramInt1, paramParcel1, paramParcel2, paramInt2);
      case 1598968902: 
        paramParcel2.writeString("com.google.android.gms.auth.api.IGoogleAuthApiCallbacks");
        return true;
      case 1: 
        paramParcel1.enforceInterface("com.google.android.gms.auth.api.IGoogleAuthApiCallbacks");
        int k = paramParcel1.readInt();
        if localif = null;
        if (k != 0) {
          localif = if.CREATOR.t(paramParcel1);
        }
        a(localif);
        paramParcel2.writeNoException();
        return true;
      }
      paramParcel1.enforceInterface("com.google.android.gms.auth.api.IGoogleAuthApiCallbacks");
      int i = paramParcel1.readInt();
      String str = paramParcel1.readString();
      int j = paramParcel1.readInt();
      PendingIntent localPendingIntent = null;
      if (j != 0) {
        localPendingIntent = (PendingIntent)PendingIntent.CREATOR.createFromParcel(paramParcel1);
      }
      a(i, str, localPendingIntent);
      paramParcel2.writeNoException();
      return true;
    }
    
    private static class a
      implements ih
    {
      private IBinder le;
      
      a(IBinder paramIBinder)
      {
        this.le = paramIBinder;
      }
      
      /* Error */
      public void a(int paramInt, String paramString, PendingIntent paramPendingIntent)
        throws RemoteException
      {
        // Byte code:
        //   0: invokestatic 25	android/os/Parcel:obtain	()Landroid/os/Parcel;
        //   3: astore 4
        //   5: invokestatic 25	android/os/Parcel:obtain	()Landroid/os/Parcel;
        //   8: astore 5
        //   10: aload 4
        //   12: ldc 27
        //   14: invokevirtual 31	android/os/Parcel:writeInterfaceToken	(Ljava/lang/String;)V
        //   17: aload 4
        //   19: iload_1
        //   20: invokevirtual 35	android/os/Parcel:writeInt	(I)V
        //   23: aload 4
        //   25: aload_2
        //   26: invokevirtual 38	android/os/Parcel:writeString	(Ljava/lang/String;)V
        //   29: aload_3
        //   30: ifnull +48 -> 78
        //   33: aload 4
        //   35: iconst_1
        //   36: invokevirtual 35	android/os/Parcel:writeInt	(I)V
        //   39: aload_3
        //   40: aload 4
        //   42: iconst_0
        //   43: invokevirtual 44	android/app/PendingIntent:writeToParcel	(Landroid/os/Parcel;I)V
        //   46: aload_0
        //   47: getfield 15	com/google/android/gms/internal/ih$a$a:le	Landroid/os/IBinder;
        //   50: iconst_2
        //   51: aload 4
        //   53: aload 5
        //   55: iconst_0
        //   56: invokeinterface 50 5 0
        //   61: pop
        //   62: aload 5
        //   64: invokevirtual 53	android/os/Parcel:readException	()V
        //   67: aload 5
        //   69: invokevirtual 56	android/os/Parcel:recycle	()V
        //   72: aload 4
        //   74: invokevirtual 56	android/os/Parcel:recycle	()V
        //   77: return
        //   78: aload 4
        //   80: iconst_0
        //   81: invokevirtual 35	android/os/Parcel:writeInt	(I)V
        //   84: goto -38 -> 46
        //   87: astore 6
        //   89: aload 5
        //   91: invokevirtual 56	android/os/Parcel:recycle	()V
        //   94: aload 4
        //   96: invokevirtual 56	android/os/Parcel:recycle	()V
        //   99: aload 6
        //   101: athrow
        // Local variable table:
        //   start	length	slot	name	signature
        //   0	102	0	this	a
        //   0	102	1	paramInt	int
        //   0	102	2	paramString	String
        //   0	102	3	paramPendingIntent	PendingIntent
        //   3	92	4	localParcel1	Parcel
        //   8	82	5	localParcel2	Parcel
        //   87	13	6	localObject	Object
        // Exception table:
        //   from	to	target	type
        //   10	29	87	finally
        //   33	46	87	finally
        //   46	67	87	finally
        //   78	84	87	finally
      }
      
      /* Error */
      public void a(if paramif)
        throws RemoteException
      {
        // Byte code:
        //   0: invokestatic 25	android/os/Parcel:obtain	()Landroid/os/Parcel;
        //   3: astore_2
        //   4: invokestatic 25	android/os/Parcel:obtain	()Landroid/os/Parcel;
        //   7: astore_3
        //   8: aload_2
        //   9: ldc 27
        //   11: invokevirtual 31	android/os/Parcel:writeInterfaceToken	(Ljava/lang/String;)V
        //   14: aload_1
        //   15: ifnull +41 -> 56
        //   18: aload_2
        //   19: iconst_1
        //   20: invokevirtual 35	android/os/Parcel:writeInt	(I)V
        //   23: aload_1
        //   24: aload_2
        //   25: iconst_0
        //   26: invokevirtual 60	com/google/android/gms/internal/if:writeToParcel	(Landroid/os/Parcel;I)V
        //   29: aload_0
        //   30: getfield 15	com/google/android/gms/internal/ih$a$a:le	Landroid/os/IBinder;
        //   33: iconst_1
        //   34: aload_2
        //   35: aload_3
        //   36: iconst_0
        //   37: invokeinterface 50 5 0
        //   42: pop
        //   43: aload_3
        //   44: invokevirtual 53	android/os/Parcel:readException	()V
        //   47: aload_3
        //   48: invokevirtual 56	android/os/Parcel:recycle	()V
        //   51: aload_2
        //   52: invokevirtual 56	android/os/Parcel:recycle	()V
        //   55: return
        //   56: aload_2
        //   57: iconst_0
        //   58: invokevirtual 35	android/os/Parcel:writeInt	(I)V
        //   61: goto -32 -> 29
        //   64: astore 4
        //   66: aload_3
        //   67: invokevirtual 56	android/os/Parcel:recycle	()V
        //   70: aload_2
        //   71: invokevirtual 56	android/os/Parcel:recycle	()V
        //   74: aload 4
        //   76: athrow
        // Local variable table:
        //   start	length	slot	name	signature
        //   0	77	0	this	a
        //   0	77	1	paramif	if
        //   3	68	2	localParcel1	Parcel
        //   7	60	3	localParcel2	Parcel
        //   64	11	4	localObject	Object
        // Exception table:
        //   from	to	target	type
        //   8	14	64	finally
        //   18	29	64	finally
        //   29	47	64	finally
        //   56	61	64	finally
      }
      
      public IBinder asBinder()
      {
        return this.le;
      }
    }
  }
}


/* Location:           C:\Users\TGKIM\Downloads\작업폴더\리버싱\androidReversetools\jd-gui-0.3.6.windows\com.appg.golfmon-1-dex2jar.jar
 * Qualified Name:     com.google.android.gms.internal.ih
 * JD-Core Version:    0.7.0.1
 */