package com.google.android.gms.internal;

import android.os.Binder;
import android.os.IBinder;
import android.os.IInterface;
import android.os.Parcel;
import android.os.Parcelable.Creator;
import android.os.RemoteException;
import com.google.android.gms.fitness.result.SessionStopResult;

public abstract interface mc
  extends IInterface
{
  public abstract void a(SessionStopResult paramSessionStopResult)
    throws RemoteException;
  
  public static abstract class a
    extends Binder
    implements mc
  {
    public a()
    {
      attachInterface(this, "com.google.android.gms.fitness.internal.ISessionStopCallback");
    }
    
    public static mc ay(IBinder paramIBinder)
    {
      if (paramIBinder == null) {
        return null;
      }
      IInterface localIInterface = paramIBinder.queryLocalInterface("com.google.android.gms.fitness.internal.ISessionStopCallback");
      if ((localIInterface != null) && ((localIInterface instanceof mc))) {
        return (mc)localIInterface;
      }
      return new a(paramIBinder);
    }
    
    public IBinder asBinder()
    {
      return this;
    }
    
    public boolean onTransact(int paramInt1, Parcel paramParcel1, Parcel paramParcel2, int paramInt2)
      throws RemoteException
    {
      switch (paramInt1)
      {
      default: 
        return super.onTransact(paramInt1, paramParcel1, paramParcel2, paramInt2);
      case 1598968902: 
        paramParcel2.writeString("com.google.android.gms.fitness.internal.ISessionStopCallback");
        return true;
      }
      paramParcel1.enforceInterface("com.google.android.gms.fitness.internal.ISessionStopCallback");
      if (paramParcel1.readInt() != 0) {}
      for (SessionStopResult localSessionStopResult = (SessionStopResult)SessionStopResult.CREATOR.createFromParcel(paramParcel1);; localSessionStopResult = null)
      {
        a(localSessionStopResult);
        paramParcel2.writeNoException();
        return true;
      }
    }
    
    private static class a
      implements mc
    {
      private IBinder le;
      
      a(IBinder paramIBinder)
      {
        this.le = paramIBinder;
      }
      
      /* Error */
      public void a(SessionStopResult paramSessionStopResult)
        throws RemoteException
      {
        // Byte code:
        //   0: invokestatic 25	android/os/Parcel:obtain	()Landroid/os/Parcel;
        //   3: astore_2
        //   4: invokestatic 25	android/os/Parcel:obtain	()Landroid/os/Parcel;
        //   7: astore_3
        //   8: aload_2
        //   9: ldc 27
        //   11: invokevirtual 31	android/os/Parcel:writeInterfaceToken	(Ljava/lang/String;)V
        //   14: aload_1
        //   15: ifnull +41 -> 56
        //   18: aload_2
        //   19: iconst_1
        //   20: invokevirtual 35	android/os/Parcel:writeInt	(I)V
        //   23: aload_1
        //   24: aload_2
        //   25: iconst_0
        //   26: invokevirtual 41	com/google/android/gms/fitness/result/SessionStopResult:writeToParcel	(Landroid/os/Parcel;I)V
        //   29: aload_0
        //   30: getfield 15	com/google/android/gms/internal/mc$a$a:le	Landroid/os/IBinder;
        //   33: iconst_1
        //   34: aload_2
        //   35: aload_3
        //   36: iconst_0
        //   37: invokeinterface 47 5 0
        //   42: pop
        //   43: aload_3
        //   44: invokevirtual 50	android/os/Parcel:readException	()V
        //   47: aload_3
        //   48: invokevirtual 53	android/os/Parcel:recycle	()V
        //   51: aload_2
        //   52: invokevirtual 53	android/os/Parcel:recycle	()V
        //   55: return
        //   56: aload_2
        //   57: iconst_0
        //   58: invokevirtual 35	android/os/Parcel:writeInt	(I)V
        //   61: goto -32 -> 29
        //   64: astore 4
        //   66: aload_3
        //   67: invokevirtual 53	android/os/Parcel:recycle	()V
        //   70: aload_2
        //   71: invokevirtual 53	android/os/Parcel:recycle	()V
        //   74: aload 4
        //   76: athrow
        // Local variable table:
        //   start	length	slot	name	signature
        //   0	77	0	this	a
        //   0	77	1	paramSessionStopResult	SessionStopResult
        //   3	68	2	localParcel1	Parcel
        //   7	60	3	localParcel2	Parcel
        //   64	11	4	localObject	Object
        // Exception table:
        //   from	to	target	type
        //   8	14	64	finally
        //   18	29	64	finally
        //   29	47	64	finally
        //   56	61	64	finally
      }
      
      public IBinder asBinder()
      {
        return this.le;
      }
    }
  }
}


/* Location:           C:\Users\TGKIM\Downloads\작업폴더\리버싱\androidReversetools\jd-gui-0.3.6.windows\com.appg.golfmon-1-dex2jar.jar
 * Qualified Name:     com.google.android.gms.internal.mc
 * JD-Core Version:    0.7.0.1
 */