package com.google.android.gms.internal;

import android.content.Intent;
import android.os.Binder;
import android.os.Bundle;
import android.os.IBinder;
import android.os.IInterface;
import android.os.Parcel;
import android.os.Parcelable.Creator;
import android.os.RemoteException;
import com.google.android.gms.dynamic.d;
import com.google.android.gms.dynamic.d.a;
import com.google.android.gms.wallet.MaskedWallet;
import com.google.android.gms.wallet.MaskedWalletRequest;
import com.google.android.gms.wallet.fragment.WalletFragmentInitParams;
import com.google.android.gms.wallet.fragment.WalletFragmentOptions;

public abstract interface qa
  extends IInterface
{
  public abstract void a(d paramd, WalletFragmentOptions paramWalletFragmentOptions, Bundle paramBundle)
    throws RemoteException;
  
  public abstract int getState()
    throws RemoteException;
  
  public abstract void initialize(WalletFragmentInitParams paramWalletFragmentInitParams)
    throws RemoteException;
  
  public abstract void onActivityResult(int paramInt1, int paramInt2, Intent paramIntent)
    throws RemoteException;
  
  public abstract void onCreate(Bundle paramBundle)
    throws RemoteException;
  
  public abstract d onCreateView(d paramd1, d paramd2, Bundle paramBundle)
    throws RemoteException;
  
  public abstract void onPause()
    throws RemoteException;
  
  public abstract void onResume()
    throws RemoteException;
  
  public abstract void onSaveInstanceState(Bundle paramBundle)
    throws RemoteException;
  
  public abstract void onStart()
    throws RemoteException;
  
  public abstract void onStop()
    throws RemoteException;
  
  public abstract void setEnabled(boolean paramBoolean)
    throws RemoteException;
  
  public abstract void updateMaskedWallet(MaskedWallet paramMaskedWallet)
    throws RemoteException;
  
  public abstract void updateMaskedWalletRequest(MaskedWalletRequest paramMaskedWalletRequest)
    throws RemoteException;
  
  public static abstract class a
    extends Binder
    implements qa
  {
    public static qa bP(IBinder paramIBinder)
    {
      if (paramIBinder == null) {
        return null;
      }
      IInterface localIInterface = paramIBinder.queryLocalInterface("com.google.android.gms.wallet.fragment.internal.IWalletFragmentDelegate");
      if ((localIInterface != null) && ((localIInterface instanceof qa))) {
        return (qa)localIInterface;
      }
      return new a(paramIBinder);
    }
    
    public boolean onTransact(int paramInt1, Parcel paramParcel1, Parcel paramParcel2, int paramInt2)
      throws RemoteException
    {
      switch (paramInt1)
      {
      default: 
        return super.onTransact(paramInt1, paramParcel1, paramParcel2, paramInt2);
      case 1598968902: 
        paramParcel2.writeString("com.google.android.gms.wallet.fragment.internal.IWalletFragmentDelegate");
        return true;
      case 1: 
        paramParcel1.enforceInterface("com.google.android.gms.wallet.fragment.internal.IWalletFragmentDelegate");
        d locald4 = d.a.ap(paramParcel1.readStrongBinder());
        WalletFragmentOptions localWalletFragmentOptions;
        if (paramParcel1.readInt() != 0)
        {
          localWalletFragmentOptions = (WalletFragmentOptions)WalletFragmentOptions.CREATOR.createFromParcel(paramParcel1);
          if (paramParcel1.readInt() == 0) {
            break label229;
          }
        }
        for (Bundle localBundle4 = (Bundle)Bundle.CREATOR.createFromParcel(paramParcel1);; localBundle4 = null)
        {
          a(locald4, localWalletFragmentOptions, localBundle4);
          paramParcel2.writeNoException();
          return true;
          localWalletFragmentOptions = null;
          break;
        }
      case 2: 
        paramParcel1.enforceInterface("com.google.android.gms.wallet.fragment.internal.IWalletFragmentDelegate");
        if (paramParcel1.readInt() != 0) {}
        for (Bundle localBundle3 = (Bundle)Bundle.CREATOR.createFromParcel(paramParcel1);; localBundle3 = null)
        {
          onCreate(localBundle3);
          paramParcel2.writeNoException();
          return true;
        }
      case 3: 
        paramParcel1.enforceInterface("com.google.android.gms.wallet.fragment.internal.IWalletFragmentDelegate");
        d locald1 = d.a.ap(paramParcel1.readStrongBinder());
        d locald2 = d.a.ap(paramParcel1.readStrongBinder());
        if (paramParcel1.readInt() != 0) {}
        for (Bundle localBundle2 = (Bundle)Bundle.CREATOR.createFromParcel(paramParcel1);; localBundle2 = null)
        {
          d locald3 = onCreateView(locald1, locald2, localBundle2);
          paramParcel2.writeNoException();
          IBinder localIBinder = null;
          if (locald3 != null) {
            localIBinder = locald3.asBinder();
          }
          paramParcel2.writeStrongBinder(localIBinder);
          return true;
        }
      case 4: 
        paramParcel1.enforceInterface("com.google.android.gms.wallet.fragment.internal.IWalletFragmentDelegate");
        onStart();
        paramParcel2.writeNoException();
        return true;
      case 5: 
        paramParcel1.enforceInterface("com.google.android.gms.wallet.fragment.internal.IWalletFragmentDelegate");
        onResume();
        paramParcel2.writeNoException();
        return true;
      case 6: 
        paramParcel1.enforceInterface("com.google.android.gms.wallet.fragment.internal.IWalletFragmentDelegate");
        onPause();
        paramParcel2.writeNoException();
        return true;
      case 7: 
        paramParcel1.enforceInterface("com.google.android.gms.wallet.fragment.internal.IWalletFragmentDelegate");
        onStop();
        paramParcel2.writeNoException();
        return true;
      case 8: 
        paramParcel1.enforceInterface("com.google.android.gms.wallet.fragment.internal.IWalletFragmentDelegate");
        if (paramParcel1.readInt() != 0) {}
        for (Bundle localBundle1 = (Bundle)Bundle.CREATOR.createFromParcel(paramParcel1);; localBundle1 = null)
        {
          onSaveInstanceState(localBundle1);
          paramParcel2.writeNoException();
          if (localBundle1 == null) {
            break;
          }
          paramParcel2.writeInt(1);
          localBundle1.writeToParcel(paramParcel2, 1);
          return true;
        }
        paramParcel2.writeInt(0);
        return true;
      case 9: 
        paramParcel1.enforceInterface("com.google.android.gms.wallet.fragment.internal.IWalletFragmentDelegate");
        int j = paramParcel1.readInt();
        int k = paramParcel1.readInt();
        if (paramParcel1.readInt() != 0) {}
        for (Intent localIntent = (Intent)Intent.CREATOR.createFromParcel(paramParcel1);; localIntent = null)
        {
          onActivityResult(j, k, localIntent);
          paramParcel2.writeNoException();
          return true;
        }
      case 10: 
        paramParcel1.enforceInterface("com.google.android.gms.wallet.fragment.internal.IWalletFragmentDelegate");
        if (paramParcel1.readInt() != 0) {}
        for (WalletFragmentInitParams localWalletFragmentInitParams = (WalletFragmentInitParams)WalletFragmentInitParams.CREATOR.createFromParcel(paramParcel1);; localWalletFragmentInitParams = null)
        {
          initialize(localWalletFragmentInitParams);
          paramParcel2.writeNoException();
          return true;
        }
      case 11: 
        paramParcel1.enforceInterface("com.google.android.gms.wallet.fragment.internal.IWalletFragmentDelegate");
        if (paramParcel1.readInt() != 0) {}
        for (MaskedWalletRequest localMaskedWalletRequest = (MaskedWalletRequest)MaskedWalletRequest.CREATOR.createFromParcel(paramParcel1);; localMaskedWalletRequest = null)
        {
          updateMaskedWalletRequest(localMaskedWalletRequest);
          paramParcel2.writeNoException();
          return true;
        }
      case 12: 
        paramParcel1.enforceInterface("com.google.android.gms.wallet.fragment.internal.IWalletFragmentDelegate");
        if (paramParcel1.readInt() != 0) {}
        for (boolean bool = true;; bool = false)
        {
          setEnabled(bool);
          paramParcel2.writeNoException();
          return true;
        }
      case 13: 
        label229:
        paramParcel1.enforceInterface("com.google.android.gms.wallet.fragment.internal.IWalletFragmentDelegate");
        int i = getState();
        paramParcel2.writeNoException();
        paramParcel2.writeInt(i);
        return true;
      }
      paramParcel1.enforceInterface("com.google.android.gms.wallet.fragment.internal.IWalletFragmentDelegate");
      if (paramParcel1.readInt() != 0) {}
      for (MaskedWallet localMaskedWallet = (MaskedWallet)MaskedWallet.CREATOR.createFromParcel(paramParcel1);; localMaskedWallet = null)
      {
        updateMaskedWallet(localMaskedWallet);
        paramParcel2.writeNoException();
        return true;
      }
    }
    
    private static class a
      implements qa
    {
      private IBinder le;
      
      a(IBinder paramIBinder)
      {
        this.le = paramIBinder;
      }
      
      public void a(d paramd, WalletFragmentOptions paramWalletFragmentOptions, Bundle paramBundle)
        throws RemoteException
      {
        Parcel localParcel1 = Parcel.obtain();
        Parcel localParcel2 = Parcel.obtain();
        label132:
        for (;;)
        {
          try
          {
            localParcel1.writeInterfaceToken("com.google.android.gms.wallet.fragment.internal.IWalletFragmentDelegate");
            IBinder localIBinder;
            if (paramd != null)
            {
              localIBinder = paramd.asBinder();
              localParcel1.writeStrongBinder(localIBinder);
              if (paramWalletFragmentOptions != null)
              {
                localParcel1.writeInt(1);
                paramWalletFragmentOptions.writeToParcel(localParcel1, 0);
                if (paramBundle == null) {
                  break label132;
                }
                localParcel1.writeInt(1);
                paramBundle.writeToParcel(localParcel1, 0);
                this.le.transact(1, localParcel1, localParcel2, 0);
                localParcel2.readException();
              }
            }
            else
            {
              localIBinder = null;
              continue;
            }
            localParcel1.writeInt(0);
            continue;
            localParcel1.writeInt(0);
          }
          finally
          {
            localParcel2.recycle();
            localParcel1.recycle();
          }
        }
      }
      
      public IBinder asBinder()
      {
        return this.le;
      }
      
      public int getState()
        throws RemoteException
      {
        Parcel localParcel1 = Parcel.obtain();
        Parcel localParcel2 = Parcel.obtain();
        try
        {
          localParcel1.writeInterfaceToken("com.google.android.gms.wallet.fragment.internal.IWalletFragmentDelegate");
          this.le.transact(13, localParcel1, localParcel2, 0);
          localParcel2.readException();
          int i = localParcel2.readInt();
          return i;
        }
        finally
        {
          localParcel2.recycle();
          localParcel1.recycle();
        }
      }
      
      /* Error */
      public void initialize(WalletFragmentInitParams paramWalletFragmentInitParams)
        throws RemoteException
      {
        // Byte code:
        //   0: invokestatic 25	android/os/Parcel:obtain	()Landroid/os/Parcel;
        //   3: astore_2
        //   4: invokestatic 25	android/os/Parcel:obtain	()Landroid/os/Parcel;
        //   7: astore_3
        //   8: aload_2
        //   9: ldc 27
        //   11: invokevirtual 31	android/os/Parcel:writeInterfaceToken	(Ljava/lang/String;)V
        //   14: aload_1
        //   15: ifnull +42 -> 57
        //   18: aload_2
        //   19: iconst_1
        //   20: invokevirtual 44	android/os/Parcel:writeInt	(I)V
        //   23: aload_1
        //   24: aload_2
        //   25: iconst_0
        //   26: invokevirtual 75	com/google/android/gms/wallet/fragment/WalletFragmentInitParams:writeToParcel	(Landroid/os/Parcel;I)V
        //   29: aload_0
        //   30: getfield 15	com/google/android/gms/internal/qa$a$a:le	Landroid/os/IBinder;
        //   33: bipush 10
        //   35: aload_2
        //   36: aload_3
        //   37: iconst_0
        //   38: invokeinterface 59 5 0
        //   43: pop
        //   44: aload_3
        //   45: invokevirtual 62	android/os/Parcel:readException	()V
        //   48: aload_3
        //   49: invokevirtual 65	android/os/Parcel:recycle	()V
        //   52: aload_2
        //   53: invokevirtual 65	android/os/Parcel:recycle	()V
        //   56: return
        //   57: aload_2
        //   58: iconst_0
        //   59: invokevirtual 44	android/os/Parcel:writeInt	(I)V
        //   62: goto -33 -> 29
        //   65: astore 4
        //   67: aload_3
        //   68: invokevirtual 65	android/os/Parcel:recycle	()V
        //   71: aload_2
        //   72: invokevirtual 65	android/os/Parcel:recycle	()V
        //   75: aload 4
        //   77: athrow
        // Local variable table:
        //   start	length	slot	name	signature
        //   0	78	0	this	a
        //   0	78	1	paramWalletFragmentInitParams	WalletFragmentInitParams
        //   3	69	2	localParcel1	Parcel
        //   7	61	3	localParcel2	Parcel
        //   65	11	4	localObject	Object
        // Exception table:
        //   from	to	target	type
        //   8	14	65	finally
        //   18	29	65	finally
        //   29	48	65	finally
        //   57	62	65	finally
      }
      
      /* Error */
      public void onActivityResult(int paramInt1, int paramInt2, Intent paramIntent)
        throws RemoteException
      {
        // Byte code:
        //   0: invokestatic 25	android/os/Parcel:obtain	()Landroid/os/Parcel;
        //   3: astore 4
        //   5: invokestatic 25	android/os/Parcel:obtain	()Landroid/os/Parcel;
        //   8: astore 5
        //   10: aload 4
        //   12: ldc 27
        //   14: invokevirtual 31	android/os/Parcel:writeInterfaceToken	(Ljava/lang/String;)V
        //   17: aload 4
        //   19: iload_1
        //   20: invokevirtual 44	android/os/Parcel:writeInt	(I)V
        //   23: aload 4
        //   25: iload_2
        //   26: invokevirtual 44	android/os/Parcel:writeInt	(I)V
        //   29: aload_3
        //   30: ifnull +49 -> 79
        //   33: aload 4
        //   35: iconst_1
        //   36: invokevirtual 44	android/os/Parcel:writeInt	(I)V
        //   39: aload_3
        //   40: aload 4
        //   42: iconst_0
        //   43: invokevirtual 80	android/content/Intent:writeToParcel	(Landroid/os/Parcel;I)V
        //   46: aload_0
        //   47: getfield 15	com/google/android/gms/internal/qa$a$a:le	Landroid/os/IBinder;
        //   50: bipush 9
        //   52: aload 4
        //   54: aload 5
        //   56: iconst_0
        //   57: invokeinterface 59 5 0
        //   62: pop
        //   63: aload 5
        //   65: invokevirtual 62	android/os/Parcel:readException	()V
        //   68: aload 5
        //   70: invokevirtual 65	android/os/Parcel:recycle	()V
        //   73: aload 4
        //   75: invokevirtual 65	android/os/Parcel:recycle	()V
        //   78: return
        //   79: aload 4
        //   81: iconst_0
        //   82: invokevirtual 44	android/os/Parcel:writeInt	(I)V
        //   85: goto -39 -> 46
        //   88: astore 6
        //   90: aload 5
        //   92: invokevirtual 65	android/os/Parcel:recycle	()V
        //   95: aload 4
        //   97: invokevirtual 65	android/os/Parcel:recycle	()V
        //   100: aload 6
        //   102: athrow
        // Local variable table:
        //   start	length	slot	name	signature
        //   0	103	0	this	a
        //   0	103	1	paramInt1	int
        //   0	103	2	paramInt2	int
        //   0	103	3	paramIntent	Intent
        //   3	93	4	localParcel1	Parcel
        //   8	83	5	localParcel2	Parcel
        //   88	13	6	localObject	Object
        // Exception table:
        //   from	to	target	type
        //   10	29	88	finally
        //   33	46	88	finally
        //   46	68	88	finally
        //   79	85	88	finally
      }
      
      /* Error */
      public void onCreate(Bundle paramBundle)
        throws RemoteException
      {
        // Byte code:
        //   0: invokestatic 25	android/os/Parcel:obtain	()Landroid/os/Parcel;
        //   3: astore_2
        //   4: invokestatic 25	android/os/Parcel:obtain	()Landroid/os/Parcel;
        //   7: astore_3
        //   8: aload_2
        //   9: ldc 27
        //   11: invokevirtual 31	android/os/Parcel:writeInterfaceToken	(Ljava/lang/String;)V
        //   14: aload_1
        //   15: ifnull +41 -> 56
        //   18: aload_2
        //   19: iconst_1
        //   20: invokevirtual 44	android/os/Parcel:writeInt	(I)V
        //   23: aload_1
        //   24: aload_2
        //   25: iconst_0
        //   26: invokevirtual 53	android/os/Bundle:writeToParcel	(Landroid/os/Parcel;I)V
        //   29: aload_0
        //   30: getfield 15	com/google/android/gms/internal/qa$a$a:le	Landroid/os/IBinder;
        //   33: iconst_2
        //   34: aload_2
        //   35: aload_3
        //   36: iconst_0
        //   37: invokeinterface 59 5 0
        //   42: pop
        //   43: aload_3
        //   44: invokevirtual 62	android/os/Parcel:readException	()V
        //   47: aload_3
        //   48: invokevirtual 65	android/os/Parcel:recycle	()V
        //   51: aload_2
        //   52: invokevirtual 65	android/os/Parcel:recycle	()V
        //   55: return
        //   56: aload_2
        //   57: iconst_0
        //   58: invokevirtual 44	android/os/Parcel:writeInt	(I)V
        //   61: goto -32 -> 29
        //   64: astore 4
        //   66: aload_3
        //   67: invokevirtual 65	android/os/Parcel:recycle	()V
        //   70: aload_2
        //   71: invokevirtual 65	android/os/Parcel:recycle	()V
        //   74: aload 4
        //   76: athrow
        // Local variable table:
        //   start	length	slot	name	signature
        //   0	77	0	this	a
        //   0	77	1	paramBundle	Bundle
        //   3	68	2	localParcel1	Parcel
        //   7	60	3	localParcel2	Parcel
        //   64	11	4	localObject	Object
        // Exception table:
        //   from	to	target	type
        //   8	14	64	finally
        //   18	29	64	finally
        //   29	47	64	finally
        //   56	61	64	finally
      }
      
      /* Error */
      public d onCreateView(d paramd1, d paramd2, Bundle paramBundle)
        throws RemoteException
      {
        // Byte code:
        //   0: invokestatic 25	android/os/Parcel:obtain	()Landroid/os/Parcel;
        //   3: astore 4
        //   5: invokestatic 25	android/os/Parcel:obtain	()Landroid/os/Parcel;
        //   8: astore 5
        //   10: aload 4
        //   12: ldc 27
        //   14: invokevirtual 31	android/os/Parcel:writeInterfaceToken	(Ljava/lang/String;)V
        //   17: aload_1
        //   18: ifnull +101 -> 119
        //   21: aload_1
        //   22: invokeinterface 37 1 0
        //   27: astore 7
        //   29: aload 4
        //   31: aload 7
        //   33: invokevirtual 40	android/os/Parcel:writeStrongBinder	(Landroid/os/IBinder;)V
        //   36: aconst_null
        //   37: astore 8
        //   39: aload_2
        //   40: ifnull +11 -> 51
        //   43: aload_2
        //   44: invokeinterface 37 1 0
        //   49: astore 8
        //   51: aload 4
        //   53: aload 8
        //   55: invokevirtual 40	android/os/Parcel:writeStrongBinder	(Landroid/os/IBinder;)V
        //   58: aload_3
        //   59: ifnull +66 -> 125
        //   62: aload 4
        //   64: iconst_1
        //   65: invokevirtual 44	android/os/Parcel:writeInt	(I)V
        //   68: aload_3
        //   69: aload 4
        //   71: iconst_0
        //   72: invokevirtual 53	android/os/Bundle:writeToParcel	(Landroid/os/Parcel;I)V
        //   75: aload_0
        //   76: getfield 15	com/google/android/gms/internal/qa$a$a:le	Landroid/os/IBinder;
        //   79: iconst_3
        //   80: aload 4
        //   82: aload 5
        //   84: iconst_0
        //   85: invokeinterface 59 5 0
        //   90: pop
        //   91: aload 5
        //   93: invokevirtual 62	android/os/Parcel:readException	()V
        //   96: aload 5
        //   98: invokevirtual 87	android/os/Parcel:readStrongBinder	()Landroid/os/IBinder;
        //   101: invokestatic 93	com/google/android/gms/dynamic/d$a:ap	(Landroid/os/IBinder;)Lcom/google/android/gms/dynamic/d;
        //   104: astore 10
        //   106: aload 5
        //   108: invokevirtual 65	android/os/Parcel:recycle	()V
        //   111: aload 4
        //   113: invokevirtual 65	android/os/Parcel:recycle	()V
        //   116: aload 10
        //   118: areturn
        //   119: aconst_null
        //   120: astore 7
        //   122: goto -93 -> 29
        //   125: aload 4
        //   127: iconst_0
        //   128: invokevirtual 44	android/os/Parcel:writeInt	(I)V
        //   131: goto -56 -> 75
        //   134: astore 6
        //   136: aload 5
        //   138: invokevirtual 65	android/os/Parcel:recycle	()V
        //   141: aload 4
        //   143: invokevirtual 65	android/os/Parcel:recycle	()V
        //   146: aload 6
        //   148: athrow
        // Local variable table:
        //   start	length	slot	name	signature
        //   0	149	0	this	a
        //   0	149	1	paramd1	d
        //   0	149	2	paramd2	d
        //   0	149	3	paramBundle	Bundle
        //   3	139	4	localParcel1	Parcel
        //   8	129	5	localParcel2	Parcel
        //   134	13	6	localObject	Object
        //   27	94	7	localIBinder1	IBinder
        //   37	17	8	localIBinder2	IBinder
        //   104	13	10	locald	d
        // Exception table:
        //   from	to	target	type
        //   10	17	134	finally
        //   21	29	134	finally
        //   29	36	134	finally
        //   43	51	134	finally
        //   51	58	134	finally
        //   62	75	134	finally
        //   75	106	134	finally
        //   125	131	134	finally
      }
      
      public void onPause()
        throws RemoteException
      {
        Parcel localParcel1 = Parcel.obtain();
        Parcel localParcel2 = Parcel.obtain();
        try
        {
          localParcel1.writeInterfaceToken("com.google.android.gms.wallet.fragment.internal.IWalletFragmentDelegate");
          this.le.transact(6, localParcel1, localParcel2, 0);
          localParcel2.readException();
          return;
        }
        finally
        {
          localParcel2.recycle();
          localParcel1.recycle();
        }
      }
      
      public void onResume()
        throws RemoteException
      {
        Parcel localParcel1 = Parcel.obtain();
        Parcel localParcel2 = Parcel.obtain();
        try
        {
          localParcel1.writeInterfaceToken("com.google.android.gms.wallet.fragment.internal.IWalletFragmentDelegate");
          this.le.transact(5, localParcel1, localParcel2, 0);
          localParcel2.readException();
          return;
        }
        finally
        {
          localParcel2.recycle();
          localParcel1.recycle();
        }
      }
      
      /* Error */
      public void onSaveInstanceState(Bundle paramBundle)
        throws RemoteException
      {
        // Byte code:
        //   0: invokestatic 25	android/os/Parcel:obtain	()Landroid/os/Parcel;
        //   3: astore_2
        //   4: invokestatic 25	android/os/Parcel:obtain	()Landroid/os/Parcel;
        //   7: astore_3
        //   8: aload_2
        //   9: ldc 27
        //   11: invokevirtual 31	android/os/Parcel:writeInterfaceToken	(Ljava/lang/String;)V
        //   14: aload_1
        //   15: ifnull +54 -> 69
        //   18: aload_2
        //   19: iconst_1
        //   20: invokevirtual 44	android/os/Parcel:writeInt	(I)V
        //   23: aload_1
        //   24: aload_2
        //   25: iconst_0
        //   26: invokevirtual 53	android/os/Bundle:writeToParcel	(Landroid/os/Parcel;I)V
        //   29: aload_0
        //   30: getfield 15	com/google/android/gms/internal/qa$a$a:le	Landroid/os/IBinder;
        //   33: bipush 8
        //   35: aload_2
        //   36: aload_3
        //   37: iconst_0
        //   38: invokeinterface 59 5 0
        //   43: pop
        //   44: aload_3
        //   45: invokevirtual 62	android/os/Parcel:readException	()V
        //   48: aload_3
        //   49: invokevirtual 70	android/os/Parcel:readInt	()I
        //   52: ifeq +8 -> 60
        //   55: aload_1
        //   56: aload_3
        //   57: invokevirtual 100	android/os/Bundle:readFromParcel	(Landroid/os/Parcel;)V
        //   60: aload_3
        //   61: invokevirtual 65	android/os/Parcel:recycle	()V
        //   64: aload_2
        //   65: invokevirtual 65	android/os/Parcel:recycle	()V
        //   68: return
        //   69: aload_2
        //   70: iconst_0
        //   71: invokevirtual 44	android/os/Parcel:writeInt	(I)V
        //   74: goto -45 -> 29
        //   77: astore 4
        //   79: aload_3
        //   80: invokevirtual 65	android/os/Parcel:recycle	()V
        //   83: aload_2
        //   84: invokevirtual 65	android/os/Parcel:recycle	()V
        //   87: aload 4
        //   89: athrow
        // Local variable table:
        //   start	length	slot	name	signature
        //   0	90	0	this	a
        //   0	90	1	paramBundle	Bundle
        //   3	81	2	localParcel1	Parcel
        //   7	73	3	localParcel2	Parcel
        //   77	11	4	localObject	Object
        // Exception table:
        //   from	to	target	type
        //   8	14	77	finally
        //   18	29	77	finally
        //   29	60	77	finally
        //   69	74	77	finally
      }
      
      public void onStart()
        throws RemoteException
      {
        Parcel localParcel1 = Parcel.obtain();
        Parcel localParcel2 = Parcel.obtain();
        try
        {
          localParcel1.writeInterfaceToken("com.google.android.gms.wallet.fragment.internal.IWalletFragmentDelegate");
          this.le.transact(4, localParcel1, localParcel2, 0);
          localParcel2.readException();
          return;
        }
        finally
        {
          localParcel2.recycle();
          localParcel1.recycle();
        }
      }
      
      public void onStop()
        throws RemoteException
      {
        Parcel localParcel1 = Parcel.obtain();
        Parcel localParcel2 = Parcel.obtain();
        try
        {
          localParcel1.writeInterfaceToken("com.google.android.gms.wallet.fragment.internal.IWalletFragmentDelegate");
          this.le.transact(7, localParcel1, localParcel2, 0);
          localParcel2.readException();
          return;
        }
        finally
        {
          localParcel2.recycle();
          localParcel1.recycle();
        }
      }
      
      public void setEnabled(boolean paramBoolean)
        throws RemoteException
      {
        Parcel localParcel1 = Parcel.obtain();
        Parcel localParcel2 = Parcel.obtain();
        try
        {
          localParcel1.writeInterfaceToken("com.google.android.gms.wallet.fragment.internal.IWalletFragmentDelegate");
          int i = 0;
          if (paramBoolean) {
            i = 1;
          }
          localParcel1.writeInt(i);
          this.le.transact(12, localParcel1, localParcel2, 0);
          localParcel2.readException();
          return;
        }
        finally
        {
          localParcel2.recycle();
          localParcel1.recycle();
        }
      }
      
      /* Error */
      public void updateMaskedWallet(MaskedWallet paramMaskedWallet)
        throws RemoteException
      {
        // Byte code:
        //   0: invokestatic 25	android/os/Parcel:obtain	()Landroid/os/Parcel;
        //   3: astore_2
        //   4: invokestatic 25	android/os/Parcel:obtain	()Landroid/os/Parcel;
        //   7: astore_3
        //   8: aload_2
        //   9: ldc 27
        //   11: invokevirtual 31	android/os/Parcel:writeInterfaceToken	(Ljava/lang/String;)V
        //   14: aload_1
        //   15: ifnull +42 -> 57
        //   18: aload_2
        //   19: iconst_1
        //   20: invokevirtual 44	android/os/Parcel:writeInt	(I)V
        //   23: aload_1
        //   24: aload_2
        //   25: iconst_0
        //   26: invokevirtual 109	com/google/android/gms/wallet/MaskedWallet:writeToParcel	(Landroid/os/Parcel;I)V
        //   29: aload_0
        //   30: getfield 15	com/google/android/gms/internal/qa$a$a:le	Landroid/os/IBinder;
        //   33: bipush 14
        //   35: aload_2
        //   36: aload_3
        //   37: iconst_0
        //   38: invokeinterface 59 5 0
        //   43: pop
        //   44: aload_3
        //   45: invokevirtual 62	android/os/Parcel:readException	()V
        //   48: aload_3
        //   49: invokevirtual 65	android/os/Parcel:recycle	()V
        //   52: aload_2
        //   53: invokevirtual 65	android/os/Parcel:recycle	()V
        //   56: return
        //   57: aload_2
        //   58: iconst_0
        //   59: invokevirtual 44	android/os/Parcel:writeInt	(I)V
        //   62: goto -33 -> 29
        //   65: astore 4
        //   67: aload_3
        //   68: invokevirtual 65	android/os/Parcel:recycle	()V
        //   71: aload_2
        //   72: invokevirtual 65	android/os/Parcel:recycle	()V
        //   75: aload 4
        //   77: athrow
        // Local variable table:
        //   start	length	slot	name	signature
        //   0	78	0	this	a
        //   0	78	1	paramMaskedWallet	MaskedWallet
        //   3	69	2	localParcel1	Parcel
        //   7	61	3	localParcel2	Parcel
        //   65	11	4	localObject	Object
        // Exception table:
        //   from	to	target	type
        //   8	14	65	finally
        //   18	29	65	finally
        //   29	48	65	finally
        //   57	62	65	finally
      }
      
      /* Error */
      public void updateMaskedWalletRequest(MaskedWalletRequest paramMaskedWalletRequest)
        throws RemoteException
      {
        // Byte code:
        //   0: invokestatic 25	android/os/Parcel:obtain	()Landroid/os/Parcel;
        //   3: astore_2
        //   4: invokestatic 25	android/os/Parcel:obtain	()Landroid/os/Parcel;
        //   7: astore_3
        //   8: aload_2
        //   9: ldc 27
        //   11: invokevirtual 31	android/os/Parcel:writeInterfaceToken	(Ljava/lang/String;)V
        //   14: aload_1
        //   15: ifnull +42 -> 57
        //   18: aload_2
        //   19: iconst_1
        //   20: invokevirtual 44	android/os/Parcel:writeInt	(I)V
        //   23: aload_1
        //   24: aload_2
        //   25: iconst_0
        //   26: invokevirtual 114	com/google/android/gms/wallet/MaskedWalletRequest:writeToParcel	(Landroid/os/Parcel;I)V
        //   29: aload_0
        //   30: getfield 15	com/google/android/gms/internal/qa$a$a:le	Landroid/os/IBinder;
        //   33: bipush 11
        //   35: aload_2
        //   36: aload_3
        //   37: iconst_0
        //   38: invokeinterface 59 5 0
        //   43: pop
        //   44: aload_3
        //   45: invokevirtual 62	android/os/Parcel:readException	()V
        //   48: aload_3
        //   49: invokevirtual 65	android/os/Parcel:recycle	()V
        //   52: aload_2
        //   53: invokevirtual 65	android/os/Parcel:recycle	()V
        //   56: return
        //   57: aload_2
        //   58: iconst_0
        //   59: invokevirtual 44	android/os/Parcel:writeInt	(I)V
        //   62: goto -33 -> 29
        //   65: astore 4
        //   67: aload_3
        //   68: invokevirtual 65	android/os/Parcel:recycle	()V
        //   71: aload_2
        //   72: invokevirtual 65	android/os/Parcel:recycle	()V
        //   75: aload 4
        //   77: athrow
        // Local variable table:
        //   start	length	slot	name	signature
        //   0	78	0	this	a
        //   0	78	1	paramMaskedWalletRequest	MaskedWalletRequest
        //   3	69	2	localParcel1	Parcel
        //   7	61	3	localParcel2	Parcel
        //   65	11	4	localObject	Object
        // Exception table:
        //   from	to	target	type
        //   8	14	65	finally
        //   18	29	65	finally
        //   29	48	65	finally
        //   57	62	65	finally
      }
    }
  }
}


/* Location:           C:\Users\TGKIM\Downloads\작업폴더\리버싱\androidReversetools\jd-gui-0.3.6.windows\com.appg.golfmon-1-dex2jar.jar
 * Qualified Name:     com.google.android.gms.internal.qa
 * JD-Core Version:    0.7.0.1
 */