package com.google.android.gms.internal;

import android.os.Binder;
import android.os.Bundle;
import android.os.IBinder;
import android.os.IInterface;
import android.os.Parcel;
import android.os.Parcelable.Creator;
import android.os.RemoteException;
import com.google.android.gms.common.api.Status;
import com.google.android.gms.common.api.StatusCreator;
import com.google.android.gms.wallet.FullWallet;
import com.google.android.gms.wallet.MaskedWallet;

public abstract interface qf
  extends IInterface
{
  public abstract void a(int paramInt, FullWallet paramFullWallet, Bundle paramBundle)
    throws RemoteException;
  
  public abstract void a(int paramInt, MaskedWallet paramMaskedWallet, Bundle paramBundle)
    throws RemoteException;
  
  public abstract void a(int paramInt, boolean paramBoolean, Bundle paramBundle)
    throws RemoteException;
  
  public abstract void a(Status paramStatus, py parampy, Bundle paramBundle)
    throws RemoteException;
  
  public abstract void i(int paramInt, Bundle paramBundle)
    throws RemoteException;
  
  public static abstract class a
    extends Binder
    implements qf
  {
    public a()
    {
      attachInterface(this, "com.google.android.gms.wallet.internal.IWalletServiceCallbacks");
    }
    
    public static qf bU(IBinder paramIBinder)
    {
      if (paramIBinder == null) {
        return null;
      }
      IInterface localIInterface = paramIBinder.queryLocalInterface("com.google.android.gms.wallet.internal.IWalletServiceCallbacks");
      if ((localIInterface != null) && ((localIInterface instanceof qf))) {
        return (qf)localIInterface;
      }
      return new a(paramIBinder);
    }
    
    public IBinder asBinder()
    {
      return this;
    }
    
    public boolean onTransact(int paramInt1, Parcel paramParcel1, Parcel paramParcel2, int paramInt2)
      throws RemoteException
    {
      switch (paramInt1)
      {
      default: 
        return super.onTransact(paramInt1, paramParcel1, paramParcel2, paramInt2);
      case 1598968902: 
        paramParcel2.writeString("com.google.android.gms.wallet.internal.IWalletServiceCallbacks");
        return true;
      case 1: 
        paramParcel1.enforceInterface("com.google.android.gms.wallet.internal.IWalletServiceCallbacks");
        int m = paramParcel1.readInt();
        MaskedWallet localMaskedWallet;
        if (paramParcel1.readInt() != 0)
        {
          localMaskedWallet = (MaskedWallet)MaskedWallet.CREATOR.createFromParcel(paramParcel1);
          if (paramParcel1.readInt() == 0) {
            break label154;
          }
        }
        for (Bundle localBundle5 = (Bundle)Bundle.CREATOR.createFromParcel(paramParcel1);; localBundle5 = null)
        {
          a(m, localMaskedWallet, localBundle5);
          paramParcel2.writeNoException();
          return true;
          localMaskedWallet = null;
          break;
        }
      case 2: 
        paramParcel1.enforceInterface("com.google.android.gms.wallet.internal.IWalletServiceCallbacks");
        int k = paramParcel1.readInt();
        FullWallet localFullWallet;
        if (paramParcel1.readInt() != 0)
        {
          localFullWallet = (FullWallet)FullWallet.CREATOR.createFromParcel(paramParcel1);
          if (paramParcel1.readInt() == 0) {
            break label236;
          }
        }
        for (Bundle localBundle4 = (Bundle)Bundle.CREATOR.createFromParcel(paramParcel1);; localBundle4 = null)
        {
          a(k, localFullWallet, localBundle4);
          paramParcel2.writeNoException();
          return true;
          localFullWallet = null;
          break;
        }
      case 3: 
        paramParcel1.enforceInterface("com.google.android.gms.wallet.internal.IWalletServiceCallbacks");
        int j = paramParcel1.readInt();
        boolean bool;
        if (paramParcel1.readInt() != 0)
        {
          bool = true;
          if (paramParcel1.readInt() == 0) {
            break label307;
          }
        }
        for (Bundle localBundle3 = (Bundle)Bundle.CREATOR.createFromParcel(paramParcel1);; localBundle3 = null)
        {
          a(j, bool, localBundle3);
          paramParcel2.writeNoException();
          return true;
          bool = false;
          break;
        }
      case 4: 
        label154:
        label236:
        paramParcel1.enforceInterface("com.google.android.gms.wallet.internal.IWalletServiceCallbacks");
        label307:
        int i = paramParcel1.readInt();
        if (paramParcel1.readInt() != 0) {}
        for (Bundle localBundle2 = (Bundle)Bundle.CREATOR.createFromParcel(paramParcel1);; localBundle2 = null)
        {
          i(i, localBundle2);
          paramParcel2.writeNoException();
          return true;
        }
      }
      paramParcel1.enforceInterface("com.google.android.gms.wallet.internal.IWalletServiceCallbacks");
      Status localStatus;
      py localpy;
      if (paramParcel1.readInt() != 0)
      {
        localStatus = Status.CREATOR.createFromParcel(paramParcel1);
        if (paramParcel1.readInt() == 0) {
          break label452;
        }
        localpy = (py)py.CREATOR.createFromParcel(paramParcel1);
        label409:
        if (paramParcel1.readInt() == 0) {
          break label458;
        }
      }
      label452:
      label458:
      for (Bundle localBundle1 = (Bundle)Bundle.CREATOR.createFromParcel(paramParcel1);; localBundle1 = null)
      {
        a(localStatus, localpy, localBundle1);
        paramParcel2.writeNoException();
        return true;
        localStatus = null;
        break;
        localpy = null;
        break label409;
      }
    }
    
    private static class a
      implements qf
    {
      private IBinder le;
      
      a(IBinder paramIBinder)
      {
        this.le = paramIBinder;
      }
      
      public void a(int paramInt, FullWallet paramFullWallet, Bundle paramBundle)
        throws RemoteException
      {
        Parcel localParcel1 = Parcel.obtain();
        Parcel localParcel2 = Parcel.obtain();
        for (;;)
        {
          try
          {
            localParcel1.writeInterfaceToken("com.google.android.gms.wallet.internal.IWalletServiceCallbacks");
            localParcel1.writeInt(paramInt);
            if (paramFullWallet != null)
            {
              localParcel1.writeInt(1);
              paramFullWallet.writeToParcel(localParcel1, 0);
              if (paramBundle != null)
              {
                localParcel1.writeInt(1);
                paramBundle.writeToParcel(localParcel1, 0);
                this.le.transact(2, localParcel1, localParcel2, 0);
                localParcel2.readException();
              }
            }
            else
            {
              localParcel1.writeInt(0);
              continue;
            }
            localParcel1.writeInt(0);
          }
          finally
          {
            localParcel2.recycle();
            localParcel1.recycle();
          }
        }
      }
      
      public void a(int paramInt, MaskedWallet paramMaskedWallet, Bundle paramBundle)
        throws RemoteException
      {
        Parcel localParcel1 = Parcel.obtain();
        Parcel localParcel2 = Parcel.obtain();
        for (;;)
        {
          try
          {
            localParcel1.writeInterfaceToken("com.google.android.gms.wallet.internal.IWalletServiceCallbacks");
            localParcel1.writeInt(paramInt);
            if (paramMaskedWallet != null)
            {
              localParcel1.writeInt(1);
              paramMaskedWallet.writeToParcel(localParcel1, 0);
              if (paramBundle != null)
              {
                localParcel1.writeInt(1);
                paramBundle.writeToParcel(localParcel1, 0);
                this.le.transact(1, localParcel1, localParcel2, 0);
                localParcel2.readException();
              }
            }
            else
            {
              localParcel1.writeInt(0);
              continue;
            }
            localParcel1.writeInt(0);
          }
          finally
          {
            localParcel2.recycle();
            localParcel1.recycle();
          }
        }
      }
      
      /* Error */
      public void a(int paramInt, boolean paramBoolean, Bundle paramBundle)
        throws RemoteException
      {
        // Byte code:
        //   0: iconst_1
        //   1: istore 4
        //   3: invokestatic 25	android/os/Parcel:obtain	()Landroid/os/Parcel;
        //   6: astore 5
        //   8: invokestatic 25	android/os/Parcel:obtain	()Landroid/os/Parcel;
        //   11: astore 6
        //   13: aload 5
        //   15: ldc 27
        //   17: invokevirtual 31	android/os/Parcel:writeInterfaceToken	(Ljava/lang/String;)V
        //   20: aload 5
        //   22: iload_1
        //   23: invokevirtual 35	android/os/Parcel:writeInt	(I)V
        //   26: iload_2
        //   27: ifeq +59 -> 86
        //   30: aload 5
        //   32: iload 4
        //   34: invokevirtual 35	android/os/Parcel:writeInt	(I)V
        //   37: aload_3
        //   38: ifnull +54 -> 92
        //   41: aload 5
        //   43: iconst_1
        //   44: invokevirtual 35	android/os/Parcel:writeInt	(I)V
        //   47: aload_3
        //   48: aload 5
        //   50: iconst_0
        //   51: invokevirtual 44	android/os/Bundle:writeToParcel	(Landroid/os/Parcel;I)V
        //   54: aload_0
        //   55: getfield 15	com/google/android/gms/internal/qf$a$a:le	Landroid/os/IBinder;
        //   58: iconst_3
        //   59: aload 5
        //   61: aload 6
        //   63: iconst_0
        //   64: invokeinterface 50 5 0
        //   69: pop
        //   70: aload 6
        //   72: invokevirtual 53	android/os/Parcel:readException	()V
        //   75: aload 6
        //   77: invokevirtual 56	android/os/Parcel:recycle	()V
        //   80: aload 5
        //   82: invokevirtual 56	android/os/Parcel:recycle	()V
        //   85: return
        //   86: iconst_0
        //   87: istore 4
        //   89: goto -59 -> 30
        //   92: aload 5
        //   94: iconst_0
        //   95: invokevirtual 35	android/os/Parcel:writeInt	(I)V
        //   98: goto -44 -> 54
        //   101: astore 7
        //   103: aload 6
        //   105: invokevirtual 56	android/os/Parcel:recycle	()V
        //   108: aload 5
        //   110: invokevirtual 56	android/os/Parcel:recycle	()V
        //   113: aload 7
        //   115: athrow
        // Local variable table:
        //   start	length	slot	name	signature
        //   0	116	0	this	a
        //   0	116	1	paramInt	int
        //   0	116	2	paramBoolean	boolean
        //   0	116	3	paramBundle	Bundle
        //   1	87	4	i	int
        //   6	103	5	localParcel1	Parcel
        //   11	93	6	localParcel2	Parcel
        //   101	13	7	localObject	Object
        // Exception table:
        //   from	to	target	type
        //   13	26	101	finally
        //   30	37	101	finally
        //   41	54	101	finally
        //   54	75	101	finally
        //   92	98	101	finally
      }
      
      public void a(Status paramStatus, py parampy, Bundle paramBundle)
        throws RemoteException
      {
        Parcel localParcel1 = Parcel.obtain();
        Parcel localParcel2 = Parcel.obtain();
        for (;;)
        {
          try
          {
            localParcel1.writeInterfaceToken("com.google.android.gms.wallet.internal.IWalletServiceCallbacks");
            if (paramStatus != null)
            {
              localParcel1.writeInt(1);
              paramStatus.writeToParcel(localParcel1, 0);
              if (parampy != null)
              {
                localParcel1.writeInt(1);
                parampy.writeToParcel(localParcel1, 0);
                if (paramBundle == null) {
                  break label133;
                }
                localParcel1.writeInt(1);
                paramBundle.writeToParcel(localParcel1, 0);
                this.le.transact(5, localParcel1, localParcel2, 0);
                localParcel2.readException();
              }
            }
            else
            {
              localParcel1.writeInt(0);
              continue;
            }
            localParcel1.writeInt(0);
          }
          finally
          {
            localParcel2.recycle();
            localParcel1.recycle();
          }
          continue;
          label133:
          localParcel1.writeInt(0);
        }
      }
      
      public IBinder asBinder()
      {
        return this.le;
      }
      
      /* Error */
      public void i(int paramInt, Bundle paramBundle)
        throws RemoteException
      {
        // Byte code:
        //   0: invokestatic 25	android/os/Parcel:obtain	()Landroid/os/Parcel;
        //   3: astore_3
        //   4: invokestatic 25	android/os/Parcel:obtain	()Landroid/os/Parcel;
        //   7: astore 4
        //   9: aload_3
        //   10: ldc 27
        //   12: invokevirtual 31	android/os/Parcel:writeInterfaceToken	(Ljava/lang/String;)V
        //   15: aload_3
        //   16: iload_1
        //   17: invokevirtual 35	android/os/Parcel:writeInt	(I)V
        //   20: aload_2
        //   21: ifnull +44 -> 65
        //   24: aload_3
        //   25: iconst_1
        //   26: invokevirtual 35	android/os/Parcel:writeInt	(I)V
        //   29: aload_2
        //   30: aload_3
        //   31: iconst_0
        //   32: invokevirtual 44	android/os/Bundle:writeToParcel	(Landroid/os/Parcel;I)V
        //   35: aload_0
        //   36: getfield 15	com/google/android/gms/internal/qf$a$a:le	Landroid/os/IBinder;
        //   39: iconst_4
        //   40: aload_3
        //   41: aload 4
        //   43: iconst_0
        //   44: invokeinterface 50 5 0
        //   49: pop
        //   50: aload 4
        //   52: invokevirtual 53	android/os/Parcel:readException	()V
        //   55: aload 4
        //   57: invokevirtual 56	android/os/Parcel:recycle	()V
        //   60: aload_3
        //   61: invokevirtual 56	android/os/Parcel:recycle	()V
        //   64: return
        //   65: aload_3
        //   66: iconst_0
        //   67: invokevirtual 35	android/os/Parcel:writeInt	(I)V
        //   70: goto -35 -> 35
        //   73: astore 5
        //   75: aload 4
        //   77: invokevirtual 56	android/os/Parcel:recycle	()V
        //   80: aload_3
        //   81: invokevirtual 56	android/os/Parcel:recycle	()V
        //   84: aload 5
        //   86: athrow
        // Local variable table:
        //   start	length	slot	name	signature
        //   0	87	0	this	a
        //   0	87	1	paramInt	int
        //   0	87	2	paramBundle	Bundle
        //   3	78	3	localParcel1	Parcel
        //   7	69	4	localParcel2	Parcel
        //   73	12	5	localObject	Object
        // Exception table:
        //   from	to	target	type
        //   9	20	73	finally
        //   24	35	73	finally
        //   35	55	73	finally
        //   65	70	73	finally
      }
    }
  }
}


/* Location:           C:\Users\TGKIM\Downloads\작업폴더\리버싱\androidReversetools\jd-gui-0.3.6.windows\com.appg.golfmon-1-dex2jar.jar
 * Qualified Name:     com.google.android.gms.internal.qf
 * JD-Core Version:    0.7.0.1
 */