package com.google.android.gms.drive.internal;

import android.os.Binder;
import android.os.IBinder;
import android.os.IInterface;
import android.os.Parcel;
import android.os.Parcelable.Creator;
import android.os.RemoteException;
import com.google.android.gms.common.api.Status;
import com.google.android.gms.common.api.StatusCreator;
import com.google.android.gms.drive.realtime.internal.m;
import com.google.android.gms.drive.realtime.internal.m.a;

public abstract interface af
  extends IInterface
{
  public abstract void a(OnContentsResponse paramOnContentsResponse)
    throws RemoteException;
  
  public abstract void a(OnDeviceUsagePreferenceResponse paramOnDeviceUsagePreferenceResponse)
    throws RemoteException;
  
  public abstract void a(OnDownloadProgressResponse paramOnDownloadProgressResponse)
    throws RemoteException;
  
  public abstract void a(OnDriveIdResponse paramOnDriveIdResponse)
    throws RemoteException;
  
  public abstract void a(OnDrivePreferencesResponse paramOnDrivePreferencesResponse)
    throws RemoteException;
  
  public abstract void a(OnListEntriesResponse paramOnListEntriesResponse)
    throws RemoteException;
  
  public abstract void a(OnListParentsResponse paramOnListParentsResponse)
    throws RemoteException;
  
  public abstract void a(OnLoadRealtimeResponse paramOnLoadRealtimeResponse, m paramm)
    throws RemoteException;
  
  public abstract void a(OnMetadataResponse paramOnMetadataResponse)
    throws RemoteException;
  
  public abstract void a(OnResourceIdSetResponse paramOnResourceIdSetResponse)
    throws RemoteException;
  
  public abstract void a(OnStorageStatsResponse paramOnStorageStatsResponse)
    throws RemoteException;
  
  public abstract void a(OnSyncMoreResponse paramOnSyncMoreResponse)
    throws RemoteException;
  
  public abstract void n(Status paramStatus)
    throws RemoteException;
  
  public abstract void onSuccess()
    throws RemoteException;
  
  public static abstract class a
    extends Binder
    implements af
  {
    public a()
    {
      attachInterface(this, "com.google.android.gms.drive.internal.IDriveServiceCallbacks");
    }
    
    public static af Y(IBinder paramIBinder)
    {
      if (paramIBinder == null) {
        return null;
      }
      IInterface localIInterface = paramIBinder.queryLocalInterface("com.google.android.gms.drive.internal.IDriveServiceCallbacks");
      if ((localIInterface != null) && ((localIInterface instanceof af))) {
        return (af)localIInterface;
      }
      return new a(paramIBinder);
    }
    
    public IBinder asBinder()
    {
      return this;
    }
    
    public boolean onTransact(int paramInt1, Parcel paramParcel1, Parcel paramParcel2, int paramInt2)
      throws RemoteException
    {
      switch (paramInt1)
      {
      default: 
        return super.onTransact(paramInt1, paramParcel1, paramParcel2, paramInt2);
      case 1598968902: 
        paramParcel2.writeString("com.google.android.gms.drive.internal.IDriveServiceCallbacks");
        return true;
      case 1: 
        paramParcel1.enforceInterface("com.google.android.gms.drive.internal.IDriveServiceCallbacks");
        int i8 = paramParcel1.readInt();
        OnDownloadProgressResponse localOnDownloadProgressResponse = null;
        if (i8 != 0) {
          localOnDownloadProgressResponse = (OnDownloadProgressResponse)OnDownloadProgressResponse.CREATOR.createFromParcel(paramParcel1);
        }
        a(localOnDownloadProgressResponse);
        paramParcel2.writeNoException();
        return true;
      case 2: 
        paramParcel1.enforceInterface("com.google.android.gms.drive.internal.IDriveServiceCallbacks");
        int i7 = paramParcel1.readInt();
        OnListEntriesResponse localOnListEntriesResponse = null;
        if (i7 != 0) {
          localOnListEntriesResponse = (OnListEntriesResponse)OnListEntriesResponse.CREATOR.createFromParcel(paramParcel1);
        }
        a(localOnListEntriesResponse);
        paramParcel2.writeNoException();
        return true;
      case 3: 
        paramParcel1.enforceInterface("com.google.android.gms.drive.internal.IDriveServiceCallbacks");
        int i6 = paramParcel1.readInt();
        OnDriveIdResponse localOnDriveIdResponse = null;
        if (i6 != 0) {
          localOnDriveIdResponse = (OnDriveIdResponse)OnDriveIdResponse.CREATOR.createFromParcel(paramParcel1);
        }
        a(localOnDriveIdResponse);
        paramParcel2.writeNoException();
        return true;
      case 4: 
        paramParcel1.enforceInterface("com.google.android.gms.drive.internal.IDriveServiceCallbacks");
        int i5 = paramParcel1.readInt();
        OnMetadataResponse localOnMetadataResponse = null;
        if (i5 != 0) {
          localOnMetadataResponse = (OnMetadataResponse)OnMetadataResponse.CREATOR.createFromParcel(paramParcel1);
        }
        a(localOnMetadataResponse);
        paramParcel2.writeNoException();
        return true;
      case 5: 
        paramParcel1.enforceInterface("com.google.android.gms.drive.internal.IDriveServiceCallbacks");
        int i4 = paramParcel1.readInt();
        OnContentsResponse localOnContentsResponse = null;
        if (i4 != 0) {
          localOnContentsResponse = (OnContentsResponse)OnContentsResponse.CREATOR.createFromParcel(paramParcel1);
        }
        a(localOnContentsResponse);
        paramParcel2.writeNoException();
        return true;
      case 6: 
        paramParcel1.enforceInterface("com.google.android.gms.drive.internal.IDriveServiceCallbacks");
        int i3 = paramParcel1.readInt();
        Status localStatus = null;
        if (i3 != 0) {
          localStatus = Status.CREATOR.createFromParcel(paramParcel1);
        }
        n(localStatus);
        paramParcel2.writeNoException();
        return true;
      case 7: 
        paramParcel1.enforceInterface("com.google.android.gms.drive.internal.IDriveServiceCallbacks");
        onSuccess();
        paramParcel2.writeNoException();
        return true;
      case 8: 
        paramParcel1.enforceInterface("com.google.android.gms.drive.internal.IDriveServiceCallbacks");
        int i2 = paramParcel1.readInt();
        OnListParentsResponse localOnListParentsResponse = null;
        if (i2 != 0) {
          localOnListParentsResponse = (OnListParentsResponse)OnListParentsResponse.CREATOR.createFromParcel(paramParcel1);
        }
        a(localOnListParentsResponse);
        paramParcel2.writeNoException();
        return true;
      case 9: 
        paramParcel1.enforceInterface("com.google.android.gms.drive.internal.IDriveServiceCallbacks");
        int i1 = paramParcel1.readInt();
        OnSyncMoreResponse localOnSyncMoreResponse = null;
        if (i1 != 0) {
          localOnSyncMoreResponse = (OnSyncMoreResponse)OnSyncMoreResponse.CREATOR.createFromParcel(paramParcel1);
        }
        a(localOnSyncMoreResponse);
        paramParcel2.writeNoException();
        return true;
      case 10: 
        paramParcel1.enforceInterface("com.google.android.gms.drive.internal.IDriveServiceCallbacks");
        int n = paramParcel1.readInt();
        OnStorageStatsResponse localOnStorageStatsResponse = null;
        if (n != 0) {
          localOnStorageStatsResponse = (OnStorageStatsResponse)OnStorageStatsResponse.CREATOR.createFromParcel(paramParcel1);
        }
        a(localOnStorageStatsResponse);
        paramParcel2.writeNoException();
        return true;
      case 11: 
        paramParcel1.enforceInterface("com.google.android.gms.drive.internal.IDriveServiceCallbacks");
        int m = paramParcel1.readInt();
        OnLoadRealtimeResponse localOnLoadRealtimeResponse = null;
        if (m != 0) {
          localOnLoadRealtimeResponse = (OnLoadRealtimeResponse)OnLoadRealtimeResponse.CREATOR.createFromParcel(paramParcel1);
        }
        a(localOnLoadRealtimeResponse, m.a.al(paramParcel1.readStrongBinder()));
        paramParcel2.writeNoException();
        return true;
      case 12: 
        paramParcel1.enforceInterface("com.google.android.gms.drive.internal.IDriveServiceCallbacks");
        int k = paramParcel1.readInt();
        OnResourceIdSetResponse localOnResourceIdSetResponse = null;
        if (k != 0) {
          localOnResourceIdSetResponse = (OnResourceIdSetResponse)OnResourceIdSetResponse.CREATOR.createFromParcel(paramParcel1);
        }
        a(localOnResourceIdSetResponse);
        paramParcel2.writeNoException();
        return true;
      case 13: 
        paramParcel1.enforceInterface("com.google.android.gms.drive.internal.IDriveServiceCallbacks");
        int j = paramParcel1.readInt();
        OnDrivePreferencesResponse localOnDrivePreferencesResponse = null;
        if (j != 0) {
          localOnDrivePreferencesResponse = (OnDrivePreferencesResponse)OnDrivePreferencesResponse.CREATOR.createFromParcel(paramParcel1);
        }
        a(localOnDrivePreferencesResponse);
        paramParcel2.writeNoException();
        return true;
      }
      paramParcel1.enforceInterface("com.google.android.gms.drive.internal.IDriveServiceCallbacks");
      int i = paramParcel1.readInt();
      OnDeviceUsagePreferenceResponse localOnDeviceUsagePreferenceResponse = null;
      if (i != 0) {
        localOnDeviceUsagePreferenceResponse = (OnDeviceUsagePreferenceResponse)OnDeviceUsagePreferenceResponse.CREATOR.createFromParcel(paramParcel1);
      }
      a(localOnDeviceUsagePreferenceResponse);
      paramParcel2.writeNoException();
      return true;
    }
    
    private static class a
      implements af
    {
      private IBinder le;
      
      a(IBinder paramIBinder)
      {
        this.le = paramIBinder;
      }
      
      /* Error */
      public void a(OnContentsResponse paramOnContentsResponse)
        throws RemoteException
      {
        // Byte code:
        //   0: invokestatic 25	android/os/Parcel:obtain	()Landroid/os/Parcel;
        //   3: astore_2
        //   4: invokestatic 25	android/os/Parcel:obtain	()Landroid/os/Parcel;
        //   7: astore_3
        //   8: aload_2
        //   9: ldc 27
        //   11: invokevirtual 31	android/os/Parcel:writeInterfaceToken	(Ljava/lang/String;)V
        //   14: aload_1
        //   15: ifnull +41 -> 56
        //   18: aload_2
        //   19: iconst_1
        //   20: invokevirtual 35	android/os/Parcel:writeInt	(I)V
        //   23: aload_1
        //   24: aload_2
        //   25: iconst_0
        //   26: invokevirtual 41	com/google/android/gms/drive/internal/OnContentsResponse:writeToParcel	(Landroid/os/Parcel;I)V
        //   29: aload_0
        //   30: getfield 15	com/google/android/gms/drive/internal/af$a$a:le	Landroid/os/IBinder;
        //   33: iconst_5
        //   34: aload_2
        //   35: aload_3
        //   36: iconst_0
        //   37: invokeinterface 47 5 0
        //   42: pop
        //   43: aload_3
        //   44: invokevirtual 50	android/os/Parcel:readException	()V
        //   47: aload_3
        //   48: invokevirtual 53	android/os/Parcel:recycle	()V
        //   51: aload_2
        //   52: invokevirtual 53	android/os/Parcel:recycle	()V
        //   55: return
        //   56: aload_2
        //   57: iconst_0
        //   58: invokevirtual 35	android/os/Parcel:writeInt	(I)V
        //   61: goto -32 -> 29
        //   64: astore 4
        //   66: aload_3
        //   67: invokevirtual 53	android/os/Parcel:recycle	()V
        //   70: aload_2
        //   71: invokevirtual 53	android/os/Parcel:recycle	()V
        //   74: aload 4
        //   76: athrow
        // Local variable table:
        //   start	length	slot	name	signature
        //   0	77	0	this	a
        //   0	77	1	paramOnContentsResponse	OnContentsResponse
        //   3	68	2	localParcel1	Parcel
        //   7	60	3	localParcel2	Parcel
        //   64	11	4	localObject	Object
        // Exception table:
        //   from	to	target	type
        //   8	14	64	finally
        //   18	29	64	finally
        //   29	47	64	finally
        //   56	61	64	finally
      }
      
      /* Error */
      public void a(OnDeviceUsagePreferenceResponse paramOnDeviceUsagePreferenceResponse)
        throws RemoteException
      {
        // Byte code:
        //   0: invokestatic 25	android/os/Parcel:obtain	()Landroid/os/Parcel;
        //   3: astore_2
        //   4: invokestatic 25	android/os/Parcel:obtain	()Landroid/os/Parcel;
        //   7: astore_3
        //   8: aload_2
        //   9: ldc 27
        //   11: invokevirtual 31	android/os/Parcel:writeInterfaceToken	(Ljava/lang/String;)V
        //   14: aload_1
        //   15: ifnull +42 -> 57
        //   18: aload_2
        //   19: iconst_1
        //   20: invokevirtual 35	android/os/Parcel:writeInt	(I)V
        //   23: aload_1
        //   24: aload_2
        //   25: iconst_0
        //   26: invokevirtual 57	com/google/android/gms/drive/internal/OnDeviceUsagePreferenceResponse:writeToParcel	(Landroid/os/Parcel;I)V
        //   29: aload_0
        //   30: getfield 15	com/google/android/gms/drive/internal/af$a$a:le	Landroid/os/IBinder;
        //   33: bipush 14
        //   35: aload_2
        //   36: aload_3
        //   37: iconst_0
        //   38: invokeinterface 47 5 0
        //   43: pop
        //   44: aload_3
        //   45: invokevirtual 50	android/os/Parcel:readException	()V
        //   48: aload_3
        //   49: invokevirtual 53	android/os/Parcel:recycle	()V
        //   52: aload_2
        //   53: invokevirtual 53	android/os/Parcel:recycle	()V
        //   56: return
        //   57: aload_2
        //   58: iconst_0
        //   59: invokevirtual 35	android/os/Parcel:writeInt	(I)V
        //   62: goto -33 -> 29
        //   65: astore 4
        //   67: aload_3
        //   68: invokevirtual 53	android/os/Parcel:recycle	()V
        //   71: aload_2
        //   72: invokevirtual 53	android/os/Parcel:recycle	()V
        //   75: aload 4
        //   77: athrow
        // Local variable table:
        //   start	length	slot	name	signature
        //   0	78	0	this	a
        //   0	78	1	paramOnDeviceUsagePreferenceResponse	OnDeviceUsagePreferenceResponse
        //   3	69	2	localParcel1	Parcel
        //   7	61	3	localParcel2	Parcel
        //   65	11	4	localObject	Object
        // Exception table:
        //   from	to	target	type
        //   8	14	65	finally
        //   18	29	65	finally
        //   29	48	65	finally
        //   57	62	65	finally
      }
      
      /* Error */
      public void a(OnDownloadProgressResponse paramOnDownloadProgressResponse)
        throws RemoteException
      {
        // Byte code:
        //   0: invokestatic 25	android/os/Parcel:obtain	()Landroid/os/Parcel;
        //   3: astore_2
        //   4: invokestatic 25	android/os/Parcel:obtain	()Landroid/os/Parcel;
        //   7: astore_3
        //   8: aload_2
        //   9: ldc 27
        //   11: invokevirtual 31	android/os/Parcel:writeInterfaceToken	(Ljava/lang/String;)V
        //   14: aload_1
        //   15: ifnull +41 -> 56
        //   18: aload_2
        //   19: iconst_1
        //   20: invokevirtual 35	android/os/Parcel:writeInt	(I)V
        //   23: aload_1
        //   24: aload_2
        //   25: iconst_0
        //   26: invokevirtual 61	com/google/android/gms/drive/internal/OnDownloadProgressResponse:writeToParcel	(Landroid/os/Parcel;I)V
        //   29: aload_0
        //   30: getfield 15	com/google/android/gms/drive/internal/af$a$a:le	Landroid/os/IBinder;
        //   33: iconst_1
        //   34: aload_2
        //   35: aload_3
        //   36: iconst_0
        //   37: invokeinterface 47 5 0
        //   42: pop
        //   43: aload_3
        //   44: invokevirtual 50	android/os/Parcel:readException	()V
        //   47: aload_3
        //   48: invokevirtual 53	android/os/Parcel:recycle	()V
        //   51: aload_2
        //   52: invokevirtual 53	android/os/Parcel:recycle	()V
        //   55: return
        //   56: aload_2
        //   57: iconst_0
        //   58: invokevirtual 35	android/os/Parcel:writeInt	(I)V
        //   61: goto -32 -> 29
        //   64: astore 4
        //   66: aload_3
        //   67: invokevirtual 53	android/os/Parcel:recycle	()V
        //   70: aload_2
        //   71: invokevirtual 53	android/os/Parcel:recycle	()V
        //   74: aload 4
        //   76: athrow
        // Local variable table:
        //   start	length	slot	name	signature
        //   0	77	0	this	a
        //   0	77	1	paramOnDownloadProgressResponse	OnDownloadProgressResponse
        //   3	68	2	localParcel1	Parcel
        //   7	60	3	localParcel2	Parcel
        //   64	11	4	localObject	Object
        // Exception table:
        //   from	to	target	type
        //   8	14	64	finally
        //   18	29	64	finally
        //   29	47	64	finally
        //   56	61	64	finally
      }
      
      /* Error */
      public void a(OnDriveIdResponse paramOnDriveIdResponse)
        throws RemoteException
      {
        // Byte code:
        //   0: invokestatic 25	android/os/Parcel:obtain	()Landroid/os/Parcel;
        //   3: astore_2
        //   4: invokestatic 25	android/os/Parcel:obtain	()Landroid/os/Parcel;
        //   7: astore_3
        //   8: aload_2
        //   9: ldc 27
        //   11: invokevirtual 31	android/os/Parcel:writeInterfaceToken	(Ljava/lang/String;)V
        //   14: aload_1
        //   15: ifnull +41 -> 56
        //   18: aload_2
        //   19: iconst_1
        //   20: invokevirtual 35	android/os/Parcel:writeInt	(I)V
        //   23: aload_1
        //   24: aload_2
        //   25: iconst_0
        //   26: invokevirtual 65	com/google/android/gms/drive/internal/OnDriveIdResponse:writeToParcel	(Landroid/os/Parcel;I)V
        //   29: aload_0
        //   30: getfield 15	com/google/android/gms/drive/internal/af$a$a:le	Landroid/os/IBinder;
        //   33: iconst_3
        //   34: aload_2
        //   35: aload_3
        //   36: iconst_0
        //   37: invokeinterface 47 5 0
        //   42: pop
        //   43: aload_3
        //   44: invokevirtual 50	android/os/Parcel:readException	()V
        //   47: aload_3
        //   48: invokevirtual 53	android/os/Parcel:recycle	()V
        //   51: aload_2
        //   52: invokevirtual 53	android/os/Parcel:recycle	()V
        //   55: return
        //   56: aload_2
        //   57: iconst_0
        //   58: invokevirtual 35	android/os/Parcel:writeInt	(I)V
        //   61: goto -32 -> 29
        //   64: astore 4
        //   66: aload_3
        //   67: invokevirtual 53	android/os/Parcel:recycle	()V
        //   70: aload_2
        //   71: invokevirtual 53	android/os/Parcel:recycle	()V
        //   74: aload 4
        //   76: athrow
        // Local variable table:
        //   start	length	slot	name	signature
        //   0	77	0	this	a
        //   0	77	1	paramOnDriveIdResponse	OnDriveIdResponse
        //   3	68	2	localParcel1	Parcel
        //   7	60	3	localParcel2	Parcel
        //   64	11	4	localObject	Object
        // Exception table:
        //   from	to	target	type
        //   8	14	64	finally
        //   18	29	64	finally
        //   29	47	64	finally
        //   56	61	64	finally
      }
      
      /* Error */
      public void a(OnDrivePreferencesResponse paramOnDrivePreferencesResponse)
        throws RemoteException
      {
        // Byte code:
        //   0: invokestatic 25	android/os/Parcel:obtain	()Landroid/os/Parcel;
        //   3: astore_2
        //   4: invokestatic 25	android/os/Parcel:obtain	()Landroid/os/Parcel;
        //   7: astore_3
        //   8: aload_2
        //   9: ldc 27
        //   11: invokevirtual 31	android/os/Parcel:writeInterfaceToken	(Ljava/lang/String;)V
        //   14: aload_1
        //   15: ifnull +42 -> 57
        //   18: aload_2
        //   19: iconst_1
        //   20: invokevirtual 35	android/os/Parcel:writeInt	(I)V
        //   23: aload_1
        //   24: aload_2
        //   25: iconst_0
        //   26: invokevirtual 69	com/google/android/gms/drive/internal/OnDrivePreferencesResponse:writeToParcel	(Landroid/os/Parcel;I)V
        //   29: aload_0
        //   30: getfield 15	com/google/android/gms/drive/internal/af$a$a:le	Landroid/os/IBinder;
        //   33: bipush 13
        //   35: aload_2
        //   36: aload_3
        //   37: iconst_0
        //   38: invokeinterface 47 5 0
        //   43: pop
        //   44: aload_3
        //   45: invokevirtual 50	android/os/Parcel:readException	()V
        //   48: aload_3
        //   49: invokevirtual 53	android/os/Parcel:recycle	()V
        //   52: aload_2
        //   53: invokevirtual 53	android/os/Parcel:recycle	()V
        //   56: return
        //   57: aload_2
        //   58: iconst_0
        //   59: invokevirtual 35	android/os/Parcel:writeInt	(I)V
        //   62: goto -33 -> 29
        //   65: astore 4
        //   67: aload_3
        //   68: invokevirtual 53	android/os/Parcel:recycle	()V
        //   71: aload_2
        //   72: invokevirtual 53	android/os/Parcel:recycle	()V
        //   75: aload 4
        //   77: athrow
        // Local variable table:
        //   start	length	slot	name	signature
        //   0	78	0	this	a
        //   0	78	1	paramOnDrivePreferencesResponse	OnDrivePreferencesResponse
        //   3	69	2	localParcel1	Parcel
        //   7	61	3	localParcel2	Parcel
        //   65	11	4	localObject	Object
        // Exception table:
        //   from	to	target	type
        //   8	14	65	finally
        //   18	29	65	finally
        //   29	48	65	finally
        //   57	62	65	finally
      }
      
      /* Error */
      public void a(OnListEntriesResponse paramOnListEntriesResponse)
        throws RemoteException
      {
        // Byte code:
        //   0: invokestatic 25	android/os/Parcel:obtain	()Landroid/os/Parcel;
        //   3: astore_2
        //   4: invokestatic 25	android/os/Parcel:obtain	()Landroid/os/Parcel;
        //   7: astore_3
        //   8: aload_2
        //   9: ldc 27
        //   11: invokevirtual 31	android/os/Parcel:writeInterfaceToken	(Ljava/lang/String;)V
        //   14: aload_1
        //   15: ifnull +41 -> 56
        //   18: aload_2
        //   19: iconst_1
        //   20: invokevirtual 35	android/os/Parcel:writeInt	(I)V
        //   23: aload_1
        //   24: aload_2
        //   25: iconst_0
        //   26: invokevirtual 73	com/google/android/gms/drive/internal/OnListEntriesResponse:writeToParcel	(Landroid/os/Parcel;I)V
        //   29: aload_0
        //   30: getfield 15	com/google/android/gms/drive/internal/af$a$a:le	Landroid/os/IBinder;
        //   33: iconst_2
        //   34: aload_2
        //   35: aload_3
        //   36: iconst_0
        //   37: invokeinterface 47 5 0
        //   42: pop
        //   43: aload_3
        //   44: invokevirtual 50	android/os/Parcel:readException	()V
        //   47: aload_3
        //   48: invokevirtual 53	android/os/Parcel:recycle	()V
        //   51: aload_2
        //   52: invokevirtual 53	android/os/Parcel:recycle	()V
        //   55: return
        //   56: aload_2
        //   57: iconst_0
        //   58: invokevirtual 35	android/os/Parcel:writeInt	(I)V
        //   61: goto -32 -> 29
        //   64: astore 4
        //   66: aload_3
        //   67: invokevirtual 53	android/os/Parcel:recycle	()V
        //   70: aload_2
        //   71: invokevirtual 53	android/os/Parcel:recycle	()V
        //   74: aload 4
        //   76: athrow
        // Local variable table:
        //   start	length	slot	name	signature
        //   0	77	0	this	a
        //   0	77	1	paramOnListEntriesResponse	OnListEntriesResponse
        //   3	68	2	localParcel1	Parcel
        //   7	60	3	localParcel2	Parcel
        //   64	11	4	localObject	Object
        // Exception table:
        //   from	to	target	type
        //   8	14	64	finally
        //   18	29	64	finally
        //   29	47	64	finally
        //   56	61	64	finally
      }
      
      /* Error */
      public void a(OnListParentsResponse paramOnListParentsResponse)
        throws RemoteException
      {
        // Byte code:
        //   0: invokestatic 25	android/os/Parcel:obtain	()Landroid/os/Parcel;
        //   3: astore_2
        //   4: invokestatic 25	android/os/Parcel:obtain	()Landroid/os/Parcel;
        //   7: astore_3
        //   8: aload_2
        //   9: ldc 27
        //   11: invokevirtual 31	android/os/Parcel:writeInterfaceToken	(Ljava/lang/String;)V
        //   14: aload_1
        //   15: ifnull +42 -> 57
        //   18: aload_2
        //   19: iconst_1
        //   20: invokevirtual 35	android/os/Parcel:writeInt	(I)V
        //   23: aload_1
        //   24: aload_2
        //   25: iconst_0
        //   26: invokevirtual 77	com/google/android/gms/drive/internal/OnListParentsResponse:writeToParcel	(Landroid/os/Parcel;I)V
        //   29: aload_0
        //   30: getfield 15	com/google/android/gms/drive/internal/af$a$a:le	Landroid/os/IBinder;
        //   33: bipush 8
        //   35: aload_2
        //   36: aload_3
        //   37: iconst_0
        //   38: invokeinterface 47 5 0
        //   43: pop
        //   44: aload_3
        //   45: invokevirtual 50	android/os/Parcel:readException	()V
        //   48: aload_3
        //   49: invokevirtual 53	android/os/Parcel:recycle	()V
        //   52: aload_2
        //   53: invokevirtual 53	android/os/Parcel:recycle	()V
        //   56: return
        //   57: aload_2
        //   58: iconst_0
        //   59: invokevirtual 35	android/os/Parcel:writeInt	(I)V
        //   62: goto -33 -> 29
        //   65: astore 4
        //   67: aload_3
        //   68: invokevirtual 53	android/os/Parcel:recycle	()V
        //   71: aload_2
        //   72: invokevirtual 53	android/os/Parcel:recycle	()V
        //   75: aload 4
        //   77: athrow
        // Local variable table:
        //   start	length	slot	name	signature
        //   0	78	0	this	a
        //   0	78	1	paramOnListParentsResponse	OnListParentsResponse
        //   3	69	2	localParcel1	Parcel
        //   7	61	3	localParcel2	Parcel
        //   65	11	4	localObject	Object
        // Exception table:
        //   from	to	target	type
        //   8	14	65	finally
        //   18	29	65	finally
        //   29	48	65	finally
        //   57	62	65	finally
      }
      
      public void a(OnLoadRealtimeResponse paramOnLoadRealtimeResponse, m paramm)
        throws RemoteException
      {
        Parcel localParcel1 = Parcel.obtain();
        Parcel localParcel2 = Parcel.obtain();
        for (;;)
        {
          try
          {
            localParcel1.writeInterfaceToken("com.google.android.gms.drive.internal.IDriveServiceCallbacks");
            if (paramOnLoadRealtimeResponse != null)
            {
              localParcel1.writeInt(1);
              paramOnLoadRealtimeResponse.writeToParcel(localParcel1, 0);
              if (paramm != null)
              {
                localIBinder = paramm.asBinder();
                localParcel1.writeStrongBinder(localIBinder);
                this.le.transact(11, localParcel1, localParcel2, 0);
                localParcel2.readException();
              }
            }
            else
            {
              localParcel1.writeInt(0);
              continue;
            }
            IBinder localIBinder = null;
          }
          finally
          {
            localParcel2.recycle();
            localParcel1.recycle();
          }
        }
      }
      
      /* Error */
      public void a(OnMetadataResponse paramOnMetadataResponse)
        throws RemoteException
      {
        // Byte code:
        //   0: invokestatic 25	android/os/Parcel:obtain	()Landroid/os/Parcel;
        //   3: astore_2
        //   4: invokestatic 25	android/os/Parcel:obtain	()Landroid/os/Parcel;
        //   7: astore_3
        //   8: aload_2
        //   9: ldc 27
        //   11: invokevirtual 31	android/os/Parcel:writeInterfaceToken	(Ljava/lang/String;)V
        //   14: aload_1
        //   15: ifnull +41 -> 56
        //   18: aload_2
        //   19: iconst_1
        //   20: invokevirtual 35	android/os/Parcel:writeInt	(I)V
        //   23: aload_1
        //   24: aload_2
        //   25: iconst_0
        //   26: invokevirtual 94	com/google/android/gms/drive/internal/OnMetadataResponse:writeToParcel	(Landroid/os/Parcel;I)V
        //   29: aload_0
        //   30: getfield 15	com/google/android/gms/drive/internal/af$a$a:le	Landroid/os/IBinder;
        //   33: iconst_4
        //   34: aload_2
        //   35: aload_3
        //   36: iconst_0
        //   37: invokeinterface 47 5 0
        //   42: pop
        //   43: aload_3
        //   44: invokevirtual 50	android/os/Parcel:readException	()V
        //   47: aload_3
        //   48: invokevirtual 53	android/os/Parcel:recycle	()V
        //   51: aload_2
        //   52: invokevirtual 53	android/os/Parcel:recycle	()V
        //   55: return
        //   56: aload_2
        //   57: iconst_0
        //   58: invokevirtual 35	android/os/Parcel:writeInt	(I)V
        //   61: goto -32 -> 29
        //   64: astore 4
        //   66: aload_3
        //   67: invokevirtual 53	android/os/Parcel:recycle	()V
        //   70: aload_2
        //   71: invokevirtual 53	android/os/Parcel:recycle	()V
        //   74: aload 4
        //   76: athrow
        // Local variable table:
        //   start	length	slot	name	signature
        //   0	77	0	this	a
        //   0	77	1	paramOnMetadataResponse	OnMetadataResponse
        //   3	68	2	localParcel1	Parcel
        //   7	60	3	localParcel2	Parcel
        //   64	11	4	localObject	Object
        // Exception table:
        //   from	to	target	type
        //   8	14	64	finally
        //   18	29	64	finally
        //   29	47	64	finally
        //   56	61	64	finally
      }
      
      /* Error */
      public void a(OnResourceIdSetResponse paramOnResourceIdSetResponse)
        throws RemoteException
      {
        // Byte code:
        //   0: invokestatic 25	android/os/Parcel:obtain	()Landroid/os/Parcel;
        //   3: astore_2
        //   4: invokestatic 25	android/os/Parcel:obtain	()Landroid/os/Parcel;
        //   7: astore_3
        //   8: aload_2
        //   9: ldc 27
        //   11: invokevirtual 31	android/os/Parcel:writeInterfaceToken	(Ljava/lang/String;)V
        //   14: aload_1
        //   15: ifnull +42 -> 57
        //   18: aload_2
        //   19: iconst_1
        //   20: invokevirtual 35	android/os/Parcel:writeInt	(I)V
        //   23: aload_1
        //   24: aload_2
        //   25: iconst_0
        //   26: invokevirtual 98	com/google/android/gms/drive/internal/OnResourceIdSetResponse:writeToParcel	(Landroid/os/Parcel;I)V
        //   29: aload_0
        //   30: getfield 15	com/google/android/gms/drive/internal/af$a$a:le	Landroid/os/IBinder;
        //   33: bipush 12
        //   35: aload_2
        //   36: aload_3
        //   37: iconst_0
        //   38: invokeinterface 47 5 0
        //   43: pop
        //   44: aload_3
        //   45: invokevirtual 50	android/os/Parcel:readException	()V
        //   48: aload_3
        //   49: invokevirtual 53	android/os/Parcel:recycle	()V
        //   52: aload_2
        //   53: invokevirtual 53	android/os/Parcel:recycle	()V
        //   56: return
        //   57: aload_2
        //   58: iconst_0
        //   59: invokevirtual 35	android/os/Parcel:writeInt	(I)V
        //   62: goto -33 -> 29
        //   65: astore 4
        //   67: aload_3
        //   68: invokevirtual 53	android/os/Parcel:recycle	()V
        //   71: aload_2
        //   72: invokevirtual 53	android/os/Parcel:recycle	()V
        //   75: aload 4
        //   77: athrow
        // Local variable table:
        //   start	length	slot	name	signature
        //   0	78	0	this	a
        //   0	78	1	paramOnResourceIdSetResponse	OnResourceIdSetResponse
        //   3	69	2	localParcel1	Parcel
        //   7	61	3	localParcel2	Parcel
        //   65	11	4	localObject	Object
        // Exception table:
        //   from	to	target	type
        //   8	14	65	finally
        //   18	29	65	finally
        //   29	48	65	finally
        //   57	62	65	finally
      }
      
      /* Error */
      public void a(OnStorageStatsResponse paramOnStorageStatsResponse)
        throws RemoteException
      {
        // Byte code:
        //   0: invokestatic 25	android/os/Parcel:obtain	()Landroid/os/Parcel;
        //   3: astore_2
        //   4: invokestatic 25	android/os/Parcel:obtain	()Landroid/os/Parcel;
        //   7: astore_3
        //   8: aload_2
        //   9: ldc 27
        //   11: invokevirtual 31	android/os/Parcel:writeInterfaceToken	(Ljava/lang/String;)V
        //   14: aload_1
        //   15: ifnull +42 -> 57
        //   18: aload_2
        //   19: iconst_1
        //   20: invokevirtual 35	android/os/Parcel:writeInt	(I)V
        //   23: aload_1
        //   24: aload_2
        //   25: iconst_0
        //   26: invokevirtual 102	com/google/android/gms/drive/internal/OnStorageStatsResponse:writeToParcel	(Landroid/os/Parcel;I)V
        //   29: aload_0
        //   30: getfield 15	com/google/android/gms/drive/internal/af$a$a:le	Landroid/os/IBinder;
        //   33: bipush 10
        //   35: aload_2
        //   36: aload_3
        //   37: iconst_0
        //   38: invokeinterface 47 5 0
        //   43: pop
        //   44: aload_3
        //   45: invokevirtual 50	android/os/Parcel:readException	()V
        //   48: aload_3
        //   49: invokevirtual 53	android/os/Parcel:recycle	()V
        //   52: aload_2
        //   53: invokevirtual 53	android/os/Parcel:recycle	()V
        //   56: return
        //   57: aload_2
        //   58: iconst_0
        //   59: invokevirtual 35	android/os/Parcel:writeInt	(I)V
        //   62: goto -33 -> 29
        //   65: astore 4
        //   67: aload_3
        //   68: invokevirtual 53	android/os/Parcel:recycle	()V
        //   71: aload_2
        //   72: invokevirtual 53	android/os/Parcel:recycle	()V
        //   75: aload 4
        //   77: athrow
        // Local variable table:
        //   start	length	slot	name	signature
        //   0	78	0	this	a
        //   0	78	1	paramOnStorageStatsResponse	OnStorageStatsResponse
        //   3	69	2	localParcel1	Parcel
        //   7	61	3	localParcel2	Parcel
        //   65	11	4	localObject	Object
        // Exception table:
        //   from	to	target	type
        //   8	14	65	finally
        //   18	29	65	finally
        //   29	48	65	finally
        //   57	62	65	finally
      }
      
      /* Error */
      public void a(OnSyncMoreResponse paramOnSyncMoreResponse)
        throws RemoteException
      {
        // Byte code:
        //   0: invokestatic 25	android/os/Parcel:obtain	()Landroid/os/Parcel;
        //   3: astore_2
        //   4: invokestatic 25	android/os/Parcel:obtain	()Landroid/os/Parcel;
        //   7: astore_3
        //   8: aload_2
        //   9: ldc 27
        //   11: invokevirtual 31	android/os/Parcel:writeInterfaceToken	(Ljava/lang/String;)V
        //   14: aload_1
        //   15: ifnull +42 -> 57
        //   18: aload_2
        //   19: iconst_1
        //   20: invokevirtual 35	android/os/Parcel:writeInt	(I)V
        //   23: aload_1
        //   24: aload_2
        //   25: iconst_0
        //   26: invokevirtual 106	com/google/android/gms/drive/internal/OnSyncMoreResponse:writeToParcel	(Landroid/os/Parcel;I)V
        //   29: aload_0
        //   30: getfield 15	com/google/android/gms/drive/internal/af$a$a:le	Landroid/os/IBinder;
        //   33: bipush 9
        //   35: aload_2
        //   36: aload_3
        //   37: iconst_0
        //   38: invokeinterface 47 5 0
        //   43: pop
        //   44: aload_3
        //   45: invokevirtual 50	android/os/Parcel:readException	()V
        //   48: aload_3
        //   49: invokevirtual 53	android/os/Parcel:recycle	()V
        //   52: aload_2
        //   53: invokevirtual 53	android/os/Parcel:recycle	()V
        //   56: return
        //   57: aload_2
        //   58: iconst_0
        //   59: invokevirtual 35	android/os/Parcel:writeInt	(I)V
        //   62: goto -33 -> 29
        //   65: astore 4
        //   67: aload_3
        //   68: invokevirtual 53	android/os/Parcel:recycle	()V
        //   71: aload_2
        //   72: invokevirtual 53	android/os/Parcel:recycle	()V
        //   75: aload 4
        //   77: athrow
        // Local variable table:
        //   start	length	slot	name	signature
        //   0	78	0	this	a
        //   0	78	1	paramOnSyncMoreResponse	OnSyncMoreResponse
        //   3	69	2	localParcel1	Parcel
        //   7	61	3	localParcel2	Parcel
        //   65	11	4	localObject	Object
        // Exception table:
        //   from	to	target	type
        //   8	14	65	finally
        //   18	29	65	finally
        //   29	48	65	finally
        //   57	62	65	finally
      }
      
      public IBinder asBinder()
      {
        return this.le;
      }
      
      /* Error */
      public void n(Status paramStatus)
        throws RemoteException
      {
        // Byte code:
        //   0: invokestatic 25	android/os/Parcel:obtain	()Landroid/os/Parcel;
        //   3: astore_2
        //   4: invokestatic 25	android/os/Parcel:obtain	()Landroid/os/Parcel;
        //   7: astore_3
        //   8: aload_2
        //   9: ldc 27
        //   11: invokevirtual 31	android/os/Parcel:writeInterfaceToken	(Ljava/lang/String;)V
        //   14: aload_1
        //   15: ifnull +42 -> 57
        //   18: aload_2
        //   19: iconst_1
        //   20: invokevirtual 35	android/os/Parcel:writeInt	(I)V
        //   23: aload_1
        //   24: aload_2
        //   25: iconst_0
        //   26: invokevirtual 111	com/google/android/gms/common/api/Status:writeToParcel	(Landroid/os/Parcel;I)V
        //   29: aload_0
        //   30: getfield 15	com/google/android/gms/drive/internal/af$a$a:le	Landroid/os/IBinder;
        //   33: bipush 6
        //   35: aload_2
        //   36: aload_3
        //   37: iconst_0
        //   38: invokeinterface 47 5 0
        //   43: pop
        //   44: aload_3
        //   45: invokevirtual 50	android/os/Parcel:readException	()V
        //   48: aload_3
        //   49: invokevirtual 53	android/os/Parcel:recycle	()V
        //   52: aload_2
        //   53: invokevirtual 53	android/os/Parcel:recycle	()V
        //   56: return
        //   57: aload_2
        //   58: iconst_0
        //   59: invokevirtual 35	android/os/Parcel:writeInt	(I)V
        //   62: goto -33 -> 29
        //   65: astore 4
        //   67: aload_3
        //   68: invokevirtual 53	android/os/Parcel:recycle	()V
        //   71: aload_2
        //   72: invokevirtual 53	android/os/Parcel:recycle	()V
        //   75: aload 4
        //   77: athrow
        // Local variable table:
        //   start	length	slot	name	signature
        //   0	78	0	this	a
        //   0	78	1	paramStatus	Status
        //   3	69	2	localParcel1	Parcel
        //   7	61	3	localParcel2	Parcel
        //   65	11	4	localObject	Object
        // Exception table:
        //   from	to	target	type
        //   8	14	65	finally
        //   18	29	65	finally
        //   29	48	65	finally
        //   57	62	65	finally
      }
      
      public void onSuccess()
        throws RemoteException
      {
        Parcel localParcel1 = Parcel.obtain();
        Parcel localParcel2 = Parcel.obtain();
        try
        {
          localParcel1.writeInterfaceToken("com.google.android.gms.drive.internal.IDriveServiceCallbacks");
          this.le.transact(7, localParcel1, localParcel2, 0);
          localParcel2.readException();
          return;
        }
        finally
        {
          localParcel2.recycle();
          localParcel1.recycle();
        }
      }
    }
  }
}


/* Location:           C:\Users\TGKIM\Downloads\작업폴더\리버싱\androidReversetools\jd-gui-0.3.6.windows\com.appg.golfmon-1-dex2jar.jar
 * Qualified Name:     com.google.android.gms.drive.internal.af
 * JD-Core Version:    0.7.0.1
 */