package com.google.android.gms.maps.model.internal;

import android.graphics.Bitmap;
import android.os.Binder;
import android.os.IBinder;
import android.os.IInterface;
import android.os.Parcel;
import android.os.Parcelable.Creator;
import android.os.RemoteException;
import com.google.android.gms.dynamic.d;
import com.google.android.gms.dynamic.d.a;

public abstract interface g
  extends IInterface
{
  public abstract d b(Bitmap paramBitmap)
    throws RemoteException;
  
  public abstract d c(float paramFloat)
    throws RemoteException;
  
  public abstract d cd(String paramString)
    throws RemoteException;
  
  public abstract d ce(String paramString)
    throws RemoteException;
  
  public abstract d cf(String paramString)
    throws RemoteException;
  
  public abstract d fo(int paramInt)
    throws RemoteException;
  
  public abstract d ok()
    throws RemoteException;
  
  public static abstract class a
    extends Binder
    implements g
  {
    public static g bv(IBinder paramIBinder)
    {
      if (paramIBinder == null) {
        return null;
      }
      IInterface localIInterface = paramIBinder.queryLocalInterface("com.google.android.gms.maps.model.internal.IBitmapDescriptorFactoryDelegate");
      if ((localIInterface != null) && ((localIInterface instanceof g))) {
        return (g)localIInterface;
      }
      return new a(paramIBinder);
    }
    
    public boolean onTransact(int paramInt1, Parcel paramParcel1, Parcel paramParcel2, int paramInt2)
      throws RemoteException
    {
      switch (paramInt1)
      {
      default: 
        return super.onTransact(paramInt1, paramParcel1, paramParcel2, paramInt2);
      case 1598968902: 
        paramParcel2.writeString("com.google.android.gms.maps.model.internal.IBitmapDescriptorFactoryDelegate");
        return true;
      case 1: 
        paramParcel1.enforceInterface("com.google.android.gms.maps.model.internal.IBitmapDescriptorFactoryDelegate");
        d locald7 = fo(paramParcel1.readInt());
        paramParcel2.writeNoException();
        if (locald7 != null) {}
        for (IBinder localIBinder7 = locald7.asBinder();; localIBinder7 = null)
        {
          paramParcel2.writeStrongBinder(localIBinder7);
          return true;
        }
      case 2: 
        paramParcel1.enforceInterface("com.google.android.gms.maps.model.internal.IBitmapDescriptorFactoryDelegate");
        d locald6 = cd(paramParcel1.readString());
        paramParcel2.writeNoException();
        IBinder localIBinder6 = null;
        if (locald6 != null) {
          localIBinder6 = locald6.asBinder();
        }
        paramParcel2.writeStrongBinder(localIBinder6);
        return true;
      case 3: 
        paramParcel1.enforceInterface("com.google.android.gms.maps.model.internal.IBitmapDescriptorFactoryDelegate");
        d locald5 = ce(paramParcel1.readString());
        paramParcel2.writeNoException();
        IBinder localIBinder5 = null;
        if (locald5 != null) {
          localIBinder5 = locald5.asBinder();
        }
        paramParcel2.writeStrongBinder(localIBinder5);
        return true;
      case 4: 
        paramParcel1.enforceInterface("com.google.android.gms.maps.model.internal.IBitmapDescriptorFactoryDelegate");
        d locald4 = ok();
        paramParcel2.writeNoException();
        IBinder localIBinder4 = null;
        if (locald4 != null) {
          localIBinder4 = locald4.asBinder();
        }
        paramParcel2.writeStrongBinder(localIBinder4);
        return true;
      case 5: 
        paramParcel1.enforceInterface("com.google.android.gms.maps.model.internal.IBitmapDescriptorFactoryDelegate");
        d locald3 = c(paramParcel1.readFloat());
        paramParcel2.writeNoException();
        IBinder localIBinder3 = null;
        if (locald3 != null) {
          localIBinder3 = locald3.asBinder();
        }
        paramParcel2.writeStrongBinder(localIBinder3);
        return true;
      case 6: 
        paramParcel1.enforceInterface("com.google.android.gms.maps.model.internal.IBitmapDescriptorFactoryDelegate");
        if (paramParcel1.readInt() != 0) {}
        for (Bitmap localBitmap = (Bitmap)Bitmap.CREATOR.createFromParcel(paramParcel1);; localBitmap = null)
        {
          d locald2 = b(localBitmap);
          paramParcel2.writeNoException();
          IBinder localIBinder2 = null;
          if (locald2 != null) {
            localIBinder2 = locald2.asBinder();
          }
          paramParcel2.writeStrongBinder(localIBinder2);
          return true;
        }
      }
      paramParcel1.enforceInterface("com.google.android.gms.maps.model.internal.IBitmapDescriptorFactoryDelegate");
      d locald1 = cf(paramParcel1.readString());
      paramParcel2.writeNoException();
      IBinder localIBinder1 = null;
      if (locald1 != null) {
        localIBinder1 = locald1.asBinder();
      }
      paramParcel2.writeStrongBinder(localIBinder1);
      return true;
    }
    
    private static class a
      implements g
    {
      private IBinder le;
      
      a(IBinder paramIBinder)
      {
        this.le = paramIBinder;
      }
      
      public IBinder asBinder()
      {
        return this.le;
      }
      
      /* Error */
      public d b(Bitmap paramBitmap)
        throws RemoteException
      {
        // Byte code:
        //   0: invokestatic 27	android/os/Parcel:obtain	()Landroid/os/Parcel;
        //   3: astore_2
        //   4: invokestatic 27	android/os/Parcel:obtain	()Landroid/os/Parcel;
        //   7: astore_3
        //   8: aload_2
        //   9: ldc 29
        //   11: invokevirtual 33	android/os/Parcel:writeInterfaceToken	(Ljava/lang/String;)V
        //   14: aload_1
        //   15: ifnull +53 -> 68
        //   18: aload_2
        //   19: iconst_1
        //   20: invokevirtual 37	android/os/Parcel:writeInt	(I)V
        //   23: aload_1
        //   24: aload_2
        //   25: iconst_0
        //   26: invokevirtual 43	android/graphics/Bitmap:writeToParcel	(Landroid/os/Parcel;I)V
        //   29: aload_0
        //   30: getfield 15	com/google/android/gms/maps/model/internal/g$a$a:le	Landroid/os/IBinder;
        //   33: bipush 6
        //   35: aload_2
        //   36: aload_3
        //   37: iconst_0
        //   38: invokeinterface 49 5 0
        //   43: pop
        //   44: aload_3
        //   45: invokevirtual 52	android/os/Parcel:readException	()V
        //   48: aload_3
        //   49: invokevirtual 55	android/os/Parcel:readStrongBinder	()Landroid/os/IBinder;
        //   52: invokestatic 61	com/google/android/gms/dynamic/d$a:ap	(Landroid/os/IBinder;)Lcom/google/android/gms/dynamic/d;
        //   55: astore 6
        //   57: aload_3
        //   58: invokevirtual 64	android/os/Parcel:recycle	()V
        //   61: aload_2
        //   62: invokevirtual 64	android/os/Parcel:recycle	()V
        //   65: aload 6
        //   67: areturn
        //   68: aload_2
        //   69: iconst_0
        //   70: invokevirtual 37	android/os/Parcel:writeInt	(I)V
        //   73: goto -44 -> 29
        //   76: astore 4
        //   78: aload_3
        //   79: invokevirtual 64	android/os/Parcel:recycle	()V
        //   82: aload_2
        //   83: invokevirtual 64	android/os/Parcel:recycle	()V
        //   86: aload 4
        //   88: athrow
        // Local variable table:
        //   start	length	slot	name	signature
        //   0	89	0	this	a
        //   0	89	1	paramBitmap	Bitmap
        //   3	80	2	localParcel1	Parcel
        //   7	72	3	localParcel2	Parcel
        //   76	11	4	localObject	Object
        //   55	11	6	locald	d
        // Exception table:
        //   from	to	target	type
        //   8	14	76	finally
        //   18	29	76	finally
        //   29	57	76	finally
        //   68	73	76	finally
      }
      
      public d c(float paramFloat)
        throws RemoteException
      {
        Parcel localParcel1 = Parcel.obtain();
        Parcel localParcel2 = Parcel.obtain();
        try
        {
          localParcel1.writeInterfaceToken("com.google.android.gms.maps.model.internal.IBitmapDescriptorFactoryDelegate");
          localParcel1.writeFloat(paramFloat);
          this.le.transact(5, localParcel1, localParcel2, 0);
          localParcel2.readException();
          d locald = d.a.ap(localParcel2.readStrongBinder());
          return locald;
        }
        finally
        {
          localParcel2.recycle();
          localParcel1.recycle();
        }
      }
      
      public d cd(String paramString)
        throws RemoteException
      {
        Parcel localParcel1 = Parcel.obtain();
        Parcel localParcel2 = Parcel.obtain();
        try
        {
          localParcel1.writeInterfaceToken("com.google.android.gms.maps.model.internal.IBitmapDescriptorFactoryDelegate");
          localParcel1.writeString(paramString);
          this.le.transact(2, localParcel1, localParcel2, 0);
          localParcel2.readException();
          d locald = d.a.ap(localParcel2.readStrongBinder());
          return locald;
        }
        finally
        {
          localParcel2.recycle();
          localParcel1.recycle();
        }
      }
      
      public d ce(String paramString)
        throws RemoteException
      {
        Parcel localParcel1 = Parcel.obtain();
        Parcel localParcel2 = Parcel.obtain();
        try
        {
          localParcel1.writeInterfaceToken("com.google.android.gms.maps.model.internal.IBitmapDescriptorFactoryDelegate");
          localParcel1.writeString(paramString);
          this.le.transact(3, localParcel1, localParcel2, 0);
          localParcel2.readException();
          d locald = d.a.ap(localParcel2.readStrongBinder());
          return locald;
        }
        finally
        {
          localParcel2.recycle();
          localParcel1.recycle();
        }
      }
      
      public d cf(String paramString)
        throws RemoteException
      {
        Parcel localParcel1 = Parcel.obtain();
        Parcel localParcel2 = Parcel.obtain();
        try
        {
          localParcel1.writeInterfaceToken("com.google.android.gms.maps.model.internal.IBitmapDescriptorFactoryDelegate");
          localParcel1.writeString(paramString);
          this.le.transact(7, localParcel1, localParcel2, 0);
          localParcel2.readException();
          d locald = d.a.ap(localParcel2.readStrongBinder());
          return locald;
        }
        finally
        {
          localParcel2.recycle();
          localParcel1.recycle();
        }
      }
      
      public d fo(int paramInt)
        throws RemoteException
      {
        Parcel localParcel1 = Parcel.obtain();
        Parcel localParcel2 = Parcel.obtain();
        try
        {
          localParcel1.writeInterfaceToken("com.google.android.gms.maps.model.internal.IBitmapDescriptorFactoryDelegate");
          localParcel1.writeInt(paramInt);
          this.le.transact(1, localParcel1, localParcel2, 0);
          localParcel2.readException();
          d locald = d.a.ap(localParcel2.readStrongBinder());
          return locald;
        }
        finally
        {
          localParcel2.recycle();
          localParcel1.recycle();
        }
      }
      
      public d ok()
        throws RemoteException
      {
        Parcel localParcel1 = Parcel.obtain();
        Parcel localParcel2 = Parcel.obtain();
        try
        {
          localParcel1.writeInterfaceToken("com.google.android.gms.maps.model.internal.IBitmapDescriptorFactoryDelegate");
          this.le.transact(4, localParcel1, localParcel2, 0);
          localParcel2.readException();
          d locald = d.a.ap(localParcel2.readStrongBinder());
          return locald;
        }
        finally
        {
          localParcel2.recycle();
          localParcel1.recycle();
        }
      }
    }
  }
}


/* Location:           C:\Users\TGKIM\Downloads\작업폴더\리버싱\androidReversetools\jd-gui-0.3.6.windows\com.appg.golfmon-1-dex2jar.jar
 * Qualified Name:     com.google.android.gms.maps.model.internal.g
 * JD-Core Version:    0.7.0.1
 */