package com.google.android.gms.maps.model.internal;

import android.os.Binder;
import android.os.IBinder;
import android.os.IInterface;
import android.os.Parcel;
import android.os.RemoteException;
import com.google.android.gms.dynamic.d;
import com.google.android.gms.dynamic.d.a;
import com.google.android.gms.maps.model.LatLng;
import com.google.android.gms.maps.model.LatLngBounds;
import com.google.android.gms.maps.model.g;

public abstract interface i
  extends IInterface
{
  public abstract void a(float paramFloat1, float paramFloat2)
    throws RemoteException;
  
  public abstract void a(a parama)
    throws RemoteException;
  
  public abstract boolean a(i parami)
    throws RemoteException;
  
  public abstract float getBearing()
    throws RemoteException;
  
  public abstract LatLngBounds getBounds()
    throws RemoteException;
  
  public abstract float getHeight()
    throws RemoteException;
  
  public abstract String getId()
    throws RemoteException;
  
  public abstract LatLng getPosition()
    throws RemoteException;
  
  public abstract float getTransparency()
    throws RemoteException;
  
  public abstract float getWidth()
    throws RemoteException;
  
  public abstract float getZIndex()
    throws RemoteException;
  
  public abstract int hashCodeRemote()
    throws RemoteException;
  
  public abstract boolean isVisible()
    throws RemoteException;
  
  public abstract void m(d paramd)
    throws RemoteException;
  
  public abstract void remove()
    throws RemoteException;
  
  public abstract void setBearing(float paramFloat)
    throws RemoteException;
  
  public abstract void setDimensions(float paramFloat)
    throws RemoteException;
  
  public abstract void setPosition(LatLng paramLatLng)
    throws RemoteException;
  
  public abstract void setPositionFromBounds(LatLngBounds paramLatLngBounds)
    throws RemoteException;
  
  public abstract void setTransparency(float paramFloat)
    throws RemoteException;
  
  public abstract void setVisible(boolean paramBoolean)
    throws RemoteException;
  
  public abstract void setZIndex(float paramFloat)
    throws RemoteException;
  
  public static abstract class a
    extends Binder
    implements i
  {
    public static i bx(IBinder paramIBinder)
    {
      if (paramIBinder == null) {
        return null;
      }
      IInterface localIInterface = paramIBinder.queryLocalInterface("com.google.android.gms.maps.model.internal.IGroundOverlayDelegate");
      if ((localIInterface != null) && ((localIInterface instanceof i))) {
        return (i)localIInterface;
      }
      return new a(paramIBinder);
    }
    
    public boolean onTransact(int paramInt1, Parcel paramParcel1, Parcel paramParcel2, int paramInt2)
      throws RemoteException
    {
      switch (paramInt1)
      {
      default: 
        return super.onTransact(paramInt1, paramParcel1, paramParcel2, paramInt2);
      case 1598968902: 
        paramParcel2.writeString("com.google.android.gms.maps.model.internal.IGroundOverlayDelegate");
        return true;
      case 1: 
        paramParcel1.enforceInterface("com.google.android.gms.maps.model.internal.IGroundOverlayDelegate");
        remove();
        paramParcel2.writeNoException();
        return true;
      case 2: 
        paramParcel1.enforceInterface("com.google.android.gms.maps.model.internal.IGroundOverlayDelegate");
        String str = getId();
        paramParcel2.writeNoException();
        paramParcel2.writeString(str);
        return true;
      case 3: 
        paramParcel1.enforceInterface("com.google.android.gms.maps.model.internal.IGroundOverlayDelegate");
        int i1 = paramParcel1.readInt();
        LatLng localLatLng2 = null;
        if (i1 != 0) {
          localLatLng2 = LatLng.CREATOR.de(paramParcel1);
        }
        setPosition(localLatLng2);
        paramParcel2.writeNoException();
        return true;
      case 4: 
        paramParcel1.enforceInterface("com.google.android.gms.maps.model.internal.IGroundOverlayDelegate");
        LatLng localLatLng1 = getPosition();
        paramParcel2.writeNoException();
        if (localLatLng1 != null)
        {
          paramParcel2.writeInt(1);
          localLatLng1.writeToParcel(paramParcel2, 1);
          return true;
        }
        paramParcel2.writeInt(0);
        return true;
      case 5: 
        paramParcel1.enforceInterface("com.google.android.gms.maps.model.internal.IGroundOverlayDelegate");
        setDimensions(paramParcel1.readFloat());
        paramParcel2.writeNoException();
        return true;
      case 6: 
        paramParcel1.enforceInterface("com.google.android.gms.maps.model.internal.IGroundOverlayDelegate");
        a(paramParcel1.readFloat(), paramParcel1.readFloat());
        paramParcel2.writeNoException();
        return true;
      case 7: 
        paramParcel1.enforceInterface("com.google.android.gms.maps.model.internal.IGroundOverlayDelegate");
        float f5 = getWidth();
        paramParcel2.writeNoException();
        paramParcel2.writeFloat(f5);
        return true;
      case 8: 
        paramParcel1.enforceInterface("com.google.android.gms.maps.model.internal.IGroundOverlayDelegate");
        float f4 = getHeight();
        paramParcel2.writeNoException();
        paramParcel2.writeFloat(f4);
        return true;
      case 9: 
        paramParcel1.enforceInterface("com.google.android.gms.maps.model.internal.IGroundOverlayDelegate");
        int n = paramParcel1.readInt();
        LatLngBounds localLatLngBounds2 = null;
        if (n != 0) {
          localLatLngBounds2 = LatLngBounds.CREATOR.dd(paramParcel1);
        }
        setPositionFromBounds(localLatLngBounds2);
        paramParcel2.writeNoException();
        return true;
      case 10: 
        paramParcel1.enforceInterface("com.google.android.gms.maps.model.internal.IGroundOverlayDelegate");
        LatLngBounds localLatLngBounds1 = getBounds();
        paramParcel2.writeNoException();
        if (localLatLngBounds1 != null)
        {
          paramParcel2.writeInt(1);
          localLatLngBounds1.writeToParcel(paramParcel2, 1);
          return true;
        }
        paramParcel2.writeInt(0);
        return true;
      case 11: 
        paramParcel1.enforceInterface("com.google.android.gms.maps.model.internal.IGroundOverlayDelegate");
        setBearing(paramParcel1.readFloat());
        paramParcel2.writeNoException();
        return true;
      case 12: 
        paramParcel1.enforceInterface("com.google.android.gms.maps.model.internal.IGroundOverlayDelegate");
        float f3 = getBearing();
        paramParcel2.writeNoException();
        paramParcel2.writeFloat(f3);
        return true;
      case 13: 
        paramParcel1.enforceInterface("com.google.android.gms.maps.model.internal.IGroundOverlayDelegate");
        setZIndex(paramParcel1.readFloat());
        paramParcel2.writeNoException();
        return true;
      case 14: 
        paramParcel1.enforceInterface("com.google.android.gms.maps.model.internal.IGroundOverlayDelegate");
        float f2 = getZIndex();
        paramParcel2.writeNoException();
        paramParcel2.writeFloat(f2);
        return true;
      case 15: 
        paramParcel1.enforceInterface("com.google.android.gms.maps.model.internal.IGroundOverlayDelegate");
        if (paramParcel1.readInt() != 0) {}
        for (boolean bool3 = true;; bool3 = false)
        {
          setVisible(bool3);
          paramParcel2.writeNoException();
          return true;
        }
      case 16: 
        paramParcel1.enforceInterface("com.google.android.gms.maps.model.internal.IGroundOverlayDelegate");
        boolean bool2 = isVisible();
        paramParcel2.writeNoException();
        int m = 0;
        if (bool2) {
          m = 1;
        }
        paramParcel2.writeInt(m);
        return true;
      case 17: 
        paramParcel1.enforceInterface("com.google.android.gms.maps.model.internal.IGroundOverlayDelegate");
        setTransparency(paramParcel1.readFloat());
        paramParcel2.writeNoException();
        return true;
      case 18: 
        paramParcel1.enforceInterface("com.google.android.gms.maps.model.internal.IGroundOverlayDelegate");
        float f1 = getTransparency();
        paramParcel2.writeNoException();
        paramParcel2.writeFloat(f1);
        return true;
      case 19: 
        paramParcel1.enforceInterface("com.google.android.gms.maps.model.internal.IGroundOverlayDelegate");
        boolean bool1 = a(bx(paramParcel1.readStrongBinder()));
        paramParcel2.writeNoException();
        int k = 0;
        if (bool1) {
          k = 1;
        }
        paramParcel2.writeInt(k);
        return true;
      case 20: 
        paramParcel1.enforceInterface("com.google.android.gms.maps.model.internal.IGroundOverlayDelegate");
        int j = hashCodeRemote();
        paramParcel2.writeNoException();
        paramParcel2.writeInt(j);
        return true;
      case 21: 
        paramParcel1.enforceInterface("com.google.android.gms.maps.model.internal.IGroundOverlayDelegate");
        m(d.a.ap(paramParcel1.readStrongBinder()));
        paramParcel2.writeNoException();
        return true;
      }
      paramParcel1.enforceInterface("com.google.android.gms.maps.model.internal.IGroundOverlayDelegate");
      int i = paramParcel1.readInt();
      a locala = null;
      if (i != 0) {
        locala = a.CREATOR.dp(paramParcel1);
      }
      a(locala);
      paramParcel2.writeNoException();
      return true;
    }
    
    private static class a
      implements i
    {
      private IBinder le;
      
      a(IBinder paramIBinder)
      {
        this.le = paramIBinder;
      }
      
      public void a(float paramFloat1, float paramFloat2)
        throws RemoteException
      {
        Parcel localParcel1 = Parcel.obtain();
        Parcel localParcel2 = Parcel.obtain();
        try
        {
          localParcel1.writeInterfaceToken("com.google.android.gms.maps.model.internal.IGroundOverlayDelegate");
          localParcel1.writeFloat(paramFloat1);
          localParcel1.writeFloat(paramFloat2);
          this.le.transact(6, localParcel1, localParcel2, 0);
          localParcel2.readException();
          return;
        }
        finally
        {
          localParcel2.recycle();
          localParcel1.recycle();
        }
      }
      
      /* Error */
      public void a(a parama)
        throws RemoteException
      {
        // Byte code:
        //   0: invokestatic 25	android/os/Parcel:obtain	()Landroid/os/Parcel;
        //   3: astore_2
        //   4: invokestatic 25	android/os/Parcel:obtain	()Landroid/os/Parcel;
        //   7: astore_3
        //   8: aload_2
        //   9: ldc 27
        //   11: invokevirtual 31	android/os/Parcel:writeInterfaceToken	(Ljava/lang/String;)V
        //   14: aload_1
        //   15: ifnull +42 -> 57
        //   18: aload_2
        //   19: iconst_1
        //   20: invokevirtual 52	android/os/Parcel:writeInt	(I)V
        //   23: aload_1
        //   24: aload_2
        //   25: iconst_0
        //   26: invokevirtual 58	com/google/android/gms/maps/model/internal/a:writeToParcel	(Landroid/os/Parcel;I)V
        //   29: aload_0
        //   30: getfield 15	com/google/android/gms/maps/model/internal/i$a$a:le	Landroid/os/IBinder;
        //   33: bipush 22
        //   35: aload_2
        //   36: aload_3
        //   37: iconst_0
        //   38: invokeinterface 41 5 0
        //   43: pop
        //   44: aload_3
        //   45: invokevirtual 44	android/os/Parcel:readException	()V
        //   48: aload_3
        //   49: invokevirtual 47	android/os/Parcel:recycle	()V
        //   52: aload_2
        //   53: invokevirtual 47	android/os/Parcel:recycle	()V
        //   56: return
        //   57: aload_2
        //   58: iconst_0
        //   59: invokevirtual 52	android/os/Parcel:writeInt	(I)V
        //   62: goto -33 -> 29
        //   65: astore 4
        //   67: aload_3
        //   68: invokevirtual 47	android/os/Parcel:recycle	()V
        //   71: aload_2
        //   72: invokevirtual 47	android/os/Parcel:recycle	()V
        //   75: aload 4
        //   77: athrow
        // Local variable table:
        //   start	length	slot	name	signature
        //   0	78	0	this	a
        //   0	78	1	parama	a
        //   3	69	2	localParcel1	Parcel
        //   7	61	3	localParcel2	Parcel
        //   65	11	4	localObject	Object
        // Exception table:
        //   from	to	target	type
        //   8	14	65	finally
        //   18	29	65	finally
        //   29	48	65	finally
        //   57	62	65	finally
      }
      
      /* Error */
      public boolean a(i parami)
        throws RemoteException
      {
        // Byte code:
        //   0: invokestatic 25	android/os/Parcel:obtain	()Landroid/os/Parcel;
        //   3: astore_2
        //   4: invokestatic 25	android/os/Parcel:obtain	()Landroid/os/Parcel;
        //   7: astore_3
        //   8: aload_2
        //   9: ldc 27
        //   11: invokevirtual 31	android/os/Parcel:writeInterfaceToken	(Ljava/lang/String;)V
        //   14: aload_1
        //   15: ifnull +64 -> 79
        //   18: aload_1
        //   19: invokeinterface 63 1 0
        //   24: astore 5
        //   26: aload_2
        //   27: aload 5
        //   29: invokevirtual 66	android/os/Parcel:writeStrongBinder	(Landroid/os/IBinder;)V
        //   32: aload_0
        //   33: getfield 15	com/google/android/gms/maps/model/internal/i$a$a:le	Landroid/os/IBinder;
        //   36: bipush 19
        //   38: aload_2
        //   39: aload_3
        //   40: iconst_0
        //   41: invokeinterface 41 5 0
        //   46: pop
        //   47: aload_3
        //   48: invokevirtual 44	android/os/Parcel:readException	()V
        //   51: aload_3
        //   52: invokevirtual 70	android/os/Parcel:readInt	()I
        //   55: istore 7
        //   57: iconst_0
        //   58: istore 8
        //   60: iload 7
        //   62: ifeq +6 -> 68
        //   65: iconst_1
        //   66: istore 8
        //   68: aload_3
        //   69: invokevirtual 47	android/os/Parcel:recycle	()V
        //   72: aload_2
        //   73: invokevirtual 47	android/os/Parcel:recycle	()V
        //   76: iload 8
        //   78: ireturn
        //   79: aconst_null
        //   80: astore 5
        //   82: goto -56 -> 26
        //   85: astore 4
        //   87: aload_3
        //   88: invokevirtual 47	android/os/Parcel:recycle	()V
        //   91: aload_2
        //   92: invokevirtual 47	android/os/Parcel:recycle	()V
        //   95: aload 4
        //   97: athrow
        // Local variable table:
        //   start	length	slot	name	signature
        //   0	98	0	this	a
        //   0	98	1	parami	i
        //   3	89	2	localParcel1	Parcel
        //   7	81	3	localParcel2	Parcel
        //   85	11	4	localObject	Object
        //   24	57	5	localIBinder	IBinder
        //   55	6	7	i	int
        //   58	19	8	bool	boolean
        // Exception table:
        //   from	to	target	type
        //   8	14	85	finally
        //   18	26	85	finally
        //   26	57	85	finally
      }
      
      public IBinder asBinder()
      {
        return this.le;
      }
      
      public float getBearing()
        throws RemoteException
      {
        Parcel localParcel1 = Parcel.obtain();
        Parcel localParcel2 = Parcel.obtain();
        try
        {
          localParcel1.writeInterfaceToken("com.google.android.gms.maps.model.internal.IGroundOverlayDelegate");
          this.le.transact(12, localParcel1, localParcel2, 0);
          localParcel2.readException();
          float f = localParcel2.readFloat();
          return f;
        }
        finally
        {
          localParcel2.recycle();
          localParcel1.recycle();
        }
      }
      
      /* Error */
      public LatLngBounds getBounds()
        throws RemoteException
      {
        // Byte code:
        //   0: invokestatic 25	android/os/Parcel:obtain	()Landroid/os/Parcel;
        //   3: astore_1
        //   4: invokestatic 25	android/os/Parcel:obtain	()Landroid/os/Parcel;
        //   7: astore_2
        //   8: aload_1
        //   9: ldc 27
        //   11: invokevirtual 31	android/os/Parcel:writeInterfaceToken	(Ljava/lang/String;)V
        //   14: aload_0
        //   15: getfield 15	com/google/android/gms/maps/model/internal/i$a$a:le	Landroid/os/IBinder;
        //   18: bipush 10
        //   20: aload_1
        //   21: aload_2
        //   22: iconst_0
        //   23: invokeinterface 41 5 0
        //   28: pop
        //   29: aload_2
        //   30: invokevirtual 44	android/os/Parcel:readException	()V
        //   33: aload_2
        //   34: invokevirtual 70	android/os/Parcel:readInt	()I
        //   37: ifeq +27 -> 64
        //   40: getstatic 83	com/google/android/gms/maps/model/LatLngBounds:CREATOR	Lcom/google/android/gms/maps/model/g;
        //   43: aload_2
        //   44: invokevirtual 89	com/google/android/gms/maps/model/g:dd	(Landroid/os/Parcel;)Lcom/google/android/gms/maps/model/LatLngBounds;
        //   47: astore 6
        //   49: aload 6
        //   51: astore 5
        //   53: aload_2
        //   54: invokevirtual 47	android/os/Parcel:recycle	()V
        //   57: aload_1
        //   58: invokevirtual 47	android/os/Parcel:recycle	()V
        //   61: aload 5
        //   63: areturn
        //   64: aconst_null
        //   65: astore 5
        //   67: goto -14 -> 53
        //   70: astore_3
        //   71: aload_2
        //   72: invokevirtual 47	android/os/Parcel:recycle	()V
        //   75: aload_1
        //   76: invokevirtual 47	android/os/Parcel:recycle	()V
        //   79: aload_3
        //   80: athrow
        // Local variable table:
        //   start	length	slot	name	signature
        //   0	81	0	this	a
        //   3	73	1	localParcel1	Parcel
        //   7	65	2	localParcel2	Parcel
        //   70	10	3	localObject	Object
        //   51	15	5	localLatLngBounds1	LatLngBounds
        //   47	3	6	localLatLngBounds2	LatLngBounds
        // Exception table:
        //   from	to	target	type
        //   8	49	70	finally
      }
      
      public float getHeight()
        throws RemoteException
      {
        Parcel localParcel1 = Parcel.obtain();
        Parcel localParcel2 = Parcel.obtain();
        try
        {
          localParcel1.writeInterfaceToken("com.google.android.gms.maps.model.internal.IGroundOverlayDelegate");
          this.le.transact(8, localParcel1, localParcel2, 0);
          localParcel2.readException();
          float f = localParcel2.readFloat();
          return f;
        }
        finally
        {
          localParcel2.recycle();
          localParcel1.recycle();
        }
      }
      
      public String getId()
        throws RemoteException
      {
        Parcel localParcel1 = Parcel.obtain();
        Parcel localParcel2 = Parcel.obtain();
        try
        {
          localParcel1.writeInterfaceToken("com.google.android.gms.maps.model.internal.IGroundOverlayDelegate");
          this.le.transact(2, localParcel1, localParcel2, 0);
          localParcel2.readException();
          String str = localParcel2.readString();
          return str;
        }
        finally
        {
          localParcel2.recycle();
          localParcel1.recycle();
        }
      }
      
      /* Error */
      public LatLng getPosition()
        throws RemoteException
      {
        // Byte code:
        //   0: invokestatic 25	android/os/Parcel:obtain	()Landroid/os/Parcel;
        //   3: astore_1
        //   4: invokestatic 25	android/os/Parcel:obtain	()Landroid/os/Parcel;
        //   7: astore_2
        //   8: aload_1
        //   9: ldc 27
        //   11: invokevirtual 31	android/os/Parcel:writeInterfaceToken	(Ljava/lang/String;)V
        //   14: aload_0
        //   15: getfield 15	com/google/android/gms/maps/model/internal/i$a$a:le	Landroid/os/IBinder;
        //   18: iconst_4
        //   19: aload_1
        //   20: aload_2
        //   21: iconst_0
        //   22: invokeinterface 41 5 0
        //   27: pop
        //   28: aload_2
        //   29: invokevirtual 44	android/os/Parcel:readException	()V
        //   32: aload_2
        //   33: invokevirtual 70	android/os/Parcel:readInt	()I
        //   36: ifeq +27 -> 63
        //   39: getstatic 102	com/google/android/gms/maps/model/LatLng:CREATOR	Lcom/google/android/gms/maps/model/i;
        //   42: aload_2
        //   43: invokevirtual 108	com/google/android/gms/maps/model/i:de	(Landroid/os/Parcel;)Lcom/google/android/gms/maps/model/LatLng;
        //   46: astore 6
        //   48: aload 6
        //   50: astore 5
        //   52: aload_2
        //   53: invokevirtual 47	android/os/Parcel:recycle	()V
        //   56: aload_1
        //   57: invokevirtual 47	android/os/Parcel:recycle	()V
        //   60: aload 5
        //   62: areturn
        //   63: aconst_null
        //   64: astore 5
        //   66: goto -14 -> 52
        //   69: astore_3
        //   70: aload_2
        //   71: invokevirtual 47	android/os/Parcel:recycle	()V
        //   74: aload_1
        //   75: invokevirtual 47	android/os/Parcel:recycle	()V
        //   78: aload_3
        //   79: athrow
        // Local variable table:
        //   start	length	slot	name	signature
        //   0	80	0	this	a
        //   3	72	1	localParcel1	Parcel
        //   7	64	2	localParcel2	Parcel
        //   69	10	3	localObject	Object
        //   50	15	5	localLatLng1	LatLng
        //   46	3	6	localLatLng2	LatLng
        // Exception table:
        //   from	to	target	type
        //   8	48	69	finally
      }
      
      public float getTransparency()
        throws RemoteException
      {
        Parcel localParcel1 = Parcel.obtain();
        Parcel localParcel2 = Parcel.obtain();
        try
        {
          localParcel1.writeInterfaceToken("com.google.android.gms.maps.model.internal.IGroundOverlayDelegate");
          this.le.transact(18, localParcel1, localParcel2, 0);
          localParcel2.readException();
          float f = localParcel2.readFloat();
          return f;
        }
        finally
        {
          localParcel2.recycle();
          localParcel1.recycle();
        }
      }
      
      public float getWidth()
        throws RemoteException
      {
        Parcel localParcel1 = Parcel.obtain();
        Parcel localParcel2 = Parcel.obtain();
        try
        {
          localParcel1.writeInterfaceToken("com.google.android.gms.maps.model.internal.IGroundOverlayDelegate");
          this.le.transact(7, localParcel1, localParcel2, 0);
          localParcel2.readException();
          float f = localParcel2.readFloat();
          return f;
        }
        finally
        {
          localParcel2.recycle();
          localParcel1.recycle();
        }
      }
      
      public float getZIndex()
        throws RemoteException
      {
        Parcel localParcel1 = Parcel.obtain();
        Parcel localParcel2 = Parcel.obtain();
        try
        {
          localParcel1.writeInterfaceToken("com.google.android.gms.maps.model.internal.IGroundOverlayDelegate");
          this.le.transact(14, localParcel1, localParcel2, 0);
          localParcel2.readException();
          float f = localParcel2.readFloat();
          return f;
        }
        finally
        {
          localParcel2.recycle();
          localParcel1.recycle();
        }
      }
      
      public int hashCodeRemote()
        throws RemoteException
      {
        Parcel localParcel1 = Parcel.obtain();
        Parcel localParcel2 = Parcel.obtain();
        try
        {
          localParcel1.writeInterfaceToken("com.google.android.gms.maps.model.internal.IGroundOverlayDelegate");
          this.le.transact(20, localParcel1, localParcel2, 0);
          localParcel2.readException();
          int i = localParcel2.readInt();
          return i;
        }
        finally
        {
          localParcel2.recycle();
          localParcel1.recycle();
        }
      }
      
      public boolean isVisible()
        throws RemoteException
      {
        Parcel localParcel1 = Parcel.obtain();
        Parcel localParcel2 = Parcel.obtain();
        try
        {
          localParcel1.writeInterfaceToken("com.google.android.gms.maps.model.internal.IGroundOverlayDelegate");
          this.le.transact(16, localParcel1, localParcel2, 0);
          localParcel2.readException();
          int i = localParcel2.readInt();
          boolean bool = false;
          if (i != 0) {
            bool = true;
          }
          return bool;
        }
        finally
        {
          localParcel2.recycle();
          localParcel1.recycle();
        }
      }
      
      /* Error */
      public void m(d paramd)
        throws RemoteException
      {
        // Byte code:
        //   0: invokestatic 25	android/os/Parcel:obtain	()Landroid/os/Parcel;
        //   3: astore_2
        //   4: invokestatic 25	android/os/Parcel:obtain	()Landroid/os/Parcel;
        //   7: astore_3
        //   8: aload_2
        //   9: ldc 27
        //   11: invokevirtual 31	android/os/Parcel:writeInterfaceToken	(Ljava/lang/String;)V
        //   14: aload_1
        //   15: ifnull +45 -> 60
        //   18: aload_1
        //   19: invokeinterface 119 1 0
        //   24: astore 5
        //   26: aload_2
        //   27: aload 5
        //   29: invokevirtual 66	android/os/Parcel:writeStrongBinder	(Landroid/os/IBinder;)V
        //   32: aload_0
        //   33: getfield 15	com/google/android/gms/maps/model/internal/i$a$a:le	Landroid/os/IBinder;
        //   36: bipush 21
        //   38: aload_2
        //   39: aload_3
        //   40: iconst_0
        //   41: invokeinterface 41 5 0
        //   46: pop
        //   47: aload_3
        //   48: invokevirtual 44	android/os/Parcel:readException	()V
        //   51: aload_3
        //   52: invokevirtual 47	android/os/Parcel:recycle	()V
        //   55: aload_2
        //   56: invokevirtual 47	android/os/Parcel:recycle	()V
        //   59: return
        //   60: aconst_null
        //   61: astore 5
        //   63: goto -37 -> 26
        //   66: astore 4
        //   68: aload_3
        //   69: invokevirtual 47	android/os/Parcel:recycle	()V
        //   72: aload_2
        //   73: invokevirtual 47	android/os/Parcel:recycle	()V
        //   76: aload 4
        //   78: athrow
        // Local variable table:
        //   start	length	slot	name	signature
        //   0	79	0	this	a
        //   0	79	1	paramd	d
        //   3	70	2	localParcel1	Parcel
        //   7	62	3	localParcel2	Parcel
        //   66	11	4	localObject	Object
        //   24	38	5	localIBinder	IBinder
        // Exception table:
        //   from	to	target	type
        //   8	14	66	finally
        //   18	26	66	finally
        //   26	51	66	finally
      }
      
      public void remove()
        throws RemoteException
      {
        Parcel localParcel1 = Parcel.obtain();
        Parcel localParcel2 = Parcel.obtain();
        try
        {
          localParcel1.writeInterfaceToken("com.google.android.gms.maps.model.internal.IGroundOverlayDelegate");
          this.le.transact(1, localParcel1, localParcel2, 0);
          localParcel2.readException();
          return;
        }
        finally
        {
          localParcel2.recycle();
          localParcel1.recycle();
        }
      }
      
      public void setBearing(float paramFloat)
        throws RemoteException
      {
        Parcel localParcel1 = Parcel.obtain();
        Parcel localParcel2 = Parcel.obtain();
        try
        {
          localParcel1.writeInterfaceToken("com.google.android.gms.maps.model.internal.IGroundOverlayDelegate");
          localParcel1.writeFloat(paramFloat);
          this.le.transact(11, localParcel1, localParcel2, 0);
          localParcel2.readException();
          return;
        }
        finally
        {
          localParcel2.recycle();
          localParcel1.recycle();
        }
      }
      
      public void setDimensions(float paramFloat)
        throws RemoteException
      {
        Parcel localParcel1 = Parcel.obtain();
        Parcel localParcel2 = Parcel.obtain();
        try
        {
          localParcel1.writeInterfaceToken("com.google.android.gms.maps.model.internal.IGroundOverlayDelegate");
          localParcel1.writeFloat(paramFloat);
          this.le.transact(5, localParcel1, localParcel2, 0);
          localParcel2.readException();
          return;
        }
        finally
        {
          localParcel2.recycle();
          localParcel1.recycle();
        }
      }
      
      /* Error */
      public void setPosition(LatLng paramLatLng)
        throws RemoteException
      {
        // Byte code:
        //   0: invokestatic 25	android/os/Parcel:obtain	()Landroid/os/Parcel;
        //   3: astore_2
        //   4: invokestatic 25	android/os/Parcel:obtain	()Landroid/os/Parcel;
        //   7: astore_3
        //   8: aload_2
        //   9: ldc 27
        //   11: invokevirtual 31	android/os/Parcel:writeInterfaceToken	(Ljava/lang/String;)V
        //   14: aload_1
        //   15: ifnull +41 -> 56
        //   18: aload_2
        //   19: iconst_1
        //   20: invokevirtual 52	android/os/Parcel:writeInt	(I)V
        //   23: aload_1
        //   24: aload_2
        //   25: iconst_0
        //   26: invokevirtual 125	com/google/android/gms/maps/model/LatLng:writeToParcel	(Landroid/os/Parcel;I)V
        //   29: aload_0
        //   30: getfield 15	com/google/android/gms/maps/model/internal/i$a$a:le	Landroid/os/IBinder;
        //   33: iconst_3
        //   34: aload_2
        //   35: aload_3
        //   36: iconst_0
        //   37: invokeinterface 41 5 0
        //   42: pop
        //   43: aload_3
        //   44: invokevirtual 44	android/os/Parcel:readException	()V
        //   47: aload_3
        //   48: invokevirtual 47	android/os/Parcel:recycle	()V
        //   51: aload_2
        //   52: invokevirtual 47	android/os/Parcel:recycle	()V
        //   55: return
        //   56: aload_2
        //   57: iconst_0
        //   58: invokevirtual 52	android/os/Parcel:writeInt	(I)V
        //   61: goto -32 -> 29
        //   64: astore 4
        //   66: aload_3
        //   67: invokevirtual 47	android/os/Parcel:recycle	()V
        //   70: aload_2
        //   71: invokevirtual 47	android/os/Parcel:recycle	()V
        //   74: aload 4
        //   76: athrow
        // Local variable table:
        //   start	length	slot	name	signature
        //   0	77	0	this	a
        //   0	77	1	paramLatLng	LatLng
        //   3	68	2	localParcel1	Parcel
        //   7	60	3	localParcel2	Parcel
        //   64	11	4	localObject	Object
        // Exception table:
        //   from	to	target	type
        //   8	14	64	finally
        //   18	29	64	finally
        //   29	47	64	finally
        //   56	61	64	finally
      }
      
      /* Error */
      public void setPositionFromBounds(LatLngBounds paramLatLngBounds)
        throws RemoteException
      {
        // Byte code:
        //   0: invokestatic 25	android/os/Parcel:obtain	()Landroid/os/Parcel;
        //   3: astore_2
        //   4: invokestatic 25	android/os/Parcel:obtain	()Landroid/os/Parcel;
        //   7: astore_3
        //   8: aload_2
        //   9: ldc 27
        //   11: invokevirtual 31	android/os/Parcel:writeInterfaceToken	(Ljava/lang/String;)V
        //   14: aload_1
        //   15: ifnull +42 -> 57
        //   18: aload_2
        //   19: iconst_1
        //   20: invokevirtual 52	android/os/Parcel:writeInt	(I)V
        //   23: aload_1
        //   24: aload_2
        //   25: iconst_0
        //   26: invokevirtual 128	com/google/android/gms/maps/model/LatLngBounds:writeToParcel	(Landroid/os/Parcel;I)V
        //   29: aload_0
        //   30: getfield 15	com/google/android/gms/maps/model/internal/i$a$a:le	Landroid/os/IBinder;
        //   33: bipush 9
        //   35: aload_2
        //   36: aload_3
        //   37: iconst_0
        //   38: invokeinterface 41 5 0
        //   43: pop
        //   44: aload_3
        //   45: invokevirtual 44	android/os/Parcel:readException	()V
        //   48: aload_3
        //   49: invokevirtual 47	android/os/Parcel:recycle	()V
        //   52: aload_2
        //   53: invokevirtual 47	android/os/Parcel:recycle	()V
        //   56: return
        //   57: aload_2
        //   58: iconst_0
        //   59: invokevirtual 52	android/os/Parcel:writeInt	(I)V
        //   62: goto -33 -> 29
        //   65: astore 4
        //   67: aload_3
        //   68: invokevirtual 47	android/os/Parcel:recycle	()V
        //   71: aload_2
        //   72: invokevirtual 47	android/os/Parcel:recycle	()V
        //   75: aload 4
        //   77: athrow
        // Local variable table:
        //   start	length	slot	name	signature
        //   0	78	0	this	a
        //   0	78	1	paramLatLngBounds	LatLngBounds
        //   3	69	2	localParcel1	Parcel
        //   7	61	3	localParcel2	Parcel
        //   65	11	4	localObject	Object
        // Exception table:
        //   from	to	target	type
        //   8	14	65	finally
        //   18	29	65	finally
        //   29	48	65	finally
        //   57	62	65	finally
      }
      
      public void setTransparency(float paramFloat)
        throws RemoteException
      {
        Parcel localParcel1 = Parcel.obtain();
        Parcel localParcel2 = Parcel.obtain();
        try
        {
          localParcel1.writeInterfaceToken("com.google.android.gms.maps.model.internal.IGroundOverlayDelegate");
          localParcel1.writeFloat(paramFloat);
          this.le.transact(17, localParcel1, localParcel2, 0);
          localParcel2.readException();
          return;
        }
        finally
        {
          localParcel2.recycle();
          localParcel1.recycle();
        }
      }
      
      public void setVisible(boolean paramBoolean)
        throws RemoteException
      {
        Parcel localParcel1 = Parcel.obtain();
        Parcel localParcel2 = Parcel.obtain();
        try
        {
          localParcel1.writeInterfaceToken("com.google.android.gms.maps.model.internal.IGroundOverlayDelegate");
          int i = 0;
          if (paramBoolean) {
            i = 1;
          }
          localParcel1.writeInt(i);
          this.le.transact(15, localParcel1, localParcel2, 0);
          localParcel2.readException();
          return;
        }
        finally
        {
          localParcel2.recycle();
          localParcel1.recycle();
        }
      }
      
      public void setZIndex(float paramFloat)
        throws RemoteException
      {
        Parcel localParcel1 = Parcel.obtain();
        Parcel localParcel2 = Parcel.obtain();
        try
        {
          localParcel1.writeInterfaceToken("com.google.android.gms.maps.model.internal.IGroundOverlayDelegate");
          localParcel1.writeFloat(paramFloat);
          this.le.transact(13, localParcel1, localParcel2, 0);
          localParcel2.readException();
          return;
        }
        finally
        {
          localParcel2.recycle();
          localParcel1.recycle();
        }
      }
    }
  }
}


/* Location:           C:\Users\TGKIM\Downloads\작업폴더\리버싱\androidReversetools\jd-gui-0.3.6.windows\com.appg.golfmon-1-dex2jar.jar
 * Qualified Name:     com.google.android.gms.maps.model.internal.i
 * JD-Core Version:    0.7.0.1
 */