package com.google.android.gms.maps.model.internal;

import android.os.Binder;
import android.os.IBinder;
import android.os.IInterface;
import android.os.Parcel;
import android.os.RemoteException;
import java.util.ArrayList;
import java.util.List;

public abstract interface j
  extends IInterface
{
  public abstract boolean b(j paramj)
    throws RemoteException;
  
  public abstract int getActiveLevelIndex()
    throws RemoteException;
  
  public abstract int getDefaultLevelIndex()
    throws RemoteException;
  
  public abstract List<IBinder> getLevels()
    throws RemoteException;
  
  public abstract int hashCodeRemote()
    throws RemoteException;
  
  public abstract boolean isUnderground()
    throws RemoteException;
  
  public static abstract class a
    extends Binder
    implements j
  {
    public static j by(IBinder paramIBinder)
    {
      if (paramIBinder == null) {
        return null;
      }
      IInterface localIInterface = paramIBinder.queryLocalInterface("com.google.android.gms.maps.model.internal.IIndoorBuildingDelegate");
      if ((localIInterface != null) && ((localIInterface instanceof j))) {
        return (j)localIInterface;
      }
      return new a(paramIBinder);
    }
    
    public boolean onTransact(int paramInt1, Parcel paramParcel1, Parcel paramParcel2, int paramInt2)
      throws RemoteException
    {
      switch (paramInt1)
      {
      default: 
        return super.onTransact(paramInt1, paramParcel1, paramParcel2, paramInt2);
      case 1598968902: 
        paramParcel2.writeString("com.google.android.gms.maps.model.internal.IIndoorBuildingDelegate");
        return true;
      case 1: 
        paramParcel1.enforceInterface("com.google.android.gms.maps.model.internal.IIndoorBuildingDelegate");
        int n = getActiveLevelIndex();
        paramParcel2.writeNoException();
        paramParcel2.writeInt(n);
        return true;
      case 2: 
        paramParcel1.enforceInterface("com.google.android.gms.maps.model.internal.IIndoorBuildingDelegate");
        int m = getDefaultLevelIndex();
        paramParcel2.writeNoException();
        paramParcel2.writeInt(m);
        return true;
      case 3: 
        paramParcel1.enforceInterface("com.google.android.gms.maps.model.internal.IIndoorBuildingDelegate");
        List localList = getLevels();
        paramParcel2.writeNoException();
        paramParcel2.writeBinderList(localList);
        return true;
      case 4: 
        paramParcel1.enforceInterface("com.google.android.gms.maps.model.internal.IIndoorBuildingDelegate");
        boolean bool2 = isUnderground();
        paramParcel2.writeNoException();
        int k = 0;
        if (bool2) {
          k = 1;
        }
        paramParcel2.writeInt(k);
        return true;
      case 5: 
        paramParcel1.enforceInterface("com.google.android.gms.maps.model.internal.IIndoorBuildingDelegate");
        boolean bool1 = b(by(paramParcel1.readStrongBinder()));
        paramParcel2.writeNoException();
        int j = 0;
        if (bool1) {
          j = 1;
        }
        paramParcel2.writeInt(j);
        return true;
      }
      paramParcel1.enforceInterface("com.google.android.gms.maps.model.internal.IIndoorBuildingDelegate");
      int i = hashCodeRemote();
      paramParcel2.writeNoException();
      paramParcel2.writeInt(i);
      return true;
    }
    
    private static class a
      implements j
    {
      private IBinder le;
      
      a(IBinder paramIBinder)
      {
        this.le = paramIBinder;
      }
      
      public IBinder asBinder()
      {
        return this.le;
      }
      
      /* Error */
      public boolean b(j paramj)
        throws RemoteException
      {
        // Byte code:
        //   0: invokestatic 27	android/os/Parcel:obtain	()Landroid/os/Parcel;
        //   3: astore_2
        //   4: invokestatic 27	android/os/Parcel:obtain	()Landroid/os/Parcel;
        //   7: astore_3
        //   8: aload_2
        //   9: ldc 29
        //   11: invokevirtual 33	android/os/Parcel:writeInterfaceToken	(Ljava/lang/String;)V
        //   14: aload_1
        //   15: ifnull +63 -> 78
        //   18: aload_1
        //   19: invokeinterface 35 1 0
        //   24: astore 5
        //   26: aload_2
        //   27: aload 5
        //   29: invokevirtual 38	android/os/Parcel:writeStrongBinder	(Landroid/os/IBinder;)V
        //   32: aload_0
        //   33: getfield 15	com/google/android/gms/maps/model/internal/j$a$a:le	Landroid/os/IBinder;
        //   36: iconst_5
        //   37: aload_2
        //   38: aload_3
        //   39: iconst_0
        //   40: invokeinterface 44 5 0
        //   45: pop
        //   46: aload_3
        //   47: invokevirtual 47	android/os/Parcel:readException	()V
        //   50: aload_3
        //   51: invokevirtual 51	android/os/Parcel:readInt	()I
        //   54: istore 7
        //   56: iconst_0
        //   57: istore 8
        //   59: iload 7
        //   61: ifeq +6 -> 67
        //   64: iconst_1
        //   65: istore 8
        //   67: aload_3
        //   68: invokevirtual 54	android/os/Parcel:recycle	()V
        //   71: aload_2
        //   72: invokevirtual 54	android/os/Parcel:recycle	()V
        //   75: iload 8
        //   77: ireturn
        //   78: aconst_null
        //   79: astore 5
        //   81: goto -55 -> 26
        //   84: astore 4
        //   86: aload_3
        //   87: invokevirtual 54	android/os/Parcel:recycle	()V
        //   90: aload_2
        //   91: invokevirtual 54	android/os/Parcel:recycle	()V
        //   94: aload 4
        //   96: athrow
        // Local variable table:
        //   start	length	slot	name	signature
        //   0	97	0	this	a
        //   0	97	1	paramj	j
        //   3	88	2	localParcel1	Parcel
        //   7	80	3	localParcel2	Parcel
        //   84	11	4	localObject	Object
        //   24	56	5	localIBinder	IBinder
        //   54	6	7	i	int
        //   57	19	8	bool	boolean
        // Exception table:
        //   from	to	target	type
        //   8	14	84	finally
        //   18	26	84	finally
        //   26	56	84	finally
      }
      
      public int getActiveLevelIndex()
        throws RemoteException
      {
        Parcel localParcel1 = Parcel.obtain();
        Parcel localParcel2 = Parcel.obtain();
        try
        {
          localParcel1.writeInterfaceToken("com.google.android.gms.maps.model.internal.IIndoorBuildingDelegate");
          this.le.transact(1, localParcel1, localParcel2, 0);
          localParcel2.readException();
          int i = localParcel2.readInt();
          return i;
        }
        finally
        {
          localParcel2.recycle();
          localParcel1.recycle();
        }
      }
      
      public int getDefaultLevelIndex()
        throws RemoteException
      {
        Parcel localParcel1 = Parcel.obtain();
        Parcel localParcel2 = Parcel.obtain();
        try
        {
          localParcel1.writeInterfaceToken("com.google.android.gms.maps.model.internal.IIndoorBuildingDelegate");
          this.le.transact(2, localParcel1, localParcel2, 0);
          localParcel2.readException();
          int i = localParcel2.readInt();
          return i;
        }
        finally
        {
          localParcel2.recycle();
          localParcel1.recycle();
        }
      }
      
      public List<IBinder> getLevels()
        throws RemoteException
      {
        Parcel localParcel1 = Parcel.obtain();
        Parcel localParcel2 = Parcel.obtain();
        try
        {
          localParcel1.writeInterfaceToken("com.google.android.gms.maps.model.internal.IIndoorBuildingDelegate");
          this.le.transact(3, localParcel1, localParcel2, 0);
          localParcel2.readException();
          ArrayList localArrayList = localParcel2.createBinderArrayList();
          return localArrayList;
        }
        finally
        {
          localParcel2.recycle();
          localParcel1.recycle();
        }
      }
      
      public int hashCodeRemote()
        throws RemoteException
      {
        Parcel localParcel1 = Parcel.obtain();
        Parcel localParcel2 = Parcel.obtain();
        try
        {
          localParcel1.writeInterfaceToken("com.google.android.gms.maps.model.internal.IIndoorBuildingDelegate");
          this.le.transact(6, localParcel1, localParcel2, 0);
          localParcel2.readException();
          int i = localParcel2.readInt();
          return i;
        }
        finally
        {
          localParcel2.recycle();
          localParcel1.recycle();
        }
      }
      
      public boolean isUnderground()
        throws RemoteException
      {
        Parcel localParcel1 = Parcel.obtain();
        Parcel localParcel2 = Parcel.obtain();
        try
        {
          localParcel1.writeInterfaceToken("com.google.android.gms.maps.model.internal.IIndoorBuildingDelegate");
          this.le.transact(4, localParcel1, localParcel2, 0);
          localParcel2.readException();
          int i = localParcel2.readInt();
          boolean bool = false;
          if (i != 0) {
            bool = true;
          }
          return bool;
        }
        finally
        {
          localParcel2.recycle();
          localParcel1.recycle();
        }
      }
    }
  }
}


/* Location:           C:\Users\TGKIM\Downloads\작업폴더\리버싱\androidReversetools\jd-gui-0.3.6.windows\com.appg.golfmon-1-dex2jar.jar
 * Qualified Name:     com.google.android.gms.maps.model.internal.j
 * JD-Core Version:    0.7.0.1
 */