package com.google.android.gms.maps.model.internal;

import android.os.Binder;
import android.os.IBinder;
import android.os.IInterface;
import android.os.Parcel;
import android.os.RemoteException;

public abstract interface n
  extends IInterface
{
  public abstract boolean a(n paramn)
    throws RemoteException;
  
  public abstract void clearTileCache()
    throws RemoteException;
  
  public abstract boolean getFadeIn()
    throws RemoteException;
  
  public abstract String getId()
    throws RemoteException;
  
  public abstract float getZIndex()
    throws RemoteException;
  
  public abstract int hashCodeRemote()
    throws RemoteException;
  
  public abstract boolean isVisible()
    throws RemoteException;
  
  public abstract void remove()
    throws RemoteException;
  
  public abstract void setFadeIn(boolean paramBoolean)
    throws RemoteException;
  
  public abstract void setVisible(boolean paramBoolean)
    throws RemoteException;
  
  public abstract void setZIndex(float paramFloat)
    throws RemoteException;
  
  public static abstract class a
    extends Binder
    implements n
  {
    public static n bD(IBinder paramIBinder)
    {
      if (paramIBinder == null) {
        return null;
      }
      IInterface localIInterface = paramIBinder.queryLocalInterface("com.google.android.gms.maps.model.internal.ITileOverlayDelegate");
      if ((localIInterface != null) && ((localIInterface instanceof n))) {
        return (n)localIInterface;
      }
      return new a(paramIBinder);
    }
    
    public boolean onTransact(int paramInt1, Parcel paramParcel1, Parcel paramParcel2, int paramInt2)
      throws RemoteException
    {
      switch (paramInt1)
      {
      default: 
        return super.onTransact(paramInt1, paramParcel1, paramParcel2, paramInt2);
      case 1598968902: 
        paramParcel2.writeString("com.google.android.gms.maps.model.internal.ITileOverlayDelegate");
        return true;
      case 1: 
        paramParcel1.enforceInterface("com.google.android.gms.maps.model.internal.ITileOverlayDelegate");
        remove();
        paramParcel2.writeNoException();
        return true;
      case 2: 
        paramParcel1.enforceInterface("com.google.android.gms.maps.model.internal.ITileOverlayDelegate");
        clearTileCache();
        paramParcel2.writeNoException();
        return true;
      case 3: 
        paramParcel1.enforceInterface("com.google.android.gms.maps.model.internal.ITileOverlayDelegate");
        String str = getId();
        paramParcel2.writeNoException();
        paramParcel2.writeString(str);
        return true;
      case 4: 
        paramParcel1.enforceInterface("com.google.android.gms.maps.model.internal.ITileOverlayDelegate");
        setZIndex(paramParcel1.readFloat());
        paramParcel2.writeNoException();
        return true;
      case 5: 
        paramParcel1.enforceInterface("com.google.android.gms.maps.model.internal.ITileOverlayDelegate");
        float f = getZIndex();
        paramParcel2.writeNoException();
        paramParcel2.writeFloat(f);
        return true;
      case 6: 
        paramParcel1.enforceInterface("com.google.android.gms.maps.model.internal.ITileOverlayDelegate");
        int i1 = paramParcel1.readInt();
        boolean bool5 = false;
        if (i1 != 0) {
          bool5 = true;
        }
        setVisible(bool5);
        paramParcel2.writeNoException();
        return true;
      case 7: 
        paramParcel1.enforceInterface("com.google.android.gms.maps.model.internal.ITileOverlayDelegate");
        boolean bool4 = isVisible();
        paramParcel2.writeNoException();
        int n = 0;
        if (bool4) {
          n = 1;
        }
        paramParcel2.writeInt(n);
        return true;
      case 8: 
        paramParcel1.enforceInterface("com.google.android.gms.maps.model.internal.ITileOverlayDelegate");
        boolean bool3 = a(bD(paramParcel1.readStrongBinder()));
        paramParcel2.writeNoException();
        int m = 0;
        if (bool3) {
          m = 1;
        }
        paramParcel2.writeInt(m);
        return true;
      case 9: 
        paramParcel1.enforceInterface("com.google.android.gms.maps.model.internal.ITileOverlayDelegate");
        int k = hashCodeRemote();
        paramParcel2.writeNoException();
        paramParcel2.writeInt(k);
        return true;
      case 10: 
        paramParcel1.enforceInterface("com.google.android.gms.maps.model.internal.ITileOverlayDelegate");
        int j = paramParcel1.readInt();
        boolean bool2 = false;
        if (j != 0) {
          bool2 = true;
        }
        setFadeIn(bool2);
        paramParcel2.writeNoException();
        return true;
      }
      paramParcel1.enforceInterface("com.google.android.gms.maps.model.internal.ITileOverlayDelegate");
      boolean bool1 = getFadeIn();
      paramParcel2.writeNoException();
      int i = 0;
      if (bool1) {
        i = 1;
      }
      paramParcel2.writeInt(i);
      return true;
    }
    
    private static class a
      implements n
    {
      private IBinder le;
      
      a(IBinder paramIBinder)
      {
        this.le = paramIBinder;
      }
      
      /* Error */
      public boolean a(n paramn)
        throws RemoteException
      {
        // Byte code:
        //   0: invokestatic 25	android/os/Parcel:obtain	()Landroid/os/Parcel;
        //   3: astore_2
        //   4: invokestatic 25	android/os/Parcel:obtain	()Landroid/os/Parcel;
        //   7: astore_3
        //   8: aload_2
        //   9: ldc 27
        //   11: invokevirtual 31	android/os/Parcel:writeInterfaceToken	(Ljava/lang/String;)V
        //   14: aload_1
        //   15: ifnull +64 -> 79
        //   18: aload_1
        //   19: invokeinterface 35 1 0
        //   24: astore 5
        //   26: aload_2
        //   27: aload 5
        //   29: invokevirtual 38	android/os/Parcel:writeStrongBinder	(Landroid/os/IBinder;)V
        //   32: aload_0
        //   33: getfield 15	com/google/android/gms/maps/model/internal/n$a$a:le	Landroid/os/IBinder;
        //   36: bipush 8
        //   38: aload_2
        //   39: aload_3
        //   40: iconst_0
        //   41: invokeinterface 44 5 0
        //   46: pop
        //   47: aload_3
        //   48: invokevirtual 47	android/os/Parcel:readException	()V
        //   51: aload_3
        //   52: invokevirtual 51	android/os/Parcel:readInt	()I
        //   55: istore 7
        //   57: iconst_0
        //   58: istore 8
        //   60: iload 7
        //   62: ifeq +6 -> 68
        //   65: iconst_1
        //   66: istore 8
        //   68: aload_3
        //   69: invokevirtual 54	android/os/Parcel:recycle	()V
        //   72: aload_2
        //   73: invokevirtual 54	android/os/Parcel:recycle	()V
        //   76: iload 8
        //   78: ireturn
        //   79: aconst_null
        //   80: astore 5
        //   82: goto -56 -> 26
        //   85: astore 4
        //   87: aload_3
        //   88: invokevirtual 54	android/os/Parcel:recycle	()V
        //   91: aload_2
        //   92: invokevirtual 54	android/os/Parcel:recycle	()V
        //   95: aload 4
        //   97: athrow
        // Local variable table:
        //   start	length	slot	name	signature
        //   0	98	0	this	a
        //   0	98	1	paramn	n
        //   3	89	2	localParcel1	Parcel
        //   7	81	3	localParcel2	Parcel
        //   85	11	4	localObject	Object
        //   24	57	5	localIBinder	IBinder
        //   55	6	7	i	int
        //   58	19	8	bool	boolean
        // Exception table:
        //   from	to	target	type
        //   8	14	85	finally
        //   18	26	85	finally
        //   26	57	85	finally
      }
      
      public IBinder asBinder()
      {
        return this.le;
      }
      
      public void clearTileCache()
        throws RemoteException
      {
        Parcel localParcel1 = Parcel.obtain();
        Parcel localParcel2 = Parcel.obtain();
        try
        {
          localParcel1.writeInterfaceToken("com.google.android.gms.maps.model.internal.ITileOverlayDelegate");
          this.le.transact(2, localParcel1, localParcel2, 0);
          localParcel2.readException();
          return;
        }
        finally
        {
          localParcel2.recycle();
          localParcel1.recycle();
        }
      }
      
      public boolean getFadeIn()
        throws RemoteException
      {
        Parcel localParcel1 = Parcel.obtain();
        Parcel localParcel2 = Parcel.obtain();
        try
        {
          localParcel1.writeInterfaceToken("com.google.android.gms.maps.model.internal.ITileOverlayDelegate");
          this.le.transact(11, localParcel1, localParcel2, 0);
          localParcel2.readException();
          int i = localParcel2.readInt();
          boolean bool = false;
          if (i != 0) {
            bool = true;
          }
          return bool;
        }
        finally
        {
          localParcel2.recycle();
          localParcel1.recycle();
        }
      }
      
      public String getId()
        throws RemoteException
      {
        Parcel localParcel1 = Parcel.obtain();
        Parcel localParcel2 = Parcel.obtain();
        try
        {
          localParcel1.writeInterfaceToken("com.google.android.gms.maps.model.internal.ITileOverlayDelegate");
          this.le.transact(3, localParcel1, localParcel2, 0);
          localParcel2.readException();
          String str = localParcel2.readString();
          return str;
        }
        finally
        {
          localParcel2.recycle();
          localParcel1.recycle();
        }
      }
      
      public float getZIndex()
        throws RemoteException
      {
        Parcel localParcel1 = Parcel.obtain();
        Parcel localParcel2 = Parcel.obtain();
        try
        {
          localParcel1.writeInterfaceToken("com.google.android.gms.maps.model.internal.ITileOverlayDelegate");
          this.le.transact(5, localParcel1, localParcel2, 0);
          localParcel2.readException();
          float f = localParcel2.readFloat();
          return f;
        }
        finally
        {
          localParcel2.recycle();
          localParcel1.recycle();
        }
      }
      
      public int hashCodeRemote()
        throws RemoteException
      {
        Parcel localParcel1 = Parcel.obtain();
        Parcel localParcel2 = Parcel.obtain();
        try
        {
          localParcel1.writeInterfaceToken("com.google.android.gms.maps.model.internal.ITileOverlayDelegate");
          this.le.transact(9, localParcel1, localParcel2, 0);
          localParcel2.readException();
          int i = localParcel2.readInt();
          return i;
        }
        finally
        {
          localParcel2.recycle();
          localParcel1.recycle();
        }
      }
      
      public boolean isVisible()
        throws RemoteException
      {
        Parcel localParcel1 = Parcel.obtain();
        Parcel localParcel2 = Parcel.obtain();
        try
        {
          localParcel1.writeInterfaceToken("com.google.android.gms.maps.model.internal.ITileOverlayDelegate");
          this.le.transact(7, localParcel1, localParcel2, 0);
          localParcel2.readException();
          int i = localParcel2.readInt();
          boolean bool = false;
          if (i != 0) {
            bool = true;
          }
          return bool;
        }
        finally
        {
          localParcel2.recycle();
          localParcel1.recycle();
        }
      }
      
      public void remove()
        throws RemoteException
      {
        Parcel localParcel1 = Parcel.obtain();
        Parcel localParcel2 = Parcel.obtain();
        try
        {
          localParcel1.writeInterfaceToken("com.google.android.gms.maps.model.internal.ITileOverlayDelegate");
          this.le.transact(1, localParcel1, localParcel2, 0);
          localParcel2.readException();
          return;
        }
        finally
        {
          localParcel2.recycle();
          localParcel1.recycle();
        }
      }
      
      public void setFadeIn(boolean paramBoolean)
        throws RemoteException
      {
        Parcel localParcel1 = Parcel.obtain();
        Parcel localParcel2 = Parcel.obtain();
        try
        {
          localParcel1.writeInterfaceToken("com.google.android.gms.maps.model.internal.ITileOverlayDelegate");
          int i = 0;
          if (paramBoolean) {
            i = 1;
          }
          localParcel1.writeInt(i);
          this.le.transact(10, localParcel1, localParcel2, 0);
          localParcel2.readException();
          return;
        }
        finally
        {
          localParcel2.recycle();
          localParcel1.recycle();
        }
      }
      
      public void setVisible(boolean paramBoolean)
        throws RemoteException
      {
        Parcel localParcel1 = Parcel.obtain();
        Parcel localParcel2 = Parcel.obtain();
        try
        {
          localParcel1.writeInterfaceToken("com.google.android.gms.maps.model.internal.ITileOverlayDelegate");
          int i = 0;
          if (paramBoolean) {
            i = 1;
          }
          localParcel1.writeInt(i);
          this.le.transact(6, localParcel1, localParcel2, 0);
          localParcel2.readException();
          return;
        }
        finally
        {
          localParcel2.recycle();
          localParcel1.recycle();
        }
      }
      
      public void setZIndex(float paramFloat)
        throws RemoteException
      {
        Parcel localParcel1 = Parcel.obtain();
        Parcel localParcel2 = Parcel.obtain();
        try
        {
          localParcel1.writeInterfaceToken("com.google.android.gms.maps.model.internal.ITileOverlayDelegate");
          localParcel1.writeFloat(paramFloat);
          this.le.transact(4, localParcel1, localParcel2, 0);
          localParcel2.readException();
          return;
        }
        finally
        {
          localParcel2.recycle();
          localParcel1.recycle();
        }
      }
    }
  }
}


/* Location:           C:\Users\TGKIM\Downloads\작업폴더\리버싱\androidReversetools\jd-gui-0.3.6.windows\com.appg.golfmon-1-dex2jar.jar
 * Qualified Name:     com.google.android.gms.maps.model.internal.n
 * JD-Core Version:    0.7.0.1
 */