package com.google.android.gms.maps.internal;

import android.os.Binder;
import android.os.IBinder;
import android.os.IInterface;
import android.os.Parcel;
import android.os.RemoteException;
import com.google.android.gms.dynamic.d;
import com.google.android.gms.dynamic.d.a;
import com.google.android.gms.maps.GoogleMapOptions;
import com.google.android.gms.maps.StreetViewPanoramaOptions;
import com.google.android.gms.maps.a;
import com.google.android.gms.maps.model.internal.g;
import com.google.android.gms.maps.model.internal.g.a;

public abstract interface c
  extends IInterface
{
  public abstract IMapViewDelegate a(d paramd, GoogleMapOptions paramGoogleMapOptions)
    throws RemoteException;
  
  public abstract IStreetViewPanoramaViewDelegate a(d paramd, StreetViewPanoramaOptions paramStreetViewPanoramaOptions)
    throws RemoteException;
  
  public abstract void a(d paramd, int paramInt)
    throws RemoteException;
  
  public abstract void i(d paramd)
    throws RemoteException;
  
  public abstract IMapFragmentDelegate j(d paramd)
    throws RemoteException;
  
  public abstract IStreetViewPanoramaFragmentDelegate k(d paramd)
    throws RemoteException;
  
  public abstract ICameraUpdateFactoryDelegate nW()
    throws RemoteException;
  
  public abstract g nX()
    throws RemoteException;
  
  public static abstract class a
    extends Binder
    implements c
  {
    public static c aS(IBinder paramIBinder)
    {
      if (paramIBinder == null) {
        return null;
      }
      IInterface localIInterface = paramIBinder.queryLocalInterface("com.google.android.gms.maps.internal.ICreator");
      if ((localIInterface != null) && ((localIInterface instanceof c))) {
        return (c)localIInterface;
      }
      return new a(paramIBinder);
    }
    
    public boolean onTransact(int paramInt1, Parcel paramParcel1, Parcel paramParcel2, int paramInt2)
      throws RemoteException
    {
      switch (paramInt1)
      {
      default: 
        return super.onTransact(paramInt1, paramParcel1, paramParcel2, paramInt2);
      case 1598968902: 
        paramParcel2.writeString("com.google.android.gms.maps.internal.ICreator");
        return true;
      case 1: 
        paramParcel1.enforceInterface("com.google.android.gms.maps.internal.ICreator");
        i(d.a.ap(paramParcel1.readStrongBinder()));
        paramParcel2.writeNoException();
        return true;
      case 2: 
        paramParcel1.enforceInterface("com.google.android.gms.maps.internal.ICreator");
        IMapFragmentDelegate localIMapFragmentDelegate = j(d.a.ap(paramParcel1.readStrongBinder()));
        paramParcel2.writeNoException();
        IBinder localIBinder6 = null;
        if (localIMapFragmentDelegate != null) {
          localIBinder6 = localIMapFragmentDelegate.asBinder();
        }
        paramParcel2.writeStrongBinder(localIBinder6);
        return true;
      case 3: 
        paramParcel1.enforceInterface("com.google.android.gms.maps.internal.ICreator");
        d locald2 = d.a.ap(paramParcel1.readStrongBinder());
        if (paramParcel1.readInt() != 0) {}
        for (GoogleMapOptions localGoogleMapOptions = GoogleMapOptions.CREATOR.cX(paramParcel1);; localGoogleMapOptions = null)
        {
          IMapViewDelegate localIMapViewDelegate = a(locald2, localGoogleMapOptions);
          paramParcel2.writeNoException();
          IBinder localIBinder5 = null;
          if (localIMapViewDelegate != null) {
            localIBinder5 = localIMapViewDelegate.asBinder();
          }
          paramParcel2.writeStrongBinder(localIBinder5);
          return true;
        }
      case 4: 
        paramParcel1.enforceInterface("com.google.android.gms.maps.internal.ICreator");
        ICameraUpdateFactoryDelegate localICameraUpdateFactoryDelegate = nW();
        paramParcel2.writeNoException();
        IBinder localIBinder4 = null;
        if (localICameraUpdateFactoryDelegate != null) {
          localIBinder4 = localICameraUpdateFactoryDelegate.asBinder();
        }
        paramParcel2.writeStrongBinder(localIBinder4);
        return true;
      case 5: 
        paramParcel1.enforceInterface("com.google.android.gms.maps.internal.ICreator");
        g localg = nX();
        paramParcel2.writeNoException();
        IBinder localIBinder3 = null;
        if (localg != null) {
          localIBinder3 = localg.asBinder();
        }
        paramParcel2.writeStrongBinder(localIBinder3);
        return true;
      case 6: 
        paramParcel1.enforceInterface("com.google.android.gms.maps.internal.ICreator");
        a(d.a.ap(paramParcel1.readStrongBinder()), paramParcel1.readInt());
        paramParcel2.writeNoException();
        return true;
      case 7: 
        paramParcel1.enforceInterface("com.google.android.gms.maps.internal.ICreator");
        d locald1 = d.a.ap(paramParcel1.readStrongBinder());
        if (paramParcel1.readInt() != 0) {}
        for (StreetViewPanoramaOptions localStreetViewPanoramaOptions = StreetViewPanoramaOptions.CREATOR.cY(paramParcel1);; localStreetViewPanoramaOptions = null)
        {
          IStreetViewPanoramaViewDelegate localIStreetViewPanoramaViewDelegate = a(locald1, localStreetViewPanoramaOptions);
          paramParcel2.writeNoException();
          IBinder localIBinder2 = null;
          if (localIStreetViewPanoramaViewDelegate != null) {
            localIBinder2 = localIStreetViewPanoramaViewDelegate.asBinder();
          }
          paramParcel2.writeStrongBinder(localIBinder2);
          return true;
        }
      }
      paramParcel1.enforceInterface("com.google.android.gms.maps.internal.ICreator");
      IStreetViewPanoramaFragmentDelegate localIStreetViewPanoramaFragmentDelegate = k(d.a.ap(paramParcel1.readStrongBinder()));
      paramParcel2.writeNoException();
      IBinder localIBinder1 = null;
      if (localIStreetViewPanoramaFragmentDelegate != null) {
        localIBinder1 = localIStreetViewPanoramaFragmentDelegate.asBinder();
      }
      paramParcel2.writeStrongBinder(localIBinder1);
      return true;
    }
    
    private static class a
      implements c
    {
      private IBinder le;
      
      a(IBinder paramIBinder)
      {
        this.le = paramIBinder;
      }
      
      /* Error */
      public IMapViewDelegate a(d paramd, GoogleMapOptions paramGoogleMapOptions)
        throws RemoteException
      {
        // Byte code:
        //   0: invokestatic 25	android/os/Parcel:obtain	()Landroid/os/Parcel;
        //   3: astore_3
        //   4: invokestatic 25	android/os/Parcel:obtain	()Landroid/os/Parcel;
        //   7: astore 4
        //   9: aload_3
        //   10: ldc 27
        //   12: invokevirtual 31	android/os/Parcel:writeInterfaceToken	(Ljava/lang/String;)V
        //   15: aload_1
        //   16: ifnull +74 -> 90
        //   19: aload_1
        //   20: invokeinterface 37 1 0
        //   25: astore 6
        //   27: aload_3
        //   28: aload 6
        //   30: invokevirtual 40	android/os/Parcel:writeStrongBinder	(Landroid/os/IBinder;)V
        //   33: aload_2
        //   34: ifnull +62 -> 96
        //   37: aload_3
        //   38: iconst_1
        //   39: invokevirtual 44	android/os/Parcel:writeInt	(I)V
        //   42: aload_2
        //   43: aload_3
        //   44: iconst_0
        //   45: invokevirtual 50	com/google/android/gms/maps/GoogleMapOptions:writeToParcel	(Landroid/os/Parcel;I)V
        //   48: aload_0
        //   49: getfield 15	com/google/android/gms/maps/internal/c$a$a:le	Landroid/os/IBinder;
        //   52: iconst_3
        //   53: aload_3
        //   54: aload 4
        //   56: iconst_0
        //   57: invokeinterface 56 5 0
        //   62: pop
        //   63: aload 4
        //   65: invokevirtual 59	android/os/Parcel:readException	()V
        //   68: aload 4
        //   70: invokevirtual 62	android/os/Parcel:readStrongBinder	()Landroid/os/IBinder;
        //   73: invokestatic 68	com/google/android/gms/maps/internal/IMapViewDelegate$a:aY	(Landroid/os/IBinder;)Lcom/google/android/gms/maps/internal/IMapViewDelegate;
        //   76: astore 8
        //   78: aload 4
        //   80: invokevirtual 71	android/os/Parcel:recycle	()V
        //   83: aload_3
        //   84: invokevirtual 71	android/os/Parcel:recycle	()V
        //   87: aload 8
        //   89: areturn
        //   90: aconst_null
        //   91: astore 6
        //   93: goto -66 -> 27
        //   96: aload_3
        //   97: iconst_0
        //   98: invokevirtual 44	android/os/Parcel:writeInt	(I)V
        //   101: goto -53 -> 48
        //   104: astore 5
        //   106: aload 4
        //   108: invokevirtual 71	android/os/Parcel:recycle	()V
        //   111: aload_3
        //   112: invokevirtual 71	android/os/Parcel:recycle	()V
        //   115: aload 5
        //   117: athrow
        // Local variable table:
        //   start	length	slot	name	signature
        //   0	118	0	this	a
        //   0	118	1	paramd	d
        //   0	118	2	paramGoogleMapOptions	GoogleMapOptions
        //   3	109	3	localParcel1	Parcel
        //   7	100	4	localParcel2	Parcel
        //   104	12	5	localObject	Object
        //   25	67	6	localIBinder	IBinder
        //   76	12	8	localIMapViewDelegate	IMapViewDelegate
        // Exception table:
        //   from	to	target	type
        //   9	15	104	finally
        //   19	27	104	finally
        //   27	33	104	finally
        //   37	48	104	finally
        //   48	78	104	finally
        //   96	101	104	finally
      }
      
      /* Error */
      public IStreetViewPanoramaViewDelegate a(d paramd, StreetViewPanoramaOptions paramStreetViewPanoramaOptions)
        throws RemoteException
      {
        // Byte code:
        //   0: invokestatic 25	android/os/Parcel:obtain	()Landroid/os/Parcel;
        //   3: astore_3
        //   4: invokestatic 25	android/os/Parcel:obtain	()Landroid/os/Parcel;
        //   7: astore 4
        //   9: aload_3
        //   10: ldc 27
        //   12: invokevirtual 31	android/os/Parcel:writeInterfaceToken	(Ljava/lang/String;)V
        //   15: aload_1
        //   16: ifnull +75 -> 91
        //   19: aload_1
        //   20: invokeinterface 37 1 0
        //   25: astore 6
        //   27: aload_3
        //   28: aload 6
        //   30: invokevirtual 40	android/os/Parcel:writeStrongBinder	(Landroid/os/IBinder;)V
        //   33: aload_2
        //   34: ifnull +63 -> 97
        //   37: aload_3
        //   38: iconst_1
        //   39: invokevirtual 44	android/os/Parcel:writeInt	(I)V
        //   42: aload_2
        //   43: aload_3
        //   44: iconst_0
        //   45: invokevirtual 75	com/google/android/gms/maps/StreetViewPanoramaOptions:writeToParcel	(Landroid/os/Parcel;I)V
        //   48: aload_0
        //   49: getfield 15	com/google/android/gms/maps/internal/c$a$a:le	Landroid/os/IBinder;
        //   52: bipush 7
        //   54: aload_3
        //   55: aload 4
        //   57: iconst_0
        //   58: invokeinterface 56 5 0
        //   63: pop
        //   64: aload 4
        //   66: invokevirtual 59	android/os/Parcel:readException	()V
        //   69: aload 4
        //   71: invokevirtual 62	android/os/Parcel:readStrongBinder	()Landroid/os/IBinder;
        //   74: invokestatic 81	com/google/android/gms/maps/internal/IStreetViewPanoramaViewDelegate$a:bt	(Landroid/os/IBinder;)Lcom/google/android/gms/maps/internal/IStreetViewPanoramaViewDelegate;
        //   77: astore 8
        //   79: aload 4
        //   81: invokevirtual 71	android/os/Parcel:recycle	()V
        //   84: aload_3
        //   85: invokevirtual 71	android/os/Parcel:recycle	()V
        //   88: aload 8
        //   90: areturn
        //   91: aconst_null
        //   92: astore 6
        //   94: goto -67 -> 27
        //   97: aload_3
        //   98: iconst_0
        //   99: invokevirtual 44	android/os/Parcel:writeInt	(I)V
        //   102: goto -54 -> 48
        //   105: astore 5
        //   107: aload 4
        //   109: invokevirtual 71	android/os/Parcel:recycle	()V
        //   112: aload_3
        //   113: invokevirtual 71	android/os/Parcel:recycle	()V
        //   116: aload 5
        //   118: athrow
        // Local variable table:
        //   start	length	slot	name	signature
        //   0	119	0	this	a
        //   0	119	1	paramd	d
        //   0	119	2	paramStreetViewPanoramaOptions	StreetViewPanoramaOptions
        //   3	110	3	localParcel1	Parcel
        //   7	101	4	localParcel2	Parcel
        //   105	12	5	localObject	Object
        //   25	68	6	localIBinder	IBinder
        //   77	12	8	localIStreetViewPanoramaViewDelegate	IStreetViewPanoramaViewDelegate
        // Exception table:
        //   from	to	target	type
        //   9	15	105	finally
        //   19	27	105	finally
        //   27	33	105	finally
        //   37	48	105	finally
        //   48	79	105	finally
        //   97	102	105	finally
      }
      
      /* Error */
      public void a(d paramd, int paramInt)
        throws RemoteException
      {
        // Byte code:
        //   0: invokestatic 25	android/os/Parcel:obtain	()Landroid/os/Parcel;
        //   3: astore_3
        //   4: invokestatic 25	android/os/Parcel:obtain	()Landroid/os/Parcel;
        //   7: astore 4
        //   9: aload_3
        //   10: ldc 27
        //   12: invokevirtual 31	android/os/Parcel:writeInterfaceToken	(Ljava/lang/String;)V
        //   15: aload_1
        //   16: ifnull +53 -> 69
        //   19: aload_1
        //   20: invokeinterface 37 1 0
        //   25: astore 6
        //   27: aload_3
        //   28: aload 6
        //   30: invokevirtual 40	android/os/Parcel:writeStrongBinder	(Landroid/os/IBinder;)V
        //   33: aload_3
        //   34: iload_2
        //   35: invokevirtual 44	android/os/Parcel:writeInt	(I)V
        //   38: aload_0
        //   39: getfield 15	com/google/android/gms/maps/internal/c$a$a:le	Landroid/os/IBinder;
        //   42: bipush 6
        //   44: aload_3
        //   45: aload 4
        //   47: iconst_0
        //   48: invokeinterface 56 5 0
        //   53: pop
        //   54: aload 4
        //   56: invokevirtual 59	android/os/Parcel:readException	()V
        //   59: aload 4
        //   61: invokevirtual 71	android/os/Parcel:recycle	()V
        //   64: aload_3
        //   65: invokevirtual 71	android/os/Parcel:recycle	()V
        //   68: return
        //   69: aconst_null
        //   70: astore 6
        //   72: goto -45 -> 27
        //   75: astore 5
        //   77: aload 4
        //   79: invokevirtual 71	android/os/Parcel:recycle	()V
        //   82: aload_3
        //   83: invokevirtual 71	android/os/Parcel:recycle	()V
        //   86: aload 5
        //   88: athrow
        // Local variable table:
        //   start	length	slot	name	signature
        //   0	89	0	this	a
        //   0	89	1	paramd	d
        //   0	89	2	paramInt	int
        //   3	80	3	localParcel1	Parcel
        //   7	71	4	localParcel2	Parcel
        //   75	12	5	localObject	Object
        //   25	46	6	localIBinder	IBinder
        // Exception table:
        //   from	to	target	type
        //   9	15	75	finally
        //   19	27	75	finally
        //   27	59	75	finally
      }
      
      public IBinder asBinder()
      {
        return this.le;
      }
      
      /* Error */
      public void i(d paramd)
        throws RemoteException
      {
        // Byte code:
        //   0: invokestatic 25	android/os/Parcel:obtain	()Landroid/os/Parcel;
        //   3: astore_2
        //   4: invokestatic 25	android/os/Parcel:obtain	()Landroid/os/Parcel;
        //   7: astore_3
        //   8: aload_2
        //   9: ldc 27
        //   11: invokevirtual 31	android/os/Parcel:writeInterfaceToken	(Ljava/lang/String;)V
        //   14: aload_1
        //   15: ifnull +44 -> 59
        //   18: aload_1
        //   19: invokeinterface 37 1 0
        //   24: astore 5
        //   26: aload_2
        //   27: aload 5
        //   29: invokevirtual 40	android/os/Parcel:writeStrongBinder	(Landroid/os/IBinder;)V
        //   32: aload_0
        //   33: getfield 15	com/google/android/gms/maps/internal/c$a$a:le	Landroid/os/IBinder;
        //   36: iconst_1
        //   37: aload_2
        //   38: aload_3
        //   39: iconst_0
        //   40: invokeinterface 56 5 0
        //   45: pop
        //   46: aload_3
        //   47: invokevirtual 59	android/os/Parcel:readException	()V
        //   50: aload_3
        //   51: invokevirtual 71	android/os/Parcel:recycle	()V
        //   54: aload_2
        //   55: invokevirtual 71	android/os/Parcel:recycle	()V
        //   58: return
        //   59: aconst_null
        //   60: astore 5
        //   62: goto -36 -> 26
        //   65: astore 4
        //   67: aload_3
        //   68: invokevirtual 71	android/os/Parcel:recycle	()V
        //   71: aload_2
        //   72: invokevirtual 71	android/os/Parcel:recycle	()V
        //   75: aload 4
        //   77: athrow
        // Local variable table:
        //   start	length	slot	name	signature
        //   0	78	0	this	a
        //   0	78	1	paramd	d
        //   3	69	2	localParcel1	Parcel
        //   7	61	3	localParcel2	Parcel
        //   65	11	4	localObject	Object
        //   24	37	5	localIBinder	IBinder
        // Exception table:
        //   from	to	target	type
        //   8	14	65	finally
        //   18	26	65	finally
        //   26	50	65	finally
      }
      
      /* Error */
      public IMapFragmentDelegate j(d paramd)
        throws RemoteException
      {
        // Byte code:
        //   0: invokestatic 25	android/os/Parcel:obtain	()Landroid/os/Parcel;
        //   3: astore_2
        //   4: invokestatic 25	android/os/Parcel:obtain	()Landroid/os/Parcel;
        //   7: astore_3
        //   8: aload_2
        //   9: ldc 27
        //   11: invokevirtual 31	android/os/Parcel:writeInterfaceToken	(Ljava/lang/String;)V
        //   14: aload_1
        //   15: ifnull +55 -> 70
        //   18: aload_1
        //   19: invokeinterface 37 1 0
        //   24: astore 5
        //   26: aload_2
        //   27: aload 5
        //   29: invokevirtual 40	android/os/Parcel:writeStrongBinder	(Landroid/os/IBinder;)V
        //   32: aload_0
        //   33: getfield 15	com/google/android/gms/maps/internal/c$a$a:le	Landroid/os/IBinder;
        //   36: iconst_2
        //   37: aload_2
        //   38: aload_3
        //   39: iconst_0
        //   40: invokeinterface 56 5 0
        //   45: pop
        //   46: aload_3
        //   47: invokevirtual 59	android/os/Parcel:readException	()V
        //   50: aload_3
        //   51: invokevirtual 62	android/os/Parcel:readStrongBinder	()Landroid/os/IBinder;
        //   54: invokestatic 92	com/google/android/gms/maps/internal/IMapFragmentDelegate$a:aX	(Landroid/os/IBinder;)Lcom/google/android/gms/maps/internal/IMapFragmentDelegate;
        //   57: astore 7
        //   59: aload_3
        //   60: invokevirtual 71	android/os/Parcel:recycle	()V
        //   63: aload_2
        //   64: invokevirtual 71	android/os/Parcel:recycle	()V
        //   67: aload 7
        //   69: areturn
        //   70: aconst_null
        //   71: astore 5
        //   73: goto -47 -> 26
        //   76: astore 4
        //   78: aload_3
        //   79: invokevirtual 71	android/os/Parcel:recycle	()V
        //   82: aload_2
        //   83: invokevirtual 71	android/os/Parcel:recycle	()V
        //   86: aload 4
        //   88: athrow
        // Local variable table:
        //   start	length	slot	name	signature
        //   0	89	0	this	a
        //   0	89	1	paramd	d
        //   3	80	2	localParcel1	Parcel
        //   7	72	3	localParcel2	Parcel
        //   76	11	4	localObject	Object
        //   24	48	5	localIBinder	IBinder
        //   57	11	7	localIMapFragmentDelegate	IMapFragmentDelegate
        // Exception table:
        //   from	to	target	type
        //   8	14	76	finally
        //   18	26	76	finally
        //   26	59	76	finally
      }
      
      /* Error */
      public IStreetViewPanoramaFragmentDelegate k(d paramd)
        throws RemoteException
      {
        // Byte code:
        //   0: invokestatic 25	android/os/Parcel:obtain	()Landroid/os/Parcel;
        //   3: astore_2
        //   4: invokestatic 25	android/os/Parcel:obtain	()Landroid/os/Parcel;
        //   7: astore_3
        //   8: aload_2
        //   9: ldc 27
        //   11: invokevirtual 31	android/os/Parcel:writeInterfaceToken	(Ljava/lang/String;)V
        //   14: aload_1
        //   15: ifnull +56 -> 71
        //   18: aload_1
        //   19: invokeinterface 37 1 0
        //   24: astore 5
        //   26: aload_2
        //   27: aload 5
        //   29: invokevirtual 40	android/os/Parcel:writeStrongBinder	(Landroid/os/IBinder;)V
        //   32: aload_0
        //   33: getfield 15	com/google/android/gms/maps/internal/c$a$a:le	Landroid/os/IBinder;
        //   36: bipush 8
        //   38: aload_2
        //   39: aload_3
        //   40: iconst_0
        //   41: invokeinterface 56 5 0
        //   46: pop
        //   47: aload_3
        //   48: invokevirtual 59	android/os/Parcel:readException	()V
        //   51: aload_3
        //   52: invokevirtual 62	android/os/Parcel:readStrongBinder	()Landroid/os/IBinder;
        //   55: invokestatic 100	com/google/android/gms/maps/internal/IStreetViewPanoramaFragmentDelegate$a:bs	(Landroid/os/IBinder;)Lcom/google/android/gms/maps/internal/IStreetViewPanoramaFragmentDelegate;
        //   58: astore 7
        //   60: aload_3
        //   61: invokevirtual 71	android/os/Parcel:recycle	()V
        //   64: aload_2
        //   65: invokevirtual 71	android/os/Parcel:recycle	()V
        //   68: aload 7
        //   70: areturn
        //   71: aconst_null
        //   72: astore 5
        //   74: goto -48 -> 26
        //   77: astore 4
        //   79: aload_3
        //   80: invokevirtual 71	android/os/Parcel:recycle	()V
        //   83: aload_2
        //   84: invokevirtual 71	android/os/Parcel:recycle	()V
        //   87: aload 4
        //   89: athrow
        // Local variable table:
        //   start	length	slot	name	signature
        //   0	90	0	this	a
        //   0	90	1	paramd	d
        //   3	81	2	localParcel1	Parcel
        //   7	73	3	localParcel2	Parcel
        //   77	11	4	localObject	Object
        //   24	49	5	localIBinder	IBinder
        //   58	11	7	localIStreetViewPanoramaFragmentDelegate	IStreetViewPanoramaFragmentDelegate
        // Exception table:
        //   from	to	target	type
        //   8	14	77	finally
        //   18	26	77	finally
        //   26	60	77	finally
      }
      
      public ICameraUpdateFactoryDelegate nW()
        throws RemoteException
      {
        Parcel localParcel1 = Parcel.obtain();
        Parcel localParcel2 = Parcel.obtain();
        try
        {
          localParcel1.writeInterfaceToken("com.google.android.gms.maps.internal.ICreator");
          this.le.transact(4, localParcel1, localParcel2, 0);
          localParcel2.readException();
          ICameraUpdateFactoryDelegate localICameraUpdateFactoryDelegate = ICameraUpdateFactoryDelegate.a.aQ(localParcel2.readStrongBinder());
          return localICameraUpdateFactoryDelegate;
        }
        finally
        {
          localParcel2.recycle();
          localParcel1.recycle();
        }
      }
      
      public g nX()
        throws RemoteException
      {
        Parcel localParcel1 = Parcel.obtain();
        Parcel localParcel2 = Parcel.obtain();
        try
        {
          localParcel1.writeInterfaceToken("com.google.android.gms.maps.internal.ICreator");
          this.le.transact(5, localParcel1, localParcel2, 0);
          localParcel2.readException();
          g localg = g.a.bv(localParcel2.readStrongBinder());
          return localg;
        }
        finally
        {
          localParcel2.recycle();
          localParcel1.recycle();
        }
      }
    }
  }
}


/* Location:           C:\Users\TGKIM\Downloads\작업폴더\리버싱\androidReversetools\jd-gui-0.3.6.windows\com.appg.golfmon-1-dex2jar.jar
 * Qualified Name:     com.google.android.gms.maps.internal.c
 * JD-Core Version:    0.7.0.1
 */