package com.google.android.gms.maps.internal;

import android.location.Location;
import android.os.Binder;
import android.os.IBinder;
import android.os.IInterface;
import android.os.Parcel;
import android.os.Parcelable.Creator;
import android.os.RemoteException;
import com.google.android.gms.dynamic.d;
import com.google.android.gms.dynamic.d.a;

public abstract interface q
  extends IInterface
{
  public abstract void c(Location paramLocation)
    throws RemoteException;
  
  public abstract void g(d paramd)
    throws RemoteException;
  
  public static abstract class a
    extends Binder
    implements q
  {
    public a()
    {
      attachInterface(this, "com.google.android.gms.maps.internal.IOnMyLocationChangeListener");
    }
    
    public static q bk(IBinder paramIBinder)
    {
      if (paramIBinder == null) {
        return null;
      }
      IInterface localIInterface = paramIBinder.queryLocalInterface("com.google.android.gms.maps.internal.IOnMyLocationChangeListener");
      if ((localIInterface != null) && ((localIInterface instanceof q))) {
        return (q)localIInterface;
      }
      return new a(paramIBinder);
    }
    
    public IBinder asBinder()
    {
      return this;
    }
    
    public boolean onTransact(int paramInt1, Parcel paramParcel1, Parcel paramParcel2, int paramInt2)
      throws RemoteException
    {
      switch (paramInt1)
      {
      default: 
        return super.onTransact(paramInt1, paramParcel1, paramParcel2, paramInt2);
      case 1598968902: 
        paramParcel2.writeString("com.google.android.gms.maps.internal.IOnMyLocationChangeListener");
        return true;
      case 1: 
        paramParcel1.enforceInterface("com.google.android.gms.maps.internal.IOnMyLocationChangeListener");
        g(d.a.ap(paramParcel1.readStrongBinder()));
        paramParcel2.writeNoException();
        return true;
      }
      paramParcel1.enforceInterface("com.google.android.gms.maps.internal.IOnMyLocationChangeListener");
      if (paramParcel1.readInt() != 0) {}
      for (Location localLocation = (Location)Location.CREATOR.createFromParcel(paramParcel1);; localLocation = null)
      {
        c(localLocation);
        paramParcel2.writeNoException();
        return true;
      }
    }
    
    private static class a
      implements q
    {
      private IBinder le;
      
      a(IBinder paramIBinder)
      {
        this.le = paramIBinder;
      }
      
      public IBinder asBinder()
      {
        return this.le;
      }
      
      /* Error */
      public void c(Location paramLocation)
        throws RemoteException
      {
        // Byte code:
        //   0: invokestatic 27	android/os/Parcel:obtain	()Landroid/os/Parcel;
        //   3: astore_2
        //   4: invokestatic 27	android/os/Parcel:obtain	()Landroid/os/Parcel;
        //   7: astore_3
        //   8: aload_2
        //   9: ldc 29
        //   11: invokevirtual 33	android/os/Parcel:writeInterfaceToken	(Ljava/lang/String;)V
        //   14: aload_1
        //   15: ifnull +41 -> 56
        //   18: aload_2
        //   19: iconst_1
        //   20: invokevirtual 37	android/os/Parcel:writeInt	(I)V
        //   23: aload_1
        //   24: aload_2
        //   25: iconst_0
        //   26: invokevirtual 43	android/location/Location:writeToParcel	(Landroid/os/Parcel;I)V
        //   29: aload_0
        //   30: getfield 15	com/google/android/gms/maps/internal/q$a$a:le	Landroid/os/IBinder;
        //   33: iconst_2
        //   34: aload_2
        //   35: aload_3
        //   36: iconst_0
        //   37: invokeinterface 49 5 0
        //   42: pop
        //   43: aload_3
        //   44: invokevirtual 52	android/os/Parcel:readException	()V
        //   47: aload_3
        //   48: invokevirtual 55	android/os/Parcel:recycle	()V
        //   51: aload_2
        //   52: invokevirtual 55	android/os/Parcel:recycle	()V
        //   55: return
        //   56: aload_2
        //   57: iconst_0
        //   58: invokevirtual 37	android/os/Parcel:writeInt	(I)V
        //   61: goto -32 -> 29
        //   64: astore 4
        //   66: aload_3
        //   67: invokevirtual 55	android/os/Parcel:recycle	()V
        //   70: aload_2
        //   71: invokevirtual 55	android/os/Parcel:recycle	()V
        //   74: aload 4
        //   76: athrow
        // Local variable table:
        //   start	length	slot	name	signature
        //   0	77	0	this	a
        //   0	77	1	paramLocation	Location
        //   3	68	2	localParcel1	Parcel
        //   7	60	3	localParcel2	Parcel
        //   64	11	4	localObject	Object
        // Exception table:
        //   from	to	target	type
        //   8	14	64	finally
        //   18	29	64	finally
        //   29	47	64	finally
        //   56	61	64	finally
      }
      
      /* Error */
      public void g(d paramd)
        throws RemoteException
      {
        // Byte code:
        //   0: invokestatic 27	android/os/Parcel:obtain	()Landroid/os/Parcel;
        //   3: astore_2
        //   4: invokestatic 27	android/os/Parcel:obtain	()Landroid/os/Parcel;
        //   7: astore_3
        //   8: aload_2
        //   9: ldc 29
        //   11: invokevirtual 33	android/os/Parcel:writeInterfaceToken	(Ljava/lang/String;)V
        //   14: aload_1
        //   15: ifnull +44 -> 59
        //   18: aload_1
        //   19: invokeinterface 61 1 0
        //   24: astore 5
        //   26: aload_2
        //   27: aload 5
        //   29: invokevirtual 64	android/os/Parcel:writeStrongBinder	(Landroid/os/IBinder;)V
        //   32: aload_0
        //   33: getfield 15	com/google/android/gms/maps/internal/q$a$a:le	Landroid/os/IBinder;
        //   36: iconst_1
        //   37: aload_2
        //   38: aload_3
        //   39: iconst_0
        //   40: invokeinterface 49 5 0
        //   45: pop
        //   46: aload_3
        //   47: invokevirtual 52	android/os/Parcel:readException	()V
        //   50: aload_3
        //   51: invokevirtual 55	android/os/Parcel:recycle	()V
        //   54: aload_2
        //   55: invokevirtual 55	android/os/Parcel:recycle	()V
        //   58: return
        //   59: aconst_null
        //   60: astore 5
        //   62: goto -36 -> 26
        //   65: astore 4
        //   67: aload_3
        //   68: invokevirtual 55	android/os/Parcel:recycle	()V
        //   71: aload_2
        //   72: invokevirtual 55	android/os/Parcel:recycle	()V
        //   75: aload 4
        //   77: athrow
        // Local variable table:
        //   start	length	slot	name	signature
        //   0	78	0	this	a
        //   0	78	1	paramd	d
        //   3	69	2	localParcel1	Parcel
        //   7	61	3	localParcel2	Parcel
        //   65	11	4	localObject	Object
        //   24	37	5	localIBinder	IBinder
        // Exception table:
        //   from	to	target	type
        //   8	14	65	finally
        //   18	26	65	finally
        //   26	50	65	finally
      }
    }
  }
}


/* Location:           C:\Users\TGKIM\Downloads\작업폴더\리버싱\androidReversetools\jd-gui-0.3.6.windows\com.appg.golfmon-1-dex2jar.jar
 * Qualified Name:     com.google.android.gms.maps.internal.q
 * JD-Core Version:    0.7.0.1
 */