package com.google.android.gms.games.internal;

import android.content.Intent;
import android.os.Binder;
import android.os.IBinder;
import android.os.IInterface;
import android.os.Parcel;
import android.os.Parcelable.Creator;
import android.os.RemoteException;
import com.google.android.gms.common.data.DataHolder;
import com.google.android.gms.common.data.f;

public abstract interface IGamesSignInCallbacks
  extends IInterface
{
  public abstract void U(DataHolder paramDataHolder)
    throws RemoteException;
  
  public abstract void V(DataHolder paramDataHolder)
    throws RemoteException;
  
  public abstract void b(int paramInt, Intent paramIntent)
    throws RemoteException;
  
  public abstract void dU(int paramInt)
    throws RemoteException;
  
  public abstract void dV(int paramInt)
    throws RemoteException;
  
  public abstract void dW(int paramInt)
    throws RemoteException;
  
  public abstract void g(DataHolder paramDataHolder)
    throws RemoteException;
  
  public static abstract class Stub
    extends Binder
    implements IGamesSignInCallbacks
  {
    public Stub()
    {
      attachInterface(this, "com.google.android.gms.games.internal.IGamesSignInCallbacks");
    }
    
    public static IGamesSignInCallbacks aF(IBinder paramIBinder)
    {
      if (paramIBinder == null) {
        return null;
      }
      IInterface localIInterface = paramIBinder.queryLocalInterface("com.google.android.gms.games.internal.IGamesSignInCallbacks");
      if ((localIInterface != null) && ((localIInterface instanceof IGamesSignInCallbacks))) {
        return (IGamesSignInCallbacks)localIInterface;
      }
      return new Proxy(paramIBinder);
    }
    
    public boolean onTransact(int paramInt1, Parcel paramParcel1, Parcel paramParcel2, int paramInt2)
      throws RemoteException
    {
      switch (paramInt1)
      {
      default: 
        return super.onTransact(paramInt1, paramParcel1, paramParcel2, paramInt2);
      case 1598968902: 
        paramParcel2.writeString("com.google.android.gms.games.internal.IGamesSignInCallbacks");
        return true;
      case 5001: 
        paramParcel1.enforceInterface("com.google.android.gms.games.internal.IGamesSignInCallbacks");
        int m = paramParcel1.readInt();
        int n = paramParcel1.readInt();
        Intent localIntent = null;
        if (n != 0) {
          localIntent = (Intent)Intent.CREATOR.createFromParcel(paramParcel1);
        }
        b(m, localIntent);
        paramParcel2.writeNoException();
        return true;
      case 5002: 
        paramParcel1.enforceInterface("com.google.android.gms.games.internal.IGamesSignInCallbacks");
        int k = paramParcel1.readInt();
        DataHolder localDataHolder3 = null;
        if (k != 0) {
          localDataHolder3 = DataHolder.CREATOR.B(paramParcel1);
        }
        U(localDataHolder3);
        paramParcel2.writeNoException();
        return true;
      case 5003: 
        paramParcel1.enforceInterface("com.google.android.gms.games.internal.IGamesSignInCallbacks");
        int j = paramParcel1.readInt();
        DataHolder localDataHolder2 = null;
        if (j != 0) {
          localDataHolder2 = DataHolder.CREATOR.B(paramParcel1);
        }
        V(localDataHolder2);
        paramParcel2.writeNoException();
        return true;
      case 5004: 
        paramParcel1.enforceInterface("com.google.android.gms.games.internal.IGamesSignInCallbacks");
        dU(paramParcel1.readInt());
        paramParcel2.writeNoException();
        return true;
      case 5005: 
        paramParcel1.enforceInterface("com.google.android.gms.games.internal.IGamesSignInCallbacks");
        int i = paramParcel1.readInt();
        DataHolder localDataHolder1 = null;
        if (i != 0) {
          localDataHolder1 = DataHolder.CREATOR.B(paramParcel1);
        }
        g(localDataHolder1);
        paramParcel2.writeNoException();
        return true;
      case 5006: 
        paramParcel1.enforceInterface("com.google.android.gms.games.internal.IGamesSignInCallbacks");
        dV(paramParcel1.readInt());
        paramParcel2.writeNoException();
        return true;
      }
      paramParcel1.enforceInterface("com.google.android.gms.games.internal.IGamesSignInCallbacks");
      dW(paramParcel1.readInt());
      paramParcel2.writeNoException();
      return true;
    }
    
    private static class Proxy
      implements IGamesSignInCallbacks
    {
      private IBinder le;
      
      Proxy(IBinder paramIBinder)
      {
        this.le = paramIBinder;
      }
      
      /* Error */
      public void U(DataHolder paramDataHolder)
        throws RemoteException
      {
        // Byte code:
        //   0: invokestatic 25	android/os/Parcel:obtain	()Landroid/os/Parcel;
        //   3: astore_2
        //   4: invokestatic 25	android/os/Parcel:obtain	()Landroid/os/Parcel;
        //   7: astore_3
        //   8: aload_2
        //   9: ldc 27
        //   11: invokevirtual 31	android/os/Parcel:writeInterfaceToken	(Ljava/lang/String;)V
        //   14: aload_1
        //   15: ifnull +43 -> 58
        //   18: aload_2
        //   19: iconst_1
        //   20: invokevirtual 35	android/os/Parcel:writeInt	(I)V
        //   23: aload_1
        //   24: aload_2
        //   25: iconst_0
        //   26: invokevirtual 41	com/google/android/gms/common/data/DataHolder:writeToParcel	(Landroid/os/Parcel;I)V
        //   29: aload_0
        //   30: getfield 15	com/google/android/gms/games/internal/IGamesSignInCallbacks$Stub$Proxy:le	Landroid/os/IBinder;
        //   33: sipush 5002
        //   36: aload_2
        //   37: aload_3
        //   38: iconst_0
        //   39: invokeinterface 47 5 0
        //   44: pop
        //   45: aload_3
        //   46: invokevirtual 50	android/os/Parcel:readException	()V
        //   49: aload_3
        //   50: invokevirtual 53	android/os/Parcel:recycle	()V
        //   53: aload_2
        //   54: invokevirtual 53	android/os/Parcel:recycle	()V
        //   57: return
        //   58: aload_2
        //   59: iconst_0
        //   60: invokevirtual 35	android/os/Parcel:writeInt	(I)V
        //   63: goto -34 -> 29
        //   66: astore 4
        //   68: aload_3
        //   69: invokevirtual 53	android/os/Parcel:recycle	()V
        //   72: aload_2
        //   73: invokevirtual 53	android/os/Parcel:recycle	()V
        //   76: aload 4
        //   78: athrow
        // Local variable table:
        //   start	length	slot	name	signature
        //   0	79	0	this	Proxy
        //   0	79	1	paramDataHolder	DataHolder
        //   3	70	2	localParcel1	Parcel
        //   7	62	3	localParcel2	Parcel
        //   66	11	4	localObject	Object
        // Exception table:
        //   from	to	target	type
        //   8	14	66	finally
        //   18	29	66	finally
        //   29	49	66	finally
        //   58	63	66	finally
      }
      
      /* Error */
      public void V(DataHolder paramDataHolder)
        throws RemoteException
      {
        // Byte code:
        //   0: invokestatic 25	android/os/Parcel:obtain	()Landroid/os/Parcel;
        //   3: astore_2
        //   4: invokestatic 25	android/os/Parcel:obtain	()Landroid/os/Parcel;
        //   7: astore_3
        //   8: aload_2
        //   9: ldc 27
        //   11: invokevirtual 31	android/os/Parcel:writeInterfaceToken	(Ljava/lang/String;)V
        //   14: aload_1
        //   15: ifnull +43 -> 58
        //   18: aload_2
        //   19: iconst_1
        //   20: invokevirtual 35	android/os/Parcel:writeInt	(I)V
        //   23: aload_1
        //   24: aload_2
        //   25: iconst_0
        //   26: invokevirtual 41	com/google/android/gms/common/data/DataHolder:writeToParcel	(Landroid/os/Parcel;I)V
        //   29: aload_0
        //   30: getfield 15	com/google/android/gms/games/internal/IGamesSignInCallbacks$Stub$Proxy:le	Landroid/os/IBinder;
        //   33: sipush 5003
        //   36: aload_2
        //   37: aload_3
        //   38: iconst_0
        //   39: invokeinterface 47 5 0
        //   44: pop
        //   45: aload_3
        //   46: invokevirtual 50	android/os/Parcel:readException	()V
        //   49: aload_3
        //   50: invokevirtual 53	android/os/Parcel:recycle	()V
        //   53: aload_2
        //   54: invokevirtual 53	android/os/Parcel:recycle	()V
        //   57: return
        //   58: aload_2
        //   59: iconst_0
        //   60: invokevirtual 35	android/os/Parcel:writeInt	(I)V
        //   63: goto -34 -> 29
        //   66: astore 4
        //   68: aload_3
        //   69: invokevirtual 53	android/os/Parcel:recycle	()V
        //   72: aload_2
        //   73: invokevirtual 53	android/os/Parcel:recycle	()V
        //   76: aload 4
        //   78: athrow
        // Local variable table:
        //   start	length	slot	name	signature
        //   0	79	0	this	Proxy
        //   0	79	1	paramDataHolder	DataHolder
        //   3	70	2	localParcel1	Parcel
        //   7	62	3	localParcel2	Parcel
        //   66	11	4	localObject	Object
        // Exception table:
        //   from	to	target	type
        //   8	14	66	finally
        //   18	29	66	finally
        //   29	49	66	finally
        //   58	63	66	finally
      }
      
      public IBinder asBinder()
      {
        return this.le;
      }
      
      /* Error */
      public void b(int paramInt, Intent paramIntent)
        throws RemoteException
      {
        // Byte code:
        //   0: invokestatic 25	android/os/Parcel:obtain	()Landroid/os/Parcel;
        //   3: astore_3
        //   4: invokestatic 25	android/os/Parcel:obtain	()Landroid/os/Parcel;
        //   7: astore 4
        //   9: aload_3
        //   10: ldc 27
        //   12: invokevirtual 31	android/os/Parcel:writeInterfaceToken	(Ljava/lang/String;)V
        //   15: aload_3
        //   16: iload_1
        //   17: invokevirtual 35	android/os/Parcel:writeInt	(I)V
        //   20: aload_2
        //   21: ifnull +46 -> 67
        //   24: aload_3
        //   25: iconst_1
        //   26: invokevirtual 35	android/os/Parcel:writeInt	(I)V
        //   29: aload_2
        //   30: aload_3
        //   31: iconst_0
        //   32: invokevirtual 61	android/content/Intent:writeToParcel	(Landroid/os/Parcel;I)V
        //   35: aload_0
        //   36: getfield 15	com/google/android/gms/games/internal/IGamesSignInCallbacks$Stub$Proxy:le	Landroid/os/IBinder;
        //   39: sipush 5001
        //   42: aload_3
        //   43: aload 4
        //   45: iconst_0
        //   46: invokeinterface 47 5 0
        //   51: pop
        //   52: aload 4
        //   54: invokevirtual 50	android/os/Parcel:readException	()V
        //   57: aload 4
        //   59: invokevirtual 53	android/os/Parcel:recycle	()V
        //   62: aload_3
        //   63: invokevirtual 53	android/os/Parcel:recycle	()V
        //   66: return
        //   67: aload_3
        //   68: iconst_0
        //   69: invokevirtual 35	android/os/Parcel:writeInt	(I)V
        //   72: goto -37 -> 35
        //   75: astore 5
        //   77: aload 4
        //   79: invokevirtual 53	android/os/Parcel:recycle	()V
        //   82: aload_3
        //   83: invokevirtual 53	android/os/Parcel:recycle	()V
        //   86: aload 5
        //   88: athrow
        // Local variable table:
        //   start	length	slot	name	signature
        //   0	89	0	this	Proxy
        //   0	89	1	paramInt	int
        //   0	89	2	paramIntent	Intent
        //   3	80	3	localParcel1	Parcel
        //   7	71	4	localParcel2	Parcel
        //   75	12	5	localObject	Object
        // Exception table:
        //   from	to	target	type
        //   9	20	75	finally
        //   24	35	75	finally
        //   35	57	75	finally
        //   67	72	75	finally
      }
      
      public void dU(int paramInt)
        throws RemoteException
      {
        Parcel localParcel1 = Parcel.obtain();
        Parcel localParcel2 = Parcel.obtain();
        try
        {
          localParcel1.writeInterfaceToken("com.google.android.gms.games.internal.IGamesSignInCallbacks");
          localParcel1.writeInt(paramInt);
          this.le.transact(5004, localParcel1, localParcel2, 0);
          localParcel2.readException();
          return;
        }
        finally
        {
          localParcel2.recycle();
          localParcel1.recycle();
        }
      }
      
      public void dV(int paramInt)
        throws RemoteException
      {
        Parcel localParcel1 = Parcel.obtain();
        Parcel localParcel2 = Parcel.obtain();
        try
        {
          localParcel1.writeInterfaceToken("com.google.android.gms.games.internal.IGamesSignInCallbacks");
          localParcel1.writeInt(paramInt);
          this.le.transact(5006, localParcel1, localParcel2, 0);
          localParcel2.readException();
          return;
        }
        finally
        {
          localParcel2.recycle();
          localParcel1.recycle();
        }
      }
      
      public void dW(int paramInt)
        throws RemoteException
      {
        Parcel localParcel1 = Parcel.obtain();
        Parcel localParcel2 = Parcel.obtain();
        try
        {
          localParcel1.writeInterfaceToken("com.google.android.gms.games.internal.IGamesSignInCallbacks");
          localParcel1.writeInt(paramInt);
          this.le.transact(14001, localParcel1, localParcel2, 0);
          localParcel2.readException();
          return;
        }
        finally
        {
          localParcel2.recycle();
          localParcel1.recycle();
        }
      }
      
      /* Error */
      public void g(DataHolder paramDataHolder)
        throws RemoteException
      {
        // Byte code:
        //   0: invokestatic 25	android/os/Parcel:obtain	()Landroid/os/Parcel;
        //   3: astore_2
        //   4: invokestatic 25	android/os/Parcel:obtain	()Landroid/os/Parcel;
        //   7: astore_3
        //   8: aload_2
        //   9: ldc 27
        //   11: invokevirtual 31	android/os/Parcel:writeInterfaceToken	(Ljava/lang/String;)V
        //   14: aload_1
        //   15: ifnull +43 -> 58
        //   18: aload_2
        //   19: iconst_1
        //   20: invokevirtual 35	android/os/Parcel:writeInt	(I)V
        //   23: aload_1
        //   24: aload_2
        //   25: iconst_0
        //   26: invokevirtual 41	com/google/android/gms/common/data/DataHolder:writeToParcel	(Landroid/os/Parcel;I)V
        //   29: aload_0
        //   30: getfield 15	com/google/android/gms/games/internal/IGamesSignInCallbacks$Stub$Proxy:le	Landroid/os/IBinder;
        //   33: sipush 5005
        //   36: aload_2
        //   37: aload_3
        //   38: iconst_0
        //   39: invokeinterface 47 5 0
        //   44: pop
        //   45: aload_3
        //   46: invokevirtual 50	android/os/Parcel:readException	()V
        //   49: aload_3
        //   50: invokevirtual 53	android/os/Parcel:recycle	()V
        //   53: aload_2
        //   54: invokevirtual 53	android/os/Parcel:recycle	()V
        //   57: return
        //   58: aload_2
        //   59: iconst_0
        //   60: invokevirtual 35	android/os/Parcel:writeInt	(I)V
        //   63: goto -34 -> 29
        //   66: astore 4
        //   68: aload_3
        //   69: invokevirtual 53	android/os/Parcel:recycle	()V
        //   72: aload_2
        //   73: invokevirtual 53	android/os/Parcel:recycle	()V
        //   76: aload 4
        //   78: athrow
        // Local variable table:
        //   start	length	slot	name	signature
        //   0	79	0	this	Proxy
        //   0	79	1	paramDataHolder	DataHolder
        //   3	70	2	localParcel1	Parcel
        //   7	62	3	localParcel2	Parcel
        //   66	11	4	localObject	Object
        // Exception table:
        //   from	to	target	type
        //   8	14	66	finally
        //   18	29	66	finally
        //   29	49	66	finally
        //   58	63	66	finally
      }
    }
  }
}


/* Location:           C:\Users\TGKIM\Downloads\작업폴더\리버싱\androidReversetools\jd-gui-0.3.6.windows\com.appg.golfmon-1-dex2jar.jar
 * Qualified Name:     com.google.android.gms.games.internal.IGamesSignInCallbacks
 * JD-Core Version:    0.7.0.1
 */