package com.google.android.gms.games.internal;

import android.os.Binder;
import android.os.IBinder;
import android.os.IInterface;
import android.os.Parcel;
import android.os.RemoteException;

public abstract interface IGamesSignInService
  extends IInterface
{
  public abstract void a(IGamesSignInCallbacks paramIGamesSignInCallbacks, String paramString)
    throws RemoteException;
  
  public abstract void a(IGamesSignInCallbacks paramIGamesSignInCallbacks, String paramString1, String paramString2)
    throws RemoteException;
  
  public abstract void a(IGamesSignInCallbacks paramIGamesSignInCallbacks, String paramString1, String paramString2, String paramString3)
    throws RemoteException;
  
  public abstract void a(IGamesSignInCallbacks paramIGamesSignInCallbacks, String paramString1, String paramString2, String paramString3, String[] paramArrayOfString)
    throws RemoteException;
  
  public abstract void a(IGamesSignInCallbacks paramIGamesSignInCallbacks, String paramString1, String paramString2, String[] paramArrayOfString)
    throws RemoteException;
  
  public abstract void a(IGamesSignInCallbacks paramIGamesSignInCallbacks, String paramString1, String paramString2, String[] paramArrayOfString, String paramString3)
    throws RemoteException;
  
  public abstract void b(IGamesSignInCallbacks paramIGamesSignInCallbacks, String paramString1, String paramString2, String paramString3)
    throws RemoteException;
  
  public abstract String bO(String paramString)
    throws RemoteException;
  
  public abstract String bP(String paramString)
    throws RemoteException;
  
  public abstract String i(String paramString, boolean paramBoolean)
    throws RemoteException;
  
  public abstract void v(String paramString1, String paramString2)
    throws RemoteException;
  
  public static abstract class Stub
    extends Binder
    implements IGamesSignInService
  {
    public Stub()
    {
      attachInterface(this, "com.google.android.gms.games.internal.IGamesSignInService");
    }
    
    public boolean onTransact(int paramInt1, Parcel paramParcel1, Parcel paramParcel2, int paramInt2)
      throws RemoteException
    {
      switch (paramInt1)
      {
      default: 
        return super.onTransact(paramInt1, paramParcel1, paramParcel2, paramInt2);
      case 1598968902: 
        paramParcel2.writeString("com.google.android.gms.games.internal.IGamesSignInService");
        return true;
      case 5001: 
        paramParcel1.enforceInterface("com.google.android.gms.games.internal.IGamesSignInService");
        String str4 = bO(paramParcel1.readString());
        paramParcel2.writeNoException();
        paramParcel2.writeString(str4);
        return true;
      case 5002: 
        paramParcel1.enforceInterface("com.google.android.gms.games.internal.IGamesSignInService");
        String str3 = bP(paramParcel1.readString());
        paramParcel2.writeNoException();
        paramParcel2.writeString(str3);
        return true;
      case 5009: 
        paramParcel1.enforceInterface("com.google.android.gms.games.internal.IGamesSignInService");
        String str1 = paramParcel1.readString();
        if (paramParcel1.readInt() != 0) {}
        for (boolean bool = true;; bool = false)
        {
          String str2 = i(str1, bool);
          paramParcel2.writeNoException();
          paramParcel2.writeString(str2);
          return true;
        }
      case 5003: 
        paramParcel1.enforceInterface("com.google.android.gms.games.internal.IGamesSignInService");
        a(IGamesSignInCallbacks.Stub.aF(paramParcel1.readStrongBinder()), paramParcel1.readString(), paramParcel1.readString(), paramParcel1.createStringArray(), paramParcel1.readString());
        paramParcel2.writeNoException();
        return true;
      case 5004: 
        paramParcel1.enforceInterface("com.google.android.gms.games.internal.IGamesSignInService");
        a(IGamesSignInCallbacks.Stub.aF(paramParcel1.readStrongBinder()), paramParcel1.readString(), paramParcel1.readString(), paramParcel1.createStringArray());
        paramParcel2.writeNoException();
        return true;
      case 5005: 
        paramParcel1.enforceInterface("com.google.android.gms.games.internal.IGamesSignInService");
        a(IGamesSignInCallbacks.Stub.aF(paramParcel1.readStrongBinder()), paramParcel1.readString(), paramParcel1.readString(), paramParcel1.readString());
        paramParcel2.writeNoException();
        return true;
      case 5006: 
        paramParcel1.enforceInterface("com.google.android.gms.games.internal.IGamesSignInService");
        a(IGamesSignInCallbacks.Stub.aF(paramParcel1.readStrongBinder()), paramParcel1.readString(), paramParcel1.readString());
        paramParcel2.writeNoException();
        return true;
      case 5007: 
        paramParcel1.enforceInterface("com.google.android.gms.games.internal.IGamesSignInService");
        b(IGamesSignInCallbacks.Stub.aF(paramParcel1.readStrongBinder()), paramParcel1.readString(), paramParcel1.readString(), paramParcel1.readString());
        paramParcel2.writeNoException();
        return true;
      case 5008: 
        paramParcel1.enforceInterface("com.google.android.gms.games.internal.IGamesSignInService");
        a(IGamesSignInCallbacks.Stub.aF(paramParcel1.readStrongBinder()), paramParcel1.readString(), paramParcel1.readString(), paramParcel1.readString(), paramParcel1.createStringArray());
        paramParcel2.writeNoException();
        return true;
      case 9001: 
        paramParcel1.enforceInterface("com.google.android.gms.games.internal.IGamesSignInService");
        v(paramParcel1.readString(), paramParcel1.readString());
        paramParcel2.writeNoException();
        return true;
      }
      paramParcel1.enforceInterface("com.google.android.gms.games.internal.IGamesSignInService");
      a(IGamesSignInCallbacks.Stub.aF(paramParcel1.readStrongBinder()), paramParcel1.readString());
      paramParcel2.writeNoException();
      return true;
    }
    
    private static class Proxy
      implements IGamesSignInService
    {
      private IBinder le;
      
      /* Error */
      public void a(IGamesSignInCallbacks paramIGamesSignInCallbacks, String paramString)
        throws RemoteException
      {
        // Byte code:
        //   0: invokestatic 18	android/os/Parcel:obtain	()Landroid/os/Parcel;
        //   3: astore_3
        //   4: invokestatic 18	android/os/Parcel:obtain	()Landroid/os/Parcel;
        //   7: astore 4
        //   9: aload_3
        //   10: ldc 20
        //   12: invokevirtual 24	android/os/Parcel:writeInterfaceToken	(Ljava/lang/String;)V
        //   15: aload_1
        //   16: ifnull +54 -> 70
        //   19: aload_1
        //   20: invokeinterface 30 1 0
        //   25: astore 6
        //   27: aload_3
        //   28: aload 6
        //   30: invokevirtual 34	android/os/Parcel:writeStrongBinder	(Landroid/os/IBinder;)V
        //   33: aload_3
        //   34: aload_2
        //   35: invokevirtual 37	android/os/Parcel:writeString	(Ljava/lang/String;)V
        //   38: aload_0
        //   39: getfield 39	com/google/android/gms/games/internal/IGamesSignInService$Stub$Proxy:le	Landroid/os/IBinder;
        //   42: sipush 14001
        //   45: aload_3
        //   46: aload 4
        //   48: iconst_0
        //   49: invokeinterface 45 5 0
        //   54: pop
        //   55: aload 4
        //   57: invokevirtual 49	android/os/Parcel:readException	()V
        //   60: aload 4
        //   62: invokevirtual 52	android/os/Parcel:recycle	()V
        //   65: aload_3
        //   66: invokevirtual 52	android/os/Parcel:recycle	()V
        //   69: return
        //   70: aconst_null
        //   71: astore 6
        //   73: goto -46 -> 27
        //   76: astore 5
        //   78: aload 4
        //   80: invokevirtual 52	android/os/Parcel:recycle	()V
        //   83: aload_3
        //   84: invokevirtual 52	android/os/Parcel:recycle	()V
        //   87: aload 5
        //   89: athrow
        // Local variable table:
        //   start	length	slot	name	signature
        //   0	90	0	this	Proxy
        //   0	90	1	paramIGamesSignInCallbacks	IGamesSignInCallbacks
        //   0	90	2	paramString	String
        //   3	81	3	localParcel1	Parcel
        //   7	72	4	localParcel2	Parcel
        //   76	12	5	localObject	Object
        //   25	47	6	localIBinder	IBinder
        // Exception table:
        //   from	to	target	type
        //   9	15	76	finally
        //   19	27	76	finally
        //   27	60	76	finally
      }
      
      /* Error */
      public void a(IGamesSignInCallbacks paramIGamesSignInCallbacks, String paramString1, String paramString2)
        throws RemoteException
      {
        // Byte code:
        //   0: invokestatic 18	android/os/Parcel:obtain	()Landroid/os/Parcel;
        //   3: astore 4
        //   5: invokestatic 18	android/os/Parcel:obtain	()Landroid/os/Parcel;
        //   8: astore 5
        //   10: aload 4
        //   12: ldc 20
        //   14: invokevirtual 24	android/os/Parcel:writeInterfaceToken	(Ljava/lang/String;)V
        //   17: aload_1
        //   18: ifnull +64 -> 82
        //   21: aload_1
        //   22: invokeinterface 30 1 0
        //   27: astore 7
        //   29: aload 4
        //   31: aload 7
        //   33: invokevirtual 34	android/os/Parcel:writeStrongBinder	(Landroid/os/IBinder;)V
        //   36: aload 4
        //   38: aload_2
        //   39: invokevirtual 37	android/os/Parcel:writeString	(Ljava/lang/String;)V
        //   42: aload 4
        //   44: aload_3
        //   45: invokevirtual 37	android/os/Parcel:writeString	(Ljava/lang/String;)V
        //   48: aload_0
        //   49: getfield 39	com/google/android/gms/games/internal/IGamesSignInService$Stub$Proxy:le	Landroid/os/IBinder;
        //   52: sipush 5006
        //   55: aload 4
        //   57: aload 5
        //   59: iconst_0
        //   60: invokeinterface 45 5 0
        //   65: pop
        //   66: aload 5
        //   68: invokevirtual 49	android/os/Parcel:readException	()V
        //   71: aload 5
        //   73: invokevirtual 52	android/os/Parcel:recycle	()V
        //   76: aload 4
        //   78: invokevirtual 52	android/os/Parcel:recycle	()V
        //   81: return
        //   82: aconst_null
        //   83: astore 7
        //   85: goto -56 -> 29
        //   88: astore 6
        //   90: aload 5
        //   92: invokevirtual 52	android/os/Parcel:recycle	()V
        //   95: aload 4
        //   97: invokevirtual 52	android/os/Parcel:recycle	()V
        //   100: aload 6
        //   102: athrow
        // Local variable table:
        //   start	length	slot	name	signature
        //   0	103	0	this	Proxy
        //   0	103	1	paramIGamesSignInCallbacks	IGamesSignInCallbacks
        //   0	103	2	paramString1	String
        //   0	103	3	paramString2	String
        //   3	93	4	localParcel1	Parcel
        //   8	83	5	localParcel2	Parcel
        //   88	13	6	localObject	Object
        //   27	57	7	localIBinder	IBinder
        // Exception table:
        //   from	to	target	type
        //   10	17	88	finally
        //   21	29	88	finally
        //   29	71	88	finally
      }
      
      /* Error */
      public void a(IGamesSignInCallbacks paramIGamesSignInCallbacks, String paramString1, String paramString2, String paramString3)
        throws RemoteException
      {
        // Byte code:
        //   0: invokestatic 18	android/os/Parcel:obtain	()Landroid/os/Parcel;
        //   3: astore 5
        //   5: invokestatic 18	android/os/Parcel:obtain	()Landroid/os/Parcel;
        //   8: astore 6
        //   10: aload 5
        //   12: ldc 20
        //   14: invokevirtual 24	android/os/Parcel:writeInterfaceToken	(Ljava/lang/String;)V
        //   17: aload_1
        //   18: ifnull +71 -> 89
        //   21: aload_1
        //   22: invokeinterface 30 1 0
        //   27: astore 8
        //   29: aload 5
        //   31: aload 8
        //   33: invokevirtual 34	android/os/Parcel:writeStrongBinder	(Landroid/os/IBinder;)V
        //   36: aload 5
        //   38: aload_2
        //   39: invokevirtual 37	android/os/Parcel:writeString	(Ljava/lang/String;)V
        //   42: aload 5
        //   44: aload_3
        //   45: invokevirtual 37	android/os/Parcel:writeString	(Ljava/lang/String;)V
        //   48: aload 5
        //   50: aload 4
        //   52: invokevirtual 37	android/os/Parcel:writeString	(Ljava/lang/String;)V
        //   55: aload_0
        //   56: getfield 39	com/google/android/gms/games/internal/IGamesSignInService$Stub$Proxy:le	Landroid/os/IBinder;
        //   59: sipush 5005
        //   62: aload 5
        //   64: aload 6
        //   66: iconst_0
        //   67: invokeinterface 45 5 0
        //   72: pop
        //   73: aload 6
        //   75: invokevirtual 49	android/os/Parcel:readException	()V
        //   78: aload 6
        //   80: invokevirtual 52	android/os/Parcel:recycle	()V
        //   83: aload 5
        //   85: invokevirtual 52	android/os/Parcel:recycle	()V
        //   88: return
        //   89: aconst_null
        //   90: astore 8
        //   92: goto -63 -> 29
        //   95: astore 7
        //   97: aload 6
        //   99: invokevirtual 52	android/os/Parcel:recycle	()V
        //   102: aload 5
        //   104: invokevirtual 52	android/os/Parcel:recycle	()V
        //   107: aload 7
        //   109: athrow
        // Local variable table:
        //   start	length	slot	name	signature
        //   0	110	0	this	Proxy
        //   0	110	1	paramIGamesSignInCallbacks	IGamesSignInCallbacks
        //   0	110	2	paramString1	String
        //   0	110	3	paramString2	String
        //   0	110	4	paramString3	String
        //   3	100	5	localParcel1	Parcel
        //   8	90	6	localParcel2	Parcel
        //   95	13	7	localObject	Object
        //   27	64	8	localIBinder	IBinder
        // Exception table:
        //   from	to	target	type
        //   10	17	95	finally
        //   21	29	95	finally
        //   29	78	95	finally
      }
      
      /* Error */
      public void a(IGamesSignInCallbacks paramIGamesSignInCallbacks, String paramString1, String paramString2, String paramString3, String[] paramArrayOfString)
        throws RemoteException
      {
        // Byte code:
        //   0: invokestatic 18	android/os/Parcel:obtain	()Landroid/os/Parcel;
        //   3: astore 6
        //   5: invokestatic 18	android/os/Parcel:obtain	()Landroid/os/Parcel;
        //   8: astore 7
        //   10: aload 6
        //   12: ldc 20
        //   14: invokevirtual 24	android/os/Parcel:writeInterfaceToken	(Ljava/lang/String;)V
        //   17: aload_1
        //   18: ifnull +78 -> 96
        //   21: aload_1
        //   22: invokeinterface 30 1 0
        //   27: astore 9
        //   29: aload 6
        //   31: aload 9
        //   33: invokevirtual 34	android/os/Parcel:writeStrongBinder	(Landroid/os/IBinder;)V
        //   36: aload 6
        //   38: aload_2
        //   39: invokevirtual 37	android/os/Parcel:writeString	(Ljava/lang/String;)V
        //   42: aload 6
        //   44: aload_3
        //   45: invokevirtual 37	android/os/Parcel:writeString	(Ljava/lang/String;)V
        //   48: aload 6
        //   50: aload 4
        //   52: invokevirtual 37	android/os/Parcel:writeString	(Ljava/lang/String;)V
        //   55: aload 6
        //   57: aload 5
        //   59: invokevirtual 59	android/os/Parcel:writeStringArray	([Ljava/lang/String;)V
        //   62: aload_0
        //   63: getfield 39	com/google/android/gms/games/internal/IGamesSignInService$Stub$Proxy:le	Landroid/os/IBinder;
        //   66: sipush 5008
        //   69: aload 6
        //   71: aload 7
        //   73: iconst_0
        //   74: invokeinterface 45 5 0
        //   79: pop
        //   80: aload 7
        //   82: invokevirtual 49	android/os/Parcel:readException	()V
        //   85: aload 7
        //   87: invokevirtual 52	android/os/Parcel:recycle	()V
        //   90: aload 6
        //   92: invokevirtual 52	android/os/Parcel:recycle	()V
        //   95: return
        //   96: aconst_null
        //   97: astore 9
        //   99: goto -70 -> 29
        //   102: astore 8
        //   104: aload 7
        //   106: invokevirtual 52	android/os/Parcel:recycle	()V
        //   109: aload 6
        //   111: invokevirtual 52	android/os/Parcel:recycle	()V
        //   114: aload 8
        //   116: athrow
        // Local variable table:
        //   start	length	slot	name	signature
        //   0	117	0	this	Proxy
        //   0	117	1	paramIGamesSignInCallbacks	IGamesSignInCallbacks
        //   0	117	2	paramString1	String
        //   0	117	3	paramString2	String
        //   0	117	4	paramString3	String
        //   0	117	5	paramArrayOfString	String[]
        //   3	107	6	localParcel1	Parcel
        //   8	97	7	localParcel2	Parcel
        //   102	13	8	localObject	Object
        //   27	71	9	localIBinder	IBinder
        // Exception table:
        //   from	to	target	type
        //   10	17	102	finally
        //   21	29	102	finally
        //   29	85	102	finally
      }
      
      /* Error */
      public void a(IGamesSignInCallbacks paramIGamesSignInCallbacks, String paramString1, String paramString2, String[] paramArrayOfString)
        throws RemoteException
      {
        // Byte code:
        //   0: invokestatic 18	android/os/Parcel:obtain	()Landroid/os/Parcel;
        //   3: astore 5
        //   5: invokestatic 18	android/os/Parcel:obtain	()Landroid/os/Parcel;
        //   8: astore 6
        //   10: aload 5
        //   12: ldc 20
        //   14: invokevirtual 24	android/os/Parcel:writeInterfaceToken	(Ljava/lang/String;)V
        //   17: aload_1
        //   18: ifnull +71 -> 89
        //   21: aload_1
        //   22: invokeinterface 30 1 0
        //   27: astore 8
        //   29: aload 5
        //   31: aload 8
        //   33: invokevirtual 34	android/os/Parcel:writeStrongBinder	(Landroid/os/IBinder;)V
        //   36: aload 5
        //   38: aload_2
        //   39: invokevirtual 37	android/os/Parcel:writeString	(Ljava/lang/String;)V
        //   42: aload 5
        //   44: aload_3
        //   45: invokevirtual 37	android/os/Parcel:writeString	(Ljava/lang/String;)V
        //   48: aload 5
        //   50: aload 4
        //   52: invokevirtual 59	android/os/Parcel:writeStringArray	([Ljava/lang/String;)V
        //   55: aload_0
        //   56: getfield 39	com/google/android/gms/games/internal/IGamesSignInService$Stub$Proxy:le	Landroid/os/IBinder;
        //   59: sipush 5004
        //   62: aload 5
        //   64: aload 6
        //   66: iconst_0
        //   67: invokeinterface 45 5 0
        //   72: pop
        //   73: aload 6
        //   75: invokevirtual 49	android/os/Parcel:readException	()V
        //   78: aload 6
        //   80: invokevirtual 52	android/os/Parcel:recycle	()V
        //   83: aload 5
        //   85: invokevirtual 52	android/os/Parcel:recycle	()V
        //   88: return
        //   89: aconst_null
        //   90: astore 8
        //   92: goto -63 -> 29
        //   95: astore 7
        //   97: aload 6
        //   99: invokevirtual 52	android/os/Parcel:recycle	()V
        //   102: aload 5
        //   104: invokevirtual 52	android/os/Parcel:recycle	()V
        //   107: aload 7
        //   109: athrow
        // Local variable table:
        //   start	length	slot	name	signature
        //   0	110	0	this	Proxy
        //   0	110	1	paramIGamesSignInCallbacks	IGamesSignInCallbacks
        //   0	110	2	paramString1	String
        //   0	110	3	paramString2	String
        //   0	110	4	paramArrayOfString	String[]
        //   3	100	5	localParcel1	Parcel
        //   8	90	6	localParcel2	Parcel
        //   95	13	7	localObject	Object
        //   27	64	8	localIBinder	IBinder
        // Exception table:
        //   from	to	target	type
        //   10	17	95	finally
        //   21	29	95	finally
        //   29	78	95	finally
      }
      
      /* Error */
      public void a(IGamesSignInCallbacks paramIGamesSignInCallbacks, String paramString1, String paramString2, String[] paramArrayOfString, String paramString3)
        throws RemoteException
      {
        // Byte code:
        //   0: invokestatic 18	android/os/Parcel:obtain	()Landroid/os/Parcel;
        //   3: astore 6
        //   5: invokestatic 18	android/os/Parcel:obtain	()Landroid/os/Parcel;
        //   8: astore 7
        //   10: aload 6
        //   12: ldc 20
        //   14: invokevirtual 24	android/os/Parcel:writeInterfaceToken	(Ljava/lang/String;)V
        //   17: aload_1
        //   18: ifnull +78 -> 96
        //   21: aload_1
        //   22: invokeinterface 30 1 0
        //   27: astore 9
        //   29: aload 6
        //   31: aload 9
        //   33: invokevirtual 34	android/os/Parcel:writeStrongBinder	(Landroid/os/IBinder;)V
        //   36: aload 6
        //   38: aload_2
        //   39: invokevirtual 37	android/os/Parcel:writeString	(Ljava/lang/String;)V
        //   42: aload 6
        //   44: aload_3
        //   45: invokevirtual 37	android/os/Parcel:writeString	(Ljava/lang/String;)V
        //   48: aload 6
        //   50: aload 4
        //   52: invokevirtual 59	android/os/Parcel:writeStringArray	([Ljava/lang/String;)V
        //   55: aload 6
        //   57: aload 5
        //   59: invokevirtual 37	android/os/Parcel:writeString	(Ljava/lang/String;)V
        //   62: aload_0
        //   63: getfield 39	com/google/android/gms/games/internal/IGamesSignInService$Stub$Proxy:le	Landroid/os/IBinder;
        //   66: sipush 5003
        //   69: aload 6
        //   71: aload 7
        //   73: iconst_0
        //   74: invokeinterface 45 5 0
        //   79: pop
        //   80: aload 7
        //   82: invokevirtual 49	android/os/Parcel:readException	()V
        //   85: aload 7
        //   87: invokevirtual 52	android/os/Parcel:recycle	()V
        //   90: aload 6
        //   92: invokevirtual 52	android/os/Parcel:recycle	()V
        //   95: return
        //   96: aconst_null
        //   97: astore 9
        //   99: goto -70 -> 29
        //   102: astore 8
        //   104: aload 7
        //   106: invokevirtual 52	android/os/Parcel:recycle	()V
        //   109: aload 6
        //   111: invokevirtual 52	android/os/Parcel:recycle	()V
        //   114: aload 8
        //   116: athrow
        // Local variable table:
        //   start	length	slot	name	signature
        //   0	117	0	this	Proxy
        //   0	117	1	paramIGamesSignInCallbacks	IGamesSignInCallbacks
        //   0	117	2	paramString1	String
        //   0	117	3	paramString2	String
        //   0	117	4	paramArrayOfString	String[]
        //   0	117	5	paramString3	String
        //   3	107	6	localParcel1	Parcel
        //   8	97	7	localParcel2	Parcel
        //   102	13	8	localObject	Object
        //   27	71	9	localIBinder	IBinder
        // Exception table:
        //   from	to	target	type
        //   10	17	102	finally
        //   21	29	102	finally
        //   29	85	102	finally
      }
      
      public IBinder asBinder()
      {
        return this.le;
      }
      
      /* Error */
      public void b(IGamesSignInCallbacks paramIGamesSignInCallbacks, String paramString1, String paramString2, String paramString3)
        throws RemoteException
      {
        // Byte code:
        //   0: invokestatic 18	android/os/Parcel:obtain	()Landroid/os/Parcel;
        //   3: astore 5
        //   5: invokestatic 18	android/os/Parcel:obtain	()Landroid/os/Parcel;
        //   8: astore 6
        //   10: aload 5
        //   12: ldc 20
        //   14: invokevirtual 24	android/os/Parcel:writeInterfaceToken	(Ljava/lang/String;)V
        //   17: aload_1
        //   18: ifnull +71 -> 89
        //   21: aload_1
        //   22: invokeinterface 30 1 0
        //   27: astore 8
        //   29: aload 5
        //   31: aload 8
        //   33: invokevirtual 34	android/os/Parcel:writeStrongBinder	(Landroid/os/IBinder;)V
        //   36: aload 5
        //   38: aload_2
        //   39: invokevirtual 37	android/os/Parcel:writeString	(Ljava/lang/String;)V
        //   42: aload 5
        //   44: aload_3
        //   45: invokevirtual 37	android/os/Parcel:writeString	(Ljava/lang/String;)V
        //   48: aload 5
        //   50: aload 4
        //   52: invokevirtual 37	android/os/Parcel:writeString	(Ljava/lang/String;)V
        //   55: aload_0
        //   56: getfield 39	com/google/android/gms/games/internal/IGamesSignInService$Stub$Proxy:le	Landroid/os/IBinder;
        //   59: sipush 5007
        //   62: aload 5
        //   64: aload 6
        //   66: iconst_0
        //   67: invokeinterface 45 5 0
        //   72: pop
        //   73: aload 6
        //   75: invokevirtual 49	android/os/Parcel:readException	()V
        //   78: aload 6
        //   80: invokevirtual 52	android/os/Parcel:recycle	()V
        //   83: aload 5
        //   85: invokevirtual 52	android/os/Parcel:recycle	()V
        //   88: return
        //   89: aconst_null
        //   90: astore 8
        //   92: goto -63 -> 29
        //   95: astore 7
        //   97: aload 6
        //   99: invokevirtual 52	android/os/Parcel:recycle	()V
        //   102: aload 5
        //   104: invokevirtual 52	android/os/Parcel:recycle	()V
        //   107: aload 7
        //   109: athrow
        // Local variable table:
        //   start	length	slot	name	signature
        //   0	110	0	this	Proxy
        //   0	110	1	paramIGamesSignInCallbacks	IGamesSignInCallbacks
        //   0	110	2	paramString1	String
        //   0	110	3	paramString2	String
        //   0	110	4	paramString3	String
        //   3	100	5	localParcel1	Parcel
        //   8	90	6	localParcel2	Parcel
        //   95	13	7	localObject	Object
        //   27	64	8	localIBinder	IBinder
        // Exception table:
        //   from	to	target	type
        //   10	17	95	finally
        //   21	29	95	finally
        //   29	78	95	finally
      }
      
      public String bO(String paramString)
        throws RemoteException
      {
        Parcel localParcel1 = Parcel.obtain();
        Parcel localParcel2 = Parcel.obtain();
        try
        {
          localParcel1.writeInterfaceToken("com.google.android.gms.games.internal.IGamesSignInService");
          localParcel1.writeString(paramString);
          this.le.transact(5001, localParcel1, localParcel2, 0);
          localParcel2.readException();
          String str = localParcel2.readString();
          return str;
        }
        finally
        {
          localParcel2.recycle();
          localParcel1.recycle();
        }
      }
      
      public String bP(String paramString)
        throws RemoteException
      {
        Parcel localParcel1 = Parcel.obtain();
        Parcel localParcel2 = Parcel.obtain();
        try
        {
          localParcel1.writeInterfaceToken("com.google.android.gms.games.internal.IGamesSignInService");
          localParcel1.writeString(paramString);
          this.le.transact(5002, localParcel1, localParcel2, 0);
          localParcel2.readException();
          String str = localParcel2.readString();
          return str;
        }
        finally
        {
          localParcel2.recycle();
          localParcel1.recycle();
        }
      }
      
      public String i(String paramString, boolean paramBoolean)
        throws RemoteException
      {
        Parcel localParcel1 = Parcel.obtain();
        Parcel localParcel2 = Parcel.obtain();
        try
        {
          localParcel1.writeInterfaceToken("com.google.android.gms.games.internal.IGamesSignInService");
          localParcel1.writeString(paramString);
          int i = 0;
          if (paramBoolean) {
            i = 1;
          }
          localParcel1.writeInt(i);
          this.le.transact(5009, localParcel1, localParcel2, 0);
          localParcel2.readException();
          String str = localParcel2.readString();
          return str;
        }
        finally
        {
          localParcel2.recycle();
          localParcel1.recycle();
        }
      }
      
      public void v(String paramString1, String paramString2)
        throws RemoteException
      {
        Parcel localParcel1 = Parcel.obtain();
        Parcel localParcel2 = Parcel.obtain();
        try
        {
          localParcel1.writeInterfaceToken("com.google.android.gms.games.internal.IGamesSignInService");
          localParcel1.writeString(paramString1);
          localParcel1.writeString(paramString2);
          this.le.transact(9001, localParcel1, localParcel2, 0);
          localParcel2.readException();
          return;
        }
        finally
        {
          localParcel2.recycle();
          localParcel1.recycle();
        }
      }
    }
  }
}


/* Location:           C:\Users\TGKIM\Downloads\작업폴더\리버싱\androidReversetools\jd-gui-0.3.6.windows\com.appg.golfmon-1-dex2jar.jar
 * Qualified Name:     com.google.android.gms.games.internal.IGamesSignInService
 * JD-Core Version:    0.7.0.1
 */