package com.google.android.gms.games.internal;

import android.os.Binder;
import android.os.IBinder;
import android.os.IInterface;
import android.os.Parcel;
import android.os.ParcelFileDescriptor;
import android.os.Parcelable.Creator;
import android.os.RemoteException;

public abstract interface IRoomServiceCallbacks
  extends IInterface
{
  public abstract void a(ParcelFileDescriptor paramParcelFileDescriptor, int paramInt)
    throws RemoteException;
  
  public abstract void a(ConnectionInfo paramConnectionInfo)
    throws RemoteException;
  
  public abstract void a(String paramString, byte[] paramArrayOfByte, int paramInt)
    throws RemoteException;
  
  public abstract void a(String paramString, String[] paramArrayOfString)
    throws RemoteException;
  
  public abstract void aG(IBinder paramIBinder)
    throws RemoteException;
  
  public abstract void b(String paramString, String[] paramArrayOfString)
    throws RemoteException;
  
  public abstract void bS(String paramString)
    throws RemoteException;
  
  public abstract void bT(String paramString)
    throws RemoteException;
  
  public abstract void bU(String paramString)
    throws RemoteException;
  
  public abstract void bV(String paramString)
    throws RemoteException;
  
  public abstract void bW(String paramString)
    throws RemoteException;
  
  public abstract void bX(String paramString)
    throws RemoteException;
  
  public abstract void c(int paramInt1, int paramInt2, String paramString)
    throws RemoteException;
  
  public abstract void c(String paramString, byte[] paramArrayOfByte)
    throws RemoteException;
  
  public abstract void c(String paramString, String[] paramArrayOfString)
    throws RemoteException;
  
  public abstract void d(String paramString, String[] paramArrayOfString)
    throws RemoteException;
  
  public abstract void dX(int paramInt)
    throws RemoteException;
  
  public abstract void e(String paramString, String[] paramArrayOfString)
    throws RemoteException;
  
  public abstract void f(String paramString, String[] paramArrayOfString)
    throws RemoteException;
  
  public abstract void g(String paramString, String[] paramArrayOfString)
    throws RemoteException;
  
  public abstract void j(String paramString, boolean paramBoolean)
    throws RemoteException;
  
  public abstract void lR()
    throws RemoteException;
  
  public abstract void lS()
    throws RemoteException;
  
  public abstract void onP2PConnected(String paramString)
    throws RemoteException;
  
  public abstract void onP2PDisconnected(String paramString)
    throws RemoteException;
  
  public abstract void x(String paramString, int paramInt)
    throws RemoteException;
  
  public static abstract class Stub
    extends Binder
    implements IRoomServiceCallbacks
  {
    public Stub()
    {
      attachInterface(this, "com.google.android.gms.games.internal.IRoomServiceCallbacks");
    }
    
    public static IRoomServiceCallbacks aH(IBinder paramIBinder)
    {
      if (paramIBinder == null) {
        return null;
      }
      IInterface localIInterface = paramIBinder.queryLocalInterface("com.google.android.gms.games.internal.IRoomServiceCallbacks");
      if ((localIInterface != null) && ((localIInterface instanceof IRoomServiceCallbacks))) {
        return (IRoomServiceCallbacks)localIInterface;
      }
      return new Proxy(paramIBinder);
    }
    
    public boolean onTransact(int paramInt1, Parcel paramParcel1, Parcel paramParcel2, int paramInt2)
      throws RemoteException
    {
      switch (paramInt1)
      {
      default: 
        return super.onTransact(paramInt1, paramParcel1, paramParcel2, paramInt2);
      case 1598968902: 
        paramParcel2.writeString("com.google.android.gms.games.internal.IRoomServiceCallbacks");
        return true;
      case 1001: 
        paramParcel1.enforceInterface("com.google.android.gms.games.internal.IRoomServiceCallbacks");
        c(paramParcel1.readInt(), paramParcel1.readInt(), paramParcel1.readString());
        return true;
      case 1002: 
        paramParcel1.enforceInterface("com.google.android.gms.games.internal.IRoomServiceCallbacks");
        a(paramParcel1.readString(), paramParcel1.createByteArray(), paramParcel1.readInt());
        return true;
      case 1003: 
        paramParcel1.enforceInterface("com.google.android.gms.games.internal.IRoomServiceCallbacks");
        bS(paramParcel1.readString());
        return true;
      case 1004: 
        paramParcel1.enforceInterface("com.google.android.gms.games.internal.IRoomServiceCallbacks");
        bT(paramParcel1.readString());
        return true;
      case 1005: 
        paramParcel1.enforceInterface("com.google.android.gms.games.internal.IRoomServiceCallbacks");
        bU(paramParcel1.readString());
        return true;
      case 1006: 
        paramParcel1.enforceInterface("com.google.android.gms.games.internal.IRoomServiceCallbacks");
        bV(paramParcel1.readString());
        return true;
      case 1007: 
        paramParcel1.enforceInterface("com.google.android.gms.games.internal.IRoomServiceCallbacks");
        bW(paramParcel1.readString());
        return true;
      case 1008: 
        paramParcel1.enforceInterface("com.google.android.gms.games.internal.IRoomServiceCallbacks");
        a(paramParcel1.readString(), paramParcel1.createStringArray());
        return true;
      case 1009: 
        paramParcel1.enforceInterface("com.google.android.gms.games.internal.IRoomServiceCallbacks");
        b(paramParcel1.readString(), paramParcel1.createStringArray());
        return true;
      case 1010: 
        paramParcel1.enforceInterface("com.google.android.gms.games.internal.IRoomServiceCallbacks");
        c(paramParcel1.readString(), paramParcel1.createStringArray());
        return true;
      case 1011: 
        paramParcel1.enforceInterface("com.google.android.gms.games.internal.IRoomServiceCallbacks");
        d(paramParcel1.readString(), paramParcel1.createStringArray());
        return true;
      case 1012: 
        paramParcel1.enforceInterface("com.google.android.gms.games.internal.IRoomServiceCallbacks");
        e(paramParcel1.readString(), paramParcel1.createStringArray());
        return true;
      case 1013: 
        paramParcel1.enforceInterface("com.google.android.gms.games.internal.IRoomServiceCallbacks");
        f(paramParcel1.readString(), paramParcel1.createStringArray());
        return true;
      case 1014: 
        paramParcel1.enforceInterface("com.google.android.gms.games.internal.IRoomServiceCallbacks");
        onP2PConnected(paramParcel1.readString());
        return true;
      case 1015: 
        paramParcel1.enforceInterface("com.google.android.gms.games.internal.IRoomServiceCallbacks");
        onP2PDisconnected(paramParcel1.readString());
        return true;
      case 1016: 
        paramParcel1.enforceInterface("com.google.android.gms.games.internal.IRoomServiceCallbacks");
        lR();
        return true;
      case 1017: 
        paramParcel1.enforceInterface("com.google.android.gms.games.internal.IRoomServiceCallbacks");
        g(paramParcel1.readString(), paramParcel1.createStringArray());
        return true;
      case 1018: 
        paramParcel1.enforceInterface("com.google.android.gms.games.internal.IRoomServiceCallbacks");
        c(paramParcel1.readString(), paramParcel1.createByteArray());
        return true;
      case 1019: 
        paramParcel1.enforceInterface("com.google.android.gms.games.internal.IRoomServiceCallbacks");
        bX(paramParcel1.readString());
        return true;
      case 1020: 
        paramParcel1.enforceInterface("com.google.android.gms.games.internal.IRoomServiceCallbacks");
        dX(paramParcel1.readInt());
        return true;
      case 1021: 
        paramParcel1.enforceInterface("com.google.android.gms.games.internal.IRoomServiceCallbacks");
        aG(paramParcel1.readStrongBinder());
        return true;
      case 1022: 
        paramParcel1.enforceInterface("com.google.android.gms.games.internal.IRoomServiceCallbacks");
        int j = paramParcel1.readInt();
        ConnectionInfo localConnectionInfo = null;
        if (j != 0) {
          localConnectionInfo = ConnectionInfo.CREATOR.ct(paramParcel1);
        }
        a(localConnectionInfo);
        return true;
      case 1023: 
        paramParcel1.enforceInterface("com.google.android.gms.games.internal.IRoomServiceCallbacks");
        lS();
        return true;
      case 1024: 
        paramParcel1.enforceInterface("com.google.android.gms.games.internal.IRoomServiceCallbacks");
        int i = paramParcel1.readInt();
        ParcelFileDescriptor localParcelFileDescriptor = null;
        if (i != 0) {
          localParcelFileDescriptor = (ParcelFileDescriptor)ParcelFileDescriptor.CREATOR.createFromParcel(paramParcel1);
        }
        a(localParcelFileDescriptor, paramParcel1.readInt());
        return true;
      case 1025: 
        paramParcel1.enforceInterface("com.google.android.gms.games.internal.IRoomServiceCallbacks");
        x(paramParcel1.readString(), paramParcel1.readInt());
        return true;
      }
      paramParcel1.enforceInterface("com.google.android.gms.games.internal.IRoomServiceCallbacks");
      String str = paramParcel1.readString();
      if (paramParcel1.readInt() != 0) {}
      for (boolean bool = true;; bool = false)
      {
        j(str, bool);
        return true;
      }
    }
    
    private static class Proxy
      implements IRoomServiceCallbacks
    {
      private IBinder le;
      
      Proxy(IBinder paramIBinder)
      {
        this.le = paramIBinder;
      }
      
      /* Error */
      public void a(ParcelFileDescriptor paramParcelFileDescriptor, int paramInt)
        throws RemoteException
      {
        // Byte code:
        //   0: invokestatic 25	android/os/Parcel:obtain	()Landroid/os/Parcel;
        //   3: astore_3
        //   4: aload_3
        //   5: ldc 27
        //   7: invokevirtual 31	android/os/Parcel:writeInterfaceToken	(Ljava/lang/String;)V
        //   10: aload_1
        //   11: ifnull +40 -> 51
        //   14: aload_3
        //   15: iconst_1
        //   16: invokevirtual 35	android/os/Parcel:writeInt	(I)V
        //   19: aload_1
        //   20: aload_3
        //   21: iconst_0
        //   22: invokevirtual 41	android/os/ParcelFileDescriptor:writeToParcel	(Landroid/os/Parcel;I)V
        //   25: aload_3
        //   26: iload_2
        //   27: invokevirtual 35	android/os/Parcel:writeInt	(I)V
        //   30: aload_0
        //   31: getfield 15	com/google/android/gms/games/internal/IRoomServiceCallbacks$Stub$Proxy:le	Landroid/os/IBinder;
        //   34: sipush 1024
        //   37: aload_3
        //   38: aconst_null
        //   39: iconst_1
        //   40: invokeinterface 47 5 0
        //   45: pop
        //   46: aload_3
        //   47: invokevirtual 50	android/os/Parcel:recycle	()V
        //   50: return
        //   51: aload_3
        //   52: iconst_0
        //   53: invokevirtual 35	android/os/Parcel:writeInt	(I)V
        //   56: goto -31 -> 25
        //   59: astore 4
        //   61: aload_3
        //   62: invokevirtual 50	android/os/Parcel:recycle	()V
        //   65: aload 4
        //   67: athrow
        // Local variable table:
        //   start	length	slot	name	signature
        //   0	68	0	this	Proxy
        //   0	68	1	paramParcelFileDescriptor	ParcelFileDescriptor
        //   0	68	2	paramInt	int
        //   3	59	3	localParcel	Parcel
        //   59	7	4	localObject	Object
        // Exception table:
        //   from	to	target	type
        //   4	10	59	finally
        //   14	25	59	finally
        //   25	46	59	finally
        //   51	56	59	finally
      }
      
      /* Error */
      public void a(ConnectionInfo paramConnectionInfo)
        throws RemoteException
      {
        // Byte code:
        //   0: invokestatic 25	android/os/Parcel:obtain	()Landroid/os/Parcel;
        //   3: astore_2
        //   4: aload_2
        //   5: ldc 27
        //   7: invokevirtual 31	android/os/Parcel:writeInterfaceToken	(Ljava/lang/String;)V
        //   10: aload_1
        //   11: ifnull +35 -> 46
        //   14: aload_2
        //   15: iconst_1
        //   16: invokevirtual 35	android/os/Parcel:writeInt	(I)V
        //   19: aload_1
        //   20: aload_2
        //   21: iconst_0
        //   22: invokevirtual 54	com/google/android/gms/games/internal/ConnectionInfo:writeToParcel	(Landroid/os/Parcel;I)V
        //   25: aload_0
        //   26: getfield 15	com/google/android/gms/games/internal/IRoomServiceCallbacks$Stub$Proxy:le	Landroid/os/IBinder;
        //   29: sipush 1022
        //   32: aload_2
        //   33: aconst_null
        //   34: iconst_1
        //   35: invokeinterface 47 5 0
        //   40: pop
        //   41: aload_2
        //   42: invokevirtual 50	android/os/Parcel:recycle	()V
        //   45: return
        //   46: aload_2
        //   47: iconst_0
        //   48: invokevirtual 35	android/os/Parcel:writeInt	(I)V
        //   51: goto -26 -> 25
        //   54: astore_3
        //   55: aload_2
        //   56: invokevirtual 50	android/os/Parcel:recycle	()V
        //   59: aload_3
        //   60: athrow
        // Local variable table:
        //   start	length	slot	name	signature
        //   0	61	0	this	Proxy
        //   0	61	1	paramConnectionInfo	ConnectionInfo
        //   3	53	2	localParcel	Parcel
        //   54	6	3	localObject	Object
        // Exception table:
        //   from	to	target	type
        //   4	10	54	finally
        //   14	25	54	finally
        //   25	41	54	finally
        //   46	51	54	finally
      }
      
      public void a(String paramString, byte[] paramArrayOfByte, int paramInt)
        throws RemoteException
      {
        Parcel localParcel = Parcel.obtain();
        try
        {
          localParcel.writeInterfaceToken("com.google.android.gms.games.internal.IRoomServiceCallbacks");
          localParcel.writeString(paramString);
          localParcel.writeByteArray(paramArrayOfByte);
          localParcel.writeInt(paramInt);
          this.le.transact(1002, localParcel, null, 1);
          return;
        }
        finally
        {
          localParcel.recycle();
        }
      }
      
      public void a(String paramString, String[] paramArrayOfString)
        throws RemoteException
      {
        Parcel localParcel = Parcel.obtain();
        try
        {
          localParcel.writeInterfaceToken("com.google.android.gms.games.internal.IRoomServiceCallbacks");
          localParcel.writeString(paramString);
          localParcel.writeStringArray(paramArrayOfString);
          this.le.transact(1008, localParcel, null, 1);
          return;
        }
        finally
        {
          localParcel.recycle();
        }
      }
      
      public void aG(IBinder paramIBinder)
        throws RemoteException
      {
        Parcel localParcel = Parcel.obtain();
        try
        {
          localParcel.writeInterfaceToken("com.google.android.gms.games.internal.IRoomServiceCallbacks");
          localParcel.writeStrongBinder(paramIBinder);
          this.le.transact(1021, localParcel, null, 1);
          return;
        }
        finally
        {
          localParcel.recycle();
        }
      }
      
      public IBinder asBinder()
      {
        return this.le;
      }
      
      public void b(String paramString, String[] paramArrayOfString)
        throws RemoteException
      {
        Parcel localParcel = Parcel.obtain();
        try
        {
          localParcel.writeInterfaceToken("com.google.android.gms.games.internal.IRoomServiceCallbacks");
          localParcel.writeString(paramString);
          localParcel.writeStringArray(paramArrayOfString);
          this.le.transact(1009, localParcel, null, 1);
          return;
        }
        finally
        {
          localParcel.recycle();
        }
      }
      
      public void bS(String paramString)
        throws RemoteException
      {
        Parcel localParcel = Parcel.obtain();
        try
        {
          localParcel.writeInterfaceToken("com.google.android.gms.games.internal.IRoomServiceCallbacks");
          localParcel.writeString(paramString);
          this.le.transact(1003, localParcel, null, 1);
          return;
        }
        finally
        {
          localParcel.recycle();
        }
      }
      
      public void bT(String paramString)
        throws RemoteException
      {
        Parcel localParcel = Parcel.obtain();
        try
        {
          localParcel.writeInterfaceToken("com.google.android.gms.games.internal.IRoomServiceCallbacks");
          localParcel.writeString(paramString);
          this.le.transact(1004, localParcel, null, 1);
          return;
        }
        finally
        {
          localParcel.recycle();
        }
      }
      
      public void bU(String paramString)
        throws RemoteException
      {
        Parcel localParcel = Parcel.obtain();
        try
        {
          localParcel.writeInterfaceToken("com.google.android.gms.games.internal.IRoomServiceCallbacks");
          localParcel.writeString(paramString);
          this.le.transact(1005, localParcel, null, 1);
          return;
        }
        finally
        {
          localParcel.recycle();
        }
      }
      
      public void bV(String paramString)
        throws RemoteException
      {
        Parcel localParcel = Parcel.obtain();
        try
        {
          localParcel.writeInterfaceToken("com.google.android.gms.games.internal.IRoomServiceCallbacks");
          localParcel.writeString(paramString);
          this.le.transact(1006, localParcel, null, 1);
          return;
        }
        finally
        {
          localParcel.recycle();
        }
      }
      
      public void bW(String paramString)
        throws RemoteException
      {
        Parcel localParcel = Parcel.obtain();
        try
        {
          localParcel.writeInterfaceToken("com.google.android.gms.games.internal.IRoomServiceCallbacks");
          localParcel.writeString(paramString);
          this.le.transact(1007, localParcel, null, 1);
          return;
        }
        finally
        {
          localParcel.recycle();
        }
      }
      
      public void bX(String paramString)
        throws RemoteException
      {
        Parcel localParcel = Parcel.obtain();
        try
        {
          localParcel.writeInterfaceToken("com.google.android.gms.games.internal.IRoomServiceCallbacks");
          localParcel.writeString(paramString);
          this.le.transact(1019, localParcel, null, 1);
          return;
        }
        finally
        {
          localParcel.recycle();
        }
      }
      
      public void c(int paramInt1, int paramInt2, String paramString)
        throws RemoteException
      {
        Parcel localParcel = Parcel.obtain();
        try
        {
          localParcel.writeInterfaceToken("com.google.android.gms.games.internal.IRoomServiceCallbacks");
          localParcel.writeInt(paramInt1);
          localParcel.writeInt(paramInt2);
          localParcel.writeString(paramString);
          this.le.transact(1001, localParcel, null, 1);
          return;
        }
        finally
        {
          localParcel.recycle();
        }
      }
      
      public void c(String paramString, byte[] paramArrayOfByte)
        throws RemoteException
      {
        Parcel localParcel = Parcel.obtain();
        try
        {
          localParcel.writeInterfaceToken("com.google.android.gms.games.internal.IRoomServiceCallbacks");
          localParcel.writeString(paramString);
          localParcel.writeByteArray(paramArrayOfByte);
          this.le.transact(1018, localParcel, null, 1);
          return;
        }
        finally
        {
          localParcel.recycle();
        }
      }
      
      public void c(String paramString, String[] paramArrayOfString)
        throws RemoteException
      {
        Parcel localParcel = Parcel.obtain();
        try
        {
          localParcel.writeInterfaceToken("com.google.android.gms.games.internal.IRoomServiceCallbacks");
          localParcel.writeString(paramString);
          localParcel.writeStringArray(paramArrayOfString);
          this.le.transact(1010, localParcel, null, 1);
          return;
        }
        finally
        {
          localParcel.recycle();
        }
      }
      
      public void d(String paramString, String[] paramArrayOfString)
        throws RemoteException
      {
        Parcel localParcel = Parcel.obtain();
        try
        {
          localParcel.writeInterfaceToken("com.google.android.gms.games.internal.IRoomServiceCallbacks");
          localParcel.writeString(paramString);
          localParcel.writeStringArray(paramArrayOfString);
          this.le.transact(1011, localParcel, null, 1);
          return;
        }
        finally
        {
          localParcel.recycle();
        }
      }
      
      public void dX(int paramInt)
        throws RemoteException
      {
        Parcel localParcel = Parcel.obtain();
        try
        {
          localParcel.writeInterfaceToken("com.google.android.gms.games.internal.IRoomServiceCallbacks");
          localParcel.writeInt(paramInt);
          this.le.transact(1020, localParcel, null, 1);
          return;
        }
        finally
        {
          localParcel.recycle();
        }
      }
      
      public void e(String paramString, String[] paramArrayOfString)
        throws RemoteException
      {
        Parcel localParcel = Parcel.obtain();
        try
        {
          localParcel.writeInterfaceToken("com.google.android.gms.games.internal.IRoomServiceCallbacks");
          localParcel.writeString(paramString);
          localParcel.writeStringArray(paramArrayOfString);
          this.le.transact(1012, localParcel, null, 1);
          return;
        }
        finally
        {
          localParcel.recycle();
        }
      }
      
      public void f(String paramString, String[] paramArrayOfString)
        throws RemoteException
      {
        Parcel localParcel = Parcel.obtain();
        try
        {
          localParcel.writeInterfaceToken("com.google.android.gms.games.internal.IRoomServiceCallbacks");
          localParcel.writeString(paramString);
          localParcel.writeStringArray(paramArrayOfString);
          this.le.transact(1013, localParcel, null, 1);
          return;
        }
        finally
        {
          localParcel.recycle();
        }
      }
      
      public void g(String paramString, String[] paramArrayOfString)
        throws RemoteException
      {
        Parcel localParcel = Parcel.obtain();
        try
        {
          localParcel.writeInterfaceToken("com.google.android.gms.games.internal.IRoomServiceCallbacks");
          localParcel.writeString(paramString);
          localParcel.writeStringArray(paramArrayOfString);
          this.le.transact(1017, localParcel, null, 1);
          return;
        }
        finally
        {
          localParcel.recycle();
        }
      }
      
      /* Error */
      public void j(String paramString, boolean paramBoolean)
        throws RemoteException
      {
        // Byte code:
        //   0: iconst_1
        //   1: istore_3
        //   2: invokestatic 25	android/os/Parcel:obtain	()Landroid/os/Parcel;
        //   5: astore 4
        //   7: aload 4
        //   9: ldc 27
        //   11: invokevirtual 31	android/os/Parcel:writeInterfaceToken	(Ljava/lang/String;)V
        //   14: aload 4
        //   16: aload_1
        //   17: invokevirtual 58	android/os/Parcel:writeString	(Ljava/lang/String;)V
        //   20: iload_2
        //   21: ifeq +32 -> 53
        //   24: aload 4
        //   26: iload_3
        //   27: invokevirtual 35	android/os/Parcel:writeInt	(I)V
        //   30: aload_0
        //   31: getfield 15	com/google/android/gms/games/internal/IRoomServiceCallbacks$Stub$Proxy:le	Landroid/os/IBinder;
        //   34: sipush 1026
        //   37: aload 4
        //   39: aconst_null
        //   40: iconst_1
        //   41: invokeinterface 47 5 0
        //   46: pop
        //   47: aload 4
        //   49: invokevirtual 50	android/os/Parcel:recycle	()V
        //   52: return
        //   53: iconst_0
        //   54: istore_3
        //   55: goto -31 -> 24
        //   58: astore 5
        //   60: aload 4
        //   62: invokevirtual 50	android/os/Parcel:recycle	()V
        //   65: aload 5
        //   67: athrow
        // Local variable table:
        //   start	length	slot	name	signature
        //   0	68	0	this	Proxy
        //   0	68	1	paramString	String
        //   0	68	2	paramBoolean	boolean
        //   1	54	3	i	int
        //   5	56	4	localParcel	Parcel
        //   58	8	5	localObject	Object
        // Exception table:
        //   from	to	target	type
        //   7	20	58	finally
        //   24	47	58	finally
      }
      
      public void lR()
        throws RemoteException
      {
        Parcel localParcel = Parcel.obtain();
        try
        {
          localParcel.writeInterfaceToken("com.google.android.gms.games.internal.IRoomServiceCallbacks");
          this.le.transact(1016, localParcel, null, 1);
          return;
        }
        finally
        {
          localParcel.recycle();
        }
      }
      
      public void lS()
        throws RemoteException
      {
        Parcel localParcel = Parcel.obtain();
        try
        {
          localParcel.writeInterfaceToken("com.google.android.gms.games.internal.IRoomServiceCallbacks");
          this.le.transact(1023, localParcel, null, 1);
          return;
        }
        finally
        {
          localParcel.recycle();
        }
      }
      
      public void onP2PConnected(String paramString)
        throws RemoteException
      {
        Parcel localParcel = Parcel.obtain();
        try
        {
          localParcel.writeInterfaceToken("com.google.android.gms.games.internal.IRoomServiceCallbacks");
          localParcel.writeString(paramString);
          this.le.transact(1014, localParcel, null, 1);
          return;
        }
        finally
        {
          localParcel.recycle();
        }
      }
      
      public void onP2PDisconnected(String paramString)
        throws RemoteException
      {
        Parcel localParcel = Parcel.obtain();
        try
        {
          localParcel.writeInterfaceToken("com.google.android.gms.games.internal.IRoomServiceCallbacks");
          localParcel.writeString(paramString);
          this.le.transact(1015, localParcel, null, 1);
          return;
        }
        finally
        {
          localParcel.recycle();
        }
      }
      
      public void x(String paramString, int paramInt)
        throws RemoteException
      {
        Parcel localParcel = Parcel.obtain();
        try
        {
          localParcel.writeInterfaceToken("com.google.android.gms.games.internal.IRoomServiceCallbacks");
          localParcel.writeString(paramString);
          localParcel.writeInt(paramInt);
          this.le.transact(1025, localParcel, null, 1);
          return;
        }
        finally
        {
          localParcel.recycle();
        }
      }
    }
  }
}


/* Location:           C:\Users\TGKIM\Downloads\작업폴더\리버싱\androidReversetools\jd-gui-0.3.6.windows\com.appg.golfmon-1-dex2jar.jar
 * Qualified Name:     com.google.android.gms.games.internal.IRoomServiceCallbacks
 * JD-Core Version:    0.7.0.1
 */