package com.google.android.gms.drive.realtime.internal;

import android.os.Binder;
import android.os.IBinder;
import android.os.IInterface;
import android.os.Parcel;
import android.os.Parcelable.Creator;
import android.os.RemoteException;
import com.google.android.gms.common.data.DataHolder;

public abstract interface m
  extends IInterface
{
  public abstract void a(int paramInt, j paramj)
    throws RemoteException;
  
  public abstract void a(BeginCompoundOperationRequest paramBeginCompoundOperationRequest, o paramo)
    throws RemoteException;
  
  public abstract void a(EndCompoundOperationRequest paramEndCompoundOperationRequest, j paramj)
    throws RemoteException;
  
  public abstract void a(EndCompoundOperationRequest paramEndCompoundOperationRequest, o paramo)
    throws RemoteException;
  
  public abstract void a(ParcelableIndexReference paramParcelableIndexReference, n paramn)
    throws RemoteException;
  
  public abstract void a(c paramc)
    throws RemoteException;
  
  public abstract void a(d paramd)
    throws RemoteException;
  
  public abstract void a(e parame)
    throws RemoteException;
  
  public abstract void a(h paramh)
    throws RemoteException;
  
  public abstract void a(i parami)
    throws RemoteException;
  
  public abstract void a(j paramj)
    throws RemoteException;
  
  public abstract void a(l paraml)
    throws RemoteException;
  
  public abstract void a(o paramo)
    throws RemoteException;
  
  public abstract void a(String paramString, int paramInt1, int paramInt2, g paramg)
    throws RemoteException;
  
  public abstract void a(String paramString, int paramInt1, int paramInt2, j paramj)
    throws RemoteException;
  
  public abstract void a(String paramString, int paramInt, DataHolder paramDataHolder, g paramg)
    throws RemoteException;
  
  public abstract void a(String paramString, int paramInt, DataHolder paramDataHolder, j paramj)
    throws RemoteException;
  
  public abstract void a(String paramString, int paramInt, o paramo)
    throws RemoteException;
  
  public abstract void a(String paramString1, int paramInt1, String paramString2, int paramInt2, j paramj)
    throws RemoteException;
  
  public abstract void a(String paramString1, int paramInt, String paramString2, j paramj)
    throws RemoteException;
  
  public abstract void a(String paramString, DataHolder paramDataHolder, j paramj)
    throws RemoteException;
  
  public abstract void a(String paramString, f paramf)
    throws RemoteException;
  
  public abstract void a(String paramString, j paramj)
    throws RemoteException;
  
  public abstract void a(String paramString, k paramk)
    throws RemoteException;
  
  public abstract void a(String paramString, l paraml)
    throws RemoteException;
  
  public abstract void a(String paramString, n paramn)
    throws RemoteException;
  
  public abstract void a(String paramString, o paramo)
    throws RemoteException;
  
  public abstract void a(String paramString1, String paramString2, f paramf)
    throws RemoteException;
  
  public abstract void a(String paramString1, String paramString2, g paramg)
    throws RemoteException;
  
  public abstract void a(String paramString1, String paramString2, j paramj)
    throws RemoteException;
  
  public abstract void b(c paramc)
    throws RemoteException;
  
  public abstract void b(j paramj)
    throws RemoteException;
  
  public abstract void b(l paraml)
    throws RemoteException;
  
  public abstract void b(o paramo)
    throws RemoteException;
  
  public abstract void b(String paramString, f paramf)
    throws RemoteException;
  
  public abstract void b(String paramString, l paraml)
    throws RemoteException;
  
  public abstract void b(String paramString, n paramn)
    throws RemoteException;
  
  public abstract void b(String paramString, o paramo)
    throws RemoteException;
  
  public abstract void c(c paramc)
    throws RemoteException;
  
  public abstract void c(String paramString, l paraml)
    throws RemoteException;
  
  public abstract void d(c paramc)
    throws RemoteException;
  
  public static abstract class a
    extends Binder
    implements m
  {
    public static m al(IBinder paramIBinder)
    {
      if (paramIBinder == null) {
        return null;
      }
      IInterface localIInterface = paramIBinder.queryLocalInterface("com.google.android.gms.drive.realtime.internal.IRealtimeService");
      if ((localIInterface != null) && ((localIInterface instanceof m))) {
        return (m)localIInterface;
      }
      return new a(paramIBinder);
    }
    
    public boolean onTransact(int paramInt1, Parcel paramParcel1, Parcel paramParcel2, int paramInt2)
      throws RemoteException
    {
      switch (paramInt1)
      {
      default: 
        return super.onTransact(paramInt1, paramParcel1, paramParcel2, paramInt2);
      case 1598968902: 
        paramParcel2.writeString("com.google.android.gms.drive.realtime.internal.IRealtimeService");
        return true;
      case 1: 
        paramParcel1.enforceInterface("com.google.android.gms.drive.realtime.internal.IRealtimeService");
        a(paramParcel1.readString(), n.a.am(paramParcel1.readStrongBinder()));
        paramParcel2.writeNoException();
        return true;
      case 2: 
        paramParcel1.enforceInterface("com.google.android.gms.drive.realtime.internal.IRealtimeService");
        a(c.a.ab(paramParcel1.readStrongBinder()));
        paramParcel2.writeNoException();
        return true;
      case 3: 
        paramParcel1.enforceInterface("com.google.android.gms.drive.realtime.internal.IRealtimeService");
        a(o.a.an(paramParcel1.readStrongBinder()));
        paramParcel2.writeNoException();
        return true;
      case 33: 
        paramParcel1.enforceInterface("com.google.android.gms.drive.realtime.internal.IRealtimeService");
        b(c.a.ab(paramParcel1.readStrongBinder()));
        paramParcel2.writeNoException();
        return true;
      case 35: 
        paramParcel1.enforceInterface("com.google.android.gms.drive.realtime.internal.IRealtimeService");
        b(o.a.an(paramParcel1.readStrongBinder()));
        paramParcel2.writeNoException();
        return true;
      case 40: 
        paramParcel1.enforceInterface("com.google.android.gms.drive.realtime.internal.IRealtimeService");
        a(l.a.ak(paramParcel1.readStrongBinder()));
        paramParcel2.writeNoException();
        return true;
      case 4: 
        paramParcel1.enforceInterface("com.google.android.gms.drive.realtime.internal.IRealtimeService");
        a(paramParcel1.readString(), paramParcel1.readString(), f.a.ae(paramParcel1.readStrongBinder()));
        paramParcel2.writeNoException();
        return true;
      case 5: 
        paramParcel1.enforceInterface("com.google.android.gms.drive.realtime.internal.IRealtimeService");
        a(paramParcel1.readString(), l.a.ak(paramParcel1.readStrongBinder()));
        paramParcel2.writeNoException();
        return true;
      case 6: 
        paramParcel1.enforceInterface("com.google.android.gms.drive.realtime.internal.IRealtimeService");
        String str3 = paramParcel1.readString();
        int i4 = paramParcel1.readInt();
        DataHolder localDataHolder3 = null;
        if (i4 != 0) {
          localDataHolder3 = DataHolder.CREATOR.B(paramParcel1);
        }
        a(str3, localDataHolder3, j.a.ai(paramParcel1.readStrongBinder()));
        paramParcel2.writeNoException();
        return true;
      case 7: 
        paramParcel1.enforceInterface("com.google.android.gms.drive.realtime.internal.IRealtimeService");
        a(paramParcel1.readString(), j.a.ai(paramParcel1.readStrongBinder()));
        paramParcel2.writeNoException();
        return true;
      case 20: 
        paramParcel1.enforceInterface("com.google.android.gms.drive.realtime.internal.IRealtimeService");
        a(paramParcel1.readString(), f.a.ae(paramParcel1.readStrongBinder()));
        paramParcel2.writeNoException();
        return true;
      case 21: 
        paramParcel1.enforceInterface("com.google.android.gms.drive.realtime.internal.IRealtimeService");
        a(paramParcel1.readString(), paramParcel1.readString(), g.a.af(paramParcel1.readStrongBinder()));
        paramParcel2.writeNoException();
        return true;
      case 8: 
        paramParcel1.enforceInterface("com.google.android.gms.drive.realtime.internal.IRealtimeService");
        b(paramParcel1.readString(), l.a.ak(paramParcel1.readStrongBinder()));
        paramParcel2.writeNoException();
        return true;
      case 9: 
        paramParcel1.enforceInterface("com.google.android.gms.drive.realtime.internal.IRealtimeService");
        b(paramParcel1.readString(), n.a.am(paramParcel1.readStrongBinder()));
        paramParcel2.writeNoException();
        return true;
      case 10: 
        paramParcel1.enforceInterface("com.google.android.gms.drive.realtime.internal.IRealtimeService");
        a(paramParcel1.readString(), paramParcel1.readInt(), paramParcel1.readString(), j.a.ai(paramParcel1.readStrongBinder()));
        paramParcel2.writeNoException();
        return true;
      case 11: 
        paramParcel1.enforceInterface("com.google.android.gms.drive.realtime.internal.IRealtimeService");
        a(paramParcel1.readString(), paramParcel1.readInt(), paramParcel1.readInt(), j.a.ai(paramParcel1.readStrongBinder()));
        paramParcel2.writeNoException();
        return true;
      case 12: 
        paramParcel1.enforceInterface("com.google.android.gms.drive.realtime.internal.IRealtimeService");
        a(paramParcel1.readString(), paramParcel1.readString(), j.a.ai(paramParcel1.readStrongBinder()));
        paramParcel2.writeNoException();
        return true;
      case 13: 
        paramParcel1.enforceInterface("com.google.android.gms.drive.realtime.internal.IRealtimeService");
        b(paramParcel1.readString(), f.a.ae(paramParcel1.readStrongBinder()));
        paramParcel2.writeNoException();
        return true;
      case 14: 
        paramParcel1.enforceInterface("com.google.android.gms.drive.realtime.internal.IRealtimeService");
        c(paramParcel1.readString(), l.a.ak(paramParcel1.readStrongBinder()));
        paramParcel2.writeNoException();
        return true;
      case 15: 
        paramParcel1.enforceInterface("com.google.android.gms.drive.realtime.internal.IRealtimeService");
        String str2 = paramParcel1.readString();
        int i2 = paramParcel1.readInt();
        int i3 = paramParcel1.readInt();
        DataHolder localDataHolder2 = null;
        if (i3 != 0) {
          localDataHolder2 = DataHolder.CREATOR.B(paramParcel1);
        }
        a(str2, i2, localDataHolder2, j.a.ai(paramParcel1.readStrongBinder()));
        paramParcel2.writeNoException();
        return true;
      case 16: 
        paramParcel1.enforceInterface("com.google.android.gms.drive.realtime.internal.IRealtimeService");
        String str1 = paramParcel1.readString();
        int n = paramParcel1.readInt();
        int i1 = paramParcel1.readInt();
        DataHolder localDataHolder1 = null;
        if (i1 != 0) {
          localDataHolder1 = DataHolder.CREATOR.B(paramParcel1);
        }
        a(str1, n, localDataHolder1, g.a.af(paramParcel1.readStrongBinder()));
        paramParcel2.writeNoException();
        return true;
      case 17: 
        paramParcel1.enforceInterface("com.google.android.gms.drive.realtime.internal.IRealtimeService");
        a(paramParcel1.readString(), paramParcel1.readInt(), paramParcel1.readInt(), g.a.af(paramParcel1.readStrongBinder()));
        paramParcel2.writeNoException();
        return true;
      case 37: 
        paramParcel1.enforceInterface("com.google.android.gms.drive.realtime.internal.IRealtimeService");
        a(paramParcel1.readString(), paramParcel1.readInt(), paramParcel1.readString(), paramParcel1.readInt(), j.a.ai(paramParcel1.readStrongBinder()));
        paramParcel2.writeNoException();
        return true;
      case 18: 
        paramParcel1.enforceInterface("com.google.android.gms.drive.realtime.internal.IRealtimeService");
        int m = paramParcel1.readInt();
        BeginCompoundOperationRequest localBeginCompoundOperationRequest = null;
        if (m != 0) {
          localBeginCompoundOperationRequest = (BeginCompoundOperationRequest)BeginCompoundOperationRequest.CREATOR.createFromParcel(paramParcel1);
        }
        a(localBeginCompoundOperationRequest, o.a.an(paramParcel1.readStrongBinder()));
        paramParcel2.writeNoException();
        return true;
      case 41: 
        paramParcel1.enforceInterface("com.google.android.gms.drive.realtime.internal.IRealtimeService");
        int k = paramParcel1.readInt();
        EndCompoundOperationRequest localEndCompoundOperationRequest2 = null;
        if (k != 0) {
          localEndCompoundOperationRequest2 = (EndCompoundOperationRequest)EndCompoundOperationRequest.CREATOR.createFromParcel(paramParcel1);
        }
        a(localEndCompoundOperationRequest2, j.a.ai(paramParcel1.readStrongBinder()));
        paramParcel2.writeNoException();
        return true;
      case 22: 
        paramParcel1.enforceInterface("com.google.android.gms.drive.realtime.internal.IRealtimeService");
        a(j.a.ai(paramParcel1.readStrongBinder()));
        paramParcel2.writeNoException();
        return true;
      case 23: 
        paramParcel1.enforceInterface("com.google.android.gms.drive.realtime.internal.IRealtimeService");
        b(j.a.ai(paramParcel1.readStrongBinder()));
        paramParcel2.writeNoException();
        return true;
      case 24: 
        paramParcel1.enforceInterface("com.google.android.gms.drive.realtime.internal.IRealtimeService");
        c(c.a.ab(paramParcel1.readStrongBinder()));
        paramParcel2.writeNoException();
        return true;
      case 25: 
        paramParcel1.enforceInterface("com.google.android.gms.drive.realtime.internal.IRealtimeService");
        d(c.a.ab(paramParcel1.readStrongBinder()));
        paramParcel2.writeNoException();
        return true;
      case 26: 
        paramParcel1.enforceInterface("com.google.android.gms.drive.realtime.internal.IRealtimeService");
        int j = paramParcel1.readInt();
        ParcelableIndexReference localParcelableIndexReference = null;
        if (j != 0) {
          localParcelableIndexReference = (ParcelableIndexReference)ParcelableIndexReference.CREATOR.createFromParcel(paramParcel1);
        }
        a(localParcelableIndexReference, n.a.am(paramParcel1.readStrongBinder()));
        paramParcel2.writeNoException();
        return true;
      case 27: 
        paramParcel1.enforceInterface("com.google.android.gms.drive.realtime.internal.IRealtimeService");
        a(paramParcel1.readString(), k.a.aj(paramParcel1.readStrongBinder()));
        paramParcel2.writeNoException();
        return true;
      case 28: 
        paramParcel1.enforceInterface("com.google.android.gms.drive.realtime.internal.IRealtimeService");
        a(paramParcel1.readString(), paramParcel1.readInt(), o.a.an(paramParcel1.readStrongBinder()));
        paramParcel2.writeNoException();
        return true;
      case 29: 
        paramParcel1.enforceInterface("com.google.android.gms.drive.realtime.internal.IRealtimeService");
        b(l.a.ak(paramParcel1.readStrongBinder()));
        paramParcel2.writeNoException();
        return true;
      case 30: 
        paramParcel1.enforceInterface("com.google.android.gms.drive.realtime.internal.IRealtimeService");
        a(paramParcel1.readInt(), j.a.ai(paramParcel1.readStrongBinder()));
        paramParcel2.writeNoException();
        return true;
      case 31: 
        paramParcel1.enforceInterface("com.google.android.gms.drive.realtime.internal.IRealtimeService");
        a(e.a.ad(paramParcel1.readStrongBinder()));
        paramParcel2.writeNoException();
        return true;
      case 32: 
        paramParcel1.enforceInterface("com.google.android.gms.drive.realtime.internal.IRealtimeService");
        a(d.a.ac(paramParcel1.readStrongBinder()));
        paramParcel2.writeNoException();
        return true;
      case 34: 
        paramParcel1.enforceInterface("com.google.android.gms.drive.realtime.internal.IRealtimeService");
        a(i.a.ah(paramParcel1.readStrongBinder()));
        paramParcel2.writeNoException();
        return true;
      case 36: 
        paramParcel1.enforceInterface("com.google.android.gms.drive.realtime.internal.IRealtimeService");
        a(h.a.ag(paramParcel1.readStrongBinder()));
        paramParcel2.writeNoException();
        return true;
      case 38: 
        paramParcel1.enforceInterface("com.google.android.gms.drive.realtime.internal.IRealtimeService");
        a(paramParcel1.readString(), o.a.an(paramParcel1.readStrongBinder()));
        paramParcel2.writeNoException();
        return true;
      case 39: 
        paramParcel1.enforceInterface("com.google.android.gms.drive.realtime.internal.IRealtimeService");
        b(paramParcel1.readString(), o.a.an(paramParcel1.readStrongBinder()));
        paramParcel2.writeNoException();
        return true;
      }
      paramParcel1.enforceInterface("com.google.android.gms.drive.realtime.internal.IRealtimeService");
      int i = paramParcel1.readInt();
      EndCompoundOperationRequest localEndCompoundOperationRequest1 = null;
      if (i != 0) {
        localEndCompoundOperationRequest1 = (EndCompoundOperationRequest)EndCompoundOperationRequest.CREATOR.createFromParcel(paramParcel1);
      }
      a(localEndCompoundOperationRequest1, o.a.an(paramParcel1.readStrongBinder()));
      paramParcel2.writeNoException();
      return true;
    }
    
    private static class a
      implements m
    {
      private IBinder le;
      
      a(IBinder paramIBinder)
      {
        this.le = paramIBinder;
      }
      
      /* Error */
      public void a(int paramInt, j paramj)
        throws RemoteException
      {
        // Byte code:
        //   0: invokestatic 25	android/os/Parcel:obtain	()Landroid/os/Parcel;
        //   3: astore_3
        //   4: invokestatic 25	android/os/Parcel:obtain	()Landroid/os/Parcel;
        //   7: astore 4
        //   9: aload_3
        //   10: ldc 27
        //   12: invokevirtual 31	android/os/Parcel:writeInterfaceToken	(Ljava/lang/String;)V
        //   15: aload_3
        //   16: iload_1
        //   17: invokevirtual 35	android/os/Parcel:writeInt	(I)V
        //   20: aload_2
        //   21: ifnull +48 -> 69
        //   24: aload_2
        //   25: invokeinterface 41 1 0
        //   30: astore 6
        //   32: aload_3
        //   33: aload 6
        //   35: invokevirtual 44	android/os/Parcel:writeStrongBinder	(Landroid/os/IBinder;)V
        //   38: aload_0
        //   39: getfield 15	com/google/android/gms/drive/realtime/internal/m$a$a:le	Landroid/os/IBinder;
        //   42: bipush 30
        //   44: aload_3
        //   45: aload 4
        //   47: iconst_0
        //   48: invokeinterface 50 5 0
        //   53: pop
        //   54: aload 4
        //   56: invokevirtual 53	android/os/Parcel:readException	()V
        //   59: aload 4
        //   61: invokevirtual 56	android/os/Parcel:recycle	()V
        //   64: aload_3
        //   65: invokevirtual 56	android/os/Parcel:recycle	()V
        //   68: return
        //   69: aconst_null
        //   70: astore 6
        //   72: goto -40 -> 32
        //   75: astore 5
        //   77: aload 4
        //   79: invokevirtual 56	android/os/Parcel:recycle	()V
        //   82: aload_3
        //   83: invokevirtual 56	android/os/Parcel:recycle	()V
        //   86: aload 5
        //   88: athrow
        // Local variable table:
        //   start	length	slot	name	signature
        //   0	89	0	this	a
        //   0	89	1	paramInt	int
        //   0	89	2	paramj	j
        //   3	80	3	localParcel1	Parcel
        //   7	71	4	localParcel2	Parcel
        //   75	12	5	localObject	Object
        //   30	41	6	localIBinder	IBinder
        // Exception table:
        //   from	to	target	type
        //   9	20	75	finally
        //   24	32	75	finally
        //   32	59	75	finally
      }
      
      public void a(BeginCompoundOperationRequest paramBeginCompoundOperationRequest, o paramo)
        throws RemoteException
      {
        Parcel localParcel1 = Parcel.obtain();
        Parcel localParcel2 = Parcel.obtain();
        for (;;)
        {
          try
          {
            localParcel1.writeInterfaceToken("com.google.android.gms.drive.realtime.internal.IRealtimeService");
            if (paramBeginCompoundOperationRequest != null)
            {
              localParcel1.writeInt(1);
              paramBeginCompoundOperationRequest.writeToParcel(localParcel1, 0);
              if (paramo != null)
              {
                localIBinder = paramo.asBinder();
                localParcel1.writeStrongBinder(localIBinder);
                this.le.transact(18, localParcel1, localParcel2, 0);
                localParcel2.readException();
              }
            }
            else
            {
              localParcel1.writeInt(0);
              continue;
            }
            IBinder localIBinder = null;
          }
          finally
          {
            localParcel2.recycle();
            localParcel1.recycle();
          }
        }
      }
      
      public void a(EndCompoundOperationRequest paramEndCompoundOperationRequest, j paramj)
        throws RemoteException
      {
        Parcel localParcel1 = Parcel.obtain();
        Parcel localParcel2 = Parcel.obtain();
        for (;;)
        {
          try
          {
            localParcel1.writeInterfaceToken("com.google.android.gms.drive.realtime.internal.IRealtimeService");
            if (paramEndCompoundOperationRequest != null)
            {
              localParcel1.writeInt(1);
              paramEndCompoundOperationRequest.writeToParcel(localParcel1, 0);
              if (paramj != null)
              {
                localIBinder = paramj.asBinder();
                localParcel1.writeStrongBinder(localIBinder);
                this.le.transact(41, localParcel1, localParcel2, 0);
                localParcel2.readException();
              }
            }
            else
            {
              localParcel1.writeInt(0);
              continue;
            }
            IBinder localIBinder = null;
          }
          finally
          {
            localParcel2.recycle();
            localParcel1.recycle();
          }
        }
      }
      
      public void a(EndCompoundOperationRequest paramEndCompoundOperationRequest, o paramo)
        throws RemoteException
      {
        Parcel localParcel1 = Parcel.obtain();
        Parcel localParcel2 = Parcel.obtain();
        for (;;)
        {
          try
          {
            localParcel1.writeInterfaceToken("com.google.android.gms.drive.realtime.internal.IRealtimeService");
            if (paramEndCompoundOperationRequest != null)
            {
              localParcel1.writeInt(1);
              paramEndCompoundOperationRequest.writeToParcel(localParcel1, 0);
              if (paramo != null)
              {
                localIBinder = paramo.asBinder();
                localParcel1.writeStrongBinder(localIBinder);
                this.le.transact(19, localParcel1, localParcel2, 0);
                localParcel2.readException();
              }
            }
            else
            {
              localParcel1.writeInt(0);
              continue;
            }
            IBinder localIBinder = null;
          }
          finally
          {
            localParcel2.recycle();
            localParcel1.recycle();
          }
        }
      }
      
      public void a(ParcelableIndexReference paramParcelableIndexReference, n paramn)
        throws RemoteException
      {
        Parcel localParcel1 = Parcel.obtain();
        Parcel localParcel2 = Parcel.obtain();
        for (;;)
        {
          try
          {
            localParcel1.writeInterfaceToken("com.google.android.gms.drive.realtime.internal.IRealtimeService");
            if (paramParcelableIndexReference != null)
            {
              localParcel1.writeInt(1);
              paramParcelableIndexReference.writeToParcel(localParcel1, 0);
              if (paramn != null)
              {
                localIBinder = paramn.asBinder();
                localParcel1.writeStrongBinder(localIBinder);
                this.le.transact(26, localParcel1, localParcel2, 0);
                localParcel2.readException();
              }
            }
            else
            {
              localParcel1.writeInt(0);
              continue;
            }
            IBinder localIBinder = null;
          }
          finally
          {
            localParcel2.recycle();
            localParcel1.recycle();
          }
        }
      }
      
      /* Error */
      public void a(c paramc)
        throws RemoteException
      {
        // Byte code:
        //   0: invokestatic 25	android/os/Parcel:obtain	()Landroid/os/Parcel;
        //   3: astore_2
        //   4: invokestatic 25	android/os/Parcel:obtain	()Landroid/os/Parcel;
        //   7: astore_3
        //   8: aload_2
        //   9: ldc 27
        //   11: invokevirtual 31	android/os/Parcel:writeInterfaceToken	(Ljava/lang/String;)V
        //   14: aload_1
        //   15: ifnull +44 -> 59
        //   18: aload_1
        //   19: invokeinterface 82 1 0
        //   24: astore 5
        //   26: aload_2
        //   27: aload 5
        //   29: invokevirtual 44	android/os/Parcel:writeStrongBinder	(Landroid/os/IBinder;)V
        //   32: aload_0
        //   33: getfield 15	com/google/android/gms/drive/realtime/internal/m$a$a:le	Landroid/os/IBinder;
        //   36: iconst_2
        //   37: aload_2
        //   38: aload_3
        //   39: iconst_0
        //   40: invokeinterface 50 5 0
        //   45: pop
        //   46: aload_3
        //   47: invokevirtual 53	android/os/Parcel:readException	()V
        //   50: aload_3
        //   51: invokevirtual 56	android/os/Parcel:recycle	()V
        //   54: aload_2
        //   55: invokevirtual 56	android/os/Parcel:recycle	()V
        //   58: return
        //   59: aconst_null
        //   60: astore 5
        //   62: goto -36 -> 26
        //   65: astore 4
        //   67: aload_3
        //   68: invokevirtual 56	android/os/Parcel:recycle	()V
        //   71: aload_2
        //   72: invokevirtual 56	android/os/Parcel:recycle	()V
        //   75: aload 4
        //   77: athrow
        // Local variable table:
        //   start	length	slot	name	signature
        //   0	78	0	this	a
        //   0	78	1	paramc	c
        //   3	69	2	localParcel1	Parcel
        //   7	61	3	localParcel2	Parcel
        //   65	11	4	localObject	Object
        //   24	37	5	localIBinder	IBinder
        // Exception table:
        //   from	to	target	type
        //   8	14	65	finally
        //   18	26	65	finally
        //   26	50	65	finally
      }
      
      /* Error */
      public void a(d paramd)
        throws RemoteException
      {
        // Byte code:
        //   0: invokestatic 25	android/os/Parcel:obtain	()Landroid/os/Parcel;
        //   3: astore_2
        //   4: invokestatic 25	android/os/Parcel:obtain	()Landroid/os/Parcel;
        //   7: astore_3
        //   8: aload_2
        //   9: ldc 27
        //   11: invokevirtual 31	android/os/Parcel:writeInterfaceToken	(Ljava/lang/String;)V
        //   14: aload_1
        //   15: ifnull +45 -> 60
        //   18: aload_1
        //   19: invokeinterface 86 1 0
        //   24: astore 5
        //   26: aload_2
        //   27: aload 5
        //   29: invokevirtual 44	android/os/Parcel:writeStrongBinder	(Landroid/os/IBinder;)V
        //   32: aload_0
        //   33: getfield 15	com/google/android/gms/drive/realtime/internal/m$a$a:le	Landroid/os/IBinder;
        //   36: bipush 32
        //   38: aload_2
        //   39: aload_3
        //   40: iconst_0
        //   41: invokeinterface 50 5 0
        //   46: pop
        //   47: aload_3
        //   48: invokevirtual 53	android/os/Parcel:readException	()V
        //   51: aload_3
        //   52: invokevirtual 56	android/os/Parcel:recycle	()V
        //   55: aload_2
        //   56: invokevirtual 56	android/os/Parcel:recycle	()V
        //   59: return
        //   60: aconst_null
        //   61: astore 5
        //   63: goto -37 -> 26
        //   66: astore 4
        //   68: aload_3
        //   69: invokevirtual 56	android/os/Parcel:recycle	()V
        //   72: aload_2
        //   73: invokevirtual 56	android/os/Parcel:recycle	()V
        //   76: aload 4
        //   78: athrow
        // Local variable table:
        //   start	length	slot	name	signature
        //   0	79	0	this	a
        //   0	79	1	paramd	d
        //   3	70	2	localParcel1	Parcel
        //   7	62	3	localParcel2	Parcel
        //   66	11	4	localObject	Object
        //   24	38	5	localIBinder	IBinder
        // Exception table:
        //   from	to	target	type
        //   8	14	66	finally
        //   18	26	66	finally
        //   26	51	66	finally
      }
      
      /* Error */
      public void a(e parame)
        throws RemoteException
      {
        // Byte code:
        //   0: invokestatic 25	android/os/Parcel:obtain	()Landroid/os/Parcel;
        //   3: astore_2
        //   4: invokestatic 25	android/os/Parcel:obtain	()Landroid/os/Parcel;
        //   7: astore_3
        //   8: aload_2
        //   9: ldc 27
        //   11: invokevirtual 31	android/os/Parcel:writeInterfaceToken	(Ljava/lang/String;)V
        //   14: aload_1
        //   15: ifnull +45 -> 60
        //   18: aload_1
        //   19: invokeinterface 90 1 0
        //   24: astore 5
        //   26: aload_2
        //   27: aload 5
        //   29: invokevirtual 44	android/os/Parcel:writeStrongBinder	(Landroid/os/IBinder;)V
        //   32: aload_0
        //   33: getfield 15	com/google/android/gms/drive/realtime/internal/m$a$a:le	Landroid/os/IBinder;
        //   36: bipush 31
        //   38: aload_2
        //   39: aload_3
        //   40: iconst_0
        //   41: invokeinterface 50 5 0
        //   46: pop
        //   47: aload_3
        //   48: invokevirtual 53	android/os/Parcel:readException	()V
        //   51: aload_3
        //   52: invokevirtual 56	android/os/Parcel:recycle	()V
        //   55: aload_2
        //   56: invokevirtual 56	android/os/Parcel:recycle	()V
        //   59: return
        //   60: aconst_null
        //   61: astore 5
        //   63: goto -37 -> 26
        //   66: astore 4
        //   68: aload_3
        //   69: invokevirtual 56	android/os/Parcel:recycle	()V
        //   72: aload_2
        //   73: invokevirtual 56	android/os/Parcel:recycle	()V
        //   76: aload 4
        //   78: athrow
        // Local variable table:
        //   start	length	slot	name	signature
        //   0	79	0	this	a
        //   0	79	1	parame	e
        //   3	70	2	localParcel1	Parcel
        //   7	62	3	localParcel2	Parcel
        //   66	11	4	localObject	Object
        //   24	38	5	localIBinder	IBinder
        // Exception table:
        //   from	to	target	type
        //   8	14	66	finally
        //   18	26	66	finally
        //   26	51	66	finally
      }
      
      /* Error */
      public void a(h paramh)
        throws RemoteException
      {
        // Byte code:
        //   0: invokestatic 25	android/os/Parcel:obtain	()Landroid/os/Parcel;
        //   3: astore_2
        //   4: invokestatic 25	android/os/Parcel:obtain	()Landroid/os/Parcel;
        //   7: astore_3
        //   8: aload_2
        //   9: ldc 27
        //   11: invokevirtual 31	android/os/Parcel:writeInterfaceToken	(Ljava/lang/String;)V
        //   14: aload_1
        //   15: ifnull +45 -> 60
        //   18: aload_1
        //   19: invokeinterface 94 1 0
        //   24: astore 5
        //   26: aload_2
        //   27: aload 5
        //   29: invokevirtual 44	android/os/Parcel:writeStrongBinder	(Landroid/os/IBinder;)V
        //   32: aload_0
        //   33: getfield 15	com/google/android/gms/drive/realtime/internal/m$a$a:le	Landroid/os/IBinder;
        //   36: bipush 36
        //   38: aload_2
        //   39: aload_3
        //   40: iconst_0
        //   41: invokeinterface 50 5 0
        //   46: pop
        //   47: aload_3
        //   48: invokevirtual 53	android/os/Parcel:readException	()V
        //   51: aload_3
        //   52: invokevirtual 56	android/os/Parcel:recycle	()V
        //   55: aload_2
        //   56: invokevirtual 56	android/os/Parcel:recycle	()V
        //   59: return
        //   60: aconst_null
        //   61: astore 5
        //   63: goto -37 -> 26
        //   66: astore 4
        //   68: aload_3
        //   69: invokevirtual 56	android/os/Parcel:recycle	()V
        //   72: aload_2
        //   73: invokevirtual 56	android/os/Parcel:recycle	()V
        //   76: aload 4
        //   78: athrow
        // Local variable table:
        //   start	length	slot	name	signature
        //   0	79	0	this	a
        //   0	79	1	paramh	h
        //   3	70	2	localParcel1	Parcel
        //   7	62	3	localParcel2	Parcel
        //   66	11	4	localObject	Object
        //   24	38	5	localIBinder	IBinder
        // Exception table:
        //   from	to	target	type
        //   8	14	66	finally
        //   18	26	66	finally
        //   26	51	66	finally
      }
      
      /* Error */
      public void a(i parami)
        throws RemoteException
      {
        // Byte code:
        //   0: invokestatic 25	android/os/Parcel:obtain	()Landroid/os/Parcel;
        //   3: astore_2
        //   4: invokestatic 25	android/os/Parcel:obtain	()Landroid/os/Parcel;
        //   7: astore_3
        //   8: aload_2
        //   9: ldc 27
        //   11: invokevirtual 31	android/os/Parcel:writeInterfaceToken	(Ljava/lang/String;)V
        //   14: aload_1
        //   15: ifnull +45 -> 60
        //   18: aload_1
        //   19: invokeinterface 98 1 0
        //   24: astore 5
        //   26: aload_2
        //   27: aload 5
        //   29: invokevirtual 44	android/os/Parcel:writeStrongBinder	(Landroid/os/IBinder;)V
        //   32: aload_0
        //   33: getfield 15	com/google/android/gms/drive/realtime/internal/m$a$a:le	Landroid/os/IBinder;
        //   36: bipush 34
        //   38: aload_2
        //   39: aload_3
        //   40: iconst_0
        //   41: invokeinterface 50 5 0
        //   46: pop
        //   47: aload_3
        //   48: invokevirtual 53	android/os/Parcel:readException	()V
        //   51: aload_3
        //   52: invokevirtual 56	android/os/Parcel:recycle	()V
        //   55: aload_2
        //   56: invokevirtual 56	android/os/Parcel:recycle	()V
        //   59: return
        //   60: aconst_null
        //   61: astore 5
        //   63: goto -37 -> 26
        //   66: astore 4
        //   68: aload_3
        //   69: invokevirtual 56	android/os/Parcel:recycle	()V
        //   72: aload_2
        //   73: invokevirtual 56	android/os/Parcel:recycle	()V
        //   76: aload 4
        //   78: athrow
        // Local variable table:
        //   start	length	slot	name	signature
        //   0	79	0	this	a
        //   0	79	1	parami	i
        //   3	70	2	localParcel1	Parcel
        //   7	62	3	localParcel2	Parcel
        //   66	11	4	localObject	Object
        //   24	38	5	localIBinder	IBinder
        // Exception table:
        //   from	to	target	type
        //   8	14	66	finally
        //   18	26	66	finally
        //   26	51	66	finally
      }
      
      /* Error */
      public void a(j paramj)
        throws RemoteException
      {
        // Byte code:
        //   0: invokestatic 25	android/os/Parcel:obtain	()Landroid/os/Parcel;
        //   3: astore_2
        //   4: invokestatic 25	android/os/Parcel:obtain	()Landroid/os/Parcel;
        //   7: astore_3
        //   8: aload_2
        //   9: ldc 27
        //   11: invokevirtual 31	android/os/Parcel:writeInterfaceToken	(Ljava/lang/String;)V
        //   14: aload_1
        //   15: ifnull +45 -> 60
        //   18: aload_1
        //   19: invokeinterface 41 1 0
        //   24: astore 5
        //   26: aload_2
        //   27: aload 5
        //   29: invokevirtual 44	android/os/Parcel:writeStrongBinder	(Landroid/os/IBinder;)V
        //   32: aload_0
        //   33: getfield 15	com/google/android/gms/drive/realtime/internal/m$a$a:le	Landroid/os/IBinder;
        //   36: bipush 22
        //   38: aload_2
        //   39: aload_3
        //   40: iconst_0
        //   41: invokeinterface 50 5 0
        //   46: pop
        //   47: aload_3
        //   48: invokevirtual 53	android/os/Parcel:readException	()V
        //   51: aload_3
        //   52: invokevirtual 56	android/os/Parcel:recycle	()V
        //   55: aload_2
        //   56: invokevirtual 56	android/os/Parcel:recycle	()V
        //   59: return
        //   60: aconst_null
        //   61: astore 5
        //   63: goto -37 -> 26
        //   66: astore 4
        //   68: aload_3
        //   69: invokevirtual 56	android/os/Parcel:recycle	()V
        //   72: aload_2
        //   73: invokevirtual 56	android/os/Parcel:recycle	()V
        //   76: aload 4
        //   78: athrow
        // Local variable table:
        //   start	length	slot	name	signature
        //   0	79	0	this	a
        //   0	79	1	paramj	j
        //   3	70	2	localParcel1	Parcel
        //   7	62	3	localParcel2	Parcel
        //   66	11	4	localObject	Object
        //   24	38	5	localIBinder	IBinder
        // Exception table:
        //   from	to	target	type
        //   8	14	66	finally
        //   18	26	66	finally
        //   26	51	66	finally
      }
      
      /* Error */
      public void a(l paraml)
        throws RemoteException
      {
        // Byte code:
        //   0: invokestatic 25	android/os/Parcel:obtain	()Landroid/os/Parcel;
        //   3: astore_2
        //   4: invokestatic 25	android/os/Parcel:obtain	()Landroid/os/Parcel;
        //   7: astore_3
        //   8: aload_2
        //   9: ldc 27
        //   11: invokevirtual 31	android/os/Parcel:writeInterfaceToken	(Ljava/lang/String;)V
        //   14: aload_1
        //   15: ifnull +45 -> 60
        //   18: aload_1
        //   19: invokeinterface 103 1 0
        //   24: astore 5
        //   26: aload_2
        //   27: aload 5
        //   29: invokevirtual 44	android/os/Parcel:writeStrongBinder	(Landroid/os/IBinder;)V
        //   32: aload_0
        //   33: getfield 15	com/google/android/gms/drive/realtime/internal/m$a$a:le	Landroid/os/IBinder;
        //   36: bipush 40
        //   38: aload_2
        //   39: aload_3
        //   40: iconst_0
        //   41: invokeinterface 50 5 0
        //   46: pop
        //   47: aload_3
        //   48: invokevirtual 53	android/os/Parcel:readException	()V
        //   51: aload_3
        //   52: invokevirtual 56	android/os/Parcel:recycle	()V
        //   55: aload_2
        //   56: invokevirtual 56	android/os/Parcel:recycle	()V
        //   59: return
        //   60: aconst_null
        //   61: astore 5
        //   63: goto -37 -> 26
        //   66: astore 4
        //   68: aload_3
        //   69: invokevirtual 56	android/os/Parcel:recycle	()V
        //   72: aload_2
        //   73: invokevirtual 56	android/os/Parcel:recycle	()V
        //   76: aload 4
        //   78: athrow
        // Local variable table:
        //   start	length	slot	name	signature
        //   0	79	0	this	a
        //   0	79	1	paraml	l
        //   3	70	2	localParcel1	Parcel
        //   7	62	3	localParcel2	Parcel
        //   66	11	4	localObject	Object
        //   24	38	5	localIBinder	IBinder
        // Exception table:
        //   from	to	target	type
        //   8	14	66	finally
        //   18	26	66	finally
        //   26	51	66	finally
      }
      
      /* Error */
      public void a(o paramo)
        throws RemoteException
      {
        // Byte code:
        //   0: invokestatic 25	android/os/Parcel:obtain	()Landroid/os/Parcel;
        //   3: astore_2
        //   4: invokestatic 25	android/os/Parcel:obtain	()Landroid/os/Parcel;
        //   7: astore_3
        //   8: aload_2
        //   9: ldc 27
        //   11: invokevirtual 31	android/os/Parcel:writeInterfaceToken	(Ljava/lang/String;)V
        //   14: aload_1
        //   15: ifnull +44 -> 59
        //   18: aload_1
        //   19: invokeinterface 66 1 0
        //   24: astore 5
        //   26: aload_2
        //   27: aload 5
        //   29: invokevirtual 44	android/os/Parcel:writeStrongBinder	(Landroid/os/IBinder;)V
        //   32: aload_0
        //   33: getfield 15	com/google/android/gms/drive/realtime/internal/m$a$a:le	Landroid/os/IBinder;
        //   36: iconst_3
        //   37: aload_2
        //   38: aload_3
        //   39: iconst_0
        //   40: invokeinterface 50 5 0
        //   45: pop
        //   46: aload_3
        //   47: invokevirtual 53	android/os/Parcel:readException	()V
        //   50: aload_3
        //   51: invokevirtual 56	android/os/Parcel:recycle	()V
        //   54: aload_2
        //   55: invokevirtual 56	android/os/Parcel:recycle	()V
        //   58: return
        //   59: aconst_null
        //   60: astore 5
        //   62: goto -36 -> 26
        //   65: astore 4
        //   67: aload_3
        //   68: invokevirtual 56	android/os/Parcel:recycle	()V
        //   71: aload_2
        //   72: invokevirtual 56	android/os/Parcel:recycle	()V
        //   75: aload 4
        //   77: athrow
        // Local variable table:
        //   start	length	slot	name	signature
        //   0	78	0	this	a
        //   0	78	1	paramo	o
        //   3	69	2	localParcel1	Parcel
        //   7	61	3	localParcel2	Parcel
        //   65	11	4	localObject	Object
        //   24	37	5	localIBinder	IBinder
        // Exception table:
        //   from	to	target	type
        //   8	14	65	finally
        //   18	26	65	finally
        //   26	50	65	finally
      }
      
      /* Error */
      public void a(String paramString, int paramInt1, int paramInt2, g paramg)
        throws RemoteException
      {
        // Byte code:
        //   0: invokestatic 25	android/os/Parcel:obtain	()Landroid/os/Parcel;
        //   3: astore 5
        //   5: invokestatic 25	android/os/Parcel:obtain	()Landroid/os/Parcel;
        //   8: astore 6
        //   10: aload 5
        //   12: ldc 27
        //   14: invokevirtual 31	android/os/Parcel:writeInterfaceToken	(Ljava/lang/String;)V
        //   17: aload 5
        //   19: aload_1
        //   20: invokevirtual 108	android/os/Parcel:writeString	(Ljava/lang/String;)V
        //   23: aload 5
        //   25: iload_2
        //   26: invokevirtual 35	android/os/Parcel:writeInt	(I)V
        //   29: aload 5
        //   31: iload_3
        //   32: invokevirtual 35	android/os/Parcel:writeInt	(I)V
        //   35: aload 4
        //   37: ifnull +52 -> 89
        //   40: aload 4
        //   42: invokeinterface 111 1 0
        //   47: astore 8
        //   49: aload 5
        //   51: aload 8
        //   53: invokevirtual 44	android/os/Parcel:writeStrongBinder	(Landroid/os/IBinder;)V
        //   56: aload_0
        //   57: getfield 15	com/google/android/gms/drive/realtime/internal/m$a$a:le	Landroid/os/IBinder;
        //   60: bipush 17
        //   62: aload 5
        //   64: aload 6
        //   66: iconst_0
        //   67: invokeinterface 50 5 0
        //   72: pop
        //   73: aload 6
        //   75: invokevirtual 53	android/os/Parcel:readException	()V
        //   78: aload 6
        //   80: invokevirtual 56	android/os/Parcel:recycle	()V
        //   83: aload 5
        //   85: invokevirtual 56	android/os/Parcel:recycle	()V
        //   88: return
        //   89: aconst_null
        //   90: astore 8
        //   92: goto -43 -> 49
        //   95: astore 7
        //   97: aload 6
        //   99: invokevirtual 56	android/os/Parcel:recycle	()V
        //   102: aload 5
        //   104: invokevirtual 56	android/os/Parcel:recycle	()V
        //   107: aload 7
        //   109: athrow
        // Local variable table:
        //   start	length	slot	name	signature
        //   0	110	0	this	a
        //   0	110	1	paramString	String
        //   0	110	2	paramInt1	int
        //   0	110	3	paramInt2	int
        //   0	110	4	paramg	g
        //   3	100	5	localParcel1	Parcel
        //   8	90	6	localParcel2	Parcel
        //   95	13	7	localObject	Object
        //   47	44	8	localIBinder	IBinder
        // Exception table:
        //   from	to	target	type
        //   10	35	95	finally
        //   40	49	95	finally
        //   49	78	95	finally
      }
      
      /* Error */
      public void a(String paramString, int paramInt1, int paramInt2, j paramj)
        throws RemoteException
      {
        // Byte code:
        //   0: invokestatic 25	android/os/Parcel:obtain	()Landroid/os/Parcel;
        //   3: astore 5
        //   5: invokestatic 25	android/os/Parcel:obtain	()Landroid/os/Parcel;
        //   8: astore 6
        //   10: aload 5
        //   12: ldc 27
        //   14: invokevirtual 31	android/os/Parcel:writeInterfaceToken	(Ljava/lang/String;)V
        //   17: aload 5
        //   19: aload_1
        //   20: invokevirtual 108	android/os/Parcel:writeString	(Ljava/lang/String;)V
        //   23: aload 5
        //   25: iload_2
        //   26: invokevirtual 35	android/os/Parcel:writeInt	(I)V
        //   29: aload 5
        //   31: iload_3
        //   32: invokevirtual 35	android/os/Parcel:writeInt	(I)V
        //   35: aload 4
        //   37: ifnull +52 -> 89
        //   40: aload 4
        //   42: invokeinterface 41 1 0
        //   47: astore 8
        //   49: aload 5
        //   51: aload 8
        //   53: invokevirtual 44	android/os/Parcel:writeStrongBinder	(Landroid/os/IBinder;)V
        //   56: aload_0
        //   57: getfield 15	com/google/android/gms/drive/realtime/internal/m$a$a:le	Landroid/os/IBinder;
        //   60: bipush 11
        //   62: aload 5
        //   64: aload 6
        //   66: iconst_0
        //   67: invokeinterface 50 5 0
        //   72: pop
        //   73: aload 6
        //   75: invokevirtual 53	android/os/Parcel:readException	()V
        //   78: aload 6
        //   80: invokevirtual 56	android/os/Parcel:recycle	()V
        //   83: aload 5
        //   85: invokevirtual 56	android/os/Parcel:recycle	()V
        //   88: return
        //   89: aconst_null
        //   90: astore 8
        //   92: goto -43 -> 49
        //   95: astore 7
        //   97: aload 6
        //   99: invokevirtual 56	android/os/Parcel:recycle	()V
        //   102: aload 5
        //   104: invokevirtual 56	android/os/Parcel:recycle	()V
        //   107: aload 7
        //   109: athrow
        // Local variable table:
        //   start	length	slot	name	signature
        //   0	110	0	this	a
        //   0	110	1	paramString	String
        //   0	110	2	paramInt1	int
        //   0	110	3	paramInt2	int
        //   0	110	4	paramj	j
        //   3	100	5	localParcel1	Parcel
        //   8	90	6	localParcel2	Parcel
        //   95	13	7	localObject	Object
        //   47	44	8	localIBinder	IBinder
        // Exception table:
        //   from	to	target	type
        //   10	35	95	finally
        //   40	49	95	finally
        //   49	78	95	finally
      }
      
      public void a(String paramString, int paramInt, DataHolder paramDataHolder, g paramg)
        throws RemoteException
      {
        Parcel localParcel1 = Parcel.obtain();
        Parcel localParcel2 = Parcel.obtain();
        for (;;)
        {
          try
          {
            localParcel1.writeInterfaceToken("com.google.android.gms.drive.realtime.internal.IRealtimeService");
            localParcel1.writeString(paramString);
            localParcel1.writeInt(paramInt);
            if (paramDataHolder != null)
            {
              localParcel1.writeInt(1);
              paramDataHolder.writeToParcel(localParcel1, 0);
              if (paramg != null)
              {
                localIBinder = paramg.asBinder();
                localParcel1.writeStrongBinder(localIBinder);
                this.le.transact(16, localParcel1, localParcel2, 0);
                localParcel2.readException();
              }
            }
            else
            {
              localParcel1.writeInt(0);
              continue;
            }
            IBinder localIBinder = null;
          }
          finally
          {
            localParcel2.recycle();
            localParcel1.recycle();
          }
        }
      }
      
      public void a(String paramString, int paramInt, DataHolder paramDataHolder, j paramj)
        throws RemoteException
      {
        Parcel localParcel1 = Parcel.obtain();
        Parcel localParcel2 = Parcel.obtain();
        for (;;)
        {
          try
          {
            localParcel1.writeInterfaceToken("com.google.android.gms.drive.realtime.internal.IRealtimeService");
            localParcel1.writeString(paramString);
            localParcel1.writeInt(paramInt);
            if (paramDataHolder != null)
            {
              localParcel1.writeInt(1);
              paramDataHolder.writeToParcel(localParcel1, 0);
              if (paramj != null)
              {
                localIBinder = paramj.asBinder();
                localParcel1.writeStrongBinder(localIBinder);
                this.le.transact(15, localParcel1, localParcel2, 0);
                localParcel2.readException();
              }
            }
            else
            {
              localParcel1.writeInt(0);
              continue;
            }
            IBinder localIBinder = null;
          }
          finally
          {
            localParcel2.recycle();
            localParcel1.recycle();
          }
        }
      }
      
      /* Error */
      public void a(String paramString, int paramInt, o paramo)
        throws RemoteException
      {
        // Byte code:
        //   0: invokestatic 25	android/os/Parcel:obtain	()Landroid/os/Parcel;
        //   3: astore 4
        //   5: invokestatic 25	android/os/Parcel:obtain	()Landroid/os/Parcel;
        //   8: astore 5
        //   10: aload 4
        //   12: ldc 27
        //   14: invokevirtual 31	android/os/Parcel:writeInterfaceToken	(Ljava/lang/String;)V
        //   17: aload 4
        //   19: aload_1
        //   20: invokevirtual 108	android/os/Parcel:writeString	(Ljava/lang/String;)V
        //   23: aload 4
        //   25: iload_2
        //   26: invokevirtual 35	android/os/Parcel:writeInt	(I)V
        //   29: aload_3
        //   30: ifnull +51 -> 81
        //   33: aload_3
        //   34: invokeinterface 66 1 0
        //   39: astore 7
        //   41: aload 4
        //   43: aload 7
        //   45: invokevirtual 44	android/os/Parcel:writeStrongBinder	(Landroid/os/IBinder;)V
        //   48: aload_0
        //   49: getfield 15	com/google/android/gms/drive/realtime/internal/m$a$a:le	Landroid/os/IBinder;
        //   52: bipush 28
        //   54: aload 4
        //   56: aload 5
        //   58: iconst_0
        //   59: invokeinterface 50 5 0
        //   64: pop
        //   65: aload 5
        //   67: invokevirtual 53	android/os/Parcel:readException	()V
        //   70: aload 5
        //   72: invokevirtual 56	android/os/Parcel:recycle	()V
        //   75: aload 4
        //   77: invokevirtual 56	android/os/Parcel:recycle	()V
        //   80: return
        //   81: aconst_null
        //   82: astore 7
        //   84: goto -43 -> 41
        //   87: astore 6
        //   89: aload 5
        //   91: invokevirtual 56	android/os/Parcel:recycle	()V
        //   94: aload 4
        //   96: invokevirtual 56	android/os/Parcel:recycle	()V
        //   99: aload 6
        //   101: athrow
        // Local variable table:
        //   start	length	slot	name	signature
        //   0	102	0	this	a
        //   0	102	1	paramString	String
        //   0	102	2	paramInt	int
        //   0	102	3	paramo	o
        //   3	92	4	localParcel1	Parcel
        //   8	82	5	localParcel2	Parcel
        //   87	13	6	localObject	Object
        //   39	44	7	localIBinder	IBinder
        // Exception table:
        //   from	to	target	type
        //   10	29	87	finally
        //   33	41	87	finally
        //   41	70	87	finally
      }
      
      /* Error */
      public void a(String paramString1, int paramInt1, String paramString2, int paramInt2, j paramj)
        throws RemoteException
      {
        // Byte code:
        //   0: invokestatic 25	android/os/Parcel:obtain	()Landroid/os/Parcel;
        //   3: astore 6
        //   5: invokestatic 25	android/os/Parcel:obtain	()Landroid/os/Parcel;
        //   8: astore 7
        //   10: aload 6
        //   12: ldc 27
        //   14: invokevirtual 31	android/os/Parcel:writeInterfaceToken	(Ljava/lang/String;)V
        //   17: aload 6
        //   19: aload_1
        //   20: invokevirtual 108	android/os/Parcel:writeString	(Ljava/lang/String;)V
        //   23: aload 6
        //   25: iload_2
        //   26: invokevirtual 35	android/os/Parcel:writeInt	(I)V
        //   29: aload 6
        //   31: aload_3
        //   32: invokevirtual 108	android/os/Parcel:writeString	(Ljava/lang/String;)V
        //   35: aload 6
        //   37: iload 4
        //   39: invokevirtual 35	android/os/Parcel:writeInt	(I)V
        //   42: aload 5
        //   44: ifnull +52 -> 96
        //   47: aload 5
        //   49: invokeinterface 41 1 0
        //   54: astore 9
        //   56: aload 6
        //   58: aload 9
        //   60: invokevirtual 44	android/os/Parcel:writeStrongBinder	(Landroid/os/IBinder;)V
        //   63: aload_0
        //   64: getfield 15	com/google/android/gms/drive/realtime/internal/m$a$a:le	Landroid/os/IBinder;
        //   67: bipush 37
        //   69: aload 6
        //   71: aload 7
        //   73: iconst_0
        //   74: invokeinterface 50 5 0
        //   79: pop
        //   80: aload 7
        //   82: invokevirtual 53	android/os/Parcel:readException	()V
        //   85: aload 7
        //   87: invokevirtual 56	android/os/Parcel:recycle	()V
        //   90: aload 6
        //   92: invokevirtual 56	android/os/Parcel:recycle	()V
        //   95: return
        //   96: aconst_null
        //   97: astore 9
        //   99: goto -43 -> 56
        //   102: astore 8
        //   104: aload 7
        //   106: invokevirtual 56	android/os/Parcel:recycle	()V
        //   109: aload 6
        //   111: invokevirtual 56	android/os/Parcel:recycle	()V
        //   114: aload 8
        //   116: athrow
        // Local variable table:
        //   start	length	slot	name	signature
        //   0	117	0	this	a
        //   0	117	1	paramString1	String
        //   0	117	2	paramInt1	int
        //   0	117	3	paramString2	String
        //   0	117	4	paramInt2	int
        //   0	117	5	paramj	j
        //   3	107	6	localParcel1	Parcel
        //   8	97	7	localParcel2	Parcel
        //   102	13	8	localObject	Object
        //   54	44	9	localIBinder	IBinder
        // Exception table:
        //   from	to	target	type
        //   10	42	102	finally
        //   47	56	102	finally
        //   56	85	102	finally
      }
      
      /* Error */
      public void a(String paramString1, int paramInt, String paramString2, j paramj)
        throws RemoteException
      {
        // Byte code:
        //   0: invokestatic 25	android/os/Parcel:obtain	()Landroid/os/Parcel;
        //   3: astore 5
        //   5: invokestatic 25	android/os/Parcel:obtain	()Landroid/os/Parcel;
        //   8: astore 6
        //   10: aload 5
        //   12: ldc 27
        //   14: invokevirtual 31	android/os/Parcel:writeInterfaceToken	(Ljava/lang/String;)V
        //   17: aload 5
        //   19: aload_1
        //   20: invokevirtual 108	android/os/Parcel:writeString	(Ljava/lang/String;)V
        //   23: aload 5
        //   25: iload_2
        //   26: invokevirtual 35	android/os/Parcel:writeInt	(I)V
        //   29: aload 5
        //   31: aload_3
        //   32: invokevirtual 108	android/os/Parcel:writeString	(Ljava/lang/String;)V
        //   35: aload 4
        //   37: ifnull +52 -> 89
        //   40: aload 4
        //   42: invokeinterface 41 1 0
        //   47: astore 8
        //   49: aload 5
        //   51: aload 8
        //   53: invokevirtual 44	android/os/Parcel:writeStrongBinder	(Landroid/os/IBinder;)V
        //   56: aload_0
        //   57: getfield 15	com/google/android/gms/drive/realtime/internal/m$a$a:le	Landroid/os/IBinder;
        //   60: bipush 10
        //   62: aload 5
        //   64: aload 6
        //   66: iconst_0
        //   67: invokeinterface 50 5 0
        //   72: pop
        //   73: aload 6
        //   75: invokevirtual 53	android/os/Parcel:readException	()V
        //   78: aload 6
        //   80: invokevirtual 56	android/os/Parcel:recycle	()V
        //   83: aload 5
        //   85: invokevirtual 56	android/os/Parcel:recycle	()V
        //   88: return
        //   89: aconst_null
        //   90: astore 8
        //   92: goto -43 -> 49
        //   95: astore 7
        //   97: aload 6
        //   99: invokevirtual 56	android/os/Parcel:recycle	()V
        //   102: aload 5
        //   104: invokevirtual 56	android/os/Parcel:recycle	()V
        //   107: aload 7
        //   109: athrow
        // Local variable table:
        //   start	length	slot	name	signature
        //   0	110	0	this	a
        //   0	110	1	paramString1	String
        //   0	110	2	paramInt	int
        //   0	110	3	paramString2	String
        //   0	110	4	paramj	j
        //   3	100	5	localParcel1	Parcel
        //   8	90	6	localParcel2	Parcel
        //   95	13	7	localObject	Object
        //   47	44	8	localIBinder	IBinder
        // Exception table:
        //   from	to	target	type
        //   10	35	95	finally
        //   40	49	95	finally
        //   49	78	95	finally
      }
      
      public void a(String paramString, DataHolder paramDataHolder, j paramj)
        throws RemoteException
      {
        Parcel localParcel1 = Parcel.obtain();
        Parcel localParcel2 = Parcel.obtain();
        for (;;)
        {
          try
          {
            localParcel1.writeInterfaceToken("com.google.android.gms.drive.realtime.internal.IRealtimeService");
            localParcel1.writeString(paramString);
            if (paramDataHolder != null)
            {
              localParcel1.writeInt(1);
              paramDataHolder.writeToParcel(localParcel1, 0);
              if (paramj != null)
              {
                localIBinder = paramj.asBinder();
                localParcel1.writeStrongBinder(localIBinder);
                this.le.transact(6, localParcel1, localParcel2, 0);
                localParcel2.readException();
              }
            }
            else
            {
              localParcel1.writeInt(0);
              continue;
            }
            IBinder localIBinder = null;
          }
          finally
          {
            localParcel2.recycle();
            localParcel1.recycle();
          }
        }
      }
      
      /* Error */
      public void a(String paramString, f paramf)
        throws RemoteException
      {
        // Byte code:
        //   0: invokestatic 25	android/os/Parcel:obtain	()Landroid/os/Parcel;
        //   3: astore_3
        //   4: invokestatic 25	android/os/Parcel:obtain	()Landroid/os/Parcel;
        //   7: astore 4
        //   9: aload_3
        //   10: ldc 27
        //   12: invokevirtual 31	android/os/Parcel:writeInterfaceToken	(Ljava/lang/String;)V
        //   15: aload_3
        //   16: aload_1
        //   17: invokevirtual 108	android/os/Parcel:writeString	(Ljava/lang/String;)V
        //   20: aload_2
        //   21: ifnull +48 -> 69
        //   24: aload_2
        //   25: invokeinterface 125 1 0
        //   30: astore 6
        //   32: aload_3
        //   33: aload 6
        //   35: invokevirtual 44	android/os/Parcel:writeStrongBinder	(Landroid/os/IBinder;)V
        //   38: aload_0
        //   39: getfield 15	com/google/android/gms/drive/realtime/internal/m$a$a:le	Landroid/os/IBinder;
        //   42: bipush 20
        //   44: aload_3
        //   45: aload 4
        //   47: iconst_0
        //   48: invokeinterface 50 5 0
        //   53: pop
        //   54: aload 4
        //   56: invokevirtual 53	android/os/Parcel:readException	()V
        //   59: aload 4
        //   61: invokevirtual 56	android/os/Parcel:recycle	()V
        //   64: aload_3
        //   65: invokevirtual 56	android/os/Parcel:recycle	()V
        //   68: return
        //   69: aconst_null
        //   70: astore 6
        //   72: goto -40 -> 32
        //   75: astore 5
        //   77: aload 4
        //   79: invokevirtual 56	android/os/Parcel:recycle	()V
        //   82: aload_3
        //   83: invokevirtual 56	android/os/Parcel:recycle	()V
        //   86: aload 5
        //   88: athrow
        // Local variable table:
        //   start	length	slot	name	signature
        //   0	89	0	this	a
        //   0	89	1	paramString	String
        //   0	89	2	paramf	f
        //   3	80	3	localParcel1	Parcel
        //   7	71	4	localParcel2	Parcel
        //   75	12	5	localObject	Object
        //   30	41	6	localIBinder	IBinder
        // Exception table:
        //   from	to	target	type
        //   9	20	75	finally
        //   24	32	75	finally
        //   32	59	75	finally
      }
      
      /* Error */
      public void a(String paramString, j paramj)
        throws RemoteException
      {
        // Byte code:
        //   0: invokestatic 25	android/os/Parcel:obtain	()Landroid/os/Parcel;
        //   3: astore_3
        //   4: invokestatic 25	android/os/Parcel:obtain	()Landroid/os/Parcel;
        //   7: astore 4
        //   9: aload_3
        //   10: ldc 27
        //   12: invokevirtual 31	android/os/Parcel:writeInterfaceToken	(Ljava/lang/String;)V
        //   15: aload_3
        //   16: aload_1
        //   17: invokevirtual 108	android/os/Parcel:writeString	(Ljava/lang/String;)V
        //   20: aload_2
        //   21: ifnull +48 -> 69
        //   24: aload_2
        //   25: invokeinterface 41 1 0
        //   30: astore 6
        //   32: aload_3
        //   33: aload 6
        //   35: invokevirtual 44	android/os/Parcel:writeStrongBinder	(Landroid/os/IBinder;)V
        //   38: aload_0
        //   39: getfield 15	com/google/android/gms/drive/realtime/internal/m$a$a:le	Landroid/os/IBinder;
        //   42: bipush 7
        //   44: aload_3
        //   45: aload 4
        //   47: iconst_0
        //   48: invokeinterface 50 5 0
        //   53: pop
        //   54: aload 4
        //   56: invokevirtual 53	android/os/Parcel:readException	()V
        //   59: aload 4
        //   61: invokevirtual 56	android/os/Parcel:recycle	()V
        //   64: aload_3
        //   65: invokevirtual 56	android/os/Parcel:recycle	()V
        //   68: return
        //   69: aconst_null
        //   70: astore 6
        //   72: goto -40 -> 32
        //   75: astore 5
        //   77: aload 4
        //   79: invokevirtual 56	android/os/Parcel:recycle	()V
        //   82: aload_3
        //   83: invokevirtual 56	android/os/Parcel:recycle	()V
        //   86: aload 5
        //   88: athrow
        // Local variable table:
        //   start	length	slot	name	signature
        //   0	89	0	this	a
        //   0	89	1	paramString	String
        //   0	89	2	paramj	j
        //   3	80	3	localParcel1	Parcel
        //   7	71	4	localParcel2	Parcel
        //   75	12	5	localObject	Object
        //   30	41	6	localIBinder	IBinder
        // Exception table:
        //   from	to	target	type
        //   9	20	75	finally
        //   24	32	75	finally
        //   32	59	75	finally
      }
      
      /* Error */
      public void a(String paramString, k paramk)
        throws RemoteException
      {
        // Byte code:
        //   0: invokestatic 25	android/os/Parcel:obtain	()Landroid/os/Parcel;
        //   3: astore_3
        //   4: invokestatic 25	android/os/Parcel:obtain	()Landroid/os/Parcel;
        //   7: astore 4
        //   9: aload_3
        //   10: ldc 27
        //   12: invokevirtual 31	android/os/Parcel:writeInterfaceToken	(Ljava/lang/String;)V
        //   15: aload_3
        //   16: aload_1
        //   17: invokevirtual 108	android/os/Parcel:writeString	(Ljava/lang/String;)V
        //   20: aload_2
        //   21: ifnull +48 -> 69
        //   24: aload_2
        //   25: invokeinterface 130 1 0
        //   30: astore 6
        //   32: aload_3
        //   33: aload 6
        //   35: invokevirtual 44	android/os/Parcel:writeStrongBinder	(Landroid/os/IBinder;)V
        //   38: aload_0
        //   39: getfield 15	com/google/android/gms/drive/realtime/internal/m$a$a:le	Landroid/os/IBinder;
        //   42: bipush 27
        //   44: aload_3
        //   45: aload 4
        //   47: iconst_0
        //   48: invokeinterface 50 5 0
        //   53: pop
        //   54: aload 4
        //   56: invokevirtual 53	android/os/Parcel:readException	()V
        //   59: aload 4
        //   61: invokevirtual 56	android/os/Parcel:recycle	()V
        //   64: aload_3
        //   65: invokevirtual 56	android/os/Parcel:recycle	()V
        //   68: return
        //   69: aconst_null
        //   70: astore 6
        //   72: goto -40 -> 32
        //   75: astore 5
        //   77: aload 4
        //   79: invokevirtual 56	android/os/Parcel:recycle	()V
        //   82: aload_3
        //   83: invokevirtual 56	android/os/Parcel:recycle	()V
        //   86: aload 5
        //   88: athrow
        // Local variable table:
        //   start	length	slot	name	signature
        //   0	89	0	this	a
        //   0	89	1	paramString	String
        //   0	89	2	paramk	k
        //   3	80	3	localParcel1	Parcel
        //   7	71	4	localParcel2	Parcel
        //   75	12	5	localObject	Object
        //   30	41	6	localIBinder	IBinder
        // Exception table:
        //   from	to	target	type
        //   9	20	75	finally
        //   24	32	75	finally
        //   32	59	75	finally
      }
      
      /* Error */
      public void a(String paramString, l paraml)
        throws RemoteException
      {
        // Byte code:
        //   0: invokestatic 25	android/os/Parcel:obtain	()Landroid/os/Parcel;
        //   3: astore_3
        //   4: invokestatic 25	android/os/Parcel:obtain	()Landroid/os/Parcel;
        //   7: astore 4
        //   9: aload_3
        //   10: ldc 27
        //   12: invokevirtual 31	android/os/Parcel:writeInterfaceToken	(Ljava/lang/String;)V
        //   15: aload_3
        //   16: aload_1
        //   17: invokevirtual 108	android/os/Parcel:writeString	(Ljava/lang/String;)V
        //   20: aload_2
        //   21: ifnull +47 -> 68
        //   24: aload_2
        //   25: invokeinterface 103 1 0
        //   30: astore 6
        //   32: aload_3
        //   33: aload 6
        //   35: invokevirtual 44	android/os/Parcel:writeStrongBinder	(Landroid/os/IBinder;)V
        //   38: aload_0
        //   39: getfield 15	com/google/android/gms/drive/realtime/internal/m$a$a:le	Landroid/os/IBinder;
        //   42: iconst_5
        //   43: aload_3
        //   44: aload 4
        //   46: iconst_0
        //   47: invokeinterface 50 5 0
        //   52: pop
        //   53: aload 4
        //   55: invokevirtual 53	android/os/Parcel:readException	()V
        //   58: aload 4
        //   60: invokevirtual 56	android/os/Parcel:recycle	()V
        //   63: aload_3
        //   64: invokevirtual 56	android/os/Parcel:recycle	()V
        //   67: return
        //   68: aconst_null
        //   69: astore 6
        //   71: goto -39 -> 32
        //   74: astore 5
        //   76: aload 4
        //   78: invokevirtual 56	android/os/Parcel:recycle	()V
        //   81: aload_3
        //   82: invokevirtual 56	android/os/Parcel:recycle	()V
        //   85: aload 5
        //   87: athrow
        // Local variable table:
        //   start	length	slot	name	signature
        //   0	88	0	this	a
        //   0	88	1	paramString	String
        //   0	88	2	paraml	l
        //   3	79	3	localParcel1	Parcel
        //   7	70	4	localParcel2	Parcel
        //   74	12	5	localObject	Object
        //   30	40	6	localIBinder	IBinder
        // Exception table:
        //   from	to	target	type
        //   9	20	74	finally
        //   24	32	74	finally
        //   32	58	74	finally
      }
      
      /* Error */
      public void a(String paramString, n paramn)
        throws RemoteException
      {
        // Byte code:
        //   0: invokestatic 25	android/os/Parcel:obtain	()Landroid/os/Parcel;
        //   3: astore_3
        //   4: invokestatic 25	android/os/Parcel:obtain	()Landroid/os/Parcel;
        //   7: astore 4
        //   9: aload_3
        //   10: ldc 27
        //   12: invokevirtual 31	android/os/Parcel:writeInterfaceToken	(Ljava/lang/String;)V
        //   15: aload_3
        //   16: aload_1
        //   17: invokevirtual 108	android/os/Parcel:writeString	(Ljava/lang/String;)V
        //   20: aload_2
        //   21: ifnull +47 -> 68
        //   24: aload_2
        //   25: invokeinterface 78 1 0
        //   30: astore 6
        //   32: aload_3
        //   33: aload 6
        //   35: invokevirtual 44	android/os/Parcel:writeStrongBinder	(Landroid/os/IBinder;)V
        //   38: aload_0
        //   39: getfield 15	com/google/android/gms/drive/realtime/internal/m$a$a:le	Landroid/os/IBinder;
        //   42: iconst_1
        //   43: aload_3
        //   44: aload 4
        //   46: iconst_0
        //   47: invokeinterface 50 5 0
        //   52: pop
        //   53: aload 4
        //   55: invokevirtual 53	android/os/Parcel:readException	()V
        //   58: aload 4
        //   60: invokevirtual 56	android/os/Parcel:recycle	()V
        //   63: aload_3
        //   64: invokevirtual 56	android/os/Parcel:recycle	()V
        //   67: return
        //   68: aconst_null
        //   69: astore 6
        //   71: goto -39 -> 32
        //   74: astore 5
        //   76: aload 4
        //   78: invokevirtual 56	android/os/Parcel:recycle	()V
        //   81: aload_3
        //   82: invokevirtual 56	android/os/Parcel:recycle	()V
        //   85: aload 5
        //   87: athrow
        // Local variable table:
        //   start	length	slot	name	signature
        //   0	88	0	this	a
        //   0	88	1	paramString	String
        //   0	88	2	paramn	n
        //   3	79	3	localParcel1	Parcel
        //   7	70	4	localParcel2	Parcel
        //   74	12	5	localObject	Object
        //   30	40	6	localIBinder	IBinder
        // Exception table:
        //   from	to	target	type
        //   9	20	74	finally
        //   24	32	74	finally
        //   32	58	74	finally
      }
      
      /* Error */
      public void a(String paramString, o paramo)
        throws RemoteException
      {
        // Byte code:
        //   0: invokestatic 25	android/os/Parcel:obtain	()Landroid/os/Parcel;
        //   3: astore_3
        //   4: invokestatic 25	android/os/Parcel:obtain	()Landroid/os/Parcel;
        //   7: astore 4
        //   9: aload_3
        //   10: ldc 27
        //   12: invokevirtual 31	android/os/Parcel:writeInterfaceToken	(Ljava/lang/String;)V
        //   15: aload_3
        //   16: aload_1
        //   17: invokevirtual 108	android/os/Parcel:writeString	(Ljava/lang/String;)V
        //   20: aload_2
        //   21: ifnull +48 -> 69
        //   24: aload_2
        //   25: invokeinterface 66 1 0
        //   30: astore 6
        //   32: aload_3
        //   33: aload 6
        //   35: invokevirtual 44	android/os/Parcel:writeStrongBinder	(Landroid/os/IBinder;)V
        //   38: aload_0
        //   39: getfield 15	com/google/android/gms/drive/realtime/internal/m$a$a:le	Landroid/os/IBinder;
        //   42: bipush 38
        //   44: aload_3
        //   45: aload 4
        //   47: iconst_0
        //   48: invokeinterface 50 5 0
        //   53: pop
        //   54: aload 4
        //   56: invokevirtual 53	android/os/Parcel:readException	()V
        //   59: aload 4
        //   61: invokevirtual 56	android/os/Parcel:recycle	()V
        //   64: aload_3
        //   65: invokevirtual 56	android/os/Parcel:recycle	()V
        //   68: return
        //   69: aconst_null
        //   70: astore 6
        //   72: goto -40 -> 32
        //   75: astore 5
        //   77: aload 4
        //   79: invokevirtual 56	android/os/Parcel:recycle	()V
        //   82: aload_3
        //   83: invokevirtual 56	android/os/Parcel:recycle	()V
        //   86: aload 5
        //   88: athrow
        // Local variable table:
        //   start	length	slot	name	signature
        //   0	89	0	this	a
        //   0	89	1	paramString	String
        //   0	89	2	paramo	o
        //   3	80	3	localParcel1	Parcel
        //   7	71	4	localParcel2	Parcel
        //   75	12	5	localObject	Object
        //   30	41	6	localIBinder	IBinder
        // Exception table:
        //   from	to	target	type
        //   9	20	75	finally
        //   24	32	75	finally
        //   32	59	75	finally
      }
      
      /* Error */
      public void a(String paramString1, String paramString2, f paramf)
        throws RemoteException
      {
        // Byte code:
        //   0: invokestatic 25	android/os/Parcel:obtain	()Landroid/os/Parcel;
        //   3: astore 4
        //   5: invokestatic 25	android/os/Parcel:obtain	()Landroid/os/Parcel;
        //   8: astore 5
        //   10: aload 4
        //   12: ldc 27
        //   14: invokevirtual 31	android/os/Parcel:writeInterfaceToken	(Ljava/lang/String;)V
        //   17: aload 4
        //   19: aload_1
        //   20: invokevirtual 108	android/os/Parcel:writeString	(Ljava/lang/String;)V
        //   23: aload 4
        //   25: aload_2
        //   26: invokevirtual 108	android/os/Parcel:writeString	(Ljava/lang/String;)V
        //   29: aload_3
        //   30: ifnull +50 -> 80
        //   33: aload_3
        //   34: invokeinterface 125 1 0
        //   39: astore 7
        //   41: aload 4
        //   43: aload 7
        //   45: invokevirtual 44	android/os/Parcel:writeStrongBinder	(Landroid/os/IBinder;)V
        //   48: aload_0
        //   49: getfield 15	com/google/android/gms/drive/realtime/internal/m$a$a:le	Landroid/os/IBinder;
        //   52: iconst_4
        //   53: aload 4
        //   55: aload 5
        //   57: iconst_0
        //   58: invokeinterface 50 5 0
        //   63: pop
        //   64: aload 5
        //   66: invokevirtual 53	android/os/Parcel:readException	()V
        //   69: aload 5
        //   71: invokevirtual 56	android/os/Parcel:recycle	()V
        //   74: aload 4
        //   76: invokevirtual 56	android/os/Parcel:recycle	()V
        //   79: return
        //   80: aconst_null
        //   81: astore 7
        //   83: goto -42 -> 41
        //   86: astore 6
        //   88: aload 5
        //   90: invokevirtual 56	android/os/Parcel:recycle	()V
        //   93: aload 4
        //   95: invokevirtual 56	android/os/Parcel:recycle	()V
        //   98: aload 6
        //   100: athrow
        // Local variable table:
        //   start	length	slot	name	signature
        //   0	101	0	this	a
        //   0	101	1	paramString1	String
        //   0	101	2	paramString2	String
        //   0	101	3	paramf	f
        //   3	91	4	localParcel1	Parcel
        //   8	81	5	localParcel2	Parcel
        //   86	13	6	localObject	Object
        //   39	43	7	localIBinder	IBinder
        // Exception table:
        //   from	to	target	type
        //   10	29	86	finally
        //   33	41	86	finally
        //   41	69	86	finally
      }
      
      /* Error */
      public void a(String paramString1, String paramString2, g paramg)
        throws RemoteException
      {
        // Byte code:
        //   0: invokestatic 25	android/os/Parcel:obtain	()Landroid/os/Parcel;
        //   3: astore 4
        //   5: invokestatic 25	android/os/Parcel:obtain	()Landroid/os/Parcel;
        //   8: astore 5
        //   10: aload 4
        //   12: ldc 27
        //   14: invokevirtual 31	android/os/Parcel:writeInterfaceToken	(Ljava/lang/String;)V
        //   17: aload 4
        //   19: aload_1
        //   20: invokevirtual 108	android/os/Parcel:writeString	(Ljava/lang/String;)V
        //   23: aload 4
        //   25: aload_2
        //   26: invokevirtual 108	android/os/Parcel:writeString	(Ljava/lang/String;)V
        //   29: aload_3
        //   30: ifnull +51 -> 81
        //   33: aload_3
        //   34: invokeinterface 111 1 0
        //   39: astore 7
        //   41: aload 4
        //   43: aload 7
        //   45: invokevirtual 44	android/os/Parcel:writeStrongBinder	(Landroid/os/IBinder;)V
        //   48: aload_0
        //   49: getfield 15	com/google/android/gms/drive/realtime/internal/m$a$a:le	Landroid/os/IBinder;
        //   52: bipush 21
        //   54: aload 4
        //   56: aload 5
        //   58: iconst_0
        //   59: invokeinterface 50 5 0
        //   64: pop
        //   65: aload 5
        //   67: invokevirtual 53	android/os/Parcel:readException	()V
        //   70: aload 5
        //   72: invokevirtual 56	android/os/Parcel:recycle	()V
        //   75: aload 4
        //   77: invokevirtual 56	android/os/Parcel:recycle	()V
        //   80: return
        //   81: aconst_null
        //   82: astore 7
        //   84: goto -43 -> 41
        //   87: astore 6
        //   89: aload 5
        //   91: invokevirtual 56	android/os/Parcel:recycle	()V
        //   94: aload 4
        //   96: invokevirtual 56	android/os/Parcel:recycle	()V
        //   99: aload 6
        //   101: athrow
        // Local variable table:
        //   start	length	slot	name	signature
        //   0	102	0	this	a
        //   0	102	1	paramString1	String
        //   0	102	2	paramString2	String
        //   0	102	3	paramg	g
        //   3	92	4	localParcel1	Parcel
        //   8	82	5	localParcel2	Parcel
        //   87	13	6	localObject	Object
        //   39	44	7	localIBinder	IBinder
        // Exception table:
        //   from	to	target	type
        //   10	29	87	finally
        //   33	41	87	finally
        //   41	70	87	finally
      }
      
      /* Error */
      public void a(String paramString1, String paramString2, j paramj)
        throws RemoteException
      {
        // Byte code:
        //   0: invokestatic 25	android/os/Parcel:obtain	()Landroid/os/Parcel;
        //   3: astore 4
        //   5: invokestatic 25	android/os/Parcel:obtain	()Landroid/os/Parcel;
        //   8: astore 5
        //   10: aload 4
        //   12: ldc 27
        //   14: invokevirtual 31	android/os/Parcel:writeInterfaceToken	(Ljava/lang/String;)V
        //   17: aload 4
        //   19: aload_1
        //   20: invokevirtual 108	android/os/Parcel:writeString	(Ljava/lang/String;)V
        //   23: aload 4
        //   25: aload_2
        //   26: invokevirtual 108	android/os/Parcel:writeString	(Ljava/lang/String;)V
        //   29: aload_3
        //   30: ifnull +51 -> 81
        //   33: aload_3
        //   34: invokeinterface 41 1 0
        //   39: astore 7
        //   41: aload 4
        //   43: aload 7
        //   45: invokevirtual 44	android/os/Parcel:writeStrongBinder	(Landroid/os/IBinder;)V
        //   48: aload_0
        //   49: getfield 15	com/google/android/gms/drive/realtime/internal/m$a$a:le	Landroid/os/IBinder;
        //   52: bipush 12
        //   54: aload 4
        //   56: aload 5
        //   58: iconst_0
        //   59: invokeinterface 50 5 0
        //   64: pop
        //   65: aload 5
        //   67: invokevirtual 53	android/os/Parcel:readException	()V
        //   70: aload 5
        //   72: invokevirtual 56	android/os/Parcel:recycle	()V
        //   75: aload 4
        //   77: invokevirtual 56	android/os/Parcel:recycle	()V
        //   80: return
        //   81: aconst_null
        //   82: astore 7
        //   84: goto -43 -> 41
        //   87: astore 6
        //   89: aload 5
        //   91: invokevirtual 56	android/os/Parcel:recycle	()V
        //   94: aload 4
        //   96: invokevirtual 56	android/os/Parcel:recycle	()V
        //   99: aload 6
        //   101: athrow
        // Local variable table:
        //   start	length	slot	name	signature
        //   0	102	0	this	a
        //   0	102	1	paramString1	String
        //   0	102	2	paramString2	String
        //   0	102	3	paramj	j
        //   3	92	4	localParcel1	Parcel
        //   8	82	5	localParcel2	Parcel
        //   87	13	6	localObject	Object
        //   39	44	7	localIBinder	IBinder
        // Exception table:
        //   from	to	target	type
        //   10	29	87	finally
        //   33	41	87	finally
        //   41	70	87	finally
      }
      
      public IBinder asBinder()
      {
        return this.le;
      }
      
      /* Error */
      public void b(c paramc)
        throws RemoteException
      {
        // Byte code:
        //   0: invokestatic 25	android/os/Parcel:obtain	()Landroid/os/Parcel;
        //   3: astore_2
        //   4: invokestatic 25	android/os/Parcel:obtain	()Landroid/os/Parcel;
        //   7: astore_3
        //   8: aload_2
        //   9: ldc 27
        //   11: invokevirtual 31	android/os/Parcel:writeInterfaceToken	(Ljava/lang/String;)V
        //   14: aload_1
        //   15: ifnull +45 -> 60
        //   18: aload_1
        //   19: invokeinterface 82 1 0
        //   24: astore 5
        //   26: aload_2
        //   27: aload 5
        //   29: invokevirtual 44	android/os/Parcel:writeStrongBinder	(Landroid/os/IBinder;)V
        //   32: aload_0
        //   33: getfield 15	com/google/android/gms/drive/realtime/internal/m$a$a:le	Landroid/os/IBinder;
        //   36: bipush 33
        //   38: aload_2
        //   39: aload_3
        //   40: iconst_0
        //   41: invokeinterface 50 5 0
        //   46: pop
        //   47: aload_3
        //   48: invokevirtual 53	android/os/Parcel:readException	()V
        //   51: aload_3
        //   52: invokevirtual 56	android/os/Parcel:recycle	()V
        //   55: aload_2
        //   56: invokevirtual 56	android/os/Parcel:recycle	()V
        //   59: return
        //   60: aconst_null
        //   61: astore 5
        //   63: goto -37 -> 26
        //   66: astore 4
        //   68: aload_3
        //   69: invokevirtual 56	android/os/Parcel:recycle	()V
        //   72: aload_2
        //   73: invokevirtual 56	android/os/Parcel:recycle	()V
        //   76: aload 4
        //   78: athrow
        // Local variable table:
        //   start	length	slot	name	signature
        //   0	79	0	this	a
        //   0	79	1	paramc	c
        //   3	70	2	localParcel1	Parcel
        //   7	62	3	localParcel2	Parcel
        //   66	11	4	localObject	Object
        //   24	38	5	localIBinder	IBinder
        // Exception table:
        //   from	to	target	type
        //   8	14	66	finally
        //   18	26	66	finally
        //   26	51	66	finally
      }
      
      /* Error */
      public void b(j paramj)
        throws RemoteException
      {
        // Byte code:
        //   0: invokestatic 25	android/os/Parcel:obtain	()Landroid/os/Parcel;
        //   3: astore_2
        //   4: invokestatic 25	android/os/Parcel:obtain	()Landroid/os/Parcel;
        //   7: astore_3
        //   8: aload_2
        //   9: ldc 27
        //   11: invokevirtual 31	android/os/Parcel:writeInterfaceToken	(Ljava/lang/String;)V
        //   14: aload_1
        //   15: ifnull +45 -> 60
        //   18: aload_1
        //   19: invokeinterface 41 1 0
        //   24: astore 5
        //   26: aload_2
        //   27: aload 5
        //   29: invokevirtual 44	android/os/Parcel:writeStrongBinder	(Landroid/os/IBinder;)V
        //   32: aload_0
        //   33: getfield 15	com/google/android/gms/drive/realtime/internal/m$a$a:le	Landroid/os/IBinder;
        //   36: bipush 23
        //   38: aload_2
        //   39: aload_3
        //   40: iconst_0
        //   41: invokeinterface 50 5 0
        //   46: pop
        //   47: aload_3
        //   48: invokevirtual 53	android/os/Parcel:readException	()V
        //   51: aload_3
        //   52: invokevirtual 56	android/os/Parcel:recycle	()V
        //   55: aload_2
        //   56: invokevirtual 56	android/os/Parcel:recycle	()V
        //   59: return
        //   60: aconst_null
        //   61: astore 5
        //   63: goto -37 -> 26
        //   66: astore 4
        //   68: aload_3
        //   69: invokevirtual 56	android/os/Parcel:recycle	()V
        //   72: aload_2
        //   73: invokevirtual 56	android/os/Parcel:recycle	()V
        //   76: aload 4
        //   78: athrow
        // Local variable table:
        //   start	length	slot	name	signature
        //   0	79	0	this	a
        //   0	79	1	paramj	j
        //   3	70	2	localParcel1	Parcel
        //   7	62	3	localParcel2	Parcel
        //   66	11	4	localObject	Object
        //   24	38	5	localIBinder	IBinder
        // Exception table:
        //   from	to	target	type
        //   8	14	66	finally
        //   18	26	66	finally
        //   26	51	66	finally
      }
      
      /* Error */
      public void b(l paraml)
        throws RemoteException
      {
        // Byte code:
        //   0: invokestatic 25	android/os/Parcel:obtain	()Landroid/os/Parcel;
        //   3: astore_2
        //   4: invokestatic 25	android/os/Parcel:obtain	()Landroid/os/Parcel;
        //   7: astore_3
        //   8: aload_2
        //   9: ldc 27
        //   11: invokevirtual 31	android/os/Parcel:writeInterfaceToken	(Ljava/lang/String;)V
        //   14: aload_1
        //   15: ifnull +45 -> 60
        //   18: aload_1
        //   19: invokeinterface 103 1 0
        //   24: astore 5
        //   26: aload_2
        //   27: aload 5
        //   29: invokevirtual 44	android/os/Parcel:writeStrongBinder	(Landroid/os/IBinder;)V
        //   32: aload_0
        //   33: getfield 15	com/google/android/gms/drive/realtime/internal/m$a$a:le	Landroid/os/IBinder;
        //   36: bipush 29
        //   38: aload_2
        //   39: aload_3
        //   40: iconst_0
        //   41: invokeinterface 50 5 0
        //   46: pop
        //   47: aload_3
        //   48: invokevirtual 53	android/os/Parcel:readException	()V
        //   51: aload_3
        //   52: invokevirtual 56	android/os/Parcel:recycle	()V
        //   55: aload_2
        //   56: invokevirtual 56	android/os/Parcel:recycle	()V
        //   59: return
        //   60: aconst_null
        //   61: astore 5
        //   63: goto -37 -> 26
        //   66: astore 4
        //   68: aload_3
        //   69: invokevirtual 56	android/os/Parcel:recycle	()V
        //   72: aload_2
        //   73: invokevirtual 56	android/os/Parcel:recycle	()V
        //   76: aload 4
        //   78: athrow
        // Local variable table:
        //   start	length	slot	name	signature
        //   0	79	0	this	a
        //   0	79	1	paraml	l
        //   3	70	2	localParcel1	Parcel
        //   7	62	3	localParcel2	Parcel
        //   66	11	4	localObject	Object
        //   24	38	5	localIBinder	IBinder
        // Exception table:
        //   from	to	target	type
        //   8	14	66	finally
        //   18	26	66	finally
        //   26	51	66	finally
      }
      
      /* Error */
      public void b(o paramo)
        throws RemoteException
      {
        // Byte code:
        //   0: invokestatic 25	android/os/Parcel:obtain	()Landroid/os/Parcel;
        //   3: astore_2
        //   4: invokestatic 25	android/os/Parcel:obtain	()Landroid/os/Parcel;
        //   7: astore_3
        //   8: aload_2
        //   9: ldc 27
        //   11: invokevirtual 31	android/os/Parcel:writeInterfaceToken	(Ljava/lang/String;)V
        //   14: aload_1
        //   15: ifnull +45 -> 60
        //   18: aload_1
        //   19: invokeinterface 66 1 0
        //   24: astore 5
        //   26: aload_2
        //   27: aload 5
        //   29: invokevirtual 44	android/os/Parcel:writeStrongBinder	(Landroid/os/IBinder;)V
        //   32: aload_0
        //   33: getfield 15	com/google/android/gms/drive/realtime/internal/m$a$a:le	Landroid/os/IBinder;
        //   36: bipush 35
        //   38: aload_2
        //   39: aload_3
        //   40: iconst_0
        //   41: invokeinterface 50 5 0
        //   46: pop
        //   47: aload_3
        //   48: invokevirtual 53	android/os/Parcel:readException	()V
        //   51: aload_3
        //   52: invokevirtual 56	android/os/Parcel:recycle	()V
        //   55: aload_2
        //   56: invokevirtual 56	android/os/Parcel:recycle	()V
        //   59: return
        //   60: aconst_null
        //   61: astore 5
        //   63: goto -37 -> 26
        //   66: astore 4
        //   68: aload_3
        //   69: invokevirtual 56	android/os/Parcel:recycle	()V
        //   72: aload_2
        //   73: invokevirtual 56	android/os/Parcel:recycle	()V
        //   76: aload 4
        //   78: athrow
        // Local variable table:
        //   start	length	slot	name	signature
        //   0	79	0	this	a
        //   0	79	1	paramo	o
        //   3	70	2	localParcel1	Parcel
        //   7	62	3	localParcel2	Parcel
        //   66	11	4	localObject	Object
        //   24	38	5	localIBinder	IBinder
        // Exception table:
        //   from	to	target	type
        //   8	14	66	finally
        //   18	26	66	finally
        //   26	51	66	finally
      }
      
      /* Error */
      public void b(String paramString, f paramf)
        throws RemoteException
      {
        // Byte code:
        //   0: invokestatic 25	android/os/Parcel:obtain	()Landroid/os/Parcel;
        //   3: astore_3
        //   4: invokestatic 25	android/os/Parcel:obtain	()Landroid/os/Parcel;
        //   7: astore 4
        //   9: aload_3
        //   10: ldc 27
        //   12: invokevirtual 31	android/os/Parcel:writeInterfaceToken	(Ljava/lang/String;)V
        //   15: aload_3
        //   16: aload_1
        //   17: invokevirtual 108	android/os/Parcel:writeString	(Ljava/lang/String;)V
        //   20: aload_2
        //   21: ifnull +48 -> 69
        //   24: aload_2
        //   25: invokeinterface 125 1 0
        //   30: astore 6
        //   32: aload_3
        //   33: aload 6
        //   35: invokevirtual 44	android/os/Parcel:writeStrongBinder	(Landroid/os/IBinder;)V
        //   38: aload_0
        //   39: getfield 15	com/google/android/gms/drive/realtime/internal/m$a$a:le	Landroid/os/IBinder;
        //   42: bipush 13
        //   44: aload_3
        //   45: aload 4
        //   47: iconst_0
        //   48: invokeinterface 50 5 0
        //   53: pop
        //   54: aload 4
        //   56: invokevirtual 53	android/os/Parcel:readException	()V
        //   59: aload 4
        //   61: invokevirtual 56	android/os/Parcel:recycle	()V
        //   64: aload_3
        //   65: invokevirtual 56	android/os/Parcel:recycle	()V
        //   68: return
        //   69: aconst_null
        //   70: astore 6
        //   72: goto -40 -> 32
        //   75: astore 5
        //   77: aload 4
        //   79: invokevirtual 56	android/os/Parcel:recycle	()V
        //   82: aload_3
        //   83: invokevirtual 56	android/os/Parcel:recycle	()V
        //   86: aload 5
        //   88: athrow
        // Local variable table:
        //   start	length	slot	name	signature
        //   0	89	0	this	a
        //   0	89	1	paramString	String
        //   0	89	2	paramf	f
        //   3	80	3	localParcel1	Parcel
        //   7	71	4	localParcel2	Parcel
        //   75	12	5	localObject	Object
        //   30	41	6	localIBinder	IBinder
        // Exception table:
        //   from	to	target	type
        //   9	20	75	finally
        //   24	32	75	finally
        //   32	59	75	finally
      }
      
      /* Error */
      public void b(String paramString, l paraml)
        throws RemoteException
      {
        // Byte code:
        //   0: invokestatic 25	android/os/Parcel:obtain	()Landroid/os/Parcel;
        //   3: astore_3
        //   4: invokestatic 25	android/os/Parcel:obtain	()Landroid/os/Parcel;
        //   7: astore 4
        //   9: aload_3
        //   10: ldc 27
        //   12: invokevirtual 31	android/os/Parcel:writeInterfaceToken	(Ljava/lang/String;)V
        //   15: aload_3
        //   16: aload_1
        //   17: invokevirtual 108	android/os/Parcel:writeString	(Ljava/lang/String;)V
        //   20: aload_2
        //   21: ifnull +48 -> 69
        //   24: aload_2
        //   25: invokeinterface 103 1 0
        //   30: astore 6
        //   32: aload_3
        //   33: aload 6
        //   35: invokevirtual 44	android/os/Parcel:writeStrongBinder	(Landroid/os/IBinder;)V
        //   38: aload_0
        //   39: getfield 15	com/google/android/gms/drive/realtime/internal/m$a$a:le	Landroid/os/IBinder;
        //   42: bipush 8
        //   44: aload_3
        //   45: aload 4
        //   47: iconst_0
        //   48: invokeinterface 50 5 0
        //   53: pop
        //   54: aload 4
        //   56: invokevirtual 53	android/os/Parcel:readException	()V
        //   59: aload 4
        //   61: invokevirtual 56	android/os/Parcel:recycle	()V
        //   64: aload_3
        //   65: invokevirtual 56	android/os/Parcel:recycle	()V
        //   68: return
        //   69: aconst_null
        //   70: astore 6
        //   72: goto -40 -> 32
        //   75: astore 5
        //   77: aload 4
        //   79: invokevirtual 56	android/os/Parcel:recycle	()V
        //   82: aload_3
        //   83: invokevirtual 56	android/os/Parcel:recycle	()V
        //   86: aload 5
        //   88: athrow
        // Local variable table:
        //   start	length	slot	name	signature
        //   0	89	0	this	a
        //   0	89	1	paramString	String
        //   0	89	2	paraml	l
        //   3	80	3	localParcel1	Parcel
        //   7	71	4	localParcel2	Parcel
        //   75	12	5	localObject	Object
        //   30	41	6	localIBinder	IBinder
        // Exception table:
        //   from	to	target	type
        //   9	20	75	finally
        //   24	32	75	finally
        //   32	59	75	finally
      }
      
      /* Error */
      public void b(String paramString, n paramn)
        throws RemoteException
      {
        // Byte code:
        //   0: invokestatic 25	android/os/Parcel:obtain	()Landroid/os/Parcel;
        //   3: astore_3
        //   4: invokestatic 25	android/os/Parcel:obtain	()Landroid/os/Parcel;
        //   7: astore 4
        //   9: aload_3
        //   10: ldc 27
        //   12: invokevirtual 31	android/os/Parcel:writeInterfaceToken	(Ljava/lang/String;)V
        //   15: aload_3
        //   16: aload_1
        //   17: invokevirtual 108	android/os/Parcel:writeString	(Ljava/lang/String;)V
        //   20: aload_2
        //   21: ifnull +48 -> 69
        //   24: aload_2
        //   25: invokeinterface 78 1 0
        //   30: astore 6
        //   32: aload_3
        //   33: aload 6
        //   35: invokevirtual 44	android/os/Parcel:writeStrongBinder	(Landroid/os/IBinder;)V
        //   38: aload_0
        //   39: getfield 15	com/google/android/gms/drive/realtime/internal/m$a$a:le	Landroid/os/IBinder;
        //   42: bipush 9
        //   44: aload_3
        //   45: aload 4
        //   47: iconst_0
        //   48: invokeinterface 50 5 0
        //   53: pop
        //   54: aload 4
        //   56: invokevirtual 53	android/os/Parcel:readException	()V
        //   59: aload 4
        //   61: invokevirtual 56	android/os/Parcel:recycle	()V
        //   64: aload_3
        //   65: invokevirtual 56	android/os/Parcel:recycle	()V
        //   68: return
        //   69: aconst_null
        //   70: astore 6
        //   72: goto -40 -> 32
        //   75: astore 5
        //   77: aload 4
        //   79: invokevirtual 56	android/os/Parcel:recycle	()V
        //   82: aload_3
        //   83: invokevirtual 56	android/os/Parcel:recycle	()V
        //   86: aload 5
        //   88: athrow
        // Local variable table:
        //   start	length	slot	name	signature
        //   0	89	0	this	a
        //   0	89	1	paramString	String
        //   0	89	2	paramn	n
        //   3	80	3	localParcel1	Parcel
        //   7	71	4	localParcel2	Parcel
        //   75	12	5	localObject	Object
        //   30	41	6	localIBinder	IBinder
        // Exception table:
        //   from	to	target	type
        //   9	20	75	finally
        //   24	32	75	finally
        //   32	59	75	finally
      }
      
      /* Error */
      public void b(String paramString, o paramo)
        throws RemoteException
      {
        // Byte code:
        //   0: invokestatic 25	android/os/Parcel:obtain	()Landroid/os/Parcel;
        //   3: astore_3
        //   4: invokestatic 25	android/os/Parcel:obtain	()Landroid/os/Parcel;
        //   7: astore 4
        //   9: aload_3
        //   10: ldc 27
        //   12: invokevirtual 31	android/os/Parcel:writeInterfaceToken	(Ljava/lang/String;)V
        //   15: aload_3
        //   16: aload_1
        //   17: invokevirtual 108	android/os/Parcel:writeString	(Ljava/lang/String;)V
        //   20: aload_2
        //   21: ifnull +48 -> 69
        //   24: aload_2
        //   25: invokeinterface 66 1 0
        //   30: astore 6
        //   32: aload_3
        //   33: aload 6
        //   35: invokevirtual 44	android/os/Parcel:writeStrongBinder	(Landroid/os/IBinder;)V
        //   38: aload_0
        //   39: getfield 15	com/google/android/gms/drive/realtime/internal/m$a$a:le	Landroid/os/IBinder;
        //   42: bipush 39
        //   44: aload_3
        //   45: aload 4
        //   47: iconst_0
        //   48: invokeinterface 50 5 0
        //   53: pop
        //   54: aload 4
        //   56: invokevirtual 53	android/os/Parcel:readException	()V
        //   59: aload 4
        //   61: invokevirtual 56	android/os/Parcel:recycle	()V
        //   64: aload_3
        //   65: invokevirtual 56	android/os/Parcel:recycle	()V
        //   68: return
        //   69: aconst_null
        //   70: astore 6
        //   72: goto -40 -> 32
        //   75: astore 5
        //   77: aload 4
        //   79: invokevirtual 56	android/os/Parcel:recycle	()V
        //   82: aload_3
        //   83: invokevirtual 56	android/os/Parcel:recycle	()V
        //   86: aload 5
        //   88: athrow
        // Local variable table:
        //   start	length	slot	name	signature
        //   0	89	0	this	a
        //   0	89	1	paramString	String
        //   0	89	2	paramo	o
        //   3	80	3	localParcel1	Parcel
        //   7	71	4	localParcel2	Parcel
        //   75	12	5	localObject	Object
        //   30	41	6	localIBinder	IBinder
        // Exception table:
        //   from	to	target	type
        //   9	20	75	finally
        //   24	32	75	finally
        //   32	59	75	finally
      }
      
      /* Error */
      public void c(c paramc)
        throws RemoteException
      {
        // Byte code:
        //   0: invokestatic 25	android/os/Parcel:obtain	()Landroid/os/Parcel;
        //   3: astore_2
        //   4: invokestatic 25	android/os/Parcel:obtain	()Landroid/os/Parcel;
        //   7: astore_3
        //   8: aload_2
        //   9: ldc 27
        //   11: invokevirtual 31	android/os/Parcel:writeInterfaceToken	(Ljava/lang/String;)V
        //   14: aload_1
        //   15: ifnull +45 -> 60
        //   18: aload_1
        //   19: invokeinterface 82 1 0
        //   24: astore 5
        //   26: aload_2
        //   27: aload 5
        //   29: invokevirtual 44	android/os/Parcel:writeStrongBinder	(Landroid/os/IBinder;)V
        //   32: aload_0
        //   33: getfield 15	com/google/android/gms/drive/realtime/internal/m$a$a:le	Landroid/os/IBinder;
        //   36: bipush 24
        //   38: aload_2
        //   39: aload_3
        //   40: iconst_0
        //   41: invokeinterface 50 5 0
        //   46: pop
        //   47: aload_3
        //   48: invokevirtual 53	android/os/Parcel:readException	()V
        //   51: aload_3
        //   52: invokevirtual 56	android/os/Parcel:recycle	()V
        //   55: aload_2
        //   56: invokevirtual 56	android/os/Parcel:recycle	()V
        //   59: return
        //   60: aconst_null
        //   61: astore 5
        //   63: goto -37 -> 26
        //   66: astore 4
        //   68: aload_3
        //   69: invokevirtual 56	android/os/Parcel:recycle	()V
        //   72: aload_2
        //   73: invokevirtual 56	android/os/Parcel:recycle	()V
        //   76: aload 4
        //   78: athrow
        // Local variable table:
        //   start	length	slot	name	signature
        //   0	79	0	this	a
        //   0	79	1	paramc	c
        //   3	70	2	localParcel1	Parcel
        //   7	62	3	localParcel2	Parcel
        //   66	11	4	localObject	Object
        //   24	38	5	localIBinder	IBinder
        // Exception table:
        //   from	to	target	type
        //   8	14	66	finally
        //   18	26	66	finally
        //   26	51	66	finally
      }
      
      /* Error */
      public void c(String paramString, l paraml)
        throws RemoteException
      {
        // Byte code:
        //   0: invokestatic 25	android/os/Parcel:obtain	()Landroid/os/Parcel;
        //   3: astore_3
        //   4: invokestatic 25	android/os/Parcel:obtain	()Landroid/os/Parcel;
        //   7: astore 4
        //   9: aload_3
        //   10: ldc 27
        //   12: invokevirtual 31	android/os/Parcel:writeInterfaceToken	(Ljava/lang/String;)V
        //   15: aload_3
        //   16: aload_1
        //   17: invokevirtual 108	android/os/Parcel:writeString	(Ljava/lang/String;)V
        //   20: aload_2
        //   21: ifnull +48 -> 69
        //   24: aload_2
        //   25: invokeinterface 103 1 0
        //   30: astore 6
        //   32: aload_3
        //   33: aload 6
        //   35: invokevirtual 44	android/os/Parcel:writeStrongBinder	(Landroid/os/IBinder;)V
        //   38: aload_0
        //   39: getfield 15	com/google/android/gms/drive/realtime/internal/m$a$a:le	Landroid/os/IBinder;
        //   42: bipush 14
        //   44: aload_3
        //   45: aload 4
        //   47: iconst_0
        //   48: invokeinterface 50 5 0
        //   53: pop
        //   54: aload 4
        //   56: invokevirtual 53	android/os/Parcel:readException	()V
        //   59: aload 4
        //   61: invokevirtual 56	android/os/Parcel:recycle	()V
        //   64: aload_3
        //   65: invokevirtual 56	android/os/Parcel:recycle	()V
        //   68: return
        //   69: aconst_null
        //   70: astore 6
        //   72: goto -40 -> 32
        //   75: astore 5
        //   77: aload 4
        //   79: invokevirtual 56	android/os/Parcel:recycle	()V
        //   82: aload_3
        //   83: invokevirtual 56	android/os/Parcel:recycle	()V
        //   86: aload 5
        //   88: athrow
        // Local variable table:
        //   start	length	slot	name	signature
        //   0	89	0	this	a
        //   0	89	1	paramString	String
        //   0	89	2	paraml	l
        //   3	80	3	localParcel1	Parcel
        //   7	71	4	localParcel2	Parcel
        //   75	12	5	localObject	Object
        //   30	41	6	localIBinder	IBinder
        // Exception table:
        //   from	to	target	type
        //   9	20	75	finally
        //   24	32	75	finally
        //   32	59	75	finally
      }
      
      /* Error */
      public void d(c paramc)
        throws RemoteException
      {
        // Byte code:
        //   0: invokestatic 25	android/os/Parcel:obtain	()Landroid/os/Parcel;
        //   3: astore_2
        //   4: invokestatic 25	android/os/Parcel:obtain	()Landroid/os/Parcel;
        //   7: astore_3
        //   8: aload_2
        //   9: ldc 27
        //   11: invokevirtual 31	android/os/Parcel:writeInterfaceToken	(Ljava/lang/String;)V
        //   14: aload_1
        //   15: ifnull +45 -> 60
        //   18: aload_1
        //   19: invokeinterface 82 1 0
        //   24: astore 5
        //   26: aload_2
        //   27: aload 5
        //   29: invokevirtual 44	android/os/Parcel:writeStrongBinder	(Landroid/os/IBinder;)V
        //   32: aload_0
        //   33: getfield 15	com/google/android/gms/drive/realtime/internal/m$a$a:le	Landroid/os/IBinder;
        //   36: bipush 25
        //   38: aload_2
        //   39: aload_3
        //   40: iconst_0
        //   41: invokeinterface 50 5 0
        //   46: pop
        //   47: aload_3
        //   48: invokevirtual 53	android/os/Parcel:readException	()V
        //   51: aload_3
        //   52: invokevirtual 56	android/os/Parcel:recycle	()V
        //   55: aload_2
        //   56: invokevirtual 56	android/os/Parcel:recycle	()V
        //   59: return
        //   60: aconst_null
        //   61: astore 5
        //   63: goto -37 -> 26
        //   66: astore 4
        //   68: aload_3
        //   69: invokevirtual 56	android/os/Parcel:recycle	()V
        //   72: aload_2
        //   73: invokevirtual 56	android/os/Parcel:recycle	()V
        //   76: aload 4
        //   78: athrow
        // Local variable table:
        //   start	length	slot	name	signature
        //   0	79	0	this	a
        //   0	79	1	paramc	c
        //   3	70	2	localParcel1	Parcel
        //   7	62	3	localParcel2	Parcel
        //   66	11	4	localObject	Object
        //   24	38	5	localIBinder	IBinder
        // Exception table:
        //   from	to	target	type
        //   8	14	66	finally
        //   18	26	66	finally
        //   26	51	66	finally
      }
    }
  }
}


/* Location:           C:\Users\TGKIM\Downloads\\\androidReversetools\jd-gui-0.3.6.windows\com.appg.golfmon-1-dex2jar.jar
 * Qualified Name:     com.google.android.gms.drive.realtime.internal.m
 * JD-Core Version:    0.7.0.1
 */